Workbook

Sheet Start-Up Costs Template
B1: START-UP COSTS
B2: YOUR COMPANY NAME | C2: =TODAY() -> 45060
B4: COST ITEMS | C4: MONTHS | D4: COST/ MONTH | E4: ONE-TIME COST | F4: TOTAL COST
B5: Advertising/Marketing | F5: =(C5*D5)+IF(E5>0,E5,0) -> 0
B6: Employee Salaries | F6: =(C6*D6)+IF(E6>0,E6,0) -> 0
B7: Employee Payroll Taxes and Benefits | F7: =(C7*D7)+IF(E7>0,E7,0) -> 0
B8: Rent/Lease Payments/Utilities | F8: =(C8*D8)+IF(E8>0,E8,0) -> 0
B9: Postage/Shipping | F9: =(C9*D9)+IF(E9>0,E9,0) -> 0
B10: ESTIMATED START-UP BUDGET | F10: =SUBTOTAL(109,StartUp[TOTAL COST]) -> 0

Sheet Start-Up Costs Example
B1: START-UP COSTS
B2: ='Start-Up Costs Template'!B2 -> YOUR COMPANY NAME | C2: =TODAY() -> 45060
B4: COST ITEMS | C4: MONTHS | D4: COST/ MONTH | E4: ONE-TIME COST | F4: TOTAL COST
B5: Advertising/Marketing | C5: 3 | D5: 300 | E5: 2000 | F5: =(C5*D5)+IF(E5>0,E5,0) -> 2900
B6: Employee Salaries | C6: 4 | D6: 3500 | E6: 2 | F6: =(C6*D6)+IF(E6>0,E6,0) -> 14002
B7: Employee Payroll Taxes and Benefits | C7: 4 | D7: 500 | E7: 2000 | F7: =(C7*D7)+IF(E7>0,E7,0) -> 4000
B8: Rent/Lease Payments/Utilities | C8: 4 | D8: 750 | E8: 3000 | F8: =(C8*D8)+IF(E8>0,E8,0) -> 6000
B9: Postage/Shipping | C9: 1 | D9: 25 | E9: 25 | F9: =(C9*D9)+IF(E9>0,E9,0) -> 50
B10: ESTIMATED START-UP BUDGET | F10: =SUM(F6:F9) -> 24052

Sheet P&L Template
B1: START-UP COSTS
B2: ='Start-Up Costs Template'!B2 -> YOUR COMPANY NAME | C2: =TODAY() -> 45060
B4: REVENUE | C4: JAN | D4: FEB | E4: MAR | F4: APR | G4: MAY | H4: JUN | I4: JUL | J4: AUG | K4: SEP | L4: OCT | M4: NOV | N4: DEC | O4: YTD
B5: Estimated Product Sales | C5: 0 | D5: 0 | E5: 0 | F5: 0 | G5: 0 | H5: 0 | I5: 0 | J5: 0 | K5: 0 | L5: 0 | M5: 0 | N5: 0 | O5: =SUM(C5:N5) -> 0
B6: Less Sales Returns & Discounts | C6: 0 | D6: 0 | E6: 0 | F6: 0 | G6: 0 | H6: 0 | I6: 0 | J6: 0 | K6: 0 | L6: 0 | M6: 0 | N6: 0 | O6: =SUM(C6:N6) -> 0
B7: Service Revenue | C7: 0 | D7: 0 | E7: 0 | F7: 0 | G7: 0 | H7: 0 | I7: 0 | J7: 0 | K7: 0 | L7: 0 | M7: 0 | N7: 0 | O7: =SUM(C7:N7) -> 0
B8: Other Revenue | C8: 0 | D8: 0 | E8: 0 | F8: 0 | G8: 0 | H8: 0 | I8: 0 | J8: 0 | K8: 0 | L8: 0 | M8: 0 | N8: 0 | O8: =SUM(C8:N8) -> 0
B9: Net Sales | C9: =SUBTOTAL(109,SampleRevenue[JAN]) -> 0 | D9: =SUBTOTAL(109,SampleRevenue[FEB]) -> 0 | E9: =SUBTOTAL(109,SampleRevenue[MAR]) -> 0 | F9: =SUBTOTAL(109,SampleRevenue[APR]) -> 0 | G9: =SUBTOTAL(109,SampleRevenue[MAY]) -> 0 | H9: =SUBTOTAL(109,SampleRevenue[JUN]) -> 0 | I9: =SUBTOTAL(109,SampleRevenue[JUL]) -> 0 | J9: =SUBTOTAL(109,SampleRevenue[AUG]) -> 0 | K9: =SUBTOTAL(109,SampleRevenue[SEP]) -> 0 | L9: =SUBTOTAL(109,SampleRevenue[OCT]) -> 0 | M9: =SUBTOTAL(109,SampleRevenue[NOV]) -> 0 | N9: =SUBTOTAL(109,SampleRevenue[DEC]) -> 0 | O9: =SUM(SampleRevenue[[#Totals],[JAN]:[DEC]]) -> 0
B10: Cost of Goods Sold | C10: =C5*0.4 -> 0 | D10: =D5*0.4 -> 0 | E10: =E5*0.4 -> 0 | F10: =F5*0.4 -> 0 | G10: =G5*0.4 -> 0 | H10: =H5*0.4 -> 0 | I10: =I5*0.4 -> 0 | J10: =J5*0.4 -> 0 | ... N10: =N5*0.4 -> 0 | O10: =SUM(C10:N10) -> 0
B11: Gross Profit | C11: =IFERROR(SampleRevenue[[#Totals],[JAN]]-C10,"") -> 0 | D11: =IFERROR(SampleRevenue[[#Totals],[FEB]]-D10,"") -> 0 | E11: =IFERROR(SampleRevenue[[#Totals],[MAR]]-E10,"") -> 0 | F11: =IFERROR(SampleRevenue[[#Totals],[APR]]-F10,"") -> 0 | G11: =IFERROR(SampleRevenue[[#Totals],[MAY]]-G10,"") -> 0 | H11: =IFERROR(SampleRevenue[[#Totals],[JUN]]-H10,"") -> 0 | I11: =IFERROR(SampleRevenue[[#Totals],[JUL]]-I10,"") -> 0 | J11: =IFERROR(SampleRevenue[[#Totals],[AUG]]-J10,"") -> 0 | K11: =IFERROR(SampleRevenue[[#Totals],[SEP]]-K10,"") -> 0 | L11: =IFERROR(SampleRevenue[[#Totals],[OCT]]-L10,"") -> 0 | M11: =IFERROR(SampleRevenue[[#Totals],[NOV]]-M10,"") -> 0 | N11: =IFERROR(SampleRevenue[[#Totals],[DEC]]-N10,"") -> 0 | O11: =SUM(C11:N11) -> 0
B13: EXPENSES | C13: JAN | D13: FEB | E13: MAR | F13: APR | G13: MAY | H13: JUN | I13: JUL | J13: AUG | K13: SEP | L13: OCT | M13: NOV | N13: DEC | O13: YTD
B14: Salaries & Wages | C14: 0 | D14: 0 | E14: 0 | F14: 0 | G14: 0 | H14: 0 | I14: 0 | J14: 0 | K14: 0 | L14: 0 | M14: 0 | N14: 0 | O14: =SUM(C14:N14) -> 0
B15: Marketing/Advertising | C15: 0 | D15: 0 | E15: 0 | F15: 0 | G15: 0 | H15: 0 | I15: 0 | J15: 0 | K15: 0 | L15: 0 | M15: 0 | N15: 0 | O15: =SUM(C15:N15) -> 0
B16: Sales Commissions | C16: 0 | D16: 0 | E16: 0 | F16: 0 | G16: 0 | H16: 0 | I16: 0 | J16: 0 | K16: 0 | L16: 0 | M16: 0 | N16: 0 | O16: =SUM(C16:N16) -> 0
B17: Rent | C17: 0 | D17: 0 | E17: 0 | F17: 0 | G17: 0 | H17: 0 | I17: 0 | J17: 0 | K17: 0 | L17: 0 | M17: 0 | N17: 0 | O17: =SUM(C17:N17) -> 0
B18: Other 1 | C18: 0 | D18: 0 | E18: 0 | F18: 0 | G18: 0 | H18: 0 | I18: 0 | J18: 0 | K18: 0 | L18: 0 | M18: 0 | N18: 0 | O18: =SUM(C18:N18) -> 0
B19: Total Expenses | C19: =IF(SUM(C14:C18)=0,"",SUM(C14:C18)) | D19: =IF(SUM(D14:D18)=0,"",SUM(D14:D18)) | E19: =IF(SUM(E14:E18)=0,"",SUM(E14:E18)) | F19: =IF(SUM(F14:F18)=0,"",SUM(F14:F18)) | G19: =IF(SUM(G14:G18)=0,"",SUM(G14:G18)) | H19: =IF(SUM(H14:H18)=0,"",SUM(H14:H18)) | I19: =IF(SUM(I14:I18)=0,"",SUM(I14:I18)) | J19: =IF(SUM(J14:J18)=0,"",SUM(J14:J18)) | ... N19: =IF(SUM(N14:N18)=0,"",SUM(N14:N18)) | O19: =SUM(SampleExpenses[[#Totals],[JAN]:[DEC]]) -> 0
B20: Income Before Taxes | C20: =IFERROR('P&L Template'!$C$11-SampleExpenses[[#Totals],[JAN]],"") | D20: =IFERROR('P&L Template'!$C$11-SampleExpenses[[#Totals],[FEB]],"") | E20: =IFERROR('P&L Template'!$C$11-SampleExpenses[[#Totals],[MAR]],"") | F20: =IFERROR('P&L Template'!$C$11-SampleExpenses[[#Totals],[APR]],"") | G20: =IFERROR('P&L Template'!$C$11-SampleExpenses[[#Totals],[MAY]],"") | H20: =IFERROR('P&L Template'!$C$11-SampleExpenses[[#Totals],[JUN]],"") | I20: =IFERROR('P&L Template'!$C$11-SampleExpenses[[#Totals],[JUL]],"") | J20: =IFERROR('P&L Template'!$C$11-SampleExpenses[[#Totals],[AUG]],"") | K20: =IFERROR('P&L Template'!$C$11-SampleExpenses[[#Totals],[SEP]],"") | L20: =IFERROR('P&L Template'!$C$11-SampleExpenses[[#Totals],[OCT]],"") | M20: =IFERROR('P&L Template'!$C$11-SampleExpenses[[#Totals],[NOV]],"") | N20: =IFERROR('P&L Template'!$C$11-SampleExpenses[[#Totals],[DEC]],"") | O20: =SUM(C20:N20) -> 0
B21: Income Tax Expense | C21: =IFERROR(C20*0.15," ") | D21: =IFERROR(D20*0.15," ") | E21: =IFERROR(E20*0.15," ") | F21: =IFERROR(F20*0.15," ") | G21: =IFERROR(G20*0.15," ") | H21: =IFERROR(H20*0.15," ") | I21: =IFERROR(I20*0.15," ") | J21: =IFERROR(J20*0.15," ") | ... N21: =IFERROR(N20*0.15," ") | O21: =SUM('P&L Template'!$C$21:$N$21) -> 0
B23: NET INCOME | C23: =IFERROR(C20-'P&L Template'!$C$21,"") | D23: =IFERROR(D20-'P&L Template'!$D$21,"") | E23: =IFERROR(E20-'P&L Template'!$E$21,"") | F23: =IFERROR(F20-'P&L Template'!$F$21,"") | G23: =IFERROR(G20-'P&L Template'!$G$21,"") | H23: =IFERROR(H20-'P&L Template'!$H$21,"") | I23: =IFERROR(I20-'P&L Template'!$I$21,"") | J23: =IFERROR(J20-'P&L Template'!$J$21,"") | K23: =IFERROR(K20-'P&L Template'!$K$21,"") | L23: =IFERROR(L20-'P&L Template'!$L$21,"") | M23: =IFERROR(M20-'P&L Template'!$M$21,"") | N23: =IFERROR(N20-'P&L Template'!$N$21,"") | O23: =IFERROR(O20-'P&L Template'!$O$21,"") -> 0

Sheet P&L Example
B1: START-UP COSTS
B2: ='Start-Up Costs Template'!B2 -> YOUR COMPANY NAME | C2: =TODAY() -> 45060
B4: REVENUE | C4: JAN | D4: FEB | E4: MAR | F4: APR | G4: MAY | H4: JUN | I4: JUL | J4: AUG | K4: SEP | L4: OCT | M4: NOV | N4: DEC | O4: YTD
B5: Estimated Product Sales | C5: 5000 | D5: 13000 | E5: 16000 | F5: 7000 | G5: 14500 | H5: 16400 | I5: 22500 | J5: 23125 | K5: 24549 | L5: 22000 | M5: 25000 | N5: 27349 | O5: =SUM(C5:N5) -> 216423
B6: Less Sales Returns & Discounts | C6: 0 | D6: -350 | E6: 0 | F6: -206 | G6: -234 | H6: 0 | I6: 0 | J6: -280 | K6: -1200 | L6: -1600 | M6: 0 | N6: -2400 | O6: =SUM(C6:N6) -> -6270
B7: Service Revenue | C7: 0 | D7: 0 | E7: 0 | F7: 0 | G7: 0 | H7: 250 | I7: 350 | J7: 100 | K7: 0 | L7: 0 | M7: 1245 | N7: 1360 | O7: =SUM(C7:N7) -> 3305
B8: Other Revenue | C8: 0 | D8: 0 | E8: 0 | F8: 0 | G8: 0 | H8: 0 | I8: 0 | J8: 1500 | K8: 0 | L8: 0 | M8: 0 | N8: 0 | O8: =SUM(C8:N8) -> 1500
B9: Net Sales | C9: =SUBTOTAL(109,ActualRevenue[JAN]) -> 5000 | D9: =SUBTOTAL(109,ActualRevenue[FEB]) -> 12650 | E9: =SUBTOTAL(109,ActualRevenue[MAR]) -> 16000 | F9: =SUBTOTAL(109,ActualRevenue[APR]) -> 6794 | G9: =SUBTOTAL(109,ActualRevenue[MAY]) -> 14266 | H9: =SUBTOTAL(109,ActualRevenue[JUN]) -> 16650 | I9: =SUBTOTAL(109,ActualRevenue[JUL]) -> 22850 | J9: =SUBTOTAL(109,ActualRevenue[AUG]) -> 24445 | K9: =SUBTOTAL(109,ActualRevenue[SEP]) -> 23349 | L9: =SUBTOTAL(109,ActualRevenue[OCT]) -> 20400 | M9: =SUBTOTAL(109,ActualRevenue[NOV]) -> 26245 | N9: =SUBTOTAL(109,ActualRevenue[DEC]) -> 26309 | O9: =SUM(ActualRevenue[[#Totals],[JAN]:[DEC]]) -> 214958
B10: Cost of Goods Sold | C10: =C5*0.4 -> 2000 | D10: =D5*0.4 -> 5200 | E10: =E5*0.4 -> 6400 | F10: =F5*0.4 -> 2800 | G10: =G5*0.4 -> 5800 | H10: =H5*0.4 -> 6560 | I10: =I5*0.4 -> 9000 | J10: =J5*0.4 -> 9250 | ... N10: =N5*0.4 -> 10939.6 | O10: =SUM(C10:N10) -> 86569.2
B11: Gross Profit | C11: =IFERROR(ActualRevenue[[#Totals],[JAN]]-C10,"") -> 3000 | D11: =IFERROR(ActualRevenue[[#Totals],[FEB]]-D10,"") -> 7450 | E11: =IFERROR(ActualRevenue[[#Totals],[MAR]]-E10,"") -> 9600 | F11: =IFERROR(ActualRevenue[[#Totals],[APR]]-F10,"") -> 3994 | G11: =IFERROR(ActualRevenue[[#Totals],[MAY]]-G10,"") -> 8466 | H11: =IFERROR(ActualRevenue[[#Totals],[JUN]]-H10,"") -> 10090 | I11: =IFERROR(ActualRevenue[[#Totals],[JUL]]-I10,"") -> 13850 | J11: =IFERROR(ActualRevenue[[#Totals],[AUG]]-J10,"") -> 15195 | K11: =IFERROR(ActualRevenue[[#Totals],[SEP]]-K10,"") -> 13529.4 | L11: =IFERROR(ActualRevenue[[#Totals],[OCT]]-L10,"") -> 11600 | M11: =IFERROR(ActualRevenue[[#Totals],[NOV]]-M10,"") -> 16245 | N11: =IFERROR(ActualRevenue[[#Totals],[DEC]]-N10,"") -> 15369.4 | O11: =SUM(C11:N11) -> 128388.8
B13: EXPENSES | C13: JAN | D13: FEB | E13: MAR | F13: APR | G13: MAY | H13: JUN | I13: JUL | J13: AUG | K13: SEP | L13: OCT | M13: NOV | N13: DEC | O13: YTD
B14: Salaries & Wages | C14: 2500 | D14: 2500 | E14: 3500 | F14: 5000 | G14: 5000 | H14: 5000 | I14: 8000 | J14: 9000 | K14: 9000 | L14: 9000 | M14: 9000 | N14: 9000 | O14: =SUM(C14:N14) -> 76500
B15: Marketing/Advertising | C15: 400 | D15: 450 | E15: 450 | F15: 450 | G15: 900 | H15: 900 | I15: 900 | J15: 900 | K15: 900 | L15: 900 | M15: 1200 | N15: 1200 | O15: =SUM(C15:N15) -> 9550
B16: Sales Commissions | C16: 250 | D16: 650 | E16: 800 | F16: 350 | G16: 725 | H16: 820 | I16: 1125 | J16: 1156.25 | K16: 1227.45 | L16: 1100 | M16: 1250 | N16: 1367.45 | O16: =SUM(C16:N16) -> 10821.15
B17: Rent | C17: 1250 | D17: 1250 | E17: 1250 | F17: 1250 | G17: 1250 | H17: 1250 | I17: 1250 | J17: 1250 | K17: 1250 | L17: 1250 | M17: 1250 | N17: 1250 | O17: =SUM(C17:N17) -> 15000
B18: Total Expenses | C18: =IF(SUM(C14:C17)=0,"",SUM(C14:C17)) -> 4400 | D18: =IF(SUM(D14:D17)=0,"",SUM(D14:D17)) -> 4850 | E18: =IF(SUM(E14:E17)=0,"",SUM(E14:E17)) -> 6000 | F18: =IF(SUM(F14:F17)=0,"",SUM(F14:F17)) -> 7050 | G18: =IF(SUM(G14:G17)=0,"",SUM(G14:G17)) -> 7875 | H18: =IF(SUM(H14:H17)=0,"",SUM(H14:H17)) -> 7970 | I18: =IF(SUM(I14:I17)=0,"",SUM(I14:I17)) -> 11275 | J18: =IF(SUM(J14:J17)=0,"",SUM(J14:J17)) -> 12306.25 | ... N18: =IF(SUM(N14:N17)=0,"",SUM(N14:N17)) -> 12817.45 | O18: =SUM(ActualExpenses[[#Totals],[JAN]:[DEC]]) -> 111871.15
B19: Income Before Taxes | C19: =IFERROR('P&L Example'!$C$11-ActualExpenses[[#Totals],[JAN]],"") -> -1400 | D19: =IFERROR('P&L Example'!$D$11-ActualExpenses[[#Totals],[FEB]],"") -> 2600 | E19: =IFERROR('P&L Example'!$E$11-ActualExpenses[[#Totals],[MAR]],"") -> 3600 | F19: =IFERROR('P&L Example'!$F$11-ActualExpenses[[#Totals],[APR]],"") -> -3056 | G19: =IFERROR('P&L Example'!$G$11-ActualExpenses[[#Totals],[MAY]],"") -> 591 | H19: =IFERROR('P&L Example'!$H$11-ActualExpenses[[#Totals],[JUN]],"") -> 2120 | I19: =IFERROR('P&L Example'!$I$11-ActualExpenses[[#Totals],[JUL]],"") -> 2575 | J19: =IFERROR('P&L Example'!$J$11-ActualExpenses[[#Totals],[AUG]],"") -> 2888.75 | K19: =IFERROR('P&L Example'!$K$11-ActualExpenses[[#Totals],[SEP]],"") -> 1151.95 | L19: =IFERROR('P&L Example'!$L$11-ActualExpenses[[#Totals],[OCT]],"") -> -650 | M19: =IFERROR('P&L Example'!$M$11-ActualExpenses[[#Totals],[NOV]],"") -> 3545 | N19: =IFERROR('P&L Example'!$N$11-ActualExpenses[[#Totals],[DEC]],"") -> 2551.95 | O19: =SUM(C19:N19) -> 16517.65
B20: Income Tax Expense | C20: =C19*0.15 -> -210 | D20: =D19*0.15 -> 390 | E20: =E19*0.15 -> 540 | F20: =F19*0.15 -> -458.4 | G20: =G19*0.15 -> 88.65 | H20: =H19*0.15 -> 318 | I20: =I19*0.15 -> 386.25 | J20: =J19*0.15 -> 433.3125 | ... N20: =N19*0.15 -> 382.7925 | O20: =SUM('P&L Example'!$C$20:$N$20) -> 2477.6475
B22: NET INCOME | C22: =IFERROR(C19-'P&L Example'!$C$20," ") -> -1190 | D22: =IFERROR(D19-'P&L Example'!$D$20," ") -> 2210 | E22: =IFERROR(E19-'P&L Example'!$E$20,"") -> 3060 | F22: =IFERROR(F19-'P&L Example'!$F$20,"") -> -2597.6 | G22: =IFERROR(G19-'P&L Example'!$G$20,"") -> 502.35 | H22: =IFERROR(H19-'P&L Example'!$H$20,"") -> 1802 | I22: =IFERROR(I19-'P&L Example'!$I$20,"") -> 2188.75 | J22: =IFERROR(J19-'P&L Example'!$J$20,"") -> 2455.4375 | K22: =IFERROR(K19-'P&L Example'!$K$20,"") -> 979.1575 | L22: =IFERROR(L19-'P&L Example'!$L$20,"") -> -552.5 | M22: =IFERROR(M19-'P&L Example'!$M$20,"") -> 3013.25 | N22: =IFERROR(N19-'P&L Example'!$N$20,"") -> 2169.1575 | O22: =IFERROR(O19-'P&L Example'!$O$20,"") -> 14040.002
