Workbook
Name ColumnTitle1: [1]!Expense[[#Headers],[Date]]
Name Company_Name: 'Revenues (Sales)'!$B$1
Name FYMonthStart: 'Revenues (Sales)'!$F$2
Name FYStartYear: 'Revenues (Sales)'!$G$2
Name Mileage_Total: [1]!Expense[[#Totals],[Mileage]]
Name Projection_Period_Title: 'Revenues (Sales)'!$B$2
Name Reimbursement_Total: [1]!Expense[[#Totals],[Reimbursement]]
Name Title1: Revenue[[#Headers],[REVENUES (SALES)]]
Name Title2: CostofSales[[#Headers],[COST OF SALES]]
Name Title3: tblExpenses[[#Headers],[EXPENSES]]
Name Wksht_Title: 'Revenues (Sales)'!$B$3

Sheet Revenues (Sales)
B1: Company Name
B2: Twelve Month | E2: Fiscal Year Begins: | F2: JAN | G2: =YEAR(TODAY()) -> 2023
B3: Profit & Loss Projection
D5: =UPPER(TEXT(DATE(FYStartYear,FYMonthNo,1),"mmm-yy")) -> JAN-23 | E5: =UPPER(TEXT(DATE(FYStartYear,FYMonthNo+1,1),"mmm-yy")) -> FEB-23 | F5: =UPPER(TEXT(DATE(FYStartYear,FYMonthNo+2,1),"mmm-yy")) -> MAR-23 | G5: =UPPER(TEXT(DATE(FYStartYear,FYMonthNo+3,1),"mmm-yy")) -> APR-23 | H5: =UPPER(TEXT(DATE(FYStartYear,FYMonthNo+4,1),"mmm-yy")) -> MAY-23 | I5: =UPPER(TEXT(DATE(FYStartYear,FYMonthNo+5,1),"mmm-yy")) -> JUN-23 | J5: =UPPER(TEXT(DATE(FYStartYear,FYMonthNo+6,1),"mmm-yy")) -> JUL-23 | K5: =UPPER(TEXT(DATE(FYStartYear,FYMonthNo+7,1),"mmm-yy")) -> AUG-23 | L5: =UPPER(TEXT(DATE(FYStartYear,FYMonthNo+8,1),"mmm-yy")) -> SEP-23 | M5: =UPPER(TEXT(DATE(FYStartYear,FYMonthNo+9,1),"mmm-yy")) -> OCT-23 | N5: =UPPER(TEXT(DATE(FYStartYear,FYMonthNo+10,1),"mmm-yy")) -> NOV-23 | O5: =UPPER(TEXT(DATE(FYStartYear,FYMonthNo+11,1),"mmm-yy")) -> DEC-23 | P5: YEARLY | Q5: IND % | R5: =LEFT(D5,3)&" %" -> JAN % | S5: =LEFT(E5,3)&" %" -> FEB % | T5: =LEFT(F5,3)&" %" -> MAR % | U5: =LEFT(G5,3)&" %" -> APR % | V5: =LEFT(H5,3)&" %" -> MAY % | W5: =LEFT(I5,3)&" %" -> JUN % | X5: =LEFT(J5,3)&" %" -> JUL % | Y5: =LEFT(K5,3)&" %" -> AUG % | ... AC5: =LEFT(O5,3)&" %" -> DEC % | AD5: YEAR %
B6: REVENUES (SALES) | C6: TREND | D6: Jan | E6: Feb | F6: Mar | G6: Apr | H6: May | I6: Jun | J6: Jul | K6: Aug | L6: Sep | M6: Oct | N6: Nov | O6: Dec | P6: Yearly | Q6: Index % | R6: Jan % | S6: Feb % | T6: Mar % | U6: Apr % | V6: May % | W6: Jun % | X6: Jul % | Y6: Aug % | Z6: Sep % | AA6: Oct % | AB6: Nov % | AC6: Dec % | AD6: Year %
B7: Revenue 1 | D7: 186 | E7: 108 | F7: 92 | G7: 122 | H7: 190 | I7: 71 | J7: 21 | K7: 37 | L7: 24 | M7: 178 | N7: 92 | O7: 97 | P7: =SUM(Revenue[[#This Row],[Jan]:[Dec]]) -> 1218 | Q7: 0.12 | R7: =IFERROR(Revenue[[#This Row],[Jan]]/Revenue[[#Totals],[Jan]],"-") -> 0.29807692 | S7: =IFERROR(Revenue[[#This Row],[Feb]]/Revenue[[#Totals],[Feb]],"-") -> 0.14673913 | T7: =IFERROR(Revenue[[#This Row],[Mar]]/Revenue[[#Totals],[Mar]],"-") -> 0.11219512 | U7: =IFERROR(Revenue[[#This Row],[Apr]]/Revenue[[#Totals],[Apr]],"-") -> 0.19967267 | V7: =IFERROR(Revenue[[#This Row],[May]]/Revenue[[#Totals],[May]],"-") -> 0.23399015 | W7: =IFERROR(Revenue[[#This Row],[Jun]]/Revenue[[#Totals],[Jun]],"-") -> 0.12283737 | X7: =IFERROR(Revenue[[#This Row],[Jul]]/Revenue[[#Totals],[Jul]],"-") -> 0.035175879 | Y7: =IFERROR(Revenue[[#This Row],[Aug]]/Revenue[[#Totals],[Aug]],"-") -> 0.054814815 | Z7: =IFERROR(Revenue[[#This Row],[Sep]]/Revenue[[#Totals],[Sep]],"-") -> 0.032258065 | AA7: =IFERROR(Revenue[[#This Row],[Oct]]/Revenue[[#Totals],[Oct]],"-") -> 0.26138032 | AB7: =IFERROR(Revenue[[#This Row],[Nov]]/Revenue[[#Totals],[Nov]],"-") -> 0.12449256 | AC7: =IFERROR(Revenue[[#This Row],[Dec]]/Revenue[[#Totals],[Dec]],"-") -> 0.093000959 | AD7: =IFERROR(Revenue[[#This Row],[Yearly]]/Revenue[[#Totals],[Yearly]],"-") -> 0.14064665
B8: Revenue 2 | D8: 15 | E8: 16 | F8: 198 | G8: 44 | H8: 25 | I8: 68 | J8: 43 | K8: 119 | L8: 37 | M8: 118 | N8: 29 | O8: 171 | P8: =SUM(Revenue[[#This Row],[Jan]:[Dec]]) -> 883 | Q8: 0.18 | R8: =IFERROR(Revenue[[#This Row],[Jan]]/Revenue[[#Totals],[Jan]],"-") -> 0.024038462 | S8: =IFERROR(Revenue[[#This Row],[Feb]]/Revenue[[#Totals],[Feb]],"-") -> 0.02173913 | T8: =IFERROR(Revenue[[#This Row],[Mar]]/Revenue[[#Totals],[Mar]],"-") -> 0.24146341 | U8: =IFERROR(Revenue[[#This Row],[Apr]]/Revenue[[#Totals],[Apr]],"-") -> 0.072013093 | V8: =IFERROR(Revenue[[#This Row],[May]]/Revenue[[#Totals],[May]],"-") -> 0.030788177 | W8: =IFERROR(Revenue[[#This Row],[Jun]]/Revenue[[#Totals],[Jun]],"-") -> 0.11764706 | X8: =IFERROR(Revenue[[#This Row],[Jul]]/Revenue[[#Totals],[Jul]],"-") -> 0.072026801 | Y8: =IFERROR(Revenue[[#This Row],[Aug]]/Revenue[[#Totals],[Aug]],"-") -> 0.1762963 | Z8: =IFERROR(Revenue[[#This Row],[Sep]]/Revenue[[#Totals],[Sep]],"-") -> 0.049731183 | AA8: =IFERROR(Revenue[[#This Row],[Oct]]/Revenue[[#Totals],[Oct]],"-") -> 0.1732746 | AB8: =IFERROR(Revenue[[#This Row],[Nov]]/Revenue[[#Totals],[Nov]],"-") -> 0.039242219 | AC8: =IFERROR(Revenue[[#This Row],[Dec]]/Revenue[[#Totals],[Dec]],"-") -> 0.16395014 | AD8: =IFERROR(Revenue[[#This Row],[Yearly]]/Revenue[[#Totals],[Yearly]],"-") -> 0.10196305
B9: Revenue 3 | D9: 166 | E9: 185 | F9: 89 | G9: 170 | H9: 131 | I9: 70 | J9: 50 | K9: 149 | L9: 179 | M9: 104 | N9: 119 | O9: 187 | P9: =SUM(Revenue[[#This Row],[Jan]:[Dec]]) -> 1599 | Q9: 0.19 | R9: =IFERROR(Revenue[[#This Row],[Jan]]/Revenue[[#Totals],[Jan]],"-") -> 0.26602564 | S9: =IFERROR(Revenue[[#This Row],[Feb]]/Revenue[[#Totals],[Feb]],"-") -> 0.2513587 | T9: =IFERROR(Revenue[[#This Row],[Mar]]/Revenue[[#Totals],[Mar]],"-") -> 0.10853659 | U9: =IFERROR(Revenue[[#This Row],[Apr]]/Revenue[[#Totals],[Apr]],"-") -> 0.27823241 | V9: =IFERROR(Revenue[[#This Row],[May]]/Revenue[[#Totals],[May]],"-") -> 0.16133005 | W9: =IFERROR(Revenue[[#This Row],[Jun]]/Revenue[[#Totals],[Jun]],"-") -> 0.12110727 | X9: =IFERROR(Revenue[[#This Row],[Jul]]/Revenue[[#Totals],[Jul]],"-") -> 0.083752094 | Y9: =IFERROR(Revenue[[#This Row],[Aug]]/Revenue[[#Totals],[Aug]],"-") -> 0.22074074 | Z9: =IFERROR(Revenue[[#This Row],[Sep]]/Revenue[[#Totals],[Sep]],"-") -> 0.2405914 | AA9: =IFERROR(Revenue[[#This Row],[Oct]]/Revenue[[#Totals],[Oct]],"-") -> 0.15271659 | AB9: =IFERROR(Revenue[[#This Row],[Nov]]/Revenue[[#Totals],[Nov]],"-") -> 0.16102842 | AC9: =IFERROR(Revenue[[#This Row],[Dec]]/Revenue[[#Totals],[Dec]],"-") -> 0.17929051 | AD9: =IFERROR(Revenue[[#This Row],[Yearly]]/Revenue[[#Totals],[Yearly]],"-") -> 0.18464203
B10: Revenue 4 | D10: 21 | E10: 113 | F10: 83 | G10: 17 | H10: 130 | I10: 26 | J10: 167 | K10: 102 | L10: 82 | M10: 33 | N10: 88 | O10: 193 | P10: =SUM(Revenue[[#This Row],[Jan]:[Dec]]) -> 1055 | Q10: 0.11 | R10: =IFERROR(Revenue[[#This Row],[Jan]]/Revenue[[#Totals],[Jan]],"-") -> 0.033653846 | S10: =IFERROR(Revenue[[#This Row],[Feb]]/Revenue[[#Totals],[Feb]],"-") -> 0.15353261 | T10: =IFERROR(Revenue[[#This Row],[Mar]]/Revenue[[#Totals],[Mar]],"-") -> 0.10121951 | U10: =IFERROR(Revenue[[#This Row],[Apr]]/Revenue[[#Totals],[Apr]],"-") -> 0.027823241 | V10: =IFERROR(Revenue[[#This Row],[May]]/Revenue[[#Totals],[May]],"-") -> 0.16009852 | W10: =IFERROR(Revenue[[#This Row],[Jun]]/Revenue[[#Totals],[Jun]],"-") -> 0.044982699 | X10: =IFERROR(Revenue[[#This Row],[Jul]]/Revenue[[#Totals],[Jul]],"-") -> 0.27973199 | Y10: =IFERROR(Revenue[[#This Row],[Aug]]/Revenue[[#Totals],[Aug]],"-") -> 0.15111111 | Z10: =IFERROR(Revenue[[#This Row],[Sep]]/Revenue[[#Totals],[Sep]],"-") -> 0.11021505 | AA10: =IFERROR(Revenue[[#This Row],[Oct]]/Revenue[[#Totals],[Oct]],"-") -> 0.04845815 | AB10: =IFERROR(Revenue[[#This Row],[Nov]]/Revenue[[#Totals],[Nov]],"-") -> 0.11907984 | AC10: =IFERROR(Revenue[[#This Row],[Dec]]/Revenue[[#Totals],[Dec]],"-") -> 0.18504314 | AD10: =IFERROR(Revenue[[#This Row],[Yearly]]/Revenue[[#Totals],[Yearly]],"-") -> 0.12182448
B11: Revenue 5 | D11: 70 | E11: 160 | F11: 125 | G11: 84 | H11: 191 | I11: 97 | J11: 52 | K11: 45 | L11: 173 | M11: 136 | N11: 144 | O11: 167 | P11: =SUM(Revenue[[#This Row],[Jan]:[Dec]]) -> 1444 | Q11: 0.2 | R11: =IFERROR(Revenue[[#This Row],[Jan]]/Revenue[[#Totals],[Jan]],"-") -> 0.11217949 | S11: =IFERROR(Revenue[[#This Row],[Feb]]/Revenue[[#Totals],[Feb]],"-") -> 0.2173913 | T11: =IFERROR(Revenue[[#This Row],[Mar]]/Revenue[[#Totals],[Mar]],"-") -> 0.15243902 | U11: =IFERROR(Revenue[[#This Row],[Apr]]/Revenue[[#Totals],[Apr]],"-") -> 0.13747954 | V11: =IFERROR(Revenue[[#This Row],[May]]/Revenue[[#Totals],[May]],"-") -> 0.23522167 | W11: =IFERROR(Revenue[[#This Row],[Jun]]/Revenue[[#Totals],[Jun]],"-") -> 0.16782007 | X11: =IFERROR(Revenue[[#This Row],[Jul]]/Revenue[[#Totals],[Jul]],"-") -> 0.087102178 | Y11: =IFERROR(Revenue[[#This Row],[Aug]]/Revenue[[#Totals],[Aug]],"-") -> 0.066666667 | Z11: =IFERROR(Revenue[[#This Row],[Sep]]/Revenue[[#Totals],[Sep]],"-") -> 0.23252688 | AA11: =IFERROR(Revenue[[#This Row],[Oct]]/Revenue[[#Totals],[Oct]],"-") -> 0.19970631 | AB11: =IFERROR(Revenue[[#This Row],[Nov]]/Revenue[[#Totals],[Nov]],"-") -> 0.19485792 | AC11: =IFERROR(Revenue[[#This Row],[Dec]]/Revenue[[#Totals],[Dec]],"-") -> 0.16011505 | AD11: =IFERROR(Revenue[[#This Row],[Yearly]]/Revenue[[#Totals],[Yearly]],"-") -> 0.16674365
B12: Revenue 6 | D12: 61 | E12: 99 | F12: 70 | G12: 162 | H12: 28 | I12: 163 | J12: 101 | K12: 103 | L12: 78 | M12: 33 | N12: 162 | O12: 159 | P12: =SUM(Revenue[[#This Row],[Jan]:[Dec]]) -> 1219 | Q12: 0.1 | R12: =IFERROR(Revenue[[#This Row],[Jan]]/Revenue[[#Totals],[Jan]],"-") -> 0.09775641 | S12: =IFERROR(Revenue[[#This Row],[Feb]]/Revenue[[#Totals],[Feb]],"-") -> 0.13451087 | T12: =IFERROR(Revenue[[#This Row],[Mar]]/Revenue[[#Totals],[Mar]],"-") -> 0.085365854 | U12: =IFERROR(Revenue[[#This Row],[Apr]]/Revenue[[#Totals],[Apr]],"-") -> 0.26513912 | V12: =IFERROR(Revenue[[#This Row],[May]]/Revenue[[#Totals],[May]],"-") -> 0.034482759 | W12: =IFERROR(Revenue[[#This Row],[Jun]]/Revenue[[#Totals],[Jun]],"-") -> 0.28200692 | X12: =IFERROR(Revenue[[#This Row],[Jul]]/Revenue[[#Totals],[Jul]],"-") -> 0.16917923 | Y12: =IFERROR(Revenue[[#This Row],[Aug]]/Revenue[[#Totals],[Aug]],"-") -> 0.15259259 | Z12: =IFERROR(Revenue[[#This Row],[Sep]]/Revenue[[#Totals],[Sep]],"-") -> 0.10483871 | AA12: =IFERROR(Revenue[[#This Row],[Oct]]/Revenue[[#Totals],[Oct]],"-") -> 0.04845815 | AB12: =IFERROR(Revenue[[#This Row],[Nov]]/Revenue[[#Totals],[Nov]],"-") -> 0.21921516 | AC12: =IFERROR(Revenue[[#This Row],[Dec]]/Revenue[[#Totals],[Dec]],"-") -> 0.15244487 | AD12: =IFERROR(Revenue[[#This Row],[Yearly]]/Revenue[[#Totals],[Yearly]],"-") -> 0.14076212
B13: Revenue 7 | D13: 105 | E13: 55 | F13: 163 | G13: 12 | H13: 117 | I13: 83 | J13: 163 | K13: 120 | L13: 171 | M13: 79 | N13: 105 | O13: 69 | P13: =SUM(Revenue[[#This Row],[Jan]:[Dec]]) -> 1242 | Q13: 0.1 | R13: =IFERROR(Revenue[[#This Row],[Jan]]/Revenue[[#Totals],[Jan]],"-") -> 0.16826923 | S13: =IFERROR(Revenue[[#This Row],[Feb]]/Revenue[[#Totals],[Feb]],"-") -> 0.074728261 | T13: =IFERROR(Revenue[[#This Row],[Mar]]/Revenue[[#Totals],[Mar]],"-") -> 0.19878049 | U13: =IFERROR(Revenue[[#This Row],[Apr]]/Revenue[[#Totals],[Apr]],"-") -> 0.019639935 | V13: =IFERROR(Revenue[[#This Row],[May]]/Revenue[[#Totals],[May]],"-") -> 0.14408867 | W13: =IFERROR(Revenue[[#This Row],[Jun]]/Revenue[[#Totals],[Jun]],"-") -> 0.14359862 | X13: =IFERROR(Revenue[[#This Row],[Jul]]/Revenue[[#Totals],[Jul]],"-") -> 0.27303183 | Y13: =IFERROR(Revenue[[#This Row],[Aug]]/Revenue[[#Totals],[Aug]],"-") -> 0.17777778 | Z13: =IFERROR(Revenue[[#This Row],[Sep]]/Revenue[[#Totals],[Sep]],"-") -> 0.22983871 | AA13: =IFERROR(Revenue[[#This Row],[Oct]]/Revenue[[#Totals],[Oct]],"-") -> 0.11600587 | AB13: =IFERROR(Revenue[[#This Row],[Nov]]/Revenue[[#Totals],[Nov]],"-") -> 0.1420839 | AC13: =IFERROR(Revenue[[#This Row],[Dec]]/Revenue[[#Totals],[Dec]],"-") -> 0.066155321 | AD13: =IFERROR(Revenue[[#This Row],[Yearly]]/Revenue[[#Totals],[Yearly]],"-") -> 0.14341801
B14: TOTAL SALES | D14: =SUBTOTAL(109,Revenue[Jan]) -> 624 | E14: =SUBTOTAL(109,Revenue[Feb]) -> 736 | F14: =SUBTOTAL(109,Revenue[Mar]) -> 820 | G14: =SUBTOTAL(109,Revenue[Apr]) -> 611 | H14: =SUBTOTAL(109,Revenue[May]) -> 812 | I14: =SUBTOTAL(109,Revenue[Jun]) -> 578 | J14: =SUBTOTAL(109,Revenue[Jul]) -> 597 | K14: =SUBTOTAL(109,Revenue[Aug]) -> 675 | L14: =SUBTOTAL(109,Revenue[Sep]) -> 744 | M14: =SUBTOTAL(109,Revenue[Oct]) -> 681 | N14: =SUBTOTAL(109,Revenue[Nov]) -> 739 | O14: =SUBTOTAL(109,Revenue[Dec]) -> 1043 | P14: =SUBTOTAL(109,Revenue[Yearly]) -> 8660 | Q14: =SUBTOTAL(109,Revenue[Index %]) -> 1 | R14: =SUBTOTAL(109,Revenue[Jan %]) -> 1 | S14: =SUBTOTAL(109,Revenue[Feb %]) -> 1 | T14: =SUBTOTAL(109,Revenue[Mar %]) -> 1 | U14: =SUBTOTAL(109,Revenue[Apr %]) -> 1 | V14: =SUBTOTAL(109,Revenue[May %]) -> 1 | W14: =SUBTOTAL(109,Revenue[Jun %]) -> 1 | X14: =SUBTOTAL(109,Revenue[Jul %]) -> 1 | Y14: =SUBTOTAL(109,Revenue[Aug %]) -> 1 | Z14: =SUBTOTAL(109,Revenue[Sep %]) -> 1 | AA14: =SUBTOTAL(109,Revenue[Oct %]) -> 1 | AB14: =SUBTOTAL(109,Revenue[Nov %]) -> 1 | AC14: =SUBTOTAL(109,Revenue[Dec %]) -> 1 | AD14: =SUBTOTAL(109,Revenue[Year %]) -> 1

Sheet Cost of Sales
B1: =Company_Name -> Company Name
B2: =Projection_Period_Title -> Twelve Month | E2: Fiscal Year: | F2: =FYMonthStart -> JAN | G2: =FYStartYear -> 2023
B3: =Wksht_Title -> Profit & Loss Projection
D5: =UPPER(TEXT(DATE(FYStartYear,FYMonthNo,1),"mmm-yy")) -> JAN-23 | E5: =UPPER(TEXT(DATE(FYStartYear,FYMonthNo+1,1),"mmm-yy")) -> FEB-23 | F5: =UPPER(TEXT(DATE(FYStartYear,FYMonthNo+2,1),"mmm-yy")) -> MAR-23 | G5: =UPPER(TEXT(DATE(FYStartYear,FYMonthNo+3,1),"mmm-yy")) -> APR-23 | H5: =UPPER(TEXT(DATE(FYStartYear,FYMonthNo+4,1),"mmm-yy")) -> MAY-23 | I5: =UPPER(TEXT(DATE(FYStartYear,FYMonthNo+5,1),"mmm-yy")) -> JUN-23 | J5: =UPPER(TEXT(DATE(FYStartYear,FYMonthNo+6,1),"mmm-yy")) -> JUL-23 | K5: =UPPER(TEXT(DATE(FYStartYear,FYMonthNo+7,1),"mmm-yy")) -> AUG-23 | L5: =UPPER(TEXT(DATE(FYStartYear,FYMonthNo+8,1),"mmm-yy")) -> SEP-23 | M5: =UPPER(TEXT(DATE(FYStartYear,FYMonthNo+9,1),"mmm-yy")) -> OCT-23 | N5: =UPPER(TEXT(DATE(FYStartYear,FYMonthNo+10,1),"mmm-yy")) -> NOV-23 | O5: =UPPER(TEXT(DATE(FYStartYear,FYMonthNo+11,1),"mmm-yy")) -> DEC-23 | P5: YEARLY | Q5: IND % | R5: =LEFT(D5,3)&" %" -> JAN % | S5: =LEFT(E5,3)&" %" -> FEB % | T5: =LEFT(F5,3)&" %" -> MAR % | U5: =LEFT(G5,3)&" %" -> APR % | V5: =LEFT(H5,3)&" %" -> MAY % | W5: =LEFT(I5,3)&" %" -> JUN % | X5: =LEFT(J5,3)&" %" -> JUL % | Y5: =LEFT(K5,3)&" %" -> AUG % | ... AC5: =LEFT(O5,3)&" %" -> DEC % | AD5: YEAR %
B6: COST OF SALES | C6: TREND | D6: Jan | E6: Feb | F6: Mar | G6: Apr | H6: May | I6: Jun | J6: Jul | K6: Aug | L6: Sep | M6: Oct | N6: Nov | O6: Dec | P6: Yearly | Q6: Index % | R6: Jan % | S6: Feb % | T6: Mar % | U6: Apr % | V6: May % | W6: Jun % | X6: Jul % | Y6: Aug % | Z6: Sep % | AA6: Oct % | AB6: Nov % | AC6: Dec % | AD6: Year %
B7: Cost 1 | D7: 61 | E7: 78 | F7: 65 | G7: 29 | H7: 125 | I7: 49 | J7: 14 | K7: 26 | L7: 14 | M7: 129 | N7: 60 | O7: 65 | P7: =SUM(CostofSales[[#This Row],[Jan]:[Dec]]) -> 715 | Q7: 0.12 | R7: =IFERROR(CostofSales[[#This Row],[Jan]]/CostofSales[[#Totals],[Jan]],"-") -> 0.23018868 | S7: =IFERROR(CostofSales[[#This Row],[Feb]]/CostofSales[[#Totals],[Feb]],"-") -> 0.21910112 | T7: =IFERROR(CostofSales[[#This Row],[Mar]]/CostofSales[[#Totals],[Mar]],"-") -> 0.20634921 | U7: =IFERROR(CostofSales[[#This Row],[Apr]]/CostofSales[[#Totals],[Apr]],"-") -> 0.12033195 | V7: =IFERROR(CostofSales[[#This Row],[May]]/CostofSales[[#Totals],[May]],"-") -> 0.31328321 | W7: =IFERROR(CostofSales[[#This Row],[Jun]]/CostofSales[[#Totals],[Jun]],"-") -> 0.15705128 | X7: =IFERROR(CostofSales[[#This Row],[Jul]]/CostofSales[[#Totals],[Jul]],"-") -> 0.046822742 | Y7: =IFERROR(CostofSales[[#This Row],[Aug]]/CostofSales[[#Totals],[Aug]],"-") -> 0.11504425 | Z7: =IFERROR(CostofSales[[#This Row],[Sep]]/CostofSales[[#Totals],[Sep]],"-") -> 0.033816425 | AA7: =IFERROR(CostofSales[[#This Row],[Oct]]/CostofSales[[#Totals],[Oct]],"-") -> 0.47080292 | AB7: =IFERROR(CostofSales[[#This Row],[Nov]]/CostofSales[[#Totals],[Nov]],"-") -> 0.22727273 | AC7: =IFERROR(CostofSales[[#This Row],[Dec]]/CostofSales[[#Totals],[Dec]],"-") -> 0.14348786 | AD7: =IFERROR(CostofSales[[#This Row],[Yearly]]/CostofSales[[#Totals],[Yearly]],"-") -> 0.18727082
B8: Cost 2 | D8: 7 | E8: 5 | F8: 69 | G8: 32 | H8: 11 | I8: 30 | J8: 27 | K8: 32 | L8: 10 | M8: 41 | N8: 13 | O8: 105 | P8: =SUM(CostofSales[[#This Row],[Jan]:[Dec]]) -> 382 | Q8: 0.18 | R8: =IFERROR(CostofSales[[#This Row],[Jan]]/CostofSales[[#Totals],[Jan]],"-") -> 0.026415094 | S8: =IFERROR(CostofSales[[#This Row],[Feb]]/CostofSales[[#Totals],[Feb]],"-") -> 0.014044944 | T8: =IFERROR(CostofSales[[#This Row],[Mar]]/CostofSales[[#Totals],[Mar]],"-") -> 0.21904762 | U8: =IFERROR(CostofSales[[#This Row],[Apr]]/CostofSales[[#Totals],[Apr]],"-") -> 0.13278008 | V8: =IFERROR(CostofSales[[#This Row],[May]]/CostofSales[[#Totals],[May]],"-") -> 0.027568922 | W8: =IFERROR(CostofSales[[#This Row],[Jun]]/CostofSales[[#Totals],[Jun]],"-") -> 0.096153846 | X8: =IFERROR(CostofSales[[#This Row],[Jul]]/CostofSales[[#Totals],[Jul]],"-") -> 0.090301003 | Y8: =IFERROR(CostofSales[[#This Row],[Aug]]/CostofSales[[#Totals],[Aug]],"-") -> 0.14159292 | Z8: =IFERROR(CostofSales[[#This Row],[Sep]]/CostofSales[[#Totals],[Sep]],"-") -> 0.024154589 | AA8: =IFERROR(CostofSales[[#This Row],[Oct]]/CostofSales[[#Totals],[Oct]],"-") -> 0.14963504 | AB8: =IFERROR(CostofSales[[#This Row],[Nov]]/CostofSales[[#Totals],[Nov]],"-") -> 0.049242424 | AC8: =IFERROR(CostofSales[[#This Row],[Dec]]/CostofSales[[#Totals],[Dec]],"-") -> 0.23178808 | AD8: =IFERROR(CostofSales[[#This Row],[Yearly]]/CostofSales[[#Totals],[Yearly]],"-") -> 0.10005238
B9: Cost 3 | D9: 99 | E9: 95 | F9: 51 | G9: 90 | H9: 21 | I9: 34 | J9: 30 | K9: 24 | L9: 109 | M9: 16 | N9: 21 | O9: 52 | P9: =SUM(CostofSales[[#This Row],[Jan]:[Dec]]) -> 642 | Q9: 0.19 | R9: =IFERROR(CostofSales[[#This Row],[Jan]]/CostofSales[[#Totals],[Jan]],"-") -> 0.37358491 | S9: =IFERROR(CostofSales[[#This Row],[Feb]]/CostofSales[[#Totals],[Feb]],"-") -> 0.26685393 | T9: =IFERROR(CostofSales[[#This Row],[Mar]]/CostofSales[[#Totals],[Mar]],"-") -> 0.16190476 | U9: =IFERROR(CostofSales[[#This Row],[Apr]]/CostofSales[[#Totals],[Apr]],"-") -> 0.37344398 | V9: =IFERROR(CostofSales[[#This Row],[May]]/CostofSales[[#Totals],[May]],"-") -> 0.052631579 | W9: =IFERROR(CostofSales[[#This Row],[Jun]]/CostofSales[[#Totals],[Jun]],"-") -> 0.10897436 | X9: =IFERROR(CostofSales[[#This Row],[Jul]]/CostofSales[[#Totals],[Jul]],"-") -> 0.10033445 | Y9: =IFERROR(CostofSales[[#This Row],[Aug]]/CostofSales[[#Totals],[Aug]],"-") -> 0.10619469 | Z9: =IFERROR(CostofSales[[#This Row],[Sep]]/CostofSales[[#Totals],[Sep]],"-") -> 0.26328502 | AA9: =IFERROR(CostofSales[[#This Row],[Oct]]/CostofSales[[#Totals],[Oct]],"-") -> 0.058394161 | AB9: =IFERROR(CostofSales[[#This Row],[Nov]]/CostofSales[[#Totals],[Nov]],"-") -> 0.079545455 | AC9: =IFERROR(CostofSales[[#This Row],[Dec]]/CostofSales[[#Totals],[Dec]],"-") -> 0.11479029 | AD9: =IFERROR(CostofSales[[#This Row],[Yearly]]/CostofSales[[#Totals],[Yearly]],"-") -> 0.16815086
B10: Cost 4 | D10: 13 | E10: 28 | F10: 15 | G10: 8 | H10: 84 | I10: 12 | J10: 54 | K10: 72 | L10: 49 | M10: 24 | N10: 60 | O10: 39 | P10: =SUM(CostofSales[[#This Row],[Jan]:[Dec]]) -> 458 | Q10: 0.11 | R10: =IFERROR(CostofSales[[#This Row],[Jan]]/CostofSales[[#Totals],[Jan]],"-") -> 0.049056604 | S10: =IFERROR(CostofSales[[#This Row],[Feb]]/CostofSales[[#Totals],[Feb]],"-") -> 0.078651685 | T10: =IFERROR(CostofSales[[#This Row],[Mar]]/CostofSales[[#Totals],[Mar]],"-") -> 0.047619048 | U10: =IFERROR(CostofSales[[#This Row],[Apr]]/CostofSales[[#Totals],[Apr]],"-") -> 0.033195021 | V10: =IFERROR(CostofSales[[#This Row],[May]]/CostofSales[[#Totals],[May]],"-") -> 0.21052632 | W10: =IFERROR(CostofSales[[#This Row],[Jun]]/CostofSales[[#Totals],[Jun]],"-") -> 0.038461538 | X10: =IFERROR(CostofSales[[#This Row],[Jul]]/CostofSales[[#Totals],[Jul]],"-") -> 0.18060201 | Y10: =IFERROR(CostofSales[[#This Row],[Aug]]/CostofSales[[#Totals],[Aug]],"-") -> 0.31858407 | Z10: =IFERROR(CostofSales[[#This Row],[Sep]]/CostofSales[[#Totals],[Sep]],"-") -> 0.11835749 | AA10: =IFERROR(CostofSales[[#This Row],[Oct]]/CostofSales[[#Totals],[Oct]],"-") -> 0.087591241 | AB10: =IFERROR(CostofSales[[#This Row],[Nov]]/CostofSales[[#Totals],[Nov]],"-") -> 0.22727273 | AC10: =IFERROR(CostofSales[[#This Row],[Dec]]/CostofSales[[#Totals],[Dec]],"-") -> 0.086092715 | AD10: =IFERROR(CostofSales[[#This Row],[Yearly]]/CostofSales[[#Totals],[Yearly]],"-") -> 0.11995809
B11: Cost 5 | D11: 34 | E11: 78 | F11: 43 | G11: 30 | H11: 77 | I11: 54 | J11: 26 | K11: 13 | L11: 56 | M11: 30 | N11: 40 | O11: 63 | P11: =SUM(CostofSales[[#This Row],[Jan]:[Dec]]) -> 544 | Q11: 0.2 | R11: =IFERROR(CostofSales[[#This Row],[Jan]]/CostofSales[[#Totals],[Jan]],"-") -> 0.12830189 | S11: =IFERROR(CostofSales[[#This Row],[Feb]]/CostofSales[[#Totals],[Feb]],"-") -> 0.21910112 | T11: =IFERROR(CostofSales[[#This Row],[Mar]]/CostofSales[[#Totals],[Mar]],"-") -> 0.13650794 | U11: =IFERROR(CostofSales[[#This Row],[Apr]]/CostofSales[[#Totals],[Apr]],"-") -> 0.12448133 | V11: =IFERROR(CostofSales[[#This Row],[May]]/CostofSales[[#Totals],[May]],"-") -> 0.19298246 | W11: =IFERROR(CostofSales[[#This Row],[Jun]]/CostofSales[[#Totals],[Jun]],"-") -> 0.17307692 | X11: =IFERROR(CostofSales[[#This Row],[Jul]]/CostofSales[[#Totals],[Jul]],"-") -> 0.086956522 | Y11: =IFERROR(CostofSales[[#This Row],[Aug]]/CostofSales[[#Totals],[Aug]],"-") -> 0.057522124 | Z11: =IFERROR(CostofSales[[#This Row],[Sep]]/CostofSales[[#Totals],[Sep]],"-") -> 0.1352657 | AA11: =IFERROR(CostofSales[[#This Row],[Oct]]/CostofSales[[#Totals],[Oct]],"-") -> 0.10948905 | AB11: =IFERROR(CostofSales[[#This Row],[Nov]]/CostofSales[[#Totals],[Nov]],"-") -> 0.15151515 | AC11: =IFERROR(CostofSales[[#This Row],[Dec]]/CostofSales[[#Totals],[Dec]],"-") -> 0.13907285 | AD11: =IFERROR(CostofSales[[#This Row],[Yearly]]/CostofSales[[#Totals],[Yearly]],"-") -> 0.14248298
B12: Cost 6 | D12: 33 | E12: 61 | F12: 42 | G12: 43 | H12: 19 | I12: 94 | J12: 46 | K12: 15 | L12: 55 | M12: 15 | N12: 37 | O12: 89 | P12: =SUM(CostofSales[[#This Row],[Jan]:[Dec]]) -> 549 | Q12: 0.1 | R12: =IFERROR(CostofSales[[#This Row],[Jan]]/CostofSales[[#Totals],[Jan]],"-") -> 0.1245283 | S12: =IFERROR(CostofSales[[#This Row],[Feb]]/CostofSales[[#Totals],[Feb]],"-") -> 0.17134831 | T12: =IFERROR(CostofSales[[#This Row],[Mar]]/CostofSales[[#Totals],[Mar]],"-") -> 0.13333333 | U12: =IFERROR(CostofSales[[#This Row],[Apr]]/CostofSales[[#Totals],[Apr]],"-") -> 0.17842324 | V12: =IFERROR(CostofSales[[#This Row],[May]]/CostofSales[[#Totals],[May]],"-") -> 0.047619048 | W12: =IFERROR(CostofSales[[#This Row],[Jun]]/CostofSales[[#Totals],[Jun]],"-") -> 0.30128205 | X12: =IFERROR(CostofSales[[#This Row],[Jul]]/CostofSales[[#Totals],[Jul]],"-") -> 0.15384615 | Y12: =IFERROR(CostofSales[[#This Row],[Aug]]/CostofSales[[#Totals],[Aug]],"-") -> 0.066371681 | Z12: =IFERROR(CostofSales[[#This Row],[Sep]]/CostofSales[[#Totals],[Sep]],"-") -> 0.13285024 | AA12: =IFERROR(CostofSales[[#This Row],[Oct]]/CostofSales[[#Totals],[Oct]],"-") -> 0.054744526 | AB12: =IFERROR(CostofSales[[#This Row],[Nov]]/CostofSales[[#Totals],[Nov]],"-") -> 0.14015152 | AC12: =IFERROR(CostofSales[[#This Row],[Dec]]/CostofSales[[#Totals],[Dec]],"-") -> 0.19646799 | AD12: =IFERROR(CostofSales[[#This Row],[Yearly]]/CostofSales[[#Totals],[Yearly]],"-") -> 0.14379256
B13: Cost 7 | D13: 18 | E13: 11 | F13: 30 | G13: 9 | H13: 62 | I13: 39 | J13: 102 | K13: 44 | L13: 121 | M13: 19 | N13: 33 | O13: 40 | P13: =SUM(CostofSales[[#This Row],[Jan]:[Dec]]) -> 528 | Q13: 0.1 | R13: =IFERROR(CostofSales[[#This Row],[Jan]]/CostofSales[[#Totals],[Jan]],"-") -> 0.067924528 | S13: =IFERROR(CostofSales[[#This Row],[Feb]]/CostofSales[[#Totals],[Feb]],"-") -> 0.030898876 | T13: =IFERROR(CostofSales[[#This Row],[Mar]]/CostofSales[[#Totals],[Mar]],"-") -> 0.095238095 | U13: =IFERROR(CostofSales[[#This Row],[Apr]]/CostofSales[[#Totals],[Apr]],"-") -> 0.037344398 | V13: =IFERROR(CostofSales[[#This Row],[May]]/CostofSales[[#Totals],[May]],"-") -> 0.15538847 | W13: =IFERROR(CostofSales[[#This Row],[Jun]]/CostofSales[[#Totals],[Jun]],"-") -> 0.125 | X13: =IFERROR(CostofSales[[#This Row],[Jul]]/CostofSales[[#Totals],[Jul]],"-") -> 0.34113712 | Y13: =IFERROR(CostofSales[[#This Row],[Aug]]/CostofSales[[#Totals],[Aug]],"-") -> 0.19469027 | Z13: =IFERROR(CostofSales[[#This Row],[Sep]]/CostofSales[[#Totals],[Sep]],"-") -> 0.29227053 | AA13: =IFERROR(CostofSales[[#This Row],[Oct]]/CostofSales[[#Totals],[Oct]],"-") -> 0.069343066 | AB13: =IFERROR(CostofSales[[#This Row],[Nov]]/CostofSales[[#Totals],[Nov]],"-") -> 0.125 | AC13: =IFERROR(CostofSales[[#This Row],[Dec]]/CostofSales[[#Totals],[Dec]],"-") -> 0.088300221 | AD13: =IFERROR(CostofSales[[#This Row],[Yearly]]/CostofSales[[#Totals],[Yearly]],"-") -> 0.1382923
B14: TOTAL COST OF SALES | D14: =SUBTOTAL(109,CostofSales[Jan]) -> 265 | E14: =SUBTOTAL(109,CostofSales[Feb]) -> 356 | F14: =SUBTOTAL(109,CostofSales[Mar]) -> 315 | G14: =SUBTOTAL(109,CostofSales[Apr]) -> 241 | H14: =SUBTOTAL(109,CostofSales[May]) -> 399 | I14: =SUBTOTAL(109,CostofSales[Jun]) -> 312 | J14: =SUBTOTAL(109,CostofSales[Jul]) -> 299 | K14: =SUBTOTAL(109,CostofSales[Aug]) -> 226 | L14: =SUBTOTAL(109,CostofSales[Sep]) -> 414 | M14: =SUBTOTAL(109,CostofSales[Oct]) -> 274 | N14: =SUBTOTAL(109,CostofSales[Nov]) -> 264 | O14: =SUBTOTAL(109,CostofSales[Dec]) -> 453 | P14: =SUBTOTAL(109,CostofSales[Yearly]) -> 3818 | Q14: =SUBTOTAL(109,CostofSales[Index %]) -> 1 | R14: =SUBTOTAL(109,CostofSales[Jan %]) -> 1 | S14: =SUBTOTAL(109,CostofSales[Feb %]) -> 1 | T14: =SUBTOTAL(109,CostofSales[Mar %]) -> 1 | U14: =SUBTOTAL(109,CostofSales[Apr %]) -> 1 | V14: =SUBTOTAL(109,CostofSales[May %]) -> 1 | W14: =SUBTOTAL(109,CostofSales[Jun %]) -> 1 | X14: =SUBTOTAL(109,CostofSales[Jul %]) -> 1 | Y14: =SUBTOTAL(109,CostofSales[Aug %]) -> 1 | Z14: =SUBTOTAL(109,CostofSales[Sep %]) -> 1 | AA14: =SUBTOTAL(109,CostofSales[Oct %]) -> 1 | AB14: =SUBTOTAL(109,CostofSales[Nov %]) -> 1 | AC14: =SUBTOTAL(109,CostofSales[Dec %]) -> 1 | AD14: =SUBTOTAL(109,CostofSales[Year %]) -> 1
B16: Gross Profit | D16: =Revenue[[#Totals],[Jan]]-CostofSales[[#Totals],[Jan]] -> 359 | E16: =Revenue[[#Totals],[Feb]]-CostofSales[[#Totals],[Feb]] -> 380 | F16: =Revenue[[#Totals],[Mar]]-CostofSales[[#Totals],[Mar]] -> 505 | G16: =Revenue[[#Totals],[Apr]]-CostofSales[[#Totals],[Apr]] -> 370 | H16: =Revenue[[#Totals],[May]]-CostofSales[[#Totals],[May]] -> 413 | I16: =Revenue[[#Totals],[Jun]]-CostofSales[[#Totals],[Jun]] -> 266 | J16: =Revenue[[#Totals],[Jul]]-CostofSales[[#Totals],[Jul]] -> 298 | K16: =Revenue[[#Totals],[Aug]]-CostofSales[[#Totals],[Aug]] -> 449 | L16: =Revenue[[#Totals],[Sep]]-CostofSales[[#Totals],[Sep]] -> 330 | M16: =Revenue[[#Totals],[Oct]]-CostofSales[[#Totals],[Oct]] -> 407 | N16: =Revenue[[#Totals],[Nov]]-CostofSales[[#Totals],[Nov]] -> 475 | O16: =Revenue[[#Totals],[Dec]]-CostofSales[[#Totals],[Dec]] -> 590 | P16: =Revenue[[#Totals],[Yearly]]-CostofSales[[#Totals],[Yearly]] -> 4842 | R16: =D16/$P$16 -> 0.074142916 | S16: =E16/$P$16 -> 0.078479967 | T16: =F16/$P$16 -> 0.10429575 | U16: =G16/$P$16 -> 0.076414705 | V16: =H16/$P$16 -> 0.085295333 | W16: =I16/$P$16 -> 0.054935977 | X16: =J16/$P$16 -> 0.061544816 | Y16: =K16/$P$16 -> 0.092730277 | ... AD16: =P16/$P$16 -> 1

Sheet Expenses
B1: =Company_Name -> Company Name
B2: =Projection_Period_Title -> Twelve Month | E2: Fiscal Year: | F2: =FYMonthStart -> JAN | G2: =FYStartYear -> 2023
B3: ='Revenues (Sales)'!$B$3 -> Profit & Loss Projection
D5: =UPPER(TEXT(DATE(FYStartYear,FYMonthNo,1),"mmm-yy")) -> JAN-23 | E5: =UPPER(TEXT(DATE(FYStartYear,FYMonthNo+1,1),"mmm-yy")) -> FEB-23 | F5: =UPPER(TEXT(DATE(FYStartYear,FYMonthNo+2,1),"mmm-yy")) -> MAR-23 | G5: =UPPER(TEXT(DATE(FYStartYear,FYMonthNo+3,1),"mmm-yy")) -> APR-23 | H5: =UPPER(TEXT(DATE(FYStartYear,FYMonthNo+4,1),"mmm-yy")) -> MAY-23 | I5: =UPPER(TEXT(DATE(FYStartYear,FYMonthNo+5,1),"mmm-yy")) -> JUN-23 | J5: =UPPER(TEXT(DATE(FYStartYear,FYMonthNo+6,1),"mmm-yy")) -> JUL-23 | K5: =UPPER(TEXT(DATE(FYStartYear,FYMonthNo+7,1),"mmm-yy")) -> AUG-23 | L5: =UPPER(TEXT(DATE(FYStartYear,FYMonthNo+8,1),"mmm-yy")) -> SEP-23 | M5: =UPPER(TEXT(DATE(FYStartYear,FYMonthNo+9,1),"mmm-yy")) -> OCT-23 | N5: =UPPER(TEXT(DATE(FYStartYear,FYMonthNo+10,1),"mmm-yy")) -> NOV-23 | O5: =UPPER(TEXT(DATE(FYStartYear,FYMonthNo+11,1),"mmm-yy")) -> DEC-23 | P5: YEARLY | Q5: IND % | R5: =LEFT(D5,3)&" %" -> JAN % | S5: =LEFT(E5,3)&" %" -> FEB % | T5: =LEFT(F5,3)&" %" -> MAR % | U5: =LEFT(G5,3)&" %" -> APR % | V5: =LEFT(H5,3)&" %" -> MAY % | W5: =LEFT(I5,3)&" %" -> JUN % | X5: =LEFT(J5,3)&" %" -> JUL % | Y5: =LEFT(K5,3)&" %" -> AUG % | ... AC5: =LEFT(O5,3)&" %" -> DEC % | AD5: YEAR %
B6: EXPENSES | C6: TREND | D6: Column1 | E6: Feb | F6: Mar | G6: Apr | H6: May | I6: Jun | J6: Jul | K6: Aug | L6: Sep | M6: Oct | N6: Nov | O6: Dec | P6: Yearly | Q6: Index % | R6: Jan % | S6: Feb % | T6: Mar % | U6: Apr % | V6: May % | W6: Jun % | X6: Jul % | Y6: Aug % | Z6: Sep % | AA6: Oct % | AB6: Nov % | AC6: Dec % | AD6: Year %
B7: Salary expenses | D7: 10 | E7: 18 | F7: 13 | G7: 8 | H7: 22 | I7: 18 | J7: 8 | K7: 17 | L7: 20 | M7: 8 | N7: 4 | O7: 12 | P7: =SUM(tblExpenses[[#This Row],[Column1]:[Dec]]) -> 158 | Q7: 0.12 | R7: =tblExpenses[[#This Row],[Column1]]/tblExpenses[[#Totals],[Column1]] -> 0.042372881 | S7: =tblExpenses[[#This Row],[Feb]]/tblExpenses[[#Totals],[Feb]] -> 0.087804878 | T7: =tblExpenses[[#This Row],[Mar]]/tblExpenses[[#Totals],[Mar]] -> 0.052208835 | U7: =tblExpenses[[#This Row],[Apr]]/tblExpenses[[#Totals],[Apr]] -> 0.030651341 | V7: =tblExpenses[[#This Row],[May]]/tblExpenses[[#Totals],[May]] -> 0.085603113 | W7: =tblExpenses[[#This Row],[Jun]]/tblExpenses[[#Totals],[Jun]] -> 0.065693431 | X7: =tblExpenses[[#This Row],[Jul]]/tblExpenses[[#Totals],[Jul]] -> 0.030075188 | Y7: =tblExpenses[[#This Row],[Aug]]/tblExpenses[[#Totals],[Aug]] -> 0.072340426 | Z7: =tblExpenses[[#This Row],[Sep]]/tblExpenses[[#Totals],[Sep]] -> 0.086956522 | AA7: =tblExpenses[[#This Row],[Oct]]/tblExpenses[[#Totals],[Oct]] -> 0.030888031 | AB7: =tblExpenses[[#This Row],[Nov]]/tblExpenses[[#Totals],[Nov]] -> 0.013513514 | AC7: =tblExpenses[[#This Row],[Dec]]/tblExpenses[[#Totals],[Dec]] -> 0.051948052 | AD7: =tblExpenses[[#This Row],[Yearly]]/tblExpenses[[#Totals],[Yearly]] -> 0.052684228
B8: Payroll expenses | D8: 23 | E8: 11 | F8: 7 | G8: 14 | H8: 12 | I8: 19 | J8: 19 | K8: 4 | L8: 7 | M8: 13 | N8: 25 | O8: 5 | P8: =SUM(tblExpenses[[#This Row],[Column1]:[Dec]]) -> 159 | Q8: 0.09 | R8: =tblExpenses[[#This Row],[Column1]]/tblExpenses[[#Totals],[Column1]] -> 0.097457627 | S8: =tblExpenses[[#This Row],[Feb]]/tblExpenses[[#Totals],[Feb]] -> 0.053658537 | T8: =tblExpenses[[#This Row],[Mar]]/tblExpenses[[#Totals],[Mar]] -> 0.02811245 | U8: =tblExpenses[[#This Row],[Apr]]/tblExpenses[[#Totals],[Apr]] -> 0.053639847 | V8: =tblExpenses[[#This Row],[May]]/tblExpenses[[#Totals],[May]] -> 0.046692607 | W8: =tblExpenses[[#This Row],[Jun]]/tblExpenses[[#Totals],[Jun]] -> 0.069343066 | X8: =tblExpenses[[#This Row],[Jul]]/tblExpenses[[#Totals],[Jul]] -> 0.071428571 | Y8: =tblExpenses[[#This Row],[Aug]]/tblExpenses[[#Totals],[Aug]] -> 0.017021277 | Z8: =tblExpenses[[#This Row],[Sep]]/tblExpenses[[#Totals],[Sep]] -> 0.030434783 | AA8: =tblExpenses[[#This Row],[Oct]]/tblExpenses[[#Totals],[Oct]] -> 0.05019305 | AB8: =tblExpenses[[#This Row],[Nov]]/tblExpenses[[#Totals],[Nov]] -> 0.084459459 | AC8: =tblExpenses[[#This Row],[Dec]]/tblExpenses[[#Totals],[Dec]] -> 0.021645022 | AD8: =tblExpenses[[#This Row],[Yearly]]/tblExpenses[[#Totals],[Yearly]] -> 0.053017673
B9: Outside services | D9: 23 | E9: 20 | F9: 3 | G9: 16 | H9: 10 | I9: 5 | J9: 20 | K9: 7 | L9: 4 | M9: 22 | N9: 13 | O9: 14 | P9: =SUM(tblExpenses[[#This Row],[Column1]:[Dec]]) -> 157 | Q9: 0.02 | R9: =tblExpenses[[#This Row],[Column1]]/tblExpenses[[#Totals],[Column1]] -> 0.097457627 | S9: =tblExpenses[[#This Row],[Feb]]/tblExpenses[[#Totals],[Feb]] -> 0.097560976 | T9: =tblExpenses[[#This Row],[Mar]]/tblExpenses[[#Totals],[Mar]] -> 0.012048193 | U9: =tblExpenses[[#This Row],[Apr]]/tblExpenses[[#Totals],[Apr]] -> 0.061302682 | V9: =tblExpenses[[#This Row],[May]]/tblExpenses[[#Totals],[May]] -> 0.038910506 | W9: =tblExpenses[[#This Row],[Jun]]/tblExpenses[[#Totals],[Jun]] -> 0.018248175 | X9: =tblExpenses[[#This Row],[Jul]]/tblExpenses[[#Totals],[Jul]] -> 0.07518797 | Y9: =tblExpenses[[#This Row],[Aug]]/tblExpenses[[#Totals],[Aug]] -> 0.029787234 | Z9: =tblExpenses[[#This Row],[Sep]]/tblExpenses[[#Totals],[Sep]] -> 0.017391304 | AA9: =tblExpenses[[#This Row],[Oct]]/tblExpenses[[#Totals],[Oct]] -> 0.084942085 | AB9: =tblExpenses[[#This Row],[Nov]]/tblExpenses[[#Totals],[Nov]] -> 0.043918919 | AC9: =tblExpenses[[#This Row],[Dec]]/tblExpenses[[#Totals],[Dec]] -> 0.060606061 | AD9: =tblExpenses[[#This Row],[Yearly]]/tblExpenses[[#Totals],[Yearly]] -> 0.052350784
B10: Supplies (office and operating) | D10: 19 | E10: 4 | F10: 7 | G10: 14 | H10: 22 | I10: 10 | J10: 22 | K10: 5 | L10: 4 | M10: 12 | N10: 18 | O10: 24 | P10: =SUM(tblExpenses[[#This Row],[Column1]:[Dec]]) -> 161 | Q10: 0.08 | R10: =tblExpenses[[#This Row],[Column1]]/tblExpenses[[#Totals],[Column1]] -> 0.080508475 | S10: =tblExpenses[[#This Row],[Feb]]/tblExpenses[[#Totals],[Feb]] -> 0.019512195 | T10: =tblExpenses[[#This Row],[Mar]]/tblExpenses[[#Totals],[Mar]] -> 0.02811245 | U10: =tblExpenses[[#This Row],[Apr]]/tblExpenses[[#Totals],[Apr]] -> 0.053639847 | V10: =tblExpenses[[#This Row],[May]]/tblExpenses[[#Totals],[May]] -> 0.085603113 | W10: =tblExpenses[[#This Row],[Jun]]/tblExpenses[[#Totals],[Jun]] -> 0.03649635 | X10: =tblExpenses[[#This Row],[Jul]]/tblExpenses[[#Totals],[Jul]] -> 0.082706767 | Y10: =tblExpenses[[#This Row],[Aug]]/tblExpenses[[#Totals],[Aug]] -> 0.021276596 | Z10: =tblExpenses[[#This Row],[Sep]]/tblExpenses[[#Totals],[Sep]] -> 0.017391304 | AA10: =tblExpenses[[#This Row],[Oct]]/tblExpenses[[#Totals],[Oct]] -> 0.046332046 | AB10: =tblExpenses[[#This Row],[Nov]]/tblExpenses[[#Totals],[Nov]] -> 0.060810811 | AC10: =tblExpenses[[#This Row],[Dec]]/tblExpenses[[#Totals],[Dec]] -> 0.1038961 | AD10: =tblExpenses[[#This Row],[Yearly]]/tblExpenses[[#Totals],[Yearly]] -> 0.053684562
B11: Repairs and maintenance | D11: 11 | E11: 11 | F11: 17 | G11: 12 | H11: 2 | I11: 14 | J11: 12 | K11: 10 | L11: 18 | M11: 11 | N11: 23 | O11: 11 | P11: =SUM(tblExpenses[[#This Row],[Column1]:[Dec]]) -> 152 | Q11: 0.03 | R11: =tblExpenses[[#This Row],[Column1]]/tblExpenses[[#Totals],[Column1]] -> 0.046610169 | S11: =tblExpenses[[#This Row],[Feb]]/tblExpenses[[#Totals],[Feb]] -> 0.053658537 | T11: =tblExpenses[[#This Row],[Mar]]/tblExpenses[[#Totals],[Mar]] -> 0.068273092 | U11: =tblExpenses[[#This Row],[Apr]]/tblExpenses[[#Totals],[Apr]] -> 0.045977011 | V11: =tblExpenses[[#This Row],[May]]/tblExpenses[[#Totals],[May]] -> 0.0077821012 | W11: =tblExpenses[[#This Row],[Jun]]/tblExpenses[[#Totals],[Jun]] -> 0.051094891 | X11: =tblExpenses[[#This Row],[Jul]]/tblExpenses[[#Totals],[Jul]] -> 0.045112782 | Y11: =tblExpenses[[#This Row],[Aug]]/tblExpenses[[#Totals],[Aug]] -> 0.042553191 | Z11: =tblExpenses[[#This Row],[Sep]]/tblExpenses[[#Totals],[Sep]] -> 0.07826087 | AA11: =tblExpenses[[#This Row],[Oct]]/tblExpenses[[#Totals],[Oct]] -> 0.042471042 | AB11: =tblExpenses[[#This Row],[Nov]]/tblExpenses[[#Totals],[Nov]] -> 0.077702703 | AC11: =tblExpenses[[#This Row],[Dec]]/tblExpenses[[#Totals],[Dec]] -> 0.047619048 | AD11: =tblExpenses[[#This Row],[Yearly]]/tblExpenses[[#Totals],[Yearly]] -> 0.050683561
B12: Advertising | D12: 2 | E12: 16 | F12: 6 | G12: 13 | H12: 11 | I12: 22 | J12: 21 | K12: 3 | L12: 12 | M12: 7 | N12: 17 | O12: 20 | P12: =SUM(tblExpenses[[#This Row],[Column1]:[Dec]]) -> 150 | Q12: 0.15 | R12: =tblExpenses[[#This Row],[Column1]]/tblExpenses[[#Totals],[Column1]] -> 0.0084745763 | S12: =tblExpenses[[#This Row],[Feb]]/tblExpenses[[#Totals],[Feb]] -> 0.07804878 | T12: =tblExpenses[[#This Row],[Mar]]/tblExpenses[[#Totals],[Mar]] -> 0.024096386 | U12: =tblExpenses[[#This Row],[Apr]]/tblExpenses[[#Totals],[Apr]] -> 0.049808429 | V12: =tblExpenses[[#This Row],[May]]/tblExpenses[[#Totals],[May]] -> 0.042801556 | W12: =tblExpenses[[#This Row],[Jun]]/tblExpenses[[#Totals],[Jun]] -> 0.080291971 | X12: =tblExpenses[[#This Row],[Jul]]/tblExpenses[[#Totals],[Jul]] -> 0.078947368 | Y12: =tblExpenses[[#This Row],[Aug]]/tblExpenses[[#Totals],[Aug]] -> 0.012765957 | Z12: =tblExpenses[[#This Row],[Sep]]/tblExpenses[[#Totals],[Sep]] -> 0.052173913 | AA12: =tblExpenses[[#This Row],[Oct]]/tblExpenses[[#Totals],[Oct]] -> 0.027027027 | AB12: =tblExpenses[[#This Row],[Nov]]/tblExpenses[[#Totals],[Nov]] -> 0.057432432 | AC12: =tblExpenses[[#This Row],[Dec]]/tblExpenses[[#Totals],[Dec]] -> 0.086580087 | AD12: =tblExpenses[[#This Row],[Yearly]]/tblExpenses[[#Totals],[Yearly]] -> 0.050016672
B13: Car, delivery and travel | D13: 8 | E13: 17 | F13: 11 | G13: 11 | H13: 21 | I13: 9 | J13: 20 | K13: 3 | L13: 14 | M13: 22 | N13: 16 | O13: 12 | P13: =SUM(tblExpenses[[#This Row],[Column1]:[Dec]]) -> 164 | Q13: 0.12 | R13: =tblExpenses[[#This Row],[Column1]]/tblExpenses[[#Totals],[Column1]] -> 0.033898305 | S13: =tblExpenses[[#This Row],[Feb]]/tblExpenses[[#Totals],[Feb]] -> 0.082926829 | T13: =tblExpenses[[#This Row],[Mar]]/tblExpenses[[#Totals],[Mar]] -> 0.044176707 | U13: =tblExpenses[[#This Row],[Apr]]/tblExpenses[[#Totals],[Apr]] -> 0.042145594 | V13: =tblExpenses[[#This Row],[May]]/tblExpenses[[#Totals],[May]] -> 0.081712062 | W13: =tblExpenses[[#This Row],[Jun]]/tblExpenses[[#Totals],[Jun]] -> 0.032846715 | X13: =tblExpenses[[#This Row],[Jul]]/tblExpenses[[#Totals],[Jul]] -> 0.07518797 | Y13: =tblExpenses[[#This Row],[Aug]]/tblExpenses[[#Totals],[Aug]] -> 0.012765957 | Z13: =tblExpenses[[#This Row],[Sep]]/tblExpenses[[#Totals],[Sep]] -> 0.060869565 | AA13: =tblExpenses[[#This Row],[Oct]]/tblExpenses[[#Totals],[Oct]] -> 0.084942085 | AB13: =tblExpenses[[#This Row],[Nov]]/tblExpenses[[#Totals],[Nov]] -> 0.054054054 | AC13: =tblExpenses[[#This Row],[Dec]]/tblExpenses[[#Totals],[Dec]] -> 0.051948052 | AD13: =tblExpenses[[#This Row],[Yearly]]/tblExpenses[[#Totals],[Yearly]] -> 0.054684895
B14: Accounting and legal | D14: 5 | E14: 13 | F14: 6 | G14: 15 | H14: 19 | I14: 10 | J14: 12 | K14: 9 | L14: 15 | M14: 16 | N14: 4 | O14: 9 | P14: =SUM(tblExpenses[[#This Row],[Column1]:[Dec]]) -> 133 | Q14: 0.09 | R14: =tblExpenses[[#This Row],[Column1]]/tblExpenses[[#Totals],[Column1]] -> 0.021186441 | S14: =tblExpenses[[#This Row],[Feb]]/tblExpenses[[#Totals],[Feb]] -> 0.063414634 | T14: =tblExpenses[[#This Row],[Mar]]/tblExpenses[[#Totals],[Mar]] -> 0.024096386 | U14: =tblExpenses[[#This Row],[Apr]]/tblExpenses[[#Totals],[Apr]] -> 0.057471264 | V14: =tblExpenses[[#This Row],[May]]/tblExpenses[[#Totals],[May]] -> 0.073929961 | W14: =tblExpenses[[#This Row],[Jun]]/tblExpenses[[#Totals],[Jun]] -> 0.03649635 | X14: =tblExpenses[[#This Row],[Jul]]/tblExpenses[[#Totals],[Jul]] -> 0.045112782 | Y14: =tblExpenses[[#This Row],[Aug]]/tblExpenses[[#Totals],[Aug]] -> 0.038297872 | Z14: =tblExpenses[[#This Row],[Sep]]/tblExpenses[[#Totals],[Sep]] -> 0.065217391 | AA14: =tblExpenses[[#This Row],[Oct]]/tblExpenses[[#Totals],[Oct]] -> 0.061776062 | AB14: =tblExpenses[[#This Row],[Nov]]/tblExpenses[[#Totals],[Nov]] -> 0.013513514 | AC14: =tblExpenses[[#This Row],[Dec]]/tblExpenses[[#Totals],[Dec]] -> 0.038961039 | AD14: =tblExpenses[[#This Row],[Yearly]]/tblExpenses[[#Totals],[Yearly]] -> 0.044348116
B15: Rent | D15: 8 | E15: 4 | F15: 23 | G15: 25 | H15: 10 | I15: 24 | J15: 22 | K15: 5 | L15: 12 | M15: 24 | N15: 24 | O15: 12 | P15: =SUM(tblExpenses[[#This Row],[Column1]:[Dec]]) -> 193 | Q15: 0.01 | R15: =tblExpenses[[#This Row],[Column1]]/tblExpenses[[#Totals],[Column1]] -> 0.033898305 | S15: =tblExpenses[[#This Row],[Feb]]/tblExpenses[[#Totals],[Feb]] -> 0.019512195 | T15: =tblExpenses[[#This Row],[Mar]]/tblExpenses[[#Totals],[Mar]] -> 0.092369478 | U15: =tblExpenses[[#This Row],[Apr]]/tblExpenses[[#Totals],[Apr]] -> 0.095785441 | V15: =tblExpenses[[#This Row],[May]]/tblExpenses[[#Totals],[May]] -> 0.038910506 | W15: =tblExpenses[[#This Row],[Jun]]/tblExpenses[[#Totals],[Jun]] -> 0.087591241 | X15: =tblExpenses[[#This Row],[Jul]]/tblExpenses[[#Totals],[Jul]] -> 0.082706767 | Y15: =tblExpenses[[#This Row],[Aug]]/tblExpenses[[#Totals],[Aug]] -> 0.021276596 | Z15: =tblExpenses[[#This Row],[Sep]]/tblExpenses[[#Totals],[Sep]] -> 0.052173913 | AA15: =tblExpenses[[#This Row],[Oct]]/tblExpenses[[#Totals],[Oct]] -> 0.092664093 | AB15: =tblExpenses[[#This Row],[Nov]]/tblExpenses[[#Totals],[Nov]] -> 0.081081081 | AC15: =tblExpenses[[#This Row],[Dec]]/tblExpenses[[#Totals],[Dec]] -> 0.051948052 | AD15: =tblExpenses[[#This Row],[Yearly]]/tblExpenses[[#Totals],[Yearly]] -> 0.064354785
B16: Telephone | D16: 25 | E16: 2 | F16: 12 | G16: 25 | H16: 10 | I16: 24 | J16: 3 | K16: 20 | L16: 3 | M16: 9 | N16: 20 | O16: 18 | P16: =SUM(tblExpenses[[#This Row],[Column1]:[Dec]]) -> 171 | Q16: 0.01 | R16: =tblExpenses[[#This Row],[Column1]]/tblExpenses[[#Totals],[Column1]] -> 0.1059322 | S16: =tblExpenses[[#This Row],[Feb]]/tblExpenses[[#Totals],[Feb]] -> 0.0097560976 | T16: =tblExpenses[[#This Row],[Mar]]/tblExpenses[[#Totals],[Mar]] -> 0.048192771 | U16: =tblExpenses[[#This Row],[Apr]]/tblExpenses[[#Totals],[Apr]] -> 0.095785441 | V16: =tblExpenses[[#This Row],[May]]/tblExpenses[[#Totals],[May]] -> 0.038910506 | W16: =tblExpenses[[#This Row],[Jun]]/tblExpenses[[#Totals],[Jun]] -> 0.087591241 | X16: =tblExpenses[[#This Row],[Jul]]/tblExpenses[[#Totals],[Jul]] -> 0.011278195 | Y16: =tblExpenses[[#This Row],[Aug]]/tblExpenses[[#Totals],[Aug]] -> 0.085106383 | Z16: =tblExpenses[[#This Row],[Sep]]/tblExpenses[[#Totals],[Sep]] -> 0.013043478 | AA16: =tblExpenses[[#This Row],[Oct]]/tblExpenses[[#Totals],[Oct]] -> 0.034749035 | AB16: =tblExpenses[[#This Row],[Nov]]/tblExpenses[[#Totals],[Nov]] -> 0.067567568 | AC16: =tblExpenses[[#This Row],[Dec]]/tblExpenses[[#Totals],[Dec]] -> 0.077922078 | AD16: =tblExpenses[[#This Row],[Yearly]]/tblExpenses[[#Totals],[Yearly]] -> 0.057019006
B17: Utilities | D17: 16 | E17: 19 | F17: 9 | G17: 16 | H17: 13 | I17: 2 | J17: 4 | K17: 24 | L17: 16 | M17: 22 | N17: 7 | O17: 18 | P17: =SUM(tblExpenses[[#This Row],[Column1]:[Dec]]) -> 166 | Q17: 0.01 | R17: =tblExpenses[[#This Row],[Column1]]/tblExpenses[[#Totals],[Column1]] -> 0.06779661 | S17: =tblExpenses[[#This Row],[Feb]]/tblExpenses[[#Totals],[Feb]] -> 0.092682927 | T17: =tblExpenses[[#This Row],[Mar]]/tblExpenses[[#Totals],[Mar]] -> 0.036144578 | U17: =tblExpenses[[#This Row],[Apr]]/tblExpenses[[#Totals],[Apr]] -> 0.061302682 | V17: =tblExpenses[[#This Row],[May]]/tblExpenses[[#Totals],[May]] -> 0.050583658 | W17: =tblExpenses[[#This Row],[Jun]]/tblExpenses[[#Totals],[Jun]] -> 0.0072992701 | X17: =tblExpenses[[#This Row],[Jul]]/tblExpenses[[#Totals],[Jul]] -> 0.015037594 | Y17: =tblExpenses[[#This Row],[Aug]]/tblExpenses[[#Totals],[Aug]] -> 0.10212766 | Z17: =tblExpenses[[#This Row],[Sep]]/tblExpenses[[#Totals],[Sep]] -> 0.069565217 | AA17: =tblExpenses[[#This Row],[Oct]]/tblExpenses[[#Totals],[Oct]] -> 0.084942085 | AB17: =tblExpenses[[#This Row],[Nov]]/tblExpenses[[#Totals],[Nov]] -> 0.023648649 | AC17: =tblExpenses[[#This Row],[Dec]]/tblExpenses[[#Totals],[Dec]] -> 0.077922078 | AD17: =tblExpenses[[#This Row],[Yearly]]/tblExpenses[[#Totals],[Yearly]] -> 0.055351784
B18: Insurance | D18: 12 | E18: 9 | F18: 16 | G18: 19 | H18: 25 | I18: 17 | J18: 20 | K18: 14 | L18: 5 | M18: 14 | N18: 5 | O18: 2 | P18: =SUM(tblExpenses[[#This Row],[Column1]:[Dec]]) -> 158 | Q18: 0.01 | R18: =tblExpenses[[#This Row],[Column1]]/tblExpenses[[#Totals],[Column1]] -> 0.050847458 | S18: =tblExpenses[[#This Row],[Feb]]/tblExpenses[[#Totals],[Feb]] -> 0.043902439 | T18: =tblExpenses[[#This Row],[Mar]]/tblExpenses[[#Totals],[Mar]] -> 0.064257028 | U18: =tblExpenses[[#This Row],[Apr]]/tblExpenses[[#Totals],[Apr]] -> 0.072796935 | V18: =tblExpenses[[#This Row],[May]]/tblExpenses[[#Totals],[May]] -> 0.097276265 | W18: =tblExpenses[[#This Row],[Jun]]/tblExpenses[[#Totals],[Jun]] -> 0.062043796 | X18: =tblExpenses[[#This Row],[Jul]]/tblExpenses[[#Totals],[Jul]] -> 0.07518797 | Y18: =tblExpenses[[#This Row],[Aug]]/tblExpenses[[#Totals],[Aug]] -> 0.059574468 | Z18: =tblExpenses[[#This Row],[Sep]]/tblExpenses[[#Totals],[Sep]] -> 0.02173913 | AA18: =tblExpenses[[#This Row],[Oct]]/tblExpenses[[#Totals],[Oct]] -> 0.054054054 | AB18: =tblExpenses[[#This Row],[Nov]]/tblExpenses[[#Totals],[Nov]] -> 0.016891892 | AC18: =tblExpenses[[#This Row],[Dec]]/tblExpenses[[#Totals],[Dec]] -> 0.0086580087 | AD18: =tblExpenses[[#This Row],[Yearly]]/tblExpenses[[#Totals],[Yearly]] -> 0.052684228
... B25: Misc. (unspecified) | D25: 8 | E25: 20 | F25: 11 | G25: 11 | H25: 11 | I25: 20 | J25: 12 | K25: 16 | L25: 5 | M25: 7 | N25: 21 | O25: 3 | P25: =SUM(tblExpenses[[#This Row],[Column1]:[Dec]]) -> 145 | Q25: 0.02 | R25: =tblExpenses[[#This Row],[Column1]]/tblExpenses[[#Totals],[Column1]] -> 0.033898305 | S25: =tblExpenses[[#This Row],[Feb]]/tblExpenses[[#Totals],[Feb]] -> 0.097560976 | T25: =tblExpenses[[#This Row],[Mar]]/tblExpenses[[#Totals],[Mar]] -> 0.044176707 | U25: =tblExpenses[[#This Row],[Apr]]/tblExpenses[[#Totals],[Apr]] -> 0.042145594 | V25: =tblExpenses[[#This Row],[May]]/tblExpenses[[#Totals],[May]] -> 0.042801556 | W25: =tblExpenses[[#This Row],[Jun]]/tblExpenses[[#Totals],[Jun]] -> 0.072992701 | X25: =tblExpenses[[#This Row],[Jul]]/tblExpenses[[#Totals],[Jul]] -> 0.045112782 | Y25: =tblExpenses[[#This Row],[Aug]]/tblExpenses[[#Totals],[Aug]] -> 0.068085106 | Z25: =tblExpenses[[#This Row],[Sep]]/tblExpenses[[#Totals],[Sep]] -> 0.02173913 | AA25: =tblExpenses[[#This Row],[Oct]]/tblExpenses[[#Totals],[Oct]] -> 0.027027027 | AB25: =tblExpenses[[#This Row],[Nov]]/tblExpenses[[#Totals],[Nov]] -> 0.070945946 | AC25: =tblExpenses[[#This Row],[Dec]]/tblExpenses[[#Totals],[Dec]] -> 0.012987013 | AD25: =tblExpenses[[#This Row],[Yearly]]/tblExpenses[[#Totals],[Yearly]] -> 0.04834945
B26: TOTAL EXPENSES | D26: =SUBTOTAL(109,tblExpenses[Column1]) -> 236 | E26: =SUBTOTAL(109,tblExpenses[Feb]) -> 205 | F26: =SUBTOTAL(109,tblExpenses[Mar]) -> 249 | G26: =SUBTOTAL(109,tblExpenses[Apr]) -> 261 | H26: =SUBTOTAL(109,tblExpenses[May]) -> 257 | I26: =SUBTOTAL(109,tblExpenses[Jun]) -> 274 | J26: =SUBTOTAL(109,tblExpenses[Jul]) -> 266 | K26: =SUBTOTAL(109,tblExpenses[Aug]) -> 235 | L26: =SUBTOTAL(109,tblExpenses[Sep]) -> 230 | M26: =SUBTOTAL(109,tblExpenses[Oct]) -> 259 | N26: =SUBTOTAL(109,tblExpenses[Nov]) -> 296 | O26: =SUBTOTAL(109,tblExpenses[Dec]) -> 231 | P26: =SUBTOTAL(109,tblExpenses[Yearly]) -> 2999 | Q26: =SUBTOTAL(109,tblExpenses[Index %]) -> 1 | R26: =SUBTOTAL(109,tblExpenses[Jan %]) -> 1 | S26: =SUBTOTAL(109,tblExpenses[Feb %]) -> 1 | T26: =SUBTOTAL(109,tblExpenses[Mar %]) -> 1 | U26: =SUBTOTAL(109,tblExpenses[Apr %]) -> 1 | V26: =SUBTOTAL(109,tblExpenses[May %]) -> 1 | W26: =SUBTOTAL(109,tblExpenses[Jun %]) -> 1 | X26: =SUBTOTAL(109,tblExpenses[Jul %]) -> 1 | Y26: =SUBTOTAL(109,tblExpenses[Aug %]) -> 1 | Z26: =SUBTOTAL(109,tblExpenses[Sep %]) -> 1 | AA26: =SUBTOTAL(109,tblExpenses[Oct %]) -> 1 | AB26: =SUBTOTAL(109,tblExpenses[Nov %]) -> 1 | AC26: =SUBTOTAL(109,tblExpenses[Dec %]) -> 1 | AD26: =SUBTOTAL(109,tblExpenses[Year %]) -> 1
B28: Net Profit | D28: ='Cost of Sales'!$D$16-tblExpenses[[#Totals],[Column1]] -> 123 | E28: ='Cost of Sales'!E16-tblExpenses[[#Totals],[Feb]] -> 175 | F28: ='Cost of Sales'!F16-tblExpenses[[#Totals],[Mar]] -> 256 | G28: ='Cost of Sales'!G16-tblExpenses[[#Totals],[Apr]] -> 109 | H28: ='Cost of Sales'!H16-tblExpenses[[#Totals],[May]] -> 156 | I28: ='Cost of Sales'!I16-tblExpenses[[#Totals],[Jun]] -> -8 | J28: ='Cost of Sales'!J16-tblExpenses[[#Totals],[Jul]] -> 32 | K28: ='Cost of Sales'!K16-tblExpenses[[#Totals],[Aug]] -> 214 | L28: ='Cost of Sales'!L16-tblExpenses[[#Totals],[Sep]] -> 100 | M28: ='Cost of Sales'!M16-tblExpenses[[#Totals],[Oct]] -> 148 | N28: ='Cost of Sales'!N16-tblExpenses[[#Totals],[Nov]] -> 179 | O28: ='Cost of Sales'!O16-tblExpenses[[#Totals],[Dec]] -> 359 | P28: =SUM(D28:O28) -> 1843 | R28: =D28/$P$28 -> 0.066739012 | S28: =E28/$P$28 -> 0.09495388 | T28: =F28/$P$28 -> 0.13890396 | U28: =G28/$P$28 -> 0.059142702 | V28: =H28/$P$28 -> 0.084644601 | W28: =I28/$P$28 -> -0.0043407488 | X28: =J28/$P$28 -> 0.017362995 | Y28: =K28/$P$28 -> 0.11611503 | ... AD28: =P28/$P$28 -> 1
