Workbook
Name FiscalYearStartDate: 'Cash Paid Out'!$B$4
Name FiscalYearStartDate: 'Cash Paid Out (Non P&L)'!$B$4
Name FiscalYearStartDate: 'Cash Receipts'!$B$4

Sheet Cash Receipts
B1: Cash Flow Statement
B3: Fiscal year begins: | D3: (Pre) Startup | E3: =UPPER(TEXT(FiscalYearStartDate,"mmm")) -> JUL | F3: =UPPER(TEXT(EOMONTH(FiscalYearStartDate,1),"mmm")) -> AUG | G3: =UPPER(TEXT(EOMONTH(FiscalYearStartDate,2),"mmm")) -> SEP | H3: =UPPER(TEXT(EOMONTH(FiscalYearStartDate,3),"mmm")) -> OCT | I3: =UPPER(TEXT(EOMONTH(FiscalYearStartDate,4),"mmm")) -> NOV | J3: =UPPER(TEXT(EOMONTH(FiscalYearStartDate,5),"mmm")) -> DEC | K3: =UPPER(TEXT(EOMONTH(FiscalYearStartDate,6),"mmm")) -> JAN | L3: =UPPER(TEXT(EOMONTH(FiscalYearStartDate,7),"mmm")) -> FEB | M3: =UPPER(TEXT(EOMONTH(FiscalYearStartDate,8),"mmm")) -> MAR | N3: =UPPER(TEXT(EOMONTH(FiscalYearStartDate,9),"mmm")) -> APR | O3: =UPPER(TEXT(EOMONTH(FiscalYearStartDate,10),"mmm")) -> MAY | P3: =UPPER(TEXT(EOMONTH(FiscalYearStartDate,11),"mmm")) -> JUN | R3: Total
B4: =DATE(YEAR(TODAY()),7,1) -> 44743 | D4: EST | E4: =FiscalYearStartDate -> 44743 | F4: =EOMONTH(E4,0)+DAY(FiscalYearStartDate) -> 44774 | G4: =EOMONTH(F4,0)+DAY(FiscalYearStartDate) -> 44805 | H4: =EOMONTH(G4,0)+DAY(FiscalYearStartDate) -> 44835 | I4: =EOMONTH(H4,0)+DAY(FiscalYearStartDate) -> 44866 | J4: =EOMONTH(I4,0)+DAY(FiscalYearStartDate) -> 44896 | K4: =EOMONTH(J4,0)+DAY(FiscalYearStartDate) -> 44927 | L4: =EOMONTH(K4,0)+DAY(FiscalYearStartDate) -> 44958 | M4: =EOMONTH(L4,0)+DAY(FiscalYearStartDate) -> 44986 | ... P4: =EOMONTH(O4,0)+DAY(FiscalYearStartDate) -> 45078 | R4: Item EST
B6: Cash on Hand (beginning of month) | D6: 100 | E6: =D14 -> 100 | F6: =E14 -> -175 | G6: =F14 -> -5 | H6: =G14 -> -51 | I6: =H14 -> 174 | J6: =I14 -> 219 | K6: =J14 -> 219 | L6: =K14 -> 219 | ... P6: =O14 -> 219 | R6: =P6 -> 219
B7: Cash Receipts
B8: Cash Sales | E8: 125 | F8: 120 | G8: 130 | H8: 100 | R8: =SUM(CashReceipts[[#This Row],[Period 0]:[Period 12]]) -> 475
B9: Collections from CR accounts | H9: 75 | I9: 45 | R9: =SUM(CashReceipts[[#This Row],[Period 0]:[Period 12]]) -> 120
B10: Loan/other cash injections | F10: 50 | G10: 50 | H10: 50 | R10: =SUM(CashReceipts[[#This Row],[Period 0]:[Period 12]]) -> 150
B11: Total | D11: =SUBTOTAL(109,CashReceipts[Period 0]) -> 0 | E11: =SUBTOTAL(109,CashReceipts[Period 1]) -> 125 | F11: =SUBTOTAL(109,CashReceipts[Period 2]) -> 170 | G11: =SUBTOTAL(109,CashReceipts[Period 3]) -> 180 | H11: =SUBTOTAL(109,CashReceipts[Period 4]) -> 225 | I11: =SUBTOTAL(109,CashReceipts[Period 5]) -> 45 | J11: =SUBTOTAL(109,CashReceipts[Period 6]) -> 0 | K11: =SUBTOTAL(109,CashReceipts[Period 7]) -> 0 | L11: =SUBTOTAL(109,CashReceipts[Period 8]) -> 0 | M11: =SUBTOTAL(109,CashReceipts[Period 9]) -> 0 | N11: =SUBTOTAL(109,CashReceipts[Period 10]) -> 0 | O11: =SUBTOTAL(109,CashReceipts[Period 11]) -> 0 | P11: =SUBTOTAL(109,CashReceipts[Period 12]) -> 0 | R11: =SUBTOTAL(109,CashReceipts[Total]) -> 745
B12: Total Cash Available (before cash out) | D12: =D6+SUM(CashReceipts[Period 0]) -> 100 | E12: =E6+SUM(CashReceipts[Period 1]) -> 225 | F12: =F6+SUM(CashReceipts[Period 2]) -> -5 | G12: =G6+SUM(CashReceipts[Period 3]) -> 175 | H12: =H6+SUM(CashReceipts[Period 4]) -> 174 | I12: =I6+SUM(CashReceipts[Period 5]) -> 219 | J12: =J6+SUM(CashReceipts[Period 6]) -> 219 | K12: =K6+SUM(CashReceipts[Period 7]) -> 219 | L12: =L6+SUM(CashReceipts[Period 8]) -> 219 | M12: =M6+SUM(CashReceipts[Period 9]) -> 219 | N12: =N6+SUM(CashReceipts[Period 10]) -> 219 | O12: =O6+SUM(CashReceipts[Period 11]) -> 219 | P12: =P6+SUM(CashReceipts[Period 12]) -> 219 | R12: =R6+SUM(CashReceipts[Total]) -> 964
B14: Cash Position (end of month) | D14: =D12-'Cash Paid Out (Non P&L)'!D12 -> 100 | E14: =E12-'Cash Paid Out (Non P&L)'!E12 -> -175 | F14: =F12-'Cash Paid Out (Non P&L)'!F12 -> -5 | G14: =G12-'Cash Paid Out (Non P&L)'!G12 -> -51 | H14: =H12-'Cash Paid Out (Non P&L)'!H12 -> 174 | I14: =I12-'Cash Paid Out (Non P&L)'!I12 -> 219 | J14: =J12-'Cash Paid Out (Non P&L)'!J12 -> 219 | K14: =K12-'Cash Paid Out (Non P&L)'!K12 -> 219 | ... P14: =P12-'Cash Paid Out (Non P&L)'!P12 -> 219 | R14: =R12-'Cash Paid Out (Non P&L)'!R12 -> 338

Sheet Cash Paid Out
B1: Cash Flow Statement
B3: Fiscal year begins: | D3: (Pre) Startup | E3: =UPPER(TEXT(FiscalYearStartDate,"mmm")) -> JUL | F3: =UPPER(TEXT(EOMONTH(FiscalYearStartDate,1),"mmm")) -> AUG | G3: =UPPER(TEXT(EOMONTH(FiscalYearStartDate,2),"mmm")) -> SEP | H3: =UPPER(TEXT(EOMONTH(FiscalYearStartDate,3),"mmm")) -> OCT | I3: =UPPER(TEXT(EOMONTH(FiscalYearStartDate,4),"mmm")) -> NOV | J3: =UPPER(TEXT(EOMONTH(FiscalYearStartDate,5),"mmm")) -> DEC | K3: =UPPER(TEXT(EOMONTH(FiscalYearStartDate,6),"mmm")) -> JAN | L3: =UPPER(TEXT(EOMONTH(FiscalYearStartDate,7),"mmm")) -> FEB | M3: =UPPER(TEXT(EOMONTH(FiscalYearStartDate,8),"mmm")) -> MAR | N3: =UPPER(TEXT(EOMONTH(FiscalYearStartDate,9),"mmm")) -> APR | O3: =UPPER(TEXT(EOMONTH(FiscalYearStartDate,10),"mmm")) -> MAY | P3: =UPPER(TEXT(EOMONTH(FiscalYearStartDate,11),"mmm")) -> JUN | R3: Total
B4: ='Cash Receipts'!FiscalYearStartDate -> 44743 | D4: EST | E4: =FiscalYearStartDate -> 44743 | F4: =EOMONTH(E4,0)+DAY(FiscalYearStartDate) -> 44774 | G4: =EOMONTH(F4,0)+DAY(FiscalYearStartDate) -> 44805 | H4: =EOMONTH(G4,0)+DAY(FiscalYearStartDate) -> 44835 | I4: =EOMONTH(H4,0)+DAY(FiscalYearStartDate) -> 44866 | J4: =EOMONTH(I4,0)+DAY(FiscalYearStartDate) -> 44896 | K4: =EOMONTH(J4,0)+DAY(FiscalYearStartDate) -> 44927 | L4: =EOMONTH(K4,0)+DAY(FiscalYearStartDate) -> 44958 | M4: =EOMONTH(L4,0)+DAY(FiscalYearStartDate) -> 44986 | ... P4: =EOMONTH(O4,0)+DAY(FiscalYearStartDate) -> 45078 | R4: Item EST
B5: Cash Paid Out
B6: Purchases (merchandise) | E6: 400 | G6: 226 | R6: =SUM(CashPaidOut[[#This Row],[Period 0]:[Period 12]]) -> 626
B7: Purchases (specify) | R7: =SUM(CashPaidOut[[#This Row],[Period 0]:[Period 12]]) -> 0
B8: Purchases (specify) | R8: =SUM(CashPaidOut[[#This Row],[Period 0]:[Period 12]]) -> 0
B9: Gross wages (exact withdrawal) | R9: =SUM(CashPaidOut[[#This Row],[Period 0]:[Period 12]]) -> 0
B10: Payroll expenses (taxes, etc.) | R10: =SUM(CashPaidOut[[#This Row],[Period 0]:[Period 12]]) -> 0
B11: Outside services | R11: =SUM(CashPaidOut[[#This Row],[Period 0]:[Period 12]]) -> 0
B12: Supplies (office & operations) | R12: =SUM(CashPaidOut[[#This Row],[Period 0]:[Period 12]]) -> 0
B13: Repairs & maintenance | R13: =SUM(CashPaidOut[[#This Row],[Period 0]:[Period 12]]) -> 0
B14: Advertising | R14: =SUM(CashPaidOut[[#This Row],[Period 0]:[Period 12]]) -> 0
B15: Car, delivery & travel | R15: =SUM(CashPaidOut[[#This Row],[Period 0]:[Period 12]]) -> 0
B16: Accounting & legal | R16: =SUM(CashPaidOut[[#This Row],[Period 0]:[Period 12]]) -> 0
B17: Rent | R17: =SUM(CashPaidOut[[#This Row],[Period 0]:[Period 12]]) -> 0
B18: Telephone | R18: =SUM(CashPaidOut[[#This Row],[Period 0]:[Period 12]]) -> 0
... B26: Miscellaneous | R26: =SUM(CashPaidOut[[#This Row],[Period 0]:[Period 12]]) -> 0
B27: Total | D27: =SUBTOTAL(109,CashPaidOut[Period 0]) -> 0 | E27: =SUBTOTAL(109,CashPaidOut[Period 1]) -> 400 | F27: =SUBTOTAL(109,CashPaidOut[Period 2]) -> 0 | G27: =SUBTOTAL(109,CashPaidOut[Period 3]) -> 226 | H27: =SUBTOTAL(109,CashPaidOut[Period 4]) -> 0 | I27: =SUBTOTAL(109,CashPaidOut[Period 5]) -> 0 | J27: =SUBTOTAL(109,CashPaidOut[Period 6]) -> 0 | K27: =SUBTOTAL(109,CashPaidOut[Period 7]) -> 0 | L27: =SUBTOTAL(109,CashPaidOut[Period 8]) -> 0 | M27: =SUBTOTAL(109,CashPaidOut[Period 9]) -> 0 | N27: =SUBTOTAL(109,CashPaidOut[Period 10]) -> 0 | O27: =SUBTOTAL(109,CashPaidOut[Period 11]) -> 0 | P27: =SUBTOTAL(109,CashPaidOut[Period 12]) -> 0 | R27: =SUBTOTAL(109,CashPaidOut[Total]) -> 626

Sheet Cash Paid Out (Non P&L)
B1: Cash Flow Statement
B3: Fiscal year begins: | D3: (Pre) Startup | E3: =UPPER(TEXT(FiscalYearStartDate,"mmm")) -> JUL | F3: =UPPER(TEXT(EOMONTH(FiscalYearStartDate,1),"mmm")) -> AUG | G3: =UPPER(TEXT(EOMONTH(FiscalYearStartDate,2),"mmm")) -> SEP | H3: =UPPER(TEXT(EOMONTH(FiscalYearStartDate,3),"mmm")) -> OCT | I3: =UPPER(TEXT(EOMONTH(FiscalYearStartDate,4),"mmm")) -> NOV | J3: =UPPER(TEXT(EOMONTH(FiscalYearStartDate,5),"mmm")) -> DEC | K3: =UPPER(TEXT(EOMONTH(FiscalYearStartDate,6),"mmm")) -> JAN | L3: =UPPER(TEXT(EOMONTH(FiscalYearStartDate,7),"mmm")) -> FEB | M3: =UPPER(TEXT(EOMONTH(FiscalYearStartDate,8),"mmm")) -> MAR | N3: =UPPER(TEXT(EOMONTH(FiscalYearStartDate,9),"mmm")) -> APR | O3: =UPPER(TEXT(EOMONTH(FiscalYearStartDate,10),"mmm")) -> MAY | P3: =UPPER(TEXT(EOMONTH(FiscalYearStartDate,11),"mmm")) -> JUN | R3: Total
B4: ='Cash Receipts'!FiscalYearStartDate -> 44743 | D4: EST | E4: =FiscalYearStartDate -> 44743 | F4: =EOMONTH(E4,0)+DAY(FiscalYearStartDate) -> 44774 | G4: =EOMONTH(F4,0)+DAY(FiscalYearStartDate) -> 44805 | H4: =EOMONTH(G4,0)+DAY(FiscalYearStartDate) -> 44835 | I4: =EOMONTH(H4,0)+DAY(FiscalYearStartDate) -> 44866 | J4: =EOMONTH(I4,0)+DAY(FiscalYearStartDate) -> 44896 | K4: =EOMONTH(J4,0)+DAY(FiscalYearStartDate) -> 44927 | L4: =EOMONTH(K4,0)+DAY(FiscalYearStartDate) -> 44958 | M4: =EOMONTH(L4,0)+DAY(FiscalYearStartDate) -> 44986 | ... P4: =EOMONTH(O4,0)+DAY(FiscalYearStartDate) -> 45078 | R4: Item EST
B5: Cash Paid Out (Non P&L)
B6: Loan principal payment | R6: =SUM(CashPaid[[#This Row],[Period 0]:[Period 12]]) -> 0
B7: Capital purchase (specify) | R7: =SUM(CashPaid[[#This Row],[Period 0]:[Period 12]]) -> 0
B8: Other startup costs | R8: =SUM(CashPaid[[#This Row],[Period 0]:[Period 12]]) -> 0
B9: Reserve and/or escrow | R9: =SUM(CashPaid[[#This Row],[Period 0]:[Period 12]]) -> 0
B10: Owners' withdrawal | R10: =SUM(CashPaid[[#This Row],[Period 0]:[Period 12]]) -> 0
B11: Total | D11: =SUBTOTAL(109,CashPaid[Period 0]) -> 0 | E11: =SUBTOTAL(109,CashPaid[Period 1]) -> 0 | F11: =SUBTOTAL(109,CashPaid[Period 2]) -> 0 | G11: =SUBTOTAL(109,CashPaid[Period 3]) -> 0 | H11: =SUBTOTAL(109,CashPaid[Period 4]) -> 0 | I11: =SUBTOTAL(109,CashPaid[Period 5]) -> 0 | J11: =SUBTOTAL(109,CashPaid[Period 6]) -> 0 | K11: =SUBTOTAL(109,CashPaid[Period 7]) -> 0 | L11: =SUBTOTAL(109,CashPaid[Period 8]) -> 0 | M11: =SUBTOTAL(109,CashPaid[Period 9]) -> 0 | N11: =SUBTOTAL(109,CashPaid[Period 10]) -> 0 | O11: =SUBTOTAL(109,CashPaid[Period 11]) -> 0 | P11: =SUBTOTAL(109,CashPaid[Period 12]) -> 0 | R11: =SUBTOTAL(109,CashPaid[Total]) -> 0
B12: Total Cash Paid Out | D12: =SUM(CashPaidOut[Period 0],CashPaid[Period 0]) -> 0 | E12: =SUM(CashPaidOut[Period 1],CashPaid[Period 1]) -> 400 | F12: =SUM(CashPaidOut[Period 2],CashPaid[Period 2]) -> 0 | G12: =SUM(CashPaidOut[Period 3],CashPaid[Period 3]) -> 226 | H12: =SUM(CashPaidOut[Period 4],CashPaid[Period 4]) -> 0 | I12: =SUM(CashPaidOut[Period 5],CashPaid[Period 5]) -> 0 | J12: =SUM(CashPaidOut[Period 6],CashPaid[Period 6]) -> 0 | K12: =SUM(CashPaidOut[Period 7],CashPaid[Period 7]) -> 0 | L12: =SUM(CashPaidOut[Period 8],CashPaid[Period 8]) -> 0 | M12: =SUM(CashPaidOut[Period 9],CashPaid[Period 9]) -> 0 | N12: =SUM(CashPaidOut[Period 10],CashPaid[Period 10]) -> 0 | O12: =SUM(CashPaidOut[Period 11],CashPaid[Period 11]) -> 0 | P12: =SUM(CashPaidOut[Period 12],CashPaid[Period 12]) -> 0 | R12: =SUM(CashPaidOut[Total],CashPaid[Total]) -> 626
