Workbook
Name CountryList: 'Lists'!$B$1:$AG$1
Name CountryISO: 'Lists'!$B$2:$AG$2
Name Incoterms: 'Lists'!$B$4:$AG$4
Name TransportMode: 'Lists'!$B$5:$AG$5
Name Currency: 'Lists'!$B$6:$AG$6
Name Units: 'Lists'!$B$7:$AG$7
Name ProcedureCode: 'Lists'!$B$8:$AG$8
Name LangCodes: 'Lists'!$B$10:$AG$10
Name VATTypeList: 'Lists'!$B$198:$AG$198
Name CountryLang_Country: 'Lists'!$A$13:$A$45
Name CountryLang_Code: 'Lists'!$B$13:$B$45
Name VAT_Country: 'Lists'!$A$202:$A$233
Name VAT_Standard: 'Lists'!$B$202:$B$233
Name VAT_Reduced1: 'Lists'!$C$202:$C$233
Name VAT_Reduced2: 'Lists'!$D$202:$D$233

Sheet Cover
A1: EU Customs Declaration — Master Template (Import/Export)
A3: One file for all EU countries + UK/NO/CH/IS/LI with auto VAT, localization, and print-ready pages.
A5: Highlights
A6: • Country selector (auto language EN/EE/DE/FR based on country)
A7: • Import / Export selector (SAD-style fields)
A8: • Items with duty/VAT/total auto-calculation
A9: • Default VAT: Standard + Reduced1 + Reduced2 (editable)
A10: • Per-line VAT Type (Standard/Reduced/Manual)
A11: • Professional formatting + print to PDF (macro module included)

Sheet Instructions
A1: EU Customs Declaration Master Template (Import/Export)
A2: Version: 2025-08-17 • Author: Imprint • Languages: EN/EE/DE/FR
A4: Pick Country and Flow on 'Declaration'. Items on 'Items'. Totals on 'Summary'. Default VAT loads by Country. You can localize labels by editing 'Translations' and language mapping on 'Lists'.

Sheet Declaration
A1: Customs Declaration (SAD-style) — Master | H1: Country | I1: =B3
H2: Flow | I2: =B4
A3: =INDEX(Translations!$B:$E, MATCH("Select Country", Translations!$A:$A, 0), MATCH($I$3, Lists!$B$10:$E$10, 0)) | H3: Language | I3: =IFERROR(XLOOKUP(B3, CountryLang_Country, CountryLang_Code), "EN")
A4: =INDEX(Translations!$B:$E, MATCH("Select Flow", Translations!$A:$A, 0), MATCH($I$3, Lists!$B$10:$E$10, 0))
A6: =INDEX(Translations!$B:$E, MATCH("Declarant (Company Name)", Translations!$A:$A, 0), MATCH($I$3, Lists!$B$10:$E$10, 0))
A7: =INDEX(Translations!$B:$E, MATCH("Registry code / EORI / VAT", Translations!$A:$A, 0), MATCH($I$3, Lists!$B$10:$E$10, 0))
A8: =INDEX(Translations!$B:$E, MATCH("Address", Translations!$A:$A, 0), MATCH($I$3, Lists!$B$10:$E$10, 0))
A9: =INDEX(Translations!$B:$E, MATCH("Contact person", Translations!$A:$A, 0), MATCH($I$3, Lists!$B$10:$E$10, 0))
A10: =INDEX(Translations!$B:$E, MATCH("Contact email", Translations!$A:$A, 0), MATCH($I$3, Lists!$B$10:$E$10, 0))
A11: =INDEX(Translations!$B:$E, MATCH("Contact phone", Translations!$A:$A, 0), MATCH($I$3, Lists!$B$10:$E$10, 0))
A13: =INDEX(Translations!$B:$E, MATCH("Consignor (Seller / Exporter)", Translations!$A:$A, 0), MATCH($I$3, Lists!$B$10:$E$10, 0))
A14: =INDEX(Translations!$B:$E, MATCH("Consignee (Buyer / Importer)", Translations!$A:$A, 0), MATCH($I$3, Lists!$B$10:$E$10, 0))
A15: =INDEX(Translations!$B:$E, MATCH("Consignor VAT/EORI", Translations!$A:$A, 0), MATCH($I$3, Lists!$B$10:$E$10, 0))
A16: =INDEX(Translations!$B:$E, MATCH("Consignee VAT/EORI", Translations!$A:$A, 0), MATCH($I$3, Lists!$B$10:$E$10, 0))
A18: =INDEX(Translations!$B:$E, MATCH("Shipment & Procedure", Translations!$A:$A, 0), MATCH($I$3, Lists!$B$10:$E$10, 0))
A20: =INDEX(Translations!$B:$E, MATCH("Procedure code", Translations!$A:$A, 0), MATCH($I$3, Lists!$B$10:$E$10, 0))
A21: =INDEX(Translations!$B:$E, MATCH("Incoterms", Translations!$A:$A, 0), MATCH($I$3, Lists!$B$10:$E$10, 0))
A22: =INDEX(Translations!$B:$E, MATCH("Country of dispatch/destination (ISO)", Translations!$A:$A, 0), MATCH($I$3, Lists!$B$10:$E$10, 0))
A23: =INDEX(Translations!$B:$E, MATCH("Mode of transport at border", Translations!$A:$A, 0), MATCH($I$3, Lists!$B$10:$E$10, 0))
A24: =INDEX(Translations!$B:$E, MATCH("Border crossing point / Vehicle No.", Translations!$A:$A, 0), MATCH($I$3, Lists!$B$10:$E$10, 0))
A25: =INDEX(Translations!$B:$E, MATCH("Invoice number / date", Translations!$A:$A, 0), MATCH($I$3, Lists!$B$10:$E$10, 0))
A26: =INDEX(Translations!$B:$E, MATCH("Reference / Order No.", Translations!$A:$A, 0), MATCH($I$3, Lists!$B$10:$E$10, 0))
A28: =INDEX(Translations!$B:$E, MATCH("Totals (from Items)", Translations!$A:$A, 0), MATCH($I$3, Lists!$B$10:$E$10, 0))
A30: =INDEX(Translations!$B:$E, MATCH("Customs Value (EUR)", Translations!$A:$A, 0), MATCH($I$3, Lists!$B$10:$E$10, 0)) | B30: =Summary!B6
A31: =INDEX(Translations!$B:$E, MATCH("Duty (EUR)", Translations!$A:$A, 0), MATCH($I$3, Lists!$B$10:$E$10, 0)) | B31: =Summary!B7
A32: =INDEX(Translations!$B:$E, MATCH("VAT (EUR)", Translations!$A:$A, 0), MATCH($I$3, Lists!$B$10:$E$10, 0)) | B32: =Summary!B8
A33: =INDEX(Translations!$B:$E, MATCH("Total Taxes (EUR)", Translations!$A:$A, 0), MATCH($I$3, Lists!$B$10:$E$10, 0)) | B33: =Summary!B9
A34: =INDEX(Translations!$B:$E, MATCH("Grand Total (EUR)", Translations!$A:$A, 0), MATCH($I$3, Lists!$B$10:$E$10, 0)) | B34: =Summary!B10

Sheet Items
A1: Line | B1: HS Code | C1: Description of goods | D1: Origin (ISO) | E1: Qty | F1: Unit | G1: Net Weight (kg) | H1: Gross Weight (kg) | I1: Currency | J1: Unit Price | K1: Line Value (Currency) | L1: Freight | M1: Insurance | N1: Other Costs | O1: Customs Value (EUR) | P1: Duty Rate (%) | Q1: Duty (EUR) | R1: VAT Type | S1: Manual VAT (%) | T1: VAT Rate (%) | U1: VAT (EUR) | V1: Total Taxes (EUR) | W1: Line Total (EUR)
A2: 1 | K2: =IFERROR(E2*J2,0) | O2: =SUM(L2:N2)+IF(I2="EUR",K2,K2) | Q2: =IFERROR(O2*P2/100,0) | R2: Standard | T2: =IF(R2="Manual", IFERROR(S2, Summary!B5), IF(R2="Reduced1", Summary!C5, IF(R2="Reduced2", Summary!D5, Summary!B5))) | U2: =IFERROR((O2+Q2)*T2/100,0) | V2: =Q2+U2 | W2: =O2+V2
A3: 2 | K3: =IFERROR(E3*J3,0) | O3: =SUM(L3:N3)+IF(I3="EUR",K3,K3) | Q3: =IFERROR(O3*P3/100,0) | R3: Standard | T3: =IF(R3="Manual", IFERROR(S3, Summary!B5), IF(R3="Reduced1", Summary!C5, IF(R3="Reduced2", Summary!D5, Summary!B5))) | U3: =IFERROR((O3+Q3)*T3/100,0) | V3: =Q3+U3 | W3: =O3+V3
A4: 3 | K4: =IFERROR(E4*J4,0) | O4: =SUM(L4:N4)+IF(I4="EUR",K4,K4) | Q4: =IFERROR(O4*P4/100,0) | R4: Standard | T4: =IF(R4="Manual", IFERROR(S4, Summary!B5), IF(R4="Reduced1", Summary!C5, IF(R4="Reduced2", Summary!D5, Summary!B5))) | U4: =IFERROR((O4+Q4)*T4/100,0) | V4: =Q4+U4 | W4: =O4+V4
A5: 4 | K5: =IFERROR(E5*J5,0) | O5: =SUM(L5:N5)+IF(I5="EUR",K5,K5) | Q5: =IFERROR(O5*P5/100,0) | R5: Standard | T5: =IF(R5="Manual", IFERROR(S5, Summary!B5), IF(R5="Reduced1", Summary!C5, IF(R5="Reduced2", Summary!D5, Summary!B5))) | U5: =IFERROR((O5+Q5)*T5/100,0) | V5: =Q5+U5 | W5: =O5+V5
A6: 5 | K6: =IFERROR(E6*J6,0) | O6: =SUM(L6:N6)+IF(I6="EUR",K6,K6) | Q6: =IFERROR(O6*P6/100,0) | R6: Standard | T6: =IF(R6="Manual", IFERROR(S6, Summary!B5), IF(R6="Reduced1", Summary!C5, IF(R6="Reduced2", Summary!D5, Summary!B5))) | U6: =IFERROR((O6+Q6)*T6/100,0) | V6: =Q6+U6 | W6: =O6+V6
A7: 6 | K7: =IFERROR(E7*J7,0) | O7: =SUM(L7:N7)+IF(I7="EUR",K7,K7) | Q7: =IFERROR(O7*P7/100,0) | R7: Standard | T7: =IF(R7="Manual", IFERROR(S7, Summary!B5), IF(R7="Reduced1", Summary!C5, IF(R7="Reduced2", Summary!D5, Summary!B5))) | U7: =IFERROR((O7+Q7)*T7/100,0) | V7: =Q7+U7 | W7: =O7+V7
A8: 7 | K8: =IFERROR(E8*J8,0) | O8: =SUM(L8:N8)+IF(I8="EUR",K8,K8) | Q8: =IFERROR(O8*P8/100,0) | R8: Standard | T8: =IF(R8="Manual", IFERROR(S8, Summary!B5), IF(R8="Reduced1", Summary!C5, IF(R8="Reduced2", Summary!D5, Summary!B5))) | U8: =IFERROR((O8+Q8)*T8/100,0) | V8: =Q8+U8 | W8: =O8+V8
A9: 8 | K9: =IFERROR(E9*J9,0) | O9: =SUM(L9:N9)+IF(I9="EUR",K9,K9) | Q9: =IFERROR(O9*P9/100,0) | R9: Standard | T9: =IF(R9="Manual", IFERROR(S9, Summary!B5), IF(R9="Reduced1", Summary!C5, IF(R9="Reduced2", Summary!D5, Summary!B5))) | U9: =IFERROR((O9+Q9)*T9/100,0) | V9: =Q9+U9 | W9: =O9+V9
A10: 9 | K10: =IFERROR(E10*J10,0) | O10: =SUM(L10:N10)+IF(I10="EUR",K10,K10) | Q10: =IFERROR(O10*P10/100,0) | R10: Standard | T10: =IF(R10="Manual", IFERROR(S10, Summary!B5), IF(R10="Reduced1", Summary!C5, IF(R10="Reduced2", Summary!D5, Summary!B5))) | U10: =IFERROR((O10+Q10)*T10/100,0) | V10: =Q10+U10 | W10: =O10+V10
A11: 10 | K11: =IFERROR(E11*J11,0) | O11: =SUM(L11:N11)+IF(I11="EUR",K11,K11) | Q11: =IFERROR(O11*P11/100,0) | R11: Standard | T11: =IF(R11="Manual", IFERROR(S11, Summary!B5), IF(R11="Reduced1", Summary!C5, IF(R11="Reduced2", Summary!D5, Summary!B5))) | U11: =IFERROR((O11+Q11)*T11/100,0) | V11: =Q11+U11 | W11: =O11+V11
A12: 11 | K12: =IFERROR(E12*J12,0) | O12: =SUM(L12:N12)+IF(I12="EUR",K12,K12) | Q12: =IFERROR(O12*P12/100,0) | R12: Standard | T12: =IF(R12="Manual", IFERROR(S12, Summary!B5), IF(R12="Reduced1", Summary!C5, IF(R12="Reduced2", Summary!D5, Summary!B5))) | U12: =IFERROR((O12+Q12)*T12/100,0) | V12: =Q12+U12 | W12: =O12+V12
A13: 12 | K13: =IFERROR(E13*J13,0) | O13: =SUM(L13:N13)+IF(I13="EUR",K13,K13) | Q13: =IFERROR(O13*P13/100,0) | R13: Standard | T13: =IF(R13="Manual", IFERROR(S13, Summary!B5), IF(R13="Reduced1", Summary!C5, IF(R13="Reduced2", Summary!D5, Summary!B5))) | U13: =IFERROR((O13+Q13)*T13/100,0) | V13: =Q13+U13 | W13: =O13+V13
A14: 13 | K14: =IFERROR(E14*J14,0) | O14: =SUM(L14:N14)+IF(I14="EUR",K14,K14) | Q14: =IFERROR(O14*P14/100,0) | R14: Standard | T14: =IF(R14="Manual", IFERROR(S14, Summary!B5), IF(R14="Reduced1", Summary!C5, IF(R14="Reduced2", Summary!D5, Summary!B5))) | U14: =IFERROR((O14+Q14)*T14/100,0) | V14: =Q14+U14 | W14: =O14+V14
A15: 14 | K15: =IFERROR(E15*J15,0) | O15: =SUM(L15:N15)+IF(I15="EUR",K15,K15) | Q15: =IFERROR(O15*P15/100,0) | R15: Standard | T15: =IF(R15="Manual", IFERROR(S15, Summary!B5), IF(R15="Reduced1", Summary!C5, IF(R15="Reduced2", Summary!D5, Summary!B5))) | U15: =IFERROR((O15+Q15)*T15/100,0) | V15: =Q15+U15 | W15: =O15+V15
A16: 15 | K16: =IFERROR(E16*J16,0) | O16: =SUM(L16:N16)+IF(I16="EUR",K16,K16) | Q16: =IFERROR(O16*P16/100,0) | R16: Standard | T16: =IF(R16="Manual", IFERROR(S16, Summary!B5), IF(R16="Reduced1", Summary!C5, IF(R16="Reduced2", Summary!D5, Summary!B5))) | U16: =IFERROR((O16+Q16)*T16/100,0) | V16: =Q16+U16 | W16: =O16+V16
A17: 16 | K17: =IFERROR(E17*J17,0) | O17: =SUM(L17:N17)+IF(I17="EUR",K17,K17) | Q17: =IFERROR(O17*P17/100,0) | R17: Standard | T17: =IF(R17="Manual", IFERROR(S17, Summary!B5), IF(R17="Reduced1", Summary!C5, IF(R17="Reduced2", Summary!D5, Summary!B5))) | U17: =IFERROR((O17+Q17)*T17/100,0) | V17: =Q17+U17 | W17: =O17+V17
A18: 17 | K18: =IFERROR(E18*J18,0) | O18: =SUM(L18:N18)+IF(I18="EUR",K18,K18) | Q18: =IFERROR(O18*P18/100,0) | R18: Standard | T18: =IF(R18="Manual", IFERROR(S18, Summary!B5), IF(R18="Reduced1", Summary!C5, IF(R18="Reduced2", Summary!D5, Summary!B5))) | U18: =IFERROR((O18+Q18)*T18/100,0) | V18: =Q18+U18 | W18: =O18+V18
A19: 18 | K19: =IFERROR(E19*J19,0) | O19: =SUM(L19:N19)+IF(I19="EUR",K19,K19) | Q19: =IFERROR(O19*P19/100,0) | R19: Standard | T19: =IF(R19="Manual", IFERROR(S19, Summary!B5), IF(R19="Reduced1", Summary!C5, IF(R19="Reduced2", Summary!D5, Summary!B5))) | U19: =IFERROR((O19+Q19)*T19/100,0) | V19: =Q19+U19 | W19: =O19+V19
A20: 19 | K20: =IFERROR(E20*J20,0) | O20: =SUM(L20:N20)+IF(I20="EUR",K20,K20) | Q20: =IFERROR(O20*P20/100,0) | R20: Standard | T20: =IF(R20="Manual", IFERROR(S20, Summary!B5), IF(R20="Reduced1", Summary!C5, IF(R20="Reduced2", Summary!D5, Summary!B5))) | U20: =IFERROR((O20+Q20)*T20/100,0) | V20: =Q20+U20 | W20: =O20+V20
A21: 20 | K21: =IFERROR(E21*J21,0) | O21: =SUM(L21:N21)+IF(I21="EUR",K21,K21) | Q21: =IFERROR(O21*P21/100,0) | R21: Standard | T21: =IF(R21="Manual", IFERROR(S21, Summary!B5), IF(R21="Reduced1", Summary!C5, IF(R21="Reduced2", Summary!D5, Summary!B5))) | U21: =IFERROR((O21+Q21)*T21/100,0) | V21: =Q21+U21 | W21: =O21+V21
A22: 21 | K22: =IFERROR(E22*J22,0) | O22: =SUM(L22:N22)+IF(I22="EUR",K22,K22) | Q22: =IFERROR(O22*P22/100,0) | R22: Standard | T22: =IF(R22="Manual", IFERROR(S22, Summary!B5), IF(R22="Reduced1", Summary!C5, IF(R22="Reduced2", Summary!D5, Summary!B5))) | U22: =IFERROR((O22+Q22)*T22/100,0) | V22: =Q22+U22 | W22: =O22+V22
A23: 22 | K23: =IFERROR(E23*J23,0) | O23: =SUM(L23:N23)+IF(I23="EUR",K23,K23) | Q23: =IFERROR(O23*P23/100,0) | R23: Standard | T23: =IF(R23="Manual", IFERROR(S23, Summary!B5), IF(R23="Reduced1", Summary!C5, IF(R23="Reduced2", Summary!D5, Summary!B5))) | U23: =IFERROR((O23+Q23)*T23/100,0) | V23: =Q23+U23 | W23: =O23+V23
A24: 23 | K24: =IFERROR(E24*J24,0) | O24: =SUM(L24:N24)+IF(I24="EUR",K24,K24) | Q24: =IFERROR(O24*P24/100,0) | R24: Standard | T24: =IF(R24="Manual", IFERROR(S24, Summary!B5), IF(R24="Reduced1", Summary!C5, IF(R24="Reduced2", Summary!D5, Summary!B5))) | U24: =IFERROR((O24+Q24)*T24/100,0) | V24: =Q24+U24 | W24: =O24+V24
A25: 24 | K25: =IFERROR(E25*J25,0) | O25: =SUM(L25:N25)+IF(I25="EUR",K25,K25) | Q25: =IFERROR(O25*P25/100,0) | R25: Standard | T25: =IF(R25="Manual", IFERROR(S25, Summary!B5), IF(R25="Reduced1", Summary!C5, IF(R25="Reduced2", Summary!D5, Summary!B5))) | U25: =IFERROR((O25+Q25)*T25/100,0) | V25: =Q25+U25 | W25: =O25+V25
A26: 25 | K26: =IFERROR(E26*J26,0) | O26: =SUM(L26:N26)+IF(I26="EUR",K26,K26) | Q26: =IFERROR(O26*P26/100,0) | R26: Standard | T26: =IF(R26="Manual", IFERROR(S26, Summary!B5), IF(R26="Reduced1", Summary!C5, IF(R26="Reduced2", Summary!D5, Summary!B5))) | U26: =IFERROR((O26+Q26)*T26/100,0) | V26: =Q26+U26 | W26: =O26+V26
A27: 26 | K27: =IFERROR(E27*J27,0) | O27: =SUM(L27:N27)+IF(I27="EUR",K27,K27) | Q27: =IFERROR(O27*P27/100,0) | R27: Standard | T27: =IF(R27="Manual", IFERROR(S27, Summary!B5), IF(R27="Reduced1", Summary!C5, IF(R27="Reduced2", Summary!D5, Summary!B5))) | U27: =IFERROR((O27+Q27)*T27/100,0) | V27: =Q27+U27 | W27: =O27+V27
A28: 27 | K28: =IFERROR(E28*J28,0) | O28: =SUM(L28:N28)+IF(I28="EUR",K28,K28) | Q28: =IFERROR(O28*P28/100,0) | R28: Standard | T28: =IF(R28="Manual", IFERROR(S28, Summary!B5), IF(R28="Reduced1", Summary!C5, IF(R28="Reduced2", Summary!D5, Summary!B5))) | U28: =IFERROR((O28+Q28)*T28/100,0) | V28: =Q28+U28 | W28: =O28+V28
A29: 28 | K29: =IFERROR(E29*J29,0) | O29: =SUM(L29:N29)+IF(I29="EUR",K29,K29) | Q29: =IFERROR(O29*P29/100,0) | R29: Standard | T29: =IF(R29="Manual", IFERROR(S29, Summary!B5), IF(R29="Reduced1", Summary!C5, IF(R29="Reduced2", Summary!D5, Summary!B5))) | U29: =IFERROR((O29+Q29)*T29/100,0) | V29: =Q29+U29 | W29: =O29+V29
A30: 29 | K30: =IFERROR(E30*J30,0) | O30: =SUM(L30:N30)+IF(I30="EUR",K30,K30) | Q30: =IFERROR(O30*P30/100,0) | R30: Standard | T30: =IF(R30="Manual", IFERROR(S30, Summary!B5), IF(R30="Reduced1", Summary!C5, IF(R30="Reduced2", Summary!D5, Summary!B5))) | U30: =IFERROR((O30+Q30)*T30/100,0) | V30: =Q30+U30 | W30: =O30+V30
A31: 30 | K31: =IFERROR(E31*J31,0) | O31: =SUM(L31:N31)+IF(I31="EUR",K31,K31) | Q31: =IFERROR(O31*P31/100,0) | R31: Standard | T31: =IF(R31="Manual", IFERROR(S31, Summary!B5), IF(R31="Reduced1", Summary!C5, IF(R31="Reduced2", Summary!D5, Summary!B5))) | U31: =IFERROR((O31+Q31)*T31/100,0) | V31: =Q31+U31 | W31: =O31+V31
A32: 31 | K32: =IFERROR(E32*J32,0) | O32: =SUM(L32:N32)+IF(I32="EUR",K32,K32) | Q32: =IFERROR(O32*P32/100,0) | R32: Standard | T32: =IF(R32="Manual", IFERROR(S32, Summary!B5), IF(R32="Reduced1", Summary!C5, IF(R32="Reduced2", Summary!D5, Summary!B5))) | U32: =IFERROR((O32+Q32)*T32/100,0) | V32: =Q32+U32 | W32: =O32+V32
A33: 32 | K33: =IFERROR(E33*J33,0) | O33: =SUM(L33:N33)+IF(I33="EUR",K33,K33) | Q33: =IFERROR(O33*P33/100,0) | R33: Standard | T33: =IF(R33="Manual", IFERROR(S33, Summary!B5), IF(R33="Reduced1", Summary!C5, IF(R33="Reduced2", Summary!D5, Summary!B5))) | U33: =IFERROR((O33+Q33)*T33/100,0) | V33: =Q33+U33 | W33: =O33+V33
A34: 33 | K34: =IFERROR(E34*J34,0) | O34: =SUM(L34:N34)+IF(I34="EUR",K34,K34) | Q34: =IFERROR(O34*P34/100,0) | R34: Standard | T34: =IF(R34="Manual", IFERROR(S34, Summary!B5), IF(R34="Reduced1", Summary!C5, IF(R34="Reduced2", Summary!D5, Summary!B5))) | U34: =IFERROR((O34+Q34)*T34/100,0) | V34: =Q34+U34 | W34: =O34+V34
A35: 34 | K35: =IFERROR(E35*J35,0) | O35: =SUM(L35:N35)+IF(I35="EUR",K35,K35) | Q35: =IFERROR(O35*P35/100,0) | R35: Standard | T35: =IF(R35="Manual", IFERROR(S35, Summary!B5), IF(R35="Reduced1", Summary!C5, IF(R35="Reduced2", Summary!D5, Summary!B5))) | U35: =IFERROR((O35+Q35)*T35/100,0) | V35: =Q35+U35 | W35: =O35+V35
A36: 35 | K36: =IFERROR(E36*J36,0) | O36: =SUM(L36:N36)+IF(I36="EUR",K36,K36) | Q36: =IFERROR(O36*P36/100,0) | R36: Standard | T36: =IF(R36="Manual", IFERROR(S36, Summary!B5), IF(R36="Reduced1", Summary!C5, IF(R36="Reduced2", Summary!D5, Summary!B5))) | U36: =IFERROR((O36+Q36)*T36/100,0) | V36: =Q36+U36 | W36: =O36+V36
A37: 36 | K37: =IFERROR(E37*J37,0) | O37: =SUM(L37:N37)+IF(I37="EUR",K37,K37) | Q37: =IFERROR(O37*P37/100,0) | R37: Standard | T37: =IF(R37="Manual", IFERROR(S37, Summary!B5), IF(R37="Reduced1", Summary!C5, IF(R37="Reduced2", Summary!D5, Summary!B5))) | U37: =IFERROR((O37+Q37)*T37/100,0) | V37: =Q37+U37 | W37: =O37+V37
A38: 37 | K38: =IFERROR(E38*J38,0) | O38: =SUM(L38:N38)+IF(I38="EUR",K38,K38) | Q38: =IFERROR(O38*P38/100,0) | R38: Standard | T38: =IF(R38="Manual", IFERROR(S38, Summary!B5), IF(R38="Reduced1", Summary!C5, IF(R38="Reduced2", Summary!D5, Summary!B5))) | U38: =IFERROR((O38+Q38)*T38/100,0) | V38: =Q38+U38 | W38: =O38+V38
A39: 38 | K39: =IFERROR(E39*J39,0) | O39: =SUM(L39:N39)+IF(I39="EUR",K39,K39) | Q39: =IFERROR(O39*P39/100,0) | R39: Standard | T39: =IF(R39="Manual", IFERROR(S39, Summary!B5), IF(R39="Reduced1", Summary!C5, IF(R39="Reduced2", Summary!D5, Summary!B5))) | U39: =IFERROR((O39+Q39)*T39/100,0) | V39: =Q39+U39 | W39: =O39+V39
A40: 39 | K40: =IFERROR(E40*J40,0) | O40: =SUM(L40:N40)+IF(I40="EUR",K40,K40) | Q40: =IFERROR(O40*P40/100,0) | R40: Standard | T40: =IF(R40="Manual", IFERROR(S40, Summary!B5), IF(R40="Reduced1", Summary!C5, IF(R40="Reduced2", Summary!D5, Summary!B5))) | U40: =IFERROR((O40+Q40)*T40/100,0) | V40: =Q40+U40 | W40: =O40+V40
A41: 40 | K41: =IFERROR(E41*J41,0) | O41: =SUM(L41:N41)+IF(I41="EUR",K41,K41) | Q41: =IFERROR(O41*P41/100,0) | R41: Standard | T41: =IF(R41="Manual", IFERROR(S41, Summary!B5), IF(R41="Reduced1", Summary!C5, IF(R41="Reduced2", Summary!D5, Summary!B5))) | U41: =IFERROR((O41+Q41)*T41/100,0) | V41: =Q41+U41 | W41: =O41+V41
A42: 41 | K42: =IFERROR(E42*J42,0) | O42: =SUM(L42:N42)+IF(I42="EUR",K42,K42) | Q42: =IFERROR(O42*P42/100,0) | R42: Standard | T42: =IF(R42="Manual", IFERROR(S42, Summary!B5), IF(R42="Reduced1", Summary!C5, IF(R42="Reduced2", Summary!D5, Summary!B5))) | U42: =IFERROR((O42+Q42)*T42/100,0) | V42: =Q42+U42 | W42: =O42+V42
A43: 42 | K43: =IFERROR(E43*J43,0) | O43: =SUM(L43:N43)+IF(I43="EUR",K43,K43) | Q43: =IFERROR(O43*P43/100,0) | R43: Standard | T43: =IF(R43="Manual", IFERROR(S43, Summary!B5), IF(R43="Reduced1", Summary!C5, IF(R43="Reduced2", Summary!D5, Summary!B5))) | U43: =IFERROR((O43+Q43)*T43/100,0) | V43: =Q43+U43 | W43: =O43+V43
A44: 43 | K44: =IFERROR(E44*J44,0) | O44: =SUM(L44:N44)+IF(I44="EUR",K44,K44) | Q44: =IFERROR(O44*P44/100,0) | R44: Standard | T44: =IF(R44="Manual", IFERROR(S44, Summary!B5), IF(R44="Reduced1", Summary!C5, IF(R44="Reduced2", Summary!D5, Summary!B5))) | U44: =IFERROR((O44+Q44)*T44/100,0) | V44: =Q44+U44 | W44: =O44+V44
A45: 44 | K45: =IFERROR(E45*J45,0) | O45: =SUM(L45:N45)+IF(I45="EUR",K45,K45) | Q45: =IFERROR(O45*P45/100,0) | R45: Standard | T45: =IF(R45="Manual", IFERROR(S45, Summary!B5), IF(R45="Reduced1", Summary!C5, IF(R45="Reduced2", Summary!D5, Summary!B5))) | U45: =IFERROR((O45+Q45)*T45/100,0) | V45: =Q45+U45 | W45: =O45+V45
A46: 45 | K46: =IFERROR(E46*J46,0) | O46: =SUM(L46:N46)+IF(I46="EUR",K46,K46) | Q46: =IFERROR(O46*P46/100,0) | R46: Standard | T46: =IF(R46="Manual", IFERROR(S46, Summary!B5), IF(R46="Reduced1", Summary!C5, IF(R46="Reduced2", Summary!D5, Summary!B5))) | U46: =IFERROR((O46+Q46)*T46/100,0) | V46: =Q46+U46 | W46: =O46+V46
A47: 46 | K47: =IFERROR(E47*J47,0) | O47: =SUM(L47:N47)+IF(I47="EUR",K47,K47) | Q47: =IFERROR(O47*P47/100,0) | R47: Standard | T47: =IF(R47="Manual", IFERROR(S47, Summary!B5), IF(R47="Reduced1", Summary!C5, IF(R47="Reduced2", Summary!D5, Summary!B5))) | U47: =IFERROR((O47+Q47)*T47/100,0) | V47: =Q47+U47 | W47: =O47+V47
A48: 47 | K48: =IFERROR(E48*J48,0) | O48: =SUM(L48:N48)+IF(I48="EUR",K48,K48) | Q48: =IFERROR(O48*P48/100,0) | R48: Standard | T48: =IF(R48="Manual", IFERROR(S48, Summary!B5), IF(R48="Reduced1", Summary!C5, IF(R48="Reduced2", Summary!D5, Summary!B5))) | U48: =IFERROR((O48+Q48)*T48/100,0) | V48: =Q48+U48 | W48: =O48+V48
A49: 48 | K49: =IFERROR(E49*J49,0) | O49: =SUM(L49:N49)+IF(I49="EUR",K49,K49) | Q49: =IFERROR(O49*P49/100,0) | R49: Standard | T49: =IF(R49="Manual", IFERROR(S49, Summary!B5), IF(R49="Reduced1", Summary!C5, IF(R49="Reduced2", Summary!D5, Summary!B5))) | U49: =IFERROR((O49+Q49)*T49/100,0) | V49: =Q49+U49 | W49: =O49+V49
A50: 49 | K50: =IFERROR(E50*J50,0) | O50: =SUM(L50:N50)+IF(I50="EUR",K50,K50) | Q50: =IFERROR(O50*P50/100,0) | R50: Standard | T50: =IF(R50="Manual", IFERROR(S50, Summary!B5), IF(R50="Reduced1", Summary!C5, IF(R50="Reduced2", Summary!D5, Summary!B5))) | U50: =IFERROR((O50+Q50)*T50/100,0) | V50: =Q50+U50 | W50: =O50+V50
A51: 50 | K51: =IFERROR(E51*J51,0) | O51: =SUM(L51:N51)+IF(I51="EUR",K51,K51) | Q51: =IFERROR(O51*P51/100,0) | R51: Standard | T51: =IF(R51="Manual", IFERROR(S51, Summary!B5), IF(R51="Reduced1", Summary!C5, IF(R51="Reduced2", Summary!D5, Summary!B5))) | U51: =IFERROR((O51+Q51)*T51/100,0) | V51: =Q51+U51 | W51: =O51+V51
A52: 51 | K52: =IFERROR(E52*J52,0) | O52: =SUM(L52:N52)+IF(I52="EUR",K52,K52) | Q52: =IFERROR(O52*P52/100,0) | R52: Standard | T52: =IF(R52="Manual", IFERROR(S52, Summary!B5), IF(R52="Reduced1", Summary!C5, IF(R52="Reduced2", Summary!D5, Summary!B5))) | U52: =IFERROR((O52+Q52)*T52/100,0) | V52: =Q52+U52 | W52: =O52+V52
A53: 52 | K53: =IFERROR(E53*J53,0) | O53: =SUM(L53:N53)+IF(I53="EUR",K53,K53) | Q53: =IFERROR(O53*P53/100,0) | R53: Standard | T53: =IF(R53="Manual", IFERROR(S53, Summary!B5), IF(R53="Reduced1", Summary!C5, IF(R53="Reduced2", Summary!D5, Summary!B5))) | U53: =IFERROR((O53+Q53)*T53/100,0) | V53: =Q53+U53 | W53: =O53+V53
A54: 53 | K54: =IFERROR(E54*J54,0) | O54: =SUM(L54:N54)+IF(I54="EUR",K54,K54) | Q54: =IFERROR(O54*P54/100,0) | R54: Standard | T54: =IF(R54="Manual", IFERROR(S54, Summary!B5), IF(R54="Reduced1", Summary!C5, IF(R54="Reduced2", Summary!D5, Summary!B5))) | U54: =IFERROR((O54+Q54)*T54/100,0) | V54: =Q54+U54 | W54: =O54+V54
A55: 54 | K55: =IFERROR(E55*J55,0) | O55: =SUM(L55:N55)+IF(I55="EUR",K55,K55) | Q55: =IFERROR(O55*P55/100,0) | R55: Standard | T55: =IF(R55="Manual", IFERROR(S55, Summary!B5), IF(R55="Reduced1", Summary!C5, IF(R55="Reduced2", Summary!D5, Summary!B5))) | U55: =IFERROR((O55+Q55)*T55/100,0) | V55: =Q55+U55 | W55: =O55+V55
A56: 55 | K56: =IFERROR(E56*J56,0) | O56: =SUM(L56:N56)+IF(I56="EUR",K56,K56) | Q56: =IFERROR(O56*P56/100,0) | R56: Standard | T56: =IF(R56="Manual", IFERROR(S56, Summary!B5), IF(R56="Reduced1", Summary!C5, IF(R56="Reduced2", Summary!D5, Summary!B5))) | U56: =IFERROR((O56+Q56)*T56/100,0) | V56: =Q56+U56 | W56: =O56+V56
A57: 56 | K57: =IFERROR(E57*J57,0) | O57: =SUM(L57:N57)+IF(I57="EUR",K57,K57) | Q57: =IFERROR(O57*P57/100,0) | R57: Standard | T57: =IF(R57="Manual", IFERROR(S57, Summary!B5), IF(R57="Reduced1", Summary!C5, IF(R57="Reduced2", Summary!D5, Summary!B5))) | U57: =IFERROR((O57+Q57)*T57/100,0) | V57: =Q57+U57 | W57: =O57+V57
A58: 57 | K58: =IFERROR(E58*J58,0) | O58: =SUM(L58:N58)+IF(I58="EUR",K58,K58) | Q58: =IFERROR(O58*P58/100,0) | R58: Standard | T58: =IF(R58="Manual", IFERROR(S58, Summary!B5), IF(R58="Reduced1", Summary!C5, IF(R58="Reduced2", Summary!D5, Summary!B5))) | U58: =IFERROR((O58+Q58)*T58/100,0) | V58: =Q58+U58 | W58: =O58+V58
A59: 58 | K59: =IFERROR(E59*J59,0) | O59: =SUM(L59:N59)+IF(I59="EUR",K59,K59) | Q59: =IFERROR(O59*P59/100,0) | R59: Standard | T59: =IF(R59="Manual", IFERROR(S59, Summary!B5), IF(R59="Reduced1", Summary!C5, IF(R59="Reduced2", Summary!D5, Summary!B5))) | U59: =IFERROR((O59+Q59)*T59/100,0) | V59: =Q59+U59 | W59: =O59+V59
A60: 59 | K60: =IFERROR(E60*J60,0) | O60: =SUM(L60:N60)+IF(I60="EUR",K60,K60) | Q60: =IFERROR(O60*P60/100,0) | R60: Standard | T60: =IF(R60="Manual", IFERROR(S60, Summary!B5), IF(R60="Reduced1", Summary!C5, IF(R60="Reduced2", Summary!D5, Summary!B5))) | U60: =IFERROR((O60+Q60)*T60/100,0) | V60: =Q60+U60 | W60: =O60+V60
A61: 60 | K61: =IFERROR(E61*J61,0) | O61: =SUM(L61:N61)+IF(I61="EUR",K61,K61) | Q61: =IFERROR(O61*P61/100,0) | R61: Standard | T61: =IF(R61="Manual", IFERROR(S61, Summary!B5), IF(R61="Reduced1", Summary!C5, IF(R61="Reduced2", Summary!D5, Summary!B5))) | U61: =IFERROR((O61+Q61)*T61/100,0) | V61: =Q61+U61 | W61: =O61+V61
A62: 61 | K62: =IFERROR(E62*J62,0) | O62: =SUM(L62:N62)+IF(I62="EUR",K62,K62) | Q62: =IFERROR(O62*P62/100,0) | R62: Standard | T62: =IF(R62="Manual", IFERROR(S62, Summary!B5), IF(R62="Reduced1", Summary!C5, IF(R62="Reduced2", Summary!D5, Summary!B5))) | U62: =IFERROR((O62+Q62)*T62/100,0) | V62: =Q62+U62 | W62: =O62+V62
A63: 62 | K63: =IFERROR(E63*J63,0) | O63: =SUM(L63:N63)+IF(I63="EUR",K63,K63) | Q63: =IFERROR(O63*P63/100,0) | R63: Standard | T63: =IF(R63="Manual", IFERROR(S63, Summary!B5), IF(R63="Reduced1", Summary!C5, IF(R63="Reduced2", Summary!D5, Summary!B5))) | U63: =IFERROR((O63+Q63)*T63/100,0) | V63: =Q63+U63 | W63: =O63+V63
A64: 63 | K64: =IFERROR(E64*J64,0) | O64: =SUM(L64:N64)+IF(I64="EUR",K64,K64) | Q64: =IFERROR(O64*P64/100,0) | R64: Standard | T64: =IF(R64="Manual", IFERROR(S64, Summary!B5), IF(R64="Reduced1", Summary!C5, IF(R64="Reduced2", Summary!D5, Summary!B5))) | U64: =IFERROR((O64+Q64)*T64/100,0) | V64: =Q64+U64 | W64: =O64+V64
A65: 64 | K65: =IFERROR(E65*J65,0) | O65: =SUM(L65:N65)+IF(I65="EUR",K65,K65) | Q65: =IFERROR(O65*P65/100,0) | R65: Standard | T65: =IF(R65="Manual", IFERROR(S65, Summary!B5), IF(R65="Reduced1", Summary!C5, IF(R65="Reduced2", Summary!D5, Summary!B5))) | U65: =IFERROR((O65+Q65)*T65/100,0) | V65: =Q65+U65 | W65: =O65+V65
A66: 65 | K66: =IFERROR(E66*J66,0) | O66: =SUM(L66:N66)+IF(I66="EUR",K66,K66) | Q66: =IFERROR(O66*P66/100,0) | R66: Standard | T66: =IF(R66="Manual", IFERROR(S66, Summary!B5), IF(R66="Reduced1", Summary!C5, IF(R66="Reduced2", Summary!D5, Summary!B5))) | U66: =IFERROR((O66+Q66)*T66/100,0) | V66: =Q66+U66 | W66: =O66+V66
A67: 66 | K67: =IFERROR(E67*J67,0) | O67: =SUM(L67:N67)+IF(I67="EUR",K67,K67) | Q67: =IFERROR(O67*P67/100,0) | R67: Standard | T67: =IF(R67="Manual", IFERROR(S67, Summary!B5), IF(R67="Reduced1", Summary!C5, IF(R67="Reduced2", Summary!D5, Summary!B5))) | U67: =IFERROR((O67+Q67)*T67/100,0) | V67: =Q67+U67 | W67: =O67+V67
A68: 67 | K68: =IFERROR(E68*J68,0) | O68: =SUM(L68:N68)+IF(I68="EUR",K68,K68) | Q68: =IFERROR(O68*P68/100,0) | R68: Standard | T68: =IF(R68="Manual", IFERROR(S68, Summary!B5), IF(R68="Reduced1", Summary!C5, IF(R68="Reduced2", Summary!D5, Summary!B5))) | U68: =IFERROR((O68+Q68)*T68/100,0) | V68: =Q68+U68 | W68: =O68+V68
A69: 68 | K69: =IFERROR(E69*J69,0) | O69: =SUM(L69:N69)+IF(I69="EUR",K69,K69) | Q69: =IFERROR(O69*P69/100,0) | R69: Standard | T69: =IF(R69="Manual", IFERROR(S69, Summary!B5), IF(R69="Reduced1", Summary!C5, IF(R69="Reduced2", Summary!D5, Summary!B5))) | U69: =IFERROR((O69+Q69)*T69/100,0) | V69: =Q69+U69 | W69: =O69+V69
A70: 69 | K70: =IFERROR(E70*J70,0) | O70: =SUM(L70:N70)+IF(I70="EUR",K70,K70) | Q70: =IFERROR(O70*P70/100,0) | R70: Standard | T70: =IF(R70="Manual", IFERROR(S70, Summary!B5), IF(R70="Reduced1", Summary!C5, IF(R70="Reduced2", Summary!D5, Summary!B5))) | U70: =IFERROR((O70+Q70)*T70/100,0) | V70: =Q70+U70 | W70: =O70+V70
A71: 70 | K71: =IFERROR(E71*J71,0) | O71: =SUM(L71:N71)+IF(I71="EUR",K71,K71) | Q71: =IFERROR(O71*P71/100,0) | R71: Standard | T71: =IF(R71="Manual", IFERROR(S71, Summary!B5), IF(R71="Reduced1", Summary!C5, IF(R71="Reduced2", Summary!D5, Summary!B5))) | U71: =IFERROR((O71+Q71)*T71/100,0) | V71: =Q71+U71 | W71: =O71+V71
A72: 71 | K72: =IFERROR(E72*J72,0) | O72: =SUM(L72:N72)+IF(I72="EUR",K72,K72) | Q72: =IFERROR(O72*P72/100,0) | R72: Standard | T72: =IF(R72="Manual", IFERROR(S72, Summary!B5), IF(R72="Reduced1", Summary!C5, IF(R72="Reduced2", Summary!D5, Summary!B5))) | U72: =IFERROR((O72+Q72)*T72/100,0) | V72: =Q72+U72 | W72: =O72+V72
A73: 72 | K73: =IFERROR(E73*J73,0) | O73: =SUM(L73:N73)+IF(I73="EUR",K73,K73) | Q73: =IFERROR(O73*P73/100,0) | R73: Standard | T73: =IF(R73="Manual", IFERROR(S73, Summary!B5), IF(R73="Reduced1", Summary!C5, IF(R73="Reduced2", Summary!D5, Summary!B5))) | U73: =IFERROR((O73+Q73)*T73/100,0) | V73: =Q73+U73 | W73: =O73+V73
A74: 73 | K74: =IFERROR(E74*J74,0) | O74: =SUM(L74:N74)+IF(I74="EUR",K74,K74) | Q74: =IFERROR(O74*P74/100,0) | R74: Standard | T74: =IF(R74="Manual", IFERROR(S74, Summary!B5), IF(R74="Reduced1", Summary!C5, IF(R74="Reduced2", Summary!D5, Summary!B5))) | U74: =IFERROR((O74+Q74)*T74/100,0) | V74: =Q74+U74 | W74: =O74+V74
A75: 74 | K75: =IFERROR(E75*J75,0) | O75: =SUM(L75:N75)+IF(I75="EUR",K75,K75) | Q75: =IFERROR(O75*P75/100,0) | R75: Standard | T75: =IF(R75="Manual", IFERROR(S75, Summary!B5), IF(R75="Reduced1", Summary!C5, IF(R75="Reduced2", Summary!D5, Summary!B5))) | U75: =IFERROR((O75+Q75)*T75/100,0) | V75: =Q75+U75 | W75: =O75+V75
A76: 75 | K76: =IFERROR(E76*J76,0) | O76: =SUM(L76:N76)+IF(I76="EUR",K76,K76) | Q76: =IFERROR(O76*P76/100,0) | R76: Standard | T76: =IF(R76="Manual", IFERROR(S76, Summary!B5), IF(R76="Reduced1", Summary!C5, IF(R76="Reduced2", Summary!D5, Summary!B5))) | U76: =IFERROR((O76+Q76)*T76/100,0) | V76: =Q76+U76 | W76: =O76+V76
A77: 76 | K77: =IFERROR(E77*J77,0) | O77: =SUM(L77:N77)+IF(I77="EUR",K77,K77) | Q77: =IFERROR(O77*P77/100,0) | R77: Standard | T77: =IF(R77="Manual", IFERROR(S77, Summary!B5), IF(R77="Reduced1", Summary!C5, IF(R77="Reduced2", Summary!D5, Summary!B5))) | U77: =IFERROR((O77+Q77)*T77/100,0) | V77: =Q77+U77 | W77: =O77+V77
A78: 77 | K78: =IFERROR(E78*J78,0) | O78: =SUM(L78:N78)+IF(I78="EUR",K78,K78) | Q78: =IFERROR(O78*P78/100,0) | R78: Standard | T78: =IF(R78="Manual", IFERROR(S78, Summary!B5), IF(R78="Reduced1", Summary!C5, IF(R78="Reduced2", Summary!D5, Summary!B5))) | U78: =IFERROR((O78+Q78)*T78/100,0) | V78: =Q78+U78 | W78: =O78+V78
A79: 78 | K79: =IFERROR(E79*J79,0) | O79: =SUM(L79:N79)+IF(I79="EUR",K79,K79) | Q79: =IFERROR(O79*P79/100,0) | R79: Standard | T79: =IF(R79="Manual", IFERROR(S79, Summary!B5), IF(R79="Reduced1", Summary!C5, IF(R79="Reduced2", Summary!D5, Summary!B5))) | U79: =IFERROR((O79+Q79)*T79/100,0) | V79: =Q79+U79 | W79: =O79+V79
A80: 79 | K80: =IFERROR(E80*J80,0) | O80: =SUM(L80:N80)+IF(I80="EUR",K80,K80) | Q80: =IFERROR(O80*P80/100,0) | R80: Standard | T80: =IF(R80="Manual", IFERROR(S80, Summary!B5), IF(R80="Reduced1", Summary!C5, IF(R80="Reduced2", Summary!D5, Summary!B5))) | U80: =IFERROR((O80+Q80)*T80/100,0) | V80: =Q80+U80 | W80: =O80+V80
A81: 80 | K81: =IFERROR(E81*J81,0) | O81: =SUM(L81:N81)+IF(I81="EUR",K81,K81) | Q81: =IFERROR(O81*P81/100,0) | R81: Standard | T81: =IF(R81="Manual", IFERROR(S81, Summary!B5), IF(R81="Reduced1", Summary!C5, IF(R81="Reduced2", Summary!D5, Summary!B5))) | U81: =IFERROR((O81+Q81)*T81/100,0) | V81: =Q81+U81 | W81: =O81+V81
A82: 81 | K82: =IFERROR(E82*J82,0) | O82: =SUM(L82:N82)+IF(I82="EUR",K82,K82) | Q82: =IFERROR(O82*P82/100,0) | R82: Standard | T82: =IF(R82="Manual", IFERROR(S82, Summary!B5), IF(R82="Reduced1", Summary!C5, IF(R82="Reduced2", Summary!D5, Summary!B5))) | U82: =IFERROR((O82+Q82)*T82/100,0) | V82: =Q82+U82 | W82: =O82+V82
A83: 82 | K83: =IFERROR(E83*J83,0) | O83: =SUM(L83:N83)+IF(I83="EUR",K83,K83) | Q83: =IFERROR(O83*P83/100,0) | R83: Standard | T83: =IF(R83="Manual", IFERROR(S83, Summary!B5), IF(R83="Reduced1", Summary!C5, IF(R83="Reduced2", Summary!D5, Summary!B5))) | U83: =IFERROR((O83+Q83)*T83/100,0) | V83: =Q83+U83 | W83: =O83+V83
A84: 83 | K84: =IFERROR(E84*J84,0) | O84: =SUM(L84:N84)+IF(I84="EUR",K84,K84) | Q84: =IFERROR(O84*P84/100,0) | R84: Standard | T84: =IF(R84="Manual", IFERROR(S84, Summary!B5), IF(R84="Reduced1", Summary!C5, IF(R84="Reduced2", Summary!D5, Summary!B5))) | U84: =IFERROR((O84+Q84)*T84/100,0) | V84: =Q84+U84 | W84: =O84+V84
A85: 84 | K85: =IFERROR(E85*J85,0) | O85: =SUM(L85:N85)+IF(I85="EUR",K85,K85) | Q85: =IFERROR(O85*P85/100,0) | R85: Standard | T85: =IF(R85="Manual", IFERROR(S85, Summary!B5), IF(R85="Reduced1", Summary!C5, IF(R85="Reduced2", Summary!D5, Summary!B5))) | U85: =IFERROR((O85+Q85)*T85/100,0) | V85: =Q85+U85 | W85: =O85+V85
A86: 85 | K86: =IFERROR(E86*J86,0) | O86: =SUM(L86:N86)+IF(I86="EUR",K86,K86) | Q86: =IFERROR(O86*P86/100,0) | R86: Standard | T86: =IF(R86="Manual", IFERROR(S86, Summary!B5), IF(R86="Reduced1", Summary!C5, IF(R86="Reduced2", Summary!D5, Summary!B5))) | U86: =IFERROR((O86+Q86)*T86/100,0) | V86: =Q86+U86 | W86: =O86+V86
A87: 86 | K87: =IFERROR(E87*J87,0) | O87: =SUM(L87:N87)+IF(I87="EUR",K87,K87) | Q87: =IFERROR(O87*P87/100,0) | R87: Standard | T87: =IF(R87="Manual", IFERROR(S87, Summary!B5), IF(R87="Reduced1", Summary!C5, IF(R87="Reduced2", Summary!D5, Summary!B5))) | U87: =IFERROR((O87+Q87)*T87/100,0) | V87: =Q87+U87 | W87: =O87+V87
A88: 87 | K88: =IFERROR(E88*J88,0) | O88: =SUM(L88:N88)+IF(I88="EUR",K88,K88) | Q88: =IFERROR(O88*P88/100,0) | R88: Standard | T88: =IF(R88="Manual", IFERROR(S88, Summary!B5), IF(R88="Reduced1", Summary!C5, IF(R88="Reduced2", Summary!D5, Summary!B5))) | U88: =IFERROR((O88+Q88)*T88/100,0) | V88: =Q88+U88 | W88: =O88+V88
A89: 88 | K89: =IFERROR(E89*J89,0) | O89: =SUM(L89:N89)+IF(I89="EUR",K89,K89) | Q89: =IFERROR(O89*P89/100,0) | R89: Standard | T89: =IF(R89="Manual", IFERROR(S89, Summary!B5), IF(R89="Reduced1", Summary!C5, IF(R89="Reduced2", Summary!D5, Summary!B5))) | U89: =IFERROR((O89+Q89)*T89/100,0) | V89: =Q89+U89 | W89: =O89+V89
A90: 89 | K90: =IFERROR(E90*J90,0) | O90: =SUM(L90:N90)+IF(I90="EUR",K90,K90) | Q90: =IFERROR(O90*P90/100,0) | R90: Standard | T90: =IF(R90="Manual", IFERROR(S90, Summary!B5), IF(R90="Reduced1", Summary!C5, IF(R90="Reduced2", Summary!D5, Summary!B5))) | U90: =IFERROR((O90+Q90)*T90/100,0) | V90: =Q90+U90 | W90: =O90+V90
A91: 90 | K91: =IFERROR(E91*J91,0) | O91: =SUM(L91:N91)+IF(I91="EUR",K91,K91) | Q91: =IFERROR(O91*P91/100,0) | R91: Standard | T91: =IF(R91="Manual", IFERROR(S91, Summary!B5), IF(R91="Reduced1", Summary!C5, IF(R91="Reduced2", Summary!D5, Summary!B5))) | U91: =IFERROR((O91+Q91)*T91/100,0) | V91: =Q91+U91 | W91: =O91+V91
A92: 91 | K92: =IFERROR(E92*J92,0) | O92: =SUM(L92:N92)+IF(I92="EUR",K92,K92) | Q92: =IFERROR(O92*P92/100,0) | R92: Standard | T92: =IF(R92="Manual", IFERROR(S92, Summary!B5), IF(R92="Reduced1", Summary!C5, IF(R92="Reduced2", Summary!D5, Summary!B5))) | U92: =IFERROR((O92+Q92)*T92/100,0) | V92: =Q92+U92 | W92: =O92+V92
A93: 92 | K93: =IFERROR(E93*J93,0) | O93: =SUM(L93:N93)+IF(I93="EUR",K93,K93) | Q93: =IFERROR(O93*P93/100,0) | R93: Standard | T93: =IF(R93="Manual", IFERROR(S93, Summary!B5), IF(R93="Reduced1", Summary!C5, IF(R93="Reduced2", Summary!D5, Summary!B5))) | U93: =IFERROR((O93+Q93)*T93/100,0) | V93: =Q93+U93 | W93: =O93+V93
A94: 93 | K94: =IFERROR(E94*J94,0) | O94: =SUM(L94:N94)+IF(I94="EUR",K94,K94) | Q94: =IFERROR(O94*P94/100,0) | R94: Standard | T94: =IF(R94="Manual", IFERROR(S94, Summary!B5), IF(R94="Reduced1", Summary!C5, IF(R94="Reduced2", Summary!D5, Summary!B5))) | U94: =IFERROR((O94+Q94)*T94/100,0) | V94: =Q94+U94 | W94: =O94+V94
A95: 94 | K95: =IFERROR(E95*J95,0) | O95: =SUM(L95:N95)+IF(I95="EUR",K95,K95) | Q95: =IFERROR(O95*P95/100,0) | R95: Standard | T95: =IF(R95="Manual", IFERROR(S95, Summary!B5), IF(R95="Reduced1", Summary!C5, IF(R95="Reduced2", Summary!D5, Summary!B5))) | U95: =IFERROR((O95+Q95)*T95/100,0) | V95: =Q95+U95 | W95: =O95+V95
A96: 95 | K96: =IFERROR(E96*J96,0) | O96: =SUM(L96:N96)+IF(I96="EUR",K96,K96) | Q96: =IFERROR(O96*P96/100,0) | R96: Standard | T96: =IF(R96="Manual", IFERROR(S96, Summary!B5), IF(R96="Reduced1", Summary!C5, IF(R96="Reduced2", Summary!D5, Summary!B5))) | U96: =IFERROR((O96+Q96)*T96/100,0) | V96: =Q96+U96 | W96: =O96+V96
A97: 96 | K97: =IFERROR(E97*J97,0) | O97: =SUM(L97:N97)+IF(I97="EUR",K97,K97) | Q97: =IFERROR(O97*P97/100,0) | R97: Standard | T97: =IF(R97="Manual", IFERROR(S97, Summary!B5), IF(R97="Reduced1", Summary!C5, IF(R97="Reduced2", Summary!D5, Summary!B5))) | U97: =IFERROR((O97+Q97)*T97/100,0) | V97: =Q97+U97 | W97: =O97+V97
A98: 97 | K98: =IFERROR(E98*J98,0) | O98: =SUM(L98:N98)+IF(I98="EUR",K98,K98) | Q98: =IFERROR(O98*P98/100,0) | R98: Standard | T98: =IF(R98="Manual", IFERROR(S98, Summary!B5), IF(R98="Reduced1", Summary!C5, IF(R98="Reduced2", Summary!D5, Summary!B5))) | U98: =IFERROR((O98+Q98)*T98/100,0) | V98: =Q98+U98 | W98: =O98+V98
A99: 98 | K99: =IFERROR(E99*J99,0) | O99: =SUM(L99:N99)+IF(I99="EUR",K99,K99) | Q99: =IFERROR(O99*P99/100,0) | R99: Standard | T99: =IF(R99="Manual", IFERROR(S99, Summary!B5), IF(R99="Reduced1", Summary!C5, IF(R99="Reduced2", Summary!D5, Summary!B5))) | U99: =IFERROR((O99+Q99)*T99/100,0) | V99: =Q99+U99 | W99: =O99+V99
A100: 99 | K100: =IFERROR(E100*J100,0) | O100: =SUM(L100:N100)+IF(I100="EUR",K100,K100) | Q100: =IFERROR(O100*P100/100,0) | R100: Standard | T100: =IF(R100="Manual", IFERROR(S100, Summary!B5), IF(R100="Reduced1", Summary!C5, IF(R100="Reduced2", Summary!D5, Summary!B5))) | U100: =IFERROR((O100+Q100)*T100/100,0) | V100: =Q100+U100 | W100: =O100+V100
...

Sheet Lists
A1: Country | B1: Austria | C1: Belgium | D1: Bulgaria | E1: Croatia | F1: Cyprus | G1: Czech Republic | H1: Denmark | I1: Estonia | J1: Finland | K1: France | L1: Germany | M1: Greece | N1: Hungary | O1: Ireland | P1: Italy | Q1: Latvia | R1: Lithuania | S1: Luxembourg | T1: Malta | U1: Netherlands | V1: Poland | W1: Portugal | X1: Romania | Y1: Slovakia | Z1: Slovenia | AA1: Spain | AB1: Sweden | AC1: United Kingdom | AD1: Norway | AE1: Switzerland | AF1: Iceland | AG1: Liechtenstein
A2: CountryISO | B2: AT | C2: BE | D2: BG | E2: HR | F2: CY | G2: CZ | H2: DK | I2: EE | J2: FI | K2: FR | L2: DE | M2: GR | N2: HU | O2: IE | P2: IT | Q2: LV | R2: LT | S2: LU | T2: MT | U2: NL | V2: PL | W2: PT | X2: RO | Y2: SK | Z2: SI | AA2: ES | AB2: SE | AC2: GB | AD2: NO | AE2: CH | AF2: IS | AG2: LI
A4: Incoterms | B4: EXW | C4: FCA | D4: CPT | E4: CIP | F4: DAP | G4: DPU | H4: DDP | I4: FAS | J4: FOB | K4: CFR | L4: CIF
A5: TransportMode | B5: 1 - Sea | C5: 2 - Rail | D5: 3 - Road | E5: 4 - Air | F5: 5 - Mail | G5: 6 - Fixed installations | H5: 7 - Inland waterway | I5: 9 - Own propulsion
A6: Currency | B6: EUR | C6: USD | D6: GBP | E6: SEK | F6: NOK | G6: DKK | H6: CHF | I6: PLN | J6: CZK | K6: JPY | L6: CNY
A7: Units | B7: PCE | C7: KG | D7: LTR | E7: MTR | F7: M2 | G7: M3 | H7: SET | I7: PAI
A8: ProcedureCode | B8: 4000 - Release for free circulation | C8: 4200 - Release + onward supply | D8: 1000 - Definitive export | E8: 1040 - Temporary export | F8: 3171 - Transit | G8: 5100 - Inward processing | H8: 6100 - Temporary admission
A10: LangCodes | B10: EN | C10: EE | D10: DE | E10: FR
A12: CountryLanguageMap
A13: Austria | B13: DE
A14: Belgium | B14: FR
A15: Bulgaria | B15: EN
A16: Croatia | B16: EN
A17: Cyprus | B17: EN
A18: Czech Republic | B18: EN
A19: Denmark | B19: EN
A20: Estonia | B20: EE
A21: Finland | B21: EN
A22: France | B22: FR
A23: Germany | B23: DE
A24: Greece | B24: EN
... A44: Liechtenstein | B44: DE
A198: VATType | B198: Standard | C198: Reduced1 | D198: Reduced2 | E198: Manual
A200: VAT_Table
A201: Country | B201: Standard | C201: Reduced1 | D201: Reduced2
A202: Austria | B202: 20 | C202: 10 | D202: 13
A203: Belgium | B203: 21 | C203: 6 | D203: 12
A204: Bulgaria | B204: 20 | C204: 9 | D204: 0
A205: Croatia | B205: 25 | C205: 13 | D205: 5
A206: Cyprus | B206: 19 | C206: 5 | D206: 9
A207: Czech Republic | B207: 21 | C207: 12 | D207: 10
A208: Denmark | B208: 25 | C208: 0 | D208: 0
A209: Estonia | B209: 22 | C209: 9 | D209: 5
A210: Finland | B210: 24 | C210: 14 | D210: 10
A211: France | B211: 20 | C211: 10 | D211: 5.5
A212: Germany | B212: 19 | C212: 7 | D212: 0
A213: Greece | B213: 24 | C213: 13 | D213: 6
... A233: Liechtenstein | B233: 8.1 | C233: 2.6 | D233: 3.8

Sheet Summary
A1: Totals
A3: Selected Country | B3: =Declaration!B3
A4: Language | B4: =Declaration!I3
A5: VAT Rates (%) | B5: =IFERROR(XLOOKUP(B3, VAT_Country, VAT_Standard),"") | C5: =IFERROR(XLOOKUP(B3, VAT_Country, VAT_Reduced1),"") | D5: =IFERROR(XLOOKUP(B3, VAT_Country, VAT_Reduced2),"")
A6: Customs Value (EUR) | B6: =SUM(Items!O2:O1000)
A7: Duty (EUR) | B7: =SUM(Items!Q2:Q1000)
A8: VAT (EUR) | B8: =SUM(Items!U2:U1000)
A9: Total Taxes (EUR) | B9: =SUM(Items!V2:V1000)
A10: Grand Total (EUR) | B10: =SUM(Items!W2:W1000)

Sheet Translations
A1: Key | B1: EN | C1: EE | D1: DE | E1: FR
A2: Select Country | B2: Select Country | C2: Vali riik | D2: Land wählen | E2: Sélectionner le pays
A3: Select Flow | B3: Select Flow | C3: Vali protsess | D3: Vorgang wählen | E3: Sélectionner le flux
A4: Declarant (Company Name) | B4: Declarant (Company Name) | C4: Deklarant (Ettevõtte nimi) | D4: Anmelder (Firmenname) | E4: Déclarant (Raison sociale)
A5: Registry code / EORI / VAT | B5: Registry code / EORI / VAT | C5: Registrikood / EORI / KMKR | D5: Reg.-Nr. / EORI / USt-IdNr. | E5: N° registre / EORI / TVA
A6: Address | B6: Address | C6: Aadress | D6: Adresse | E6: Adresse
A7: Contact person | B7: Contact person | C7: Kontaktisik | D7: Ansprechpartner | E7: Contact
A8: Contact email | B8: Contact email | C8: E-post | D8: E-Mail | E8: E-mail
A9: Contact phone | B9: Contact phone | C9: Telefon | D9: Telefon | E9: Téléphone
A10: Consignor (Seller / Exporter) | B10: Consignor (Seller / Exporter) | C10: Saatja (Müüja / Eksportija) | D10: Versender (Verkäufer / Exporteur) | E10: Expéditeur (Vendeur / Exportateur)
A11: Consignee (Buyer / Importer) | B11: Consignee (Buyer / Importer) | C11: Saaja (Ostja / Importija) | D11: Empfänger (Käufer / Importeur) | E11: Destinataire (Acheteur / Importateur)
A12: Consignor VAT/EORI | B12: Consignor VAT/EORI | C12: Saatja KMKR/EORI | D12: USt-IdNr./EORI des Versenders | E12: TVA/EORI de l’expéditeur
... A28: Language | B28: Language | C28: Keel | D28: Sprache | E28: Langue
