Workbook
Name Bills: Table13910109[Bills]
Name Bills: Table13910119[Bills]
Name Bills: Table13910129[Bills]
Name Bills: Table1391018[Bills]
Name Bills: Table1391039[Bills]
Name Bills: Table1391049[Bills]
Name Bills: Table1391059[Bills]
Name Bills: Table1391069[Bills]
Name Bills: Table1391079[Bills]
Name Bills: Table1391089[Bills]
Name Bills: Table1391099[Bills]
Name Bills: Table13910[Bills]
Name Entertainment: Table138107[Entertainment]
Name Entertainment: Table138117[Entertainment]
Name Entertainment: Table138127[Entertainment]
Name Entertainment: Table13816[Entertainment]
Name Entertainment: Table13837[Entertainment]
Name Entertainment: Table13847[Entertainment]
Name Entertainment: Table13857[Entertainment]
Name Entertainment: Table13867[Entertainment]
Name Entertainment: Table13877[Entertainment]
Name Entertainment: Table13887[Entertainment]
Name Entertainment: Table13897[Entertainment]
Name Entertainment: Table138[Entertainment]
Name Housing: Table1102[Housing]
Name Housing: Table1112[Housing]
Name Housing: Table1122[Housing]
Name Housing: Table111[Housing]
Name Housing: Table132[Housing]
Name Housing: Table142[Housing]
Name Housing: Table152[Housing]
Name Housing: Table162[Housing]
Name Housing: Table172[Housing]
Name Housing: Table182[Housing]
Name Housing: Table192[Housing]
Name Housing: Table1[Housing]
Name Income: Table136105[Income]
Name Income: Table136115[Income]
Name Income: Table136125[Income]
Name Income: Table13614[Income]
Name Income: Table13635[Income]
Name Income: Table13645[Income]
Name Income: Table13655[Income]
Name Income: Table13665[Income]
Name Income: Table13675[Income]
Name Income: Table13685[Income]
Name Income: Table13695[Income]
Name Income: Table136[Income]
Name Living: Table137106[Living]
Name Living: Table137116[Living]
Name Living: Table137126[Living]
Name Living: Table13715[Living]
Name Living: Table13736[Living]
Name Living: Table13746[Living]
Name Living: Table13756[Living]
Name Living: Table13766[Living]
Name Living: Table13776[Living]
Name Living: Table13786[Living]
Name Living: Table13796[Living]
Name Living: Table137[Living]

Sheet Mo.1
G1: 41518 | V1: Category | W1: Budget | X1: Actual | Y1: Status | Z1: Min Bal
H2: Budget | I2: Actual | J2: Variance | V2: =Table136[[#Headers],[Income]] -> Income | W2: =SUM(Table136[Budget]) -> 5100 | X2: =SUM(Table136[Actual]) -> 5167.35 | Y2: Pending | Z2: =AVERAGE(Z12:Z42) -> 2207.4039
B3: Checkbook / Register by Robert McQuaig Blog | G3: BOM Balance | H3: =I3 -> 1156.74 | I3: 1156.74 | J3: =I3-H3 -> 0 | V3: =Table1[[#Headers],[Housing]] -> Housing | W3: =SUM(Table1[Budget]) -> 1650 | X3: =SUM(Table1[Actual]) -> 1549.15 | Y3: Scheduled
B4: Article: | C4: Monthly Personal Budget Tracking | G4: Total Inflow | H4: =Table136[[#Totals],[Budget]] -> 5100 | I4: =Table136[[#Totals],[Actual]] -> 5167.35 | J4: =I4-H4 -> 67.35 | V4: =Table13[[#Headers],[Transportation]] -> Transportation | W4: =SUM(Table13[Budget]) -> 1000 | X4: =SUM(Table13[Actual]) -> 1168.79 | Y4: Cleared
B5: All Templates: | C5: Excel Templates by Robert McQuaig | G5: Total Outflow | H5: =Table1[[#Totals],[Budget]]+Table13[[#Totals],[Budget]]+Table13910[[#Totals],[Budget]]+Table137[[#Totals],[Budget]]+Table138[[#Totals],[Budget]]+Table139[[#Totals],[Budget]] -> 4285 | I5: =Table1[[#Totals],[Actual]]+Table13[[#Totals],[Actual]]+Table13910[[#Totals],[Actual]]+Table137[[#Totals],[Actual]]+Table138[[#Totals],[Actual]]+Table139[[#Totals],[Actual]] -> 3025.21 | J5: =I5-H5 -> -1259.79 | V5: =Table13910[[#Headers],[Bills]] -> Bills | W5: =SUM(Table13910[Budget]) -> 385 | X5: =SUM(Table13910[Actual]) -> 275
B6: © 2012-2013 Robert McQuaig Blog | G6: Difference | H6: =H3+H4-H5 -> 1971.74 | I6: =I3+I4-I5 -> 3298.88 | J6: =J3+J4-J5 -> 1327.14 | V6: =Table137[[#Headers],[Living]] -> Living | W6: =SUM(Table137[Budget]) -> 800 | X6: =SUM(Table137[Actual]) -> 21.39
V7: =Table138[[#Headers],[Entertainment]] -> Entertainment | W7: =SUM(Table138[Budget]) -> 300 | X7: =SUM(Table138[Actual]) -> 10.88
V8: =Table139[[#Headers],[Misc.]] -> Misc. | W8: =SUM(Table139[Budget]) -> 150 | X8: =SUM(Table139[Actual]) -> 0
G10: =CONCATENATE(Table136[[#Headers],[Income]]," - Budget & Tracking") -> Income - Budget & Tracking | N10: Budgeted Credits | W10: Account Balance / Tracking & Forecast
G11: Income | H11: Budget | I11: Actual | J11: Variance | N11: Description | O11: Category | P11: Sub-Category | Q11: Date | R11: Amount | S11: Status | W11: Date | X11: Credit | Y11: Debit | Z11: Balance
G12: Company A | H12: 3000 | I12: =SUMIFS(Table4420[Amount],Table4420[Category],Table136[[#Headers],[Income]],Table4420[Sub-Category],Table136[[#This Row],[Income]])+SUMIFS(Table44[Amount],Table44[Category],Table136[[#Headers],[Income]],Table44[Sub-Category],Table136[[#This Row],[Income]]) -> 2967.35 | J12: =Table136[[#This Row],[Actual]]-Table136[[#This Row],[Budget]] -> -32.65 | N12: Paycheck A | O12: Income | P12: Company A | Q12: 41522 | R12: 1467.35 | S12: Cleared | W12: =G1 -> 41518 | X12: =SUMIFS(Table4420[Amount],Table4420[Date],W12,Table4420[Category],Table136[[#Headers],[Income]])+SUMIFS(Table44[Amount],Table44[Date],W12,Table44[Category],Table136[[#Headers],[Income]]) -> 0 | Y12: =SUMIFS(Table4[Amount],Table4[Date],W12,Table4[Category],"<>"&Table136[[#Headers],[Income]])+SUMIFS(Table44[Amount],Table44[Date],W12,Table44[Category],"<>"&Table136[[#Headers],[Income]]) -> 873.67 | Z12: =I3+X12-Y12 -> 283.07 | AA12: =Z2 -> 2207.4039
G13: Company B | H13: 2000 | I13: =SUMIFS(Table4420[Amount],Table4420[Category],Table136[[#Headers],[Income]],Table4420[Sub-Category],Table136[[#This Row],[Income]])+SUMIFS(Table44[Amount],Table44[Category],Table136[[#Headers],[Income]],Table44[Sub-Category],Table136[[#This Row],[Income]]) -> 2200 | J13: =Table136[[#This Row],[Actual]]-Table136[[#This Row],[Budget]] -> 200 | N13: Paycheck B | O13: Income | P13: Company B | Q13: 41530 | R13: 1100 | S13: Pending | W13: =W12+1 -> 41519 | X13: =SUMIFS(Table4420[Amount],Table4420[Date],W13,Table4420[Category],Table136[[#Headers],[Income]])+SUMIFS(Table44[Amount],Table44[Date],W13,Table44[Category],Table136[[#Headers],[Income]]) -> 0 | Y13: =SUMIFS(Table4[Amount],Table4[Date],W13,Table4[Category],"<>"&Table136[[#Headers],[Income]])+SUMIFS(Table44[Amount],Table44[Date],W13,Table44[Category],"<>"&Table136[[#Headers],[Income]]) -> 0 | Z13: =Z12+X13-Y13 -> 283.07 | AA13: =AA12 -> 2207.4039
G14: Side Work | H14: 100 | I14: =SUMIFS(Table4420[Amount],Table4420[Category],Table136[[#Headers],[Income]],Table4420[Sub-Category],Table136[[#This Row],[Income]])+SUMIFS(Table44[Amount],Table44[Category],Table136[[#Headers],[Income]],Table44[Sub-Category],Table136[[#This Row],[Income]]) -> 0 | J14: =Table136[[#This Row],[Actual]]-Table136[[#This Row],[Budget]] -> -100 | N14: Paycheck A | O14: Income | P14: Company A | Q14: 41537 | R14: 1500 | S14: Pending | W14: =W13+1 -> 41520 | X14: =SUMIFS(Table4420[Amount],Table4420[Date],W14,Table4420[Category],Table136[[#Headers],[Income]])+SUMIFS(Table44[Amount],Table44[Date],W14,Table44[Category],Table136[[#Headers],[Income]]) -> 0 | Y14: =SUMIFS(Table4[Amount],Table4[Date],W14,Table4[Category],"<>"&Table136[[#Headers],[Income]])+SUMIFS(Table44[Amount],Table44[Date],W14,Table44[Category],"<>"&Table136[[#Headers],[Income]]) -> 0 | Z14: =Z13+X14-Y14 -> 283.07 | AA14: =AA13 -> 2207.4039
G15: Other | H15: 0 | I15: =SUMIFS(Table4420[Amount],Table4420[Category],Table136[[#Headers],[Income]],Table4420[Sub-Category],Table136[[#This Row],[Income]])+SUMIFS(Table44[Amount],Table44[Category],Table136[[#Headers],[Income]],Table44[Sub-Category],Table136[[#This Row],[Income]]) -> 0 | J15: =Table136[[#This Row],[Actual]]-Table136[[#This Row],[Budget]] -> 0 | N15: Paycheck B | O15: Income | P15: Company B | Q15: 41544 | R15: 1100 | S15: Pending | W15: =W14+1 -> 41521 | X15: =SUMIFS(Table4420[Amount],Table4420[Date],W15,Table4420[Category],Table136[[#Headers],[Income]])+SUMIFS(Table44[Amount],Table44[Date],W15,Table44[Category],Table136[[#Headers],[Income]]) -> 0 | Y15: =SUMIFS(Table4[Amount],Table4[Date],W15,Table4[Category],"<>"&Table136[[#Headers],[Income]])+SUMIFS(Table44[Amount],Table44[Date],W15,Table44[Category],"<>"&Table136[[#Headers],[Income]]) -> 0 | Z15: =Z14+X15-Y15 -> 283.07 | AA15: =AA14 -> 2207.4039
G16: Total | H16: =SUBTOTAL(109,Table136[Budget]) -> 5100 | I16: =SUBTOTAL(109,Table136[Actual]) -> 5167.35 | J16: =SUBTOTAL(109,Table136[Variance]) -> 67.35 | W16: =W15+1 -> 41522 | X16: =SUMIFS(Table4420[Amount],Table4420[Date],W16,Table4420[Category],Table136[[#Headers],[Income]])+SUMIFS(Table44[Amount],Table44[Date],W16,Table44[Category],Table136[[#Headers],[Income]]) -> 1467.35 | Y16: =SUMIFS(Table4[Amount],Table4[Date],W16,Table4[Category],"<>"&Table136[[#Headers],[Income]])+SUMIFS(Table44[Amount],Table44[Date],W16,Table44[Category],"<>"&Table136[[#Headers],[Income]]) -> 0 | Z16: =Z15+X16-Y16 -> 1750.42 | AA16: =AA15 -> 2207.4039
N17: Budgeted Debits | W17: =W16+1 -> 41523 | X17: =SUMIFS(Table4420[Amount],Table4420[Date],W17,Table4420[Category],Table136[[#Headers],[Income]])+SUMIFS(Table44[Amount],Table44[Date],W17,Table44[Category],Table136[[#Headers],[Income]]) -> 0 | Y17: =SUMIFS(Table4[Amount],Table4[Date],W17,Table4[Category],"<>"&Table136[[#Headers],[Income]])+SUMIFS(Table44[Amount],Table44[Date],W17,Table44[Category],"<>"&Table136[[#Headers],[Income]]) -> 213.28 | Z17: =Z16+X17-Y17 -> 1537.14 | AA17: =AA16 -> 2207.4039
G18: =CONCATENATE(Table1[[#Headers],[Housing]]," - Budget & Tracking") -> Housing - Budget & Tracking | N18: Description | O18: Category | P18: Sub-Category | Q18: Date | R18: Amount | S18: Status | W18: =W17+1 -> 41524 | X18: =SUMIFS(Table4420[Amount],Table4420[Date],W18,Table4420[Category],Table136[[#Headers],[Income]])+SUMIFS(Table44[Amount],Table44[Date],W18,Table44[Category],Table136[[#Headers],[Income]]) -> 0 | Y18: =SUMIFS(Table4[Amount],Table4[Date],W18,Table4[Category],"<>"&Table136[[#Headers],[Income]])+SUMIFS(Table44[Amount],Table44[Date],W18,Table44[Category],"<>"&Table136[[#Headers],[Income]]) -> 42.58 | Z18: =Z17+X18-Y18 -> 1494.56 | AA18: =AA17 -> 2207.4039
G19: Housing | H19: Budget | I19: Actual | J19: Variance | N19: Mortgage Company | O19: Housing | P19: Mortgage | Q19: 41518 | R19: 873.67 | S19: Cleared | W19: =W18+1 -> 41525 | X19: =SUMIFS(Table4420[Amount],Table4420[Date],W19,Table4420[Category],Table136[[#Headers],[Income]])+SUMIFS(Table44[Amount],Table44[Date],W19,Table44[Category],Table136[[#Headers],[Income]]) -> 0 | Y19: =SUMIFS(Table4[Amount],Table4[Date],W19,Table4[Category],"<>"&Table136[[#Headers],[Income]])+SUMIFS(Table44[Amount],Table44[Date],W19,Table44[Category],"<>"&Table136[[#Headers],[Income]]) -> 0 | Z19: =Z18+X19-Y19 -> 1494.56 | AA19: =AA18 -> 2207.4039
G20: Mortgage | H20: 900 | I20: =SUMIFS(Table4[Amount],Table4[Category],Table1[[#Headers],[Housing]],Table4[Sub-Category],Table1[[#This Row],[Housing]])+SUMIFS(Table44[Amount],Table44[Category],Table1[[#Headers],[Housing]],Table44[Sub-Category],Table1[[#This Row],[Housing]]) -> 873.67 | J20: =Table1[[#This Row],[Budget]]-Table1[[#This Row],[Actual]] -> 26.33 | N20: Phone Company | O20: Housing | P20: Telephone | Q20: 41523 | R20: 116.08 | S20: Cleared | W20: =W19+1 -> 41526 | X20: =SUMIFS(Table4420[Amount],Table4420[Date],W20,Table4420[Category],Table136[[#Headers],[Income]])+SUMIFS(Table44[Amount],Table44[Date],W20,Table44[Category],Table136[[#Headers],[Income]]) -> 0 | Y20: =SUMIFS(Table4[Amount],Table4[Date],W20,Table4[Category],"<>"&Table136[[#Headers],[Income]])+SUMIFS(Table44[Amount],Table44[Date],W20,Table44[Category],"<>"&Table136[[#Headers],[Income]]) -> 129.55 | Z20: =Z19+X20-Y20 -> 1365.01 | AA20: =AA19 -> 2207.4039
G21: Electricity | H21: 150 | I21: =SUMIFS(Table4[Amount],Table4[Category],Table1[[#Headers],[Housing]],Table4[Sub-Category],Table1[[#This Row],[Housing]])+SUMIFS(Table44[Amount],Table44[Category],Table1[[#Headers],[Housing]],Table44[Sub-Category],Table1[[#This Row],[Housing]]) -> 126.17 | J21: =Table1[[#This Row],[Budget]]-Table1[[#This Row],[Actual]] -> 23.83 | N21: HoA | O21: Housing | P21: Other | Q21: 41524 | R21: 35 | S21: Cleared | W21: =W20+1 -> 41527 | X21: =SUMIFS(Table4420[Amount],Table4420[Date],W21,Table4420[Category],Table136[[#Headers],[Income]])+SUMIFS(Table44[Amount],Table44[Date],W21,Table44[Category],Table136[[#Headers],[Income]]) -> 0 | Y21: =SUMIFS(Table4[Amount],Table4[Date],W21,Table4[Category],"<>"&Table136[[#Headers],[Income]])+SUMIFS(Table44[Amount],Table44[Date],W21,Table44[Category],"<>"&Table136[[#Headers],[Income]]) -> 0 | Z21: =Z20+X21-Y21 -> 1365.01 | AA21: =AA20 -> 2207.4039
G22: Water | H22: 50 | I22: =SUMIFS(Table4[Amount],Table4[Category],Table1[[#Headers],[Housing]],Table4[Sub-Category],Table1[[#This Row],[Housing]])+SUMIFS(Table44[Amount],Table44[Category],Table1[[#Headers],[Housing]],Table44[Sub-Category],Table1[[#This Row],[Housing]]) -> 40.15 | J22: =Table1[[#This Row],[Budget]]-Table1[[#This Row],[Actual]] -> 9.85 | N22: Water Company | O22: Housing | P22: Water | Q22: 41526 | R22: 40.15 | S22: Cleared | W22: =W21+1 -> 41528 | X22: =SUMIFS(Table4420[Amount],Table4420[Date],W22,Table4420[Category],Table136[[#Headers],[Income]])+SUMIFS(Table44[Amount],Table44[Date],W22,Table44[Category],Table136[[#Headers],[Income]]) -> 0 | Y22: =SUMIFS(Table4[Amount],Table4[Date],W22,Table4[Category],"<>"&Table136[[#Headers],[Income]])+SUMIFS(Table44[Amount],Table44[Date],W22,Table44[Category],"<>"&Table136[[#Headers],[Income]]) -> 0 | Z22: =Z21+X22-Y22 -> 1365.01 | AA22: =AA21 -> 2207.4039
G23: Gas | H23: 50 | I23: =SUMIFS(Table4[Amount],Table4[Category],Table1[[#Headers],[Housing]],Table4[Sub-Category],Table1[[#This Row],[Housing]])+SUMIFS(Table44[Amount],Table44[Category],Table1[[#Headers],[Housing]],Table44[Sub-Category],Table1[[#This Row],[Housing]]) -> 51.17 | J23: =Table1[[#This Row],[Budget]]-Table1[[#This Row],[Actual]] -> -1.17 | N23: Gas Company | O23: Housing | P23: Gas | Q23: 41526 | R23: 51.17 | S23: Cleared | W23: =W22+1 -> 41529 | X23: =SUMIFS(Table4420[Amount],Table4420[Date],W23,Table4420[Category],Table136[[#Headers],[Income]])+SUMIFS(Table44[Amount],Table44[Date],W23,Table44[Category],Table136[[#Headers],[Income]]) -> 0 | Y23: =SUMIFS(Table4[Amount],Table4[Date],W23,Table4[Category],"<>"&Table136[[#Headers],[Income]])+SUMIFS(Table44[Amount],Table44[Date],W23,Table44[Category],"<>"&Table136[[#Headers],[Income]]) -> 0 | Z23: =Z22+X23-Y23 -> 1365.01 | AA23: =AA22 -> 2207.4039
G24: Television | H24: 150 | I24: =SUMIFS(Table4[Amount],Table4[Category],Table1[[#Headers],[Housing]],Table4[Sub-Category],Table1[[#This Row],[Housing]])+SUMIFS(Table44[Amount],Table44[Category],Table1[[#Headers],[Housing]],Table44[Sub-Category],Table1[[#This Row],[Housing]]) -> 150 | J24: =Table1[[#This Row],[Budget]]-Table1[[#This Row],[Actual]] -> 0 | N24: Electric Company | O24: Housing | P24: Electricity | Q24: 41531 | R24: 126.17 | S24: Cleared | W24: =W23+1 -> 41530 | X24: =SUMIFS(Table4420[Amount],Table4420[Date],W24,Table4420[Category],Table136[[#Headers],[Income]])+SUMIFS(Table44[Amount],Table44[Date],W24,Table44[Category],Table136[[#Headers],[Income]]) -> 1100 | Y24: =SUMIFS(Table4[Amount],Table4[Date],W24,Table4[Category],"<>"&Table136[[#Headers],[Income]])+SUMIFS(Table44[Amount],Table44[Date],W24,Table44[Category],"<>"&Table136[[#Headers],[Income]]) -> 0 | Z24: =Z23+X24-Y24 -> 2465.01 | AA24: =AA23 -> 2207.4039
G25: Internet | H25: 50 | I25: =SUMIFS(Table4[Amount],Table4[Category],Table1[[#Headers],[Housing]],Table4[Sub-Category],Table1[[#This Row],[Housing]])+SUMIFS(Table44[Amount],Table44[Category],Table1[[#Headers],[Housing]],Table44[Sub-Category],Table1[[#This Row],[Housing]]) -> 46.17 | J25: =Table1[[#This Row],[Budget]]-Table1[[#This Row],[Actual]] -> 3.83 | N25: Telephone Company | O25: Housing | P25: Internet | Q25: 41534 | R25: 46.17 | S25: Scheduled | W25: =W24+1 -> 41531 | X25: =SUMIFS(Table4420[Amount],Table4420[Date],W25,Table4420[Category],Table136[[#Headers],[Income]])+SUMIFS(Table44[Amount],Table44[Date],W25,Table44[Category],Table136[[#Headers],[Income]]) -> 0 | Y25: =SUMIFS(Table4[Amount],Table4[Date],W25,Table4[Category],"<>"&Table136[[#Headers],[Income]])+SUMIFS(Table44[Amount],Table44[Date],W25,Table44[Category],"<>"&Table136[[#Headers],[Income]]) -> 126.17 | Z25: =Z24+X25-Y25 -> 2338.84 | AA25: =AA24 -> 2207.4039
G26: Telephone | H26: 100 | I26: =SUMIFS(Table4[Amount],Table4[Category],Table1[[#Headers],[Housing]],Table4[Sub-Category],Table1[[#This Row],[Housing]])+SUMIFS(Table44[Amount],Table44[Category],Table1[[#Headers],[Housing]],Table44[Sub-Category],Table1[[#This Row],[Housing]]) -> 116.08 | J26: =Table1[[#This Row],[Budget]]-Table1[[#This Row],[Actual]] -> -16.08 | N26: Insurance Company | O26: Transportation | P26: Insurance | Q26: 41535 | R26: 115.79 | S26: Scheduled | W26: =W25+1 -> 41532 | X26: =SUMIFS(Table4420[Amount],Table4420[Date],W26,Table4420[Category],Table136[[#Headers],[Income]])+SUMIFS(Table44[Amount],Table44[Date],W26,Table44[Category],Table136[[#Headers],[Income]]) -> 0 | Y26: =SUMIFS(Table4[Amount],Table4[Date],W26,Table4[Category],"<>"&Table136[[#Headers],[Income]])+SUMIFS(Table44[Amount],Table44[Date],W26,Table44[Category],"<>"&Table136[[#Headers],[Income]]) -> 0 | Z26: =Z25+X26-Y26 -> 2338.84 | AA26: =AA25 -> 2207.4039
G27: Supplies | H27: 100 | I27: =SUMIFS(Table4[Amount],Table4[Category],Table1[[#Headers],[Housing]],Table4[Sub-Category],Table1[[#This Row],[Housing]])+SUMIFS(Table44[Amount],Table44[Category],Table1[[#Headers],[Housing]],Table44[Sub-Category],Table1[[#This Row],[Housing]]) -> 110.74 | J27: =Table1[[#This Row],[Budget]]-Table1[[#This Row],[Actual]] -> -10.74 | N27: Credit Card Company | O27: Bills | P27: Credit Card 1 | Q27: 41539 | R27: 250 | S27: Pending | W27: =W26+1 -> 41533 | X27: =SUMIFS(Table4420[Amount],Table4420[Date],W27,Table4420[Category],Table136[[#Headers],[Income]])+SUMIFS(Table44[Amount],Table44[Date],W27,Table44[Category],Table136[[#Headers],[Income]]) -> 0 | Y27: =SUMIFS(Table4[Amount],Table4[Date],W27,Table4[Category],"<>"&Table136[[#Headers],[Income]])+SUMIFS(Table44[Amount],Table44[Date],W27,Table44[Category],"<>"&Table136[[#Headers],[Income]]) -> 0 | Z27: =Z26+X27-Y27 -> 2338.84 | AA27: =AA26 -> 2207.4039
G28: Other | H28: 100 | I28: =SUMIFS(Table4[Amount],Table4[Category],Table1[[#Headers],[Housing]],Table4[Sub-Category],Table1[[#This Row],[Housing]])+SUMIFS(Table44[Amount],Table44[Category],Table1[[#Headers],[Housing]],Table44[Sub-Category],Table1[[#This Row],[Housing]]) -> 35 | J28: =Table1[[#This Row],[Budget]]-Table1[[#This Row],[Actual]] -> 65 | N28: Auto Finance Company 1 | O28: Transportation | P28: Auto 1 | Q28: 41541 | R28: 350 | S28: Pending | W28: =W27+1 -> 41534 | X28: =SUMIFS(Table4420[Amount],Table4420[Date],W28,Table4420[Category],Table136[[#Headers],[Income]])+SUMIFS(Table44[Amount],Table44[Date],W28,Table44[Category],Table136[[#Headers],[Income]]) -> 0 | Y28: =SUMIFS(Table4[Amount],Table4[Date],W28,Table4[Category],"<>"&Table136[[#Headers],[Income]])+SUMIFS(Table44[Amount],Table44[Date],W28,Table44[Category],"<>"&Table136[[#Headers],[Income]]) -> 46.17 | Z28: =Z27+X28-Y28 -> 2292.67 | AA28: =AA27 -> 2207.4039
G29: Total | H29: =SUBTOTAL(109,Table1[Budget]) -> 1650 | I29: =SUBTOTAL(109,Table1[Actual]) -> 1549.15 | J29: =SUBTOTAL(109,Table1[Variance]) -> 100.85 | N29: Television Company | O29: Housing | P29: Television | Q29: 41541 | R29: 150 | S29: Pending | W29: =W28+1 -> 41535 | X29: =SUMIFS(Table4420[Amount],Table4420[Date],W29,Table4420[Category],Table136[[#Headers],[Income]])+SUMIFS(Table44[Amount],Table44[Date],W29,Table44[Category],Table136[[#Headers],[Income]]) -> 0 | Y29: =SUMIFS(Table4[Amount],Table4[Date],W29,Table4[Category],"<>"&Table136[[#Headers],[Income]])+SUMIFS(Table44[Amount],Table44[Date],W29,Table44[Category],"<>"&Table136[[#Headers],[Income]]) -> 115.79 | Z29: =Z28+X29-Y29 -> 2176.88 | AA29: =AA28 -> 2207.4039
N30: Credit Card Company | O30: Bills | P30: Credit Card 2 | Q30: 41542 | R30: 25 | S30: Pending | W30: =W29+1 -> 41536 | X30: =SUMIFS(Table4420[Amount],Table4420[Date],W30,Table4420[Category],Table136[[#Headers],[Income]])+SUMIFS(Table44[Amount],Table44[Date],W30,Table44[Category],Table136[[#Headers],[Income]]) -> 0 | Y30: =SUMIFS(Table4[Amount],Table4[Date],W30,Table4[Category],"<>"&Table136[[#Headers],[Income]])+SUMIFS(Table44[Amount],Table44[Date],W30,Table44[Category],"<>"&Table136[[#Headers],[Income]]) -> 0 | Z30: =Z29+X30-Y30 -> 2176.88 | AA30: =AA29 -> 2207.4039
B31: TIP: Hover over the yellow highlighted sections for tips on how to use that section. | G31: =CONCATENATE(Table13[[#Headers],[Transportation]]," - Budget & Tracking") -> Transportation - Budget & Tracking | N31: Auto Finance Company 2 | O31: Transportation | P31: Auto 2 | Q31: 41544 | R31: 703 | S31: Pending | W31: =W30+1 -> 41537 | X31: =SUMIFS(Table4420[Amount],Table4420[Date],W31,Table4420[Category],Table136[[#Headers],[Income]])+SUMIFS(Table44[Amount],Table44[Date],W31,Table44[Category],Table136[[#Headers],[Income]]) -> 1500 | Y31: =SUMIFS(Table4[Amount],Table4[Date],W31,Table4[Category],"<>"&Table136[[#Headers],[Income]])+SUMIFS(Table44[Amount],Table44[Date],W31,Table44[Category],"<>"&Table136[[#Headers],[Income]]) -> 0 | Z31: =Z30+X31-Y31 -> 3676.88 | AA31: =AA30 -> 2207.4039
G32: Transportation | H32: Budget | I32: Actual | J32: Variance | W32: =W31+1 -> 41538 | X32: =SUMIFS(Table4420[Amount],Table4420[Date],W32,Table4420[Category],Table136[[#Headers],[Income]])+SUMIFS(Table44[Amount],Table44[Date],W32,Table44[Category],Table136[[#Headers],[Income]]) -> 0 | Y32: =SUMIFS(Table4[Amount],Table4[Date],W32,Table4[Category],"<>"&Table136[[#Headers],[Income]])+SUMIFS(Table44[Amount],Table44[Date],W32,Table44[Category],"<>"&Table136[[#Headers],[Income]]) -> 0 | Z32: =Z31+X32-Y32 -> 3676.88 | AA32: =AA31 -> 2207.4039
G33: Auto 1 | H33: 250 | I33: =SUMIFS(Table4[Amount],Table4[Category],Table13[[#Headers],[Transportation]],Table4[Sub-Category],Table13[[#This Row],[Transportation]])+SUMIFS(Table44[Amount],Table44[Category],Table13[[#Headers],[Transportation]],Table44[Sub-Category],Table13[[#This Row],[Transportation]]) -> 350 | J33: =Table13[[#This Row],[Budget]]-Table13[[#This Row],[Actual]] -> -100 | N33: All Other Transactions | W33: =W32+1 -> 41539 | X33: =SUMIFS(Table4420[Amount],Table4420[Date],W33,Table4420[Category],Table136[[#Headers],[Income]])+SUMIFS(Table44[Amount],Table44[Date],W33,Table44[Category],Table136[[#Headers],[Income]]) -> 0 | Y33: =SUMIFS(Table4[Amount],Table4[Date],W33,Table4[Category],"<>"&Table136[[#Headers],[Income]])+SUMIFS(Table44[Amount],Table44[Date],W33,Table44[Category],"<>"&Table136[[#Headers],[Income]]) -> 250 | Z33: =Z32+X33-Y33 -> 3426.88 | AA33: =AA32 -> 2207.4039
G34: Auto 2 | H34: 300 | I34: =SUMIFS(Table4[Amount],Table4[Category],Table13[[#Headers],[Transportation]],Table4[Sub-Category],Table13[[#This Row],[Transportation]])+SUMIFS(Table44[Amount],Table44[Category],Table13[[#Headers],[Transportation]],Table44[Sub-Category],Table13[[#This Row],[Transportation]]) -> 703 | J34: =Table13[[#This Row],[Budget]]-Table13[[#This Row],[Actual]] -> -403 | N34: Description | O34: Category | P34: Sub-Category | Q34: Date | R34: Amount | S34: Status | W34: =W33+1 -> 41540 | X34: =SUMIFS(Table4420[Amount],Table4420[Date],W34,Table4420[Category],Table136[[#Headers],[Income]])+SUMIFS(Table44[Amount],Table44[Date],W34,Table44[Category],Table136[[#Headers],[Income]]) -> 0 | Y34: =SUMIFS(Table4[Amount],Table4[Date],W34,Table4[Category],"<>"&Table136[[#Headers],[Income]])+SUMIFS(Table44[Amount],Table44[Date],W34,Table44[Category],"<>"&Table136[[#Headers],[Income]]) -> 0 | Z34: =Z33+X34-Y34 -> 3426.88 | AA34: =AA33 -> 2207.4039
G35: Insurance | H35: 200 | I35: =SUMIFS(Table4[Amount],Table4[Category],Table13[[#Headers],[Transportation]],Table4[Sub-Category],Table13[[#This Row],[Transportation]])+SUMIFS(Table44[Amount],Table44[Category],Table13[[#Headers],[Transportation]],Table44[Sub-Category],Table13[[#This Row],[Transportation]]) -> 115.79 | J35: =Table13[[#This Row],[Budget]]-Table13[[#This Row],[Actual]] -> 84.21 | N35: Pet Products | O35: Living | P35: Grocery | Q35: 41523 | R35: 21.39 | S35: Cleared | W35: =W34+1 -> 41541 | X35: =SUMIFS(Table4420[Amount],Table4420[Date],W35,Table4420[Category],Table136[[#Headers],[Income]])+SUMIFS(Table44[Amount],Table44[Date],W35,Table44[Category],Table136[[#Headers],[Income]]) -> 0 | Y35: =SUMIFS(Table4[Amount],Table4[Date],W35,Table4[Category],"<>"&Table136[[#Headers],[Income]])+SUMIFS(Table44[Amount],Table44[Date],W35,Table44[Category],"<>"&Table136[[#Headers],[Income]]) -> 500 | Z35: =Z34+X35-Y35 -> 2926.88 | AA35: =AA34 -> 2207.4039
G36: Fuel | H36: 250 | I36: =SUMIFS(Table4[Amount],Table4[Category],Table13[[#Headers],[Transportation]],Table4[Sub-Category],Table13[[#This Row],[Transportation]])+SUMIFS(Table44[Amount],Table44[Category],Table13[[#Headers],[Transportation]],Table44[Sub-Category],Table13[[#This Row],[Transportation]]) -> 0 | J36: =Table13[[#This Row],[Budget]]-Table13[[#This Row],[Actual]] -> 250 | N36: Home Improvement | O36: Housing | P36: Supplies | Q36: 41523 | R36: 33.24 | S36: Cleared | W36: =W35+1 -> 41542 | X36: =SUMIFS(Table4420[Amount],Table4420[Date],W36,Table4420[Category],Table136[[#Headers],[Income]])+SUMIFS(Table44[Amount],Table44[Date],W36,Table44[Category],Table136[[#Headers],[Income]]) -> 0 | Y36: =SUMIFS(Table4[Amount],Table4[Date],W36,Table4[Category],"<>"&Table136[[#Headers],[Income]])+SUMIFS(Table44[Amount],Table44[Date],W36,Table44[Category],"<>"&Table136[[#Headers],[Income]]) -> 25 | Z36: =Z35+X36-Y36 -> 2901.88 | AA36: =AA35 -> 2207.4039
G37: Total | H37: =SUBTOTAL(109,Table13[Budget]) -> 1000 | I37: =SUBTOTAL(109,Table13[Actual]) -> 1168.79 | J37: =SUBTOTAL(109,Table13[Variance]) -> -168.79 | N37: Home Improvement | O37: Housing | P37: Supplies | Q37: 41523 | R37: 31.69 | S37: Cleared | W37: =W36+1 -> 41543 | X37: =SUMIFS(Table4420[Amount],Table4420[Date],W37,Table4420[Category],Table136[[#Headers],[Income]])+SUMIFS(Table44[Amount],Table44[Date],W37,Table44[Category],Table136[[#Headers],[Income]]) -> 0 | Y37: =SUMIFS(Table4[Amount],Table4[Date],W37,Table4[Category],"<>"&Table136[[#Headers],[Income]])+SUMIFS(Table44[Amount],Table44[Date],W37,Table44[Category],"<>"&Table136[[#Headers],[Income]]) -> 0 | Z37: =Z36+X37-Y37 -> 2901.88 | AA37: =AA36 -> 2207.4039
N38: Lunch @ Subway | O38: Entertainment | P38: Dining Out | Q38: 41523 | R38: 10.88 | S38: Cleared | W38: =W37+1 -> 41544 | X38: =SUMIFS(Table4420[Amount],Table4420[Date],W38,Table4420[Category],Table136[[#Headers],[Income]])+SUMIFS(Table44[Amount],Table44[Date],W38,Table44[Category],Table136[[#Headers],[Income]]) -> 1100 | Y38: =SUMIFS(Table4[Amount],Table4[Date],W38,Table4[Category],"<>"&Table136[[#Headers],[Income]])+SUMIFS(Table44[Amount],Table44[Date],W38,Table44[Category],"<>"&Table136[[#Headers],[Income]]) -> 703 | Z38: =Z37+X38-Y38 -> 3298.88 | AA38: =AA37 -> 2207.4039
G39: =CONCATENATE(Table13910[[#Headers],[Bills]]," - Budget & Tracking") -> Bills - Budget & Tracking | N39: Home Improvement | O39: Housing | P39: Supplies | Q39: 41524 | R39: 7.58 | S39: Cleared | W39: =W38+1 -> 41545 | X39: =SUMIFS(Table4420[Amount],Table4420[Date],W39,Table4420[Category],Table136[[#Headers],[Income]])+SUMIFS(Table44[Amount],Table44[Date],W39,Table44[Category],Table136[[#Headers],[Income]]) -> 0 | Y39: =SUMIFS(Table4[Amount],Table4[Date],W39,Table4[Category],"<>"&Table136[[#Headers],[Income]])+SUMIFS(Table44[Amount],Table44[Date],W39,Table44[Category],"<>"&Table136[[#Headers],[Income]]) -> 0 | Z39: =Z38+X39-Y39 -> 3298.88 | AA39: =AA38 -> 2207.4039
G40: Bills | H40: Budget | I40: Actual | J40: Variance | N40: New Dishes | O40: Housing | P40: Supplies | Q40: 41526 | R40: 38.23 | S40: Cleared | W40: =W39+1 -> 41546 | X40: =SUMIFS(Table4420[Amount],Table4420[Date],W40,Table4420[Category],Table136[[#Headers],[Income]])+SUMIFS(Table44[Amount],Table44[Date],W40,Table44[Category],Table136[[#Headers],[Income]]) -> 0 | Y40: =SUMIFS(Table4[Amount],Table4[Date],W40,Table4[Category],"<>"&Table136[[#Headers],[Income]])+SUMIFS(Table44[Amount],Table44[Date],W40,Table44[Category],"<>"&Table136[[#Headers],[Income]]) -> 0 | Z40: =Z39+X40-Y40 -> 3298.88 | AA40: =AA39 -> 2207.4039
G41: Credit Card 1 | H41: 50 | I41: =SUMIFS(Table4[Amount],Table4[Category],Table13910[[#Headers],[Bills]],Table4[Sub-Category],Table13910[[#This Row],[Bills]])+SUMIFS(Table44[Amount],Table44[Category],Table13910[[#Headers],[Bills]],Table44[Sub-Category],Table13910[[#This Row],[Bills]]) -> 250 | J41: =Table13910[[#This Row],[Budget]]-Table13910[[#This Row],[Actual]] -> -200 | W41: =W40+1 -> 41547 | X41: =SUMIFS(Table4420[Amount],Table4420[Date],W41,Table4420[Category],Table136[[#Headers],[Income]])+SUMIFS(Table44[Amount],Table44[Date],W41,Table44[Category],Table136[[#Headers],[Income]]) -> 0 | Y41: =SUMIFS(Table4[Amount],Table4[Date],W41,Table4[Category],"<>"&Table136[[#Headers],[Income]])+SUMIFS(Table44[Amount],Table44[Date],W41,Table44[Category],"<>"&Table136[[#Headers],[Income]]) -> 0 | Z41: =Z40+X41-Y41 -> 3298.88 | AA41: =AA40 -> 2207.4039
G42: Credit Card 2 | H42: 250 | I42: =SUMIFS(Table4[Amount],Table4[Category],Table13910[[#Headers],[Bills]],Table4[Sub-Category],Table13910[[#This Row],[Bills]])+SUMIFS(Table44[Amount],Table44[Category],Table13910[[#Headers],[Bills]],Table44[Sub-Category],Table13910[[#This Row],[Bills]]) -> 25 | J42: =Table13910[[#This Row],[Budget]]-Table13910[[#This Row],[Actual]] -> 225 | W42: =W41+1 -> 41548 | X42: =SUMIFS(Table4420[Amount],Table4420[Date],W42,Table4420[Category],Table136[[#Headers],[Income]])+SUMIFS(Table44[Amount],Table44[Date],W42,Table44[Category],Table136[[#Headers],[Income]]) -> 0 | Y42: =SUMIFS(Table4[Amount],Table4[Date],W42,Table4[Category],"<>"&Table136[[#Headers],[Income]])+SUMIFS(Table44[Amount],Table44[Date],W42,Table44[Category],"<>"&Table136[[#Headers],[Income]]) -> 0 | Z42: =Z41+X42-Y42 -> 3298.88 | AA42: =AA41 -> 2207.4039
G43: Bill 1 | H43: 25 | I43: =SUMIFS(Table4[Amount],Table4[Category],Table13910[[#Headers],[Bills]],Table4[Sub-Category],Table13910[[#This Row],[Bills]])+SUMIFS(Table44[Amount],Table44[Category],Table13910[[#Headers],[Bills]],Table44[Sub-Category],Table13910[[#This Row],[Bills]]) -> 0 | J43: =Table13910[[#This Row],[Budget]]-Table13910[[#This Row],[Actual]] -> 25
G44: Bill 2 | H44: 25 | I44: =SUMIFS(Table4[Amount],Table4[Category],Table13910[[#Headers],[Bills]],Table4[Sub-Category],Table13910[[#This Row],[Bills]])+SUMIFS(Table44[Amount],Table44[Category],Table13910[[#Headers],[Bills]],Table44[Sub-Category],Table13910[[#This Row],[Bills]]) -> 0 | J44: =Table13910[[#This Row],[Budget]]-Table13910[[#This Row],[Actual]] -> 25
G45: Bill 3 | H45: 35 | I45: =SUMIFS(Table4[Amount],Table4[Category],Table13910[[#Headers],[Bills]],Table4[Sub-Category],Table13910[[#This Row],[Bills]])+SUMIFS(Table44[Amount],Table44[Category],Table13910[[#Headers],[Bills]],Table44[Sub-Category],Table13910[[#This Row],[Bills]]) -> 0 | J45: =Table13910[[#This Row],[Budget]]-Table13910[[#This Row],[Actual]] -> 35
G46: Total | H46: =SUBTOTAL(109,Table13910[Budget]) -> 385 | I46: =SUBTOTAL(109,Table13910[Actual]) -> 275 | J46: =SUBTOTAL(109,Table13910[Variance]) -> 110
G48: =CONCATENATE(Table137[[#Headers],[Living]]," - Budget & Tracking") -> Living - Budget & Tracking
G49: Living | H49: Budget | I49: Actual | J49: Variance
G50: Grocery | H50: 400 | I50: =SUMIFS(Table4[Amount],Table4[Category],Table137[[#Headers],[Living]],Table4[Sub-Category],Table137[[#This Row],[Living]])+SUMIFS(Table44[Amount],Table44[Category],Table137[[#Headers],[Living]],Table44[Sub-Category],Table137[[#This Row],[Living]]) -> 21.39 | J50: =Table137[[#This Row],[Budget]]-Table137[[#This Row],[Actual]] -> 378.61
G51: Work Spend 1 | H51: 150 | I51: =SUMIFS(Table4[Amount],Table4[Category],Table137[[#Headers],[Living]],Table4[Sub-Category],Table137[[#This Row],[Living]])+SUMIFS(Table44[Amount],Table44[Category],Table137[[#Headers],[Living]],Table44[Sub-Category],Table137[[#This Row],[Living]]) -> 0 | J51: =Table137[[#This Row],[Budget]]-Table137[[#This Row],[Actual]] -> 150
G52: Work Spend 2 | H52: 150 | I52: =SUMIFS(Table4[Amount],Table4[Category],Table137[[#Headers],[Living]],Table4[Sub-Category],Table137[[#This Row],[Living]])+SUMIFS(Table44[Amount],Table44[Category],Table137[[#Headers],[Living]],Table44[Sub-Category],Table137[[#This Row],[Living]]) -> 0 | J52: =Table137[[#This Row],[Budget]]-Table137[[#This Row],[Actual]] -> 150
G53: Other | H53: 100 | I53: =SUMIFS(Table4[Amount],Table4[Category],Table137[[#Headers],[Living]],Table4[Sub-Category],Table137[[#This Row],[Living]])+SUMIFS(Table44[Amount],Table44[Category],Table137[[#Headers],[Living]],Table44[Sub-Category],Table137[[#This Row],[Living]]) -> 0 | J53: =Table137[[#This Row],[Budget]]-Table137[[#This Row],[Actual]] -> 100
G54: Total | H54: =SUBTOTAL(109,Table137[Budget]) -> 800 | I54: =SUBTOTAL(109,Table137[Actual]) -> 21.39 | J54: =SUBTOTAL(109,Table137[Variance]) -> 778.61
G56: =CONCATENATE(Table138[[#Headers],[Entertainment]]," - Budget & Tracking") -> Entertainment - Budget & Tracking
G57: Entertainment | H57: Budget | I57: Actual | J57: Variance
G58: Dining Out | H58: 200 | I58: =SUMIFS(Table4[Amount],Table4[Category],Table138[[#Headers],[Entertainment]],Table4[Sub-Category],Table138[[#This Row],[Entertainment]])+SUMIFS(Table44[Amount],Table44[Category],Table138[[#Headers],[Entertainment]],Table44[Sub-Category],Table138[[#This Row],[Entertainment]]) -> 10.88 | J58: =Table138[[#This Row],[Budget]]-Table138[[#This Row],[Actual]] -> 189.12
G59: Other | H59: 100 | I59: =SUMIFS(Table4[Amount],Table4[Category],Table138[[#Headers],[Entertainment]],Table4[Sub-Category],Table138[[#This Row],[Entertainment]])+SUMIFS(Table44[Amount],Table44[Category],Table138[[#Headers],[Entertainment]],Table44[Sub-Category],Table138[[#This Row],[Entertainment]]) -> 0 | J59: =Table138[[#This Row],[Budget]]-Table138[[#This Row],[Actual]] -> 100
G60: Total | H60: =SUBTOTAL(109,Table138[Budget]) -> 300 | I60: =SUBTOTAL(109,Table138[Actual]) -> 10.88 | J60: =SUBTOTAL(109,Table138[Variance]) -> 289.12
G62: =CONCATENATE(Table139[[#Headers],[Misc.]]," - Budget & Tracking") -> Misc. - Budget & Tracking
G63: Misc. | H63: Budget | I63: Actual | J63: Variance
G64: Dry Cleaning | H64: 50 | I64: =SUMIFS(Table4[Amount],Table4[Category],Table139[[#Headers],[Misc.]],Table4[Sub-Category],Table139[[#This Row],[Misc.]])+SUMIFS(Table44[Amount],Table44[Category],Table139[[#Headers],[Misc.]],Table44[Sub-Category],Table139[[#This Row],[Misc.]]) -> 0 | J64: =Table139[[#This Row],[Budget]]-Table139[[#This Row],[Actual]] -> 50
G65: Other | H65: 100 | I65: =SUMIFS(Table4[Amount],Table4[Category],Table139[[#Headers],[Misc.]],Table4[Sub-Category],Table139[[#This Row],[Misc.]])+SUMIFS(Table44[Amount],Table44[Category],Table139[[#Headers],[Misc.]],Table44[Sub-Category],Table139[[#This Row],[Misc.]]) -> 0 | J65: =Table139[[#This Row],[Budget]]-Table139[[#This Row],[Actual]] -> 100
G66: Total | H66: =SUBTOTAL(109,Table139[Budget]) -> 150 | I66: =SUBTOTAL(109,Table139[Actual]) -> 0 | J66: =SUBTOTAL(109,Table139[Variance]) -> 150

Sheet Mo.2
C1: =DATE(YEAR(Mo.1!G1),MONTH(Mo.1!G1)+1,DAY(Mo.1!G1)) -> 41548 | R1: Category | S1: Budget | T1: Actual | U1: Status | V1: Min Bal
D2: Budget | E2: Actual | F2: Variance | R2: =Table13614[[#Headers],[Income]] -> Income | S2: =SUM(Table13614[Budget]) -> 0 | T2: =SUM(Table13614[Actual]) -> 0 | U2: Pending | V2: =AVERAGE(V12:V42) -> 3298.88
C3: BOM Balance | D3: =Mo.1!H6 -> 1971.74 | E3: =Mo.1!I6 -> 3298.88 | F3: =E3-D3 -> 1327.14 | R3: =Table111[[#Headers],[Housing]] -> Housing | S3: =SUM(Table111[Budget]) -> 0 | T3: =SUM(Table111[Actual]) -> 0 | U3: Scheduled
C4: Total Inflow | D4: =Table13614[[#Totals],[Budget]] -> 0 | E4: =Table13614[[#Totals],[Actual]] -> 0 | F4: =E4-D4 -> 0 | R4: =Table1312[[#Headers],[Transportation]] -> Transportation | S4: =SUM(Table1312[Budget]) -> 0 | T4: =SUM(Table1312[Actual]) -> 0 | U4: Cleared
C5: Total Outflow | D5: =Table111[[#Totals],[Budget]]+Table1312[[#Totals],[Budget]]+Table1391018[[#Totals],[Budget]]+Table13715[[#Totals],[Budget]]+Table13816[[#Totals],[Budget]]+Table13917[[#Totals],[Budget]] -> 0 | E5: =Table111[[#Totals],[Actual]]+Table1312[[#Totals],[Actual]]+Table1391018[[#Totals],[Actual]]+Table13715[[#Totals],[Actual]]+Table13816[[#Totals],[Actual]]+Table13917[[#Totals],[Actual]] -> 0 | F5: =E5-D5 -> 0 | R5: =Table1391018[[#Headers],[Bills]] -> Bills | S5: =SUM(Table1391018[Budget]) -> 0 | T5: =SUM(Table1391018[Actual]) -> 0
C6: Difference | D6: =D3+D4-D5 -> 1971.74 | E6: =E3+E4-E5 -> 3298.88 | F6: =F3+F4-F5 -> 1327.14 | R6: =Table13715[[#Headers],[Living]] -> Living | S6: =SUM(Table13715[Budget]) -> 0 | T6: =SUM(Table13715[Actual]) -> 0
R7: =Table13816[[#Headers],[Entertainment]] -> Entertainment | S7: =SUM(Table13816[Budget]) -> 0 | T7: =SUM(Table13816[Actual]) -> 0
R8: =Table13917[[#Headers],[Misc.]] -> Misc. | S8: =SUM(Table13917[Budget]) -> 0 | T8: =SUM(Table13917[Actual]) -> 0
C10: =CONCATENATE(Table13614[[#Headers],[Income]]," - Budget & Tracking") -> Income - Budget & Tracking | J10: Budgeted Credits | S10: Account Balance / Tracking & Forecast
C11: Income | D11: Budget | E11: Actual | F11: Variance | J11: Description | K11: Category | L11: Sub-Category | M11: Date | N11: Amount | O11: Status | S11: Date | T11: Credit | U11: Debit | V11: Balance
E12: =SUMIFS(Table442021[Amount],Table442021[Category],Table13614[[#Headers],[Income]],Table442021[Sub-Category],Table13614[[#This Row],[Income]])+SUMIFS(Table4419[Amount],Table4419[Category],Table13614[[#Headers],[Income]],Table4419[Sub-Category],Table13614[[#This Row],[Income]]) -> 0 | F12: =Table13614[[#This Row],[Actual]]-Table13614[[#This Row],[Budget]] -> 0 | S12: =C1 -> 41548 | T12: =SUMIFS(Table442021[Amount],Table442021[Date],S12,Table442021[Category],Table13614[[#Headers],[Income]])+SUMIFS(Table4419[Amount],Table4419[Date],S12,Table4419[Category],Table13614[[#Headers],[Income]]) -> 0 | U12: =SUMIFS(Table413[Amount],Table413[Date],S12,Table413[Category],"<>"&Table13614[[#Headers],[Income]])+SUMIFS(Table4419[Amount],Table4419[Date],S12,Table4419[Category],"<>"&Table13614[[#Headers],[Income]]) -> 0 | V12: =E3+T12-U12 -> 3298.88 | W12: =V2 -> 3298.88
E13: =SUMIFS(Table442021[Amount],Table442021[Category],Table13614[[#Headers],[Income]],Table442021[Sub-Category],Table13614[[#This Row],[Income]])+SUMIFS(Table4419[Amount],Table4419[Category],Table13614[[#Headers],[Income]],Table4419[Sub-Category],Table13614[[#This Row],[Income]]) -> 0 | F13: =Table13614[[#This Row],[Actual]]-Table13614[[#This Row],[Budget]] -> 0 | S13: =S12+1 -> 41549 | T13: =SUMIFS(Table442021[Amount],Table442021[Date],S13,Table442021[Category],Table13614[[#Headers],[Income]])+SUMIFS(Table4419[Amount],Table4419[Date],S13,Table4419[Category],Table13614[[#Headers],[Income]]) -> 0 | U13: =SUMIFS(Table413[Amount],Table413[Date],S13,Table413[Category],"<>"&Table13614[[#Headers],[Income]])+SUMIFS(Table4419[Amount],Table4419[Date],S13,Table4419[Category],"<>"&Table13614[[#Headers],[Income]]) -> 0 | V13: =V12+T13-U13 -> 3298.88 | W13: =W12 -> 3298.88
E14: =SUMIFS(Table442021[Amount],Table442021[Category],Table13614[[#Headers],[Income]],Table442021[Sub-Category],Table13614[[#This Row],[Income]])+SUMIFS(Table4419[Amount],Table4419[Category],Table13614[[#Headers],[Income]],Table4419[Sub-Category],Table13614[[#This Row],[Income]]) -> 0 | F14: =Table13614[[#This Row],[Actual]]-Table13614[[#This Row],[Budget]] -> 0 | S14: =S13+1 -> 41550 | T14: =SUMIFS(Table442021[Amount],Table442021[Date],S14,Table442021[Category],Table13614[[#Headers],[Income]])+SUMIFS(Table4419[Amount],Table4419[Date],S14,Table4419[Category],Table13614[[#Headers],[Income]]) -> 0 | U14: =SUMIFS(Table413[Amount],Table413[Date],S14,Table413[Category],"<>"&Table13614[[#Headers],[Income]])+SUMIFS(Table4419[Amount],Table4419[Date],S14,Table4419[Category],"<>"&Table13614[[#Headers],[Income]]) -> 0 | V14: =V13+T14-U14 -> 3298.88 | W14: =W13 -> 3298.88
E15: =SUMIFS(Table442021[Amount],Table442021[Category],Table13614[[#Headers],[Income]],Table442021[Sub-Category],Table13614[[#This Row],[Income]])+SUMIFS(Table4419[Amount],Table4419[Category],Table13614[[#Headers],[Income]],Table4419[Sub-Category],Table13614[[#This Row],[Income]]) -> 0 | F15: =Table13614[[#This Row],[Actual]]-Table13614[[#This Row],[Budget]] -> 0 | S15: =S14+1 -> 41551 | T15: =SUMIFS(Table442021[Amount],Table442021[Date],S15,Table442021[Category],Table13614[[#Headers],[Income]])+SUMIFS(Table4419[Amount],Table4419[Date],S15,Table4419[Category],Table13614[[#Headers],[Income]]) -> 0 | U15: =SUMIFS(Table413[Amount],Table413[Date],S15,Table413[Category],"<>"&Table13614[[#Headers],[Income]])+SUMIFS(Table4419[Amount],Table4419[Date],S15,Table4419[Category],"<>"&Table13614[[#Headers],[Income]]) -> 0 | V15: =V14+T15-U15 -> 3298.88 | W15: =W14 -> 3298.88
C16: Total | D16: =SUBTOTAL(109,Table13614[Budget]) -> 0 | E16: =SUBTOTAL(109,Table13614[Actual]) -> 0 | F16: =SUBTOTAL(109,Table13614[Variance]) -> 0 | S16: =S15+1 -> 41552 | T16: =SUMIFS(Table442021[Amount],Table442021[Date],S16,Table442021[Category],Table13614[[#Headers],[Income]])+SUMIFS(Table4419[Amount],Table4419[Date],S16,Table4419[Category],Table13614[[#Headers],[Income]]) -> 0 | U16: =SUMIFS(Table413[Amount],Table413[Date],S16,Table413[Category],"<>"&Table13614[[#Headers],[Income]])+SUMIFS(Table4419[Amount],Table4419[Date],S16,Table4419[Category],"<>"&Table13614[[#Headers],[Income]]) -> 0 | V16: =V15+T16-U16 -> 3298.88 | W16: =W15 -> 3298.88
J17: Budgeted Debits | S17: =S16+1 -> 41553 | T17: =SUMIFS(Table442021[Amount],Table442021[Date],S17,Table442021[Category],Table13614[[#Headers],[Income]])+SUMIFS(Table4419[Amount],Table4419[Date],S17,Table4419[Category],Table13614[[#Headers],[Income]]) -> 0 | U17: =SUMIFS(Table413[Amount],Table413[Date],S17,Table413[Category],"<>"&Table13614[[#Headers],[Income]])+SUMIFS(Table4419[Amount],Table4419[Date],S17,Table4419[Category],"<>"&Table13614[[#Headers],[Income]]) -> 0 | V17: =V16+T17-U17 -> 3298.88 | W17: =W16 -> 3298.88
C18: =CONCATENATE(Table111[[#Headers],[Housing]]," - Budget & Tracking") -> Housing - Budget & Tracking | J18: Description | K18: Category | L18: Sub-Category | M18: Date | N18: Amount | O18: Status | S18: =S17+1 -> 41554 | T18: =SUMIFS(Table442021[Amount],Table442021[Date],S18,Table442021[Category],Table13614[[#Headers],[Income]])+SUMIFS(Table4419[Amount],Table4419[Date],S18,Table4419[Category],Table13614[[#Headers],[Income]]) -> 0 | U18: =SUMIFS(Table413[Amount],Table413[Date],S18,Table413[Category],"<>"&Table13614[[#Headers],[Income]])+SUMIFS(Table4419[Amount],Table4419[Date],S18,Table4419[Category],"<>"&Table13614[[#Headers],[Income]]) -> 0 | V18: =V17+T18-U18 -> 3298.88 | W18: =W17 -> 3298.88
C19: Housing | D19: Budget | E19: Actual | F19: Variance | S19: =S18+1 -> 41555 | T19: =SUMIFS(Table442021[Amount],Table442021[Date],S19,Table442021[Category],Table13614[[#Headers],[Income]])+SUMIFS(Table4419[Amount],Table4419[Date],S19,Table4419[Category],Table13614[[#Headers],[Income]]) -> 0 | U19: =SUMIFS(Table413[Amount],Table413[Date],S19,Table413[Category],"<>"&Table13614[[#Headers],[Income]])+SUMIFS(Table4419[Amount],Table4419[Date],S19,Table4419[Category],"<>"&Table13614[[#Headers],[Income]]) -> 0 | V19: =V18+T19-U19 -> 3298.88 | W19: =W18 -> 3298.88
E20: =SUMIFS(Table413[Amount],Table413[Category],Table111[[#Headers],[Housing]],Table413[Sub-Category],Table111[[#This Row],[Housing]])+SUMIFS(Table4419[Amount],Table4419[Category],Table111[[#Headers],[Housing]],Table4419[Sub-Category],Table111[[#This Row],[Housing]]) -> 0 | F20: =Table111[[#This Row],[Budget]]-Table111[[#This Row],[Actual]] -> 0 | S20: =S19+1 -> 41556 | T20: =SUMIFS(Table442021[Amount],Table442021[Date],S20,Table442021[Category],Table13614[[#Headers],[Income]])+SUMIFS(Table4419[Amount],Table4419[Date],S20,Table4419[Category],Table13614[[#Headers],[Income]]) -> 0 | U20: =SUMIFS(Table413[Amount],Table413[Date],S20,Table413[Category],"<>"&Table13614[[#Headers],[Income]])+SUMIFS(Table4419[Amount],Table4419[Date],S20,Table4419[Category],"<>"&Table13614[[#Headers],[Income]]) -> 0 | V20: =V19+T20-U20 -> 3298.88 | W20: =W19 -> 3298.88
E21: =SUMIFS(Table413[Amount],Table413[Category],Table111[[#Headers],[Housing]],Table413[Sub-Category],Table111[[#This Row],[Housing]])+SUMIFS(Table4419[Amount],Table4419[Category],Table111[[#Headers],[Housing]],Table4419[Sub-Category],Table111[[#This Row],[Housing]]) -> 0 | F21: =Table111[[#This Row],[Budget]]-Table111[[#This Row],[Actual]] -> 0 | S21: =S20+1 -> 41557 | T21: =SUMIFS(Table442021[Amount],Table442021[Date],S21,Table442021[Category],Table13614[[#Headers],[Income]])+SUMIFS(Table4419[Amount],Table4419[Date],S21,Table4419[Category],Table13614[[#Headers],[Income]]) -> 0 | U21: =SUMIFS(Table413[Amount],Table413[Date],S21,Table413[Category],"<>"&Table13614[[#Headers],[Income]])+SUMIFS(Table4419[Amount],Table4419[Date],S21,Table4419[Category],"<>"&Table13614[[#Headers],[Income]]) -> 0 | V21: =V20+T21-U21 -> 3298.88 | W21: =W20 -> 3298.88
E22: =SUMIFS(Table413[Amount],Table413[Category],Table111[[#Headers],[Housing]],Table413[Sub-Category],Table111[[#This Row],[Housing]])+SUMIFS(Table4419[Amount],Table4419[Category],Table111[[#Headers],[Housing]],Table4419[Sub-Category],Table111[[#This Row],[Housing]]) -> 0 | F22: =Table111[[#This Row],[Budget]]-Table111[[#This Row],[Actual]] -> 0 | S22: =S21+1 -> 41558 | T22: =SUMIFS(Table442021[Amount],Table442021[Date],S22,Table442021[Category],Table13614[[#Headers],[Income]])+SUMIFS(Table4419[Amount],Table4419[Date],S22,Table4419[Category],Table13614[[#Headers],[Income]]) -> 0 | U22: =SUMIFS(Table413[Amount],Table413[Date],S22,Table413[Category],"<>"&Table13614[[#Headers],[Income]])+SUMIFS(Table4419[Amount],Table4419[Date],S22,Table4419[Category],"<>"&Table13614[[#Headers],[Income]]) -> 0 | V22: =V21+T22-U22 -> 3298.88 | W22: =W21 -> 3298.88
E23: =SUMIFS(Table413[Amount],Table413[Category],Table111[[#Headers],[Housing]],Table413[Sub-Category],Table111[[#This Row],[Housing]])+SUMIFS(Table4419[Amount],Table4419[Category],Table111[[#Headers],[Housing]],Table4419[Sub-Category],Table111[[#This Row],[Housing]]) -> 0 | F23: =Table111[[#This Row],[Budget]]-Table111[[#This Row],[Actual]] -> 0 | S23: =S22+1 -> 41559 | T23: =SUMIFS(Table442021[Amount],Table442021[Date],S23,Table442021[Category],Table13614[[#Headers],[Income]])+SUMIFS(Table4419[Amount],Table4419[Date],S23,Table4419[Category],Table13614[[#Headers],[Income]]) -> 0 | U23: =SUMIFS(Table413[Amount],Table413[Date],S23,Table413[Category],"<>"&Table13614[[#Headers],[Income]])+SUMIFS(Table4419[Amount],Table4419[Date],S23,Table4419[Category],"<>"&Table13614[[#Headers],[Income]]) -> 0 | V23: =V22+T23-U23 -> 3298.88 | W23: =W22 -> 3298.88
E24: =SUMIFS(Table413[Amount],Table413[Category],Table111[[#Headers],[Housing]],Table413[Sub-Category],Table111[[#This Row],[Housing]])+SUMIFS(Table4419[Amount],Table4419[Category],Table111[[#Headers],[Housing]],Table4419[Sub-Category],Table111[[#This Row],[Housing]]) -> 0 | F24: =Table111[[#This Row],[Budget]]-Table111[[#This Row],[Actual]] -> 0 | S24: =S23+1 -> 41560 | T24: =SUMIFS(Table442021[Amount],Table442021[Date],S24,Table442021[Category],Table13614[[#Headers],[Income]])+SUMIFS(Table4419[Amount],Table4419[Date],S24,Table4419[Category],Table13614[[#Headers],[Income]]) -> 0 | U24: =SUMIFS(Table413[Amount],Table413[Date],S24,Table413[Category],"<>"&Table13614[[#Headers],[Income]])+SUMIFS(Table4419[Amount],Table4419[Date],S24,Table4419[Category],"<>"&Table13614[[#Headers],[Income]]) -> 0 | V24: =V23+T24-U24 -> 3298.88 | W24: =W23 -> 3298.88
E25: =SUMIFS(Table413[Amount],Table413[Category],Table111[[#Headers],[Housing]],Table413[Sub-Category],Table111[[#This Row],[Housing]])+SUMIFS(Table4419[Amount],Table4419[Category],Table111[[#Headers],[Housing]],Table4419[Sub-Category],Table111[[#This Row],[Housing]]) -> 0 | F25: =Table111[[#This Row],[Budget]]-Table111[[#This Row],[Actual]] -> 0 | S25: =S24+1 -> 41561 | T25: =SUMIFS(Table442021[Amount],Table442021[Date],S25,Table442021[Category],Table13614[[#Headers],[Income]])+SUMIFS(Table4419[Amount],Table4419[Date],S25,Table4419[Category],Table13614[[#Headers],[Income]]) -> 0 | U25: =SUMIFS(Table413[Amount],Table413[Date],S25,Table413[Category],"<>"&Table13614[[#Headers],[Income]])+SUMIFS(Table4419[Amount],Table4419[Date],S25,Table4419[Category],"<>"&Table13614[[#Headers],[Income]]) -> 0 | V25: =V24+T25-U25 -> 3298.88 | W25: =W24 -> 3298.88
E26: =SUMIFS(Table413[Amount],Table413[Category],Table111[[#Headers],[Housing]],Table413[Sub-Category],Table111[[#This Row],[Housing]])+SUMIFS(Table4419[Amount],Table4419[Category],Table111[[#Headers],[Housing]],Table4419[Sub-Category],Table111[[#This Row],[Housing]]) -> 0 | F26: =Table111[[#This Row],[Budget]]-Table111[[#This Row],[Actual]] -> 0 | S26: =S25+1 -> 41562 | T26: =SUMIFS(Table442021[Amount],Table442021[Date],S26,Table442021[Category],Table13614[[#Headers],[Income]])+SUMIFS(Table4419[Amount],Table4419[Date],S26,Table4419[Category],Table13614[[#Headers],[Income]]) -> 0 | U26: =SUMIFS(Table413[Amount],Table413[Date],S26,Table413[Category],"<>"&Table13614[[#Headers],[Income]])+SUMIFS(Table4419[Amount],Table4419[Date],S26,Table4419[Category],"<>"&Table13614[[#Headers],[Income]]) -> 0 | V26: =V25+T26-U26 -> 3298.88 | W26: =W25 -> 3298.88
E27: =SUMIFS(Table413[Amount],Table413[Category],Table111[[#Headers],[Housing]],Table413[Sub-Category],Table111[[#This Row],[Housing]])+SUMIFS(Table4419[Amount],Table4419[Category],Table111[[#Headers],[Housing]],Table4419[Sub-Category],Table111[[#This Row],[Housing]]) -> 0 | F27: =Table111[[#This Row],[Budget]]-Table111[[#This Row],[Actual]] -> 0 | S27: =S26+1 -> 41563 | T27: =SUMIFS(Table442021[Amount],Table442021[Date],S27,Table442021[Category],Table13614[[#Headers],[Income]])+SUMIFS(Table4419[Amount],Table4419[Date],S27,Table4419[Category],Table13614[[#Headers],[Income]]) -> 0 | U27: =SUMIFS(Table413[Amount],Table413[Date],S27,Table413[Category],"<>"&Table13614[[#Headers],[Income]])+SUMIFS(Table4419[Amount],Table4419[Date],S27,Table4419[Category],"<>"&Table13614[[#Headers],[Income]]) -> 0 | V27: =V26+T27-U27 -> 3298.88 | W27: =W26 -> 3298.88
E28: =SUMIFS(Table413[Amount],Table413[Category],Table111[[#Headers],[Housing]],Table413[Sub-Category],Table111[[#This Row],[Housing]])+SUMIFS(Table4419[Amount],Table4419[Category],Table111[[#Headers],[Housing]],Table4419[Sub-Category],Table111[[#This Row],[Housing]]) -> 0 | F28: =Table111[[#This Row],[Budget]]-Table111[[#This Row],[Actual]] -> 0 | S28: =S27+1 -> 41564 | T28: =SUMIFS(Table442021[Amount],Table442021[Date],S28,Table442021[Category],Table13614[[#Headers],[Income]])+SUMIFS(Table4419[Amount],Table4419[Date],S28,Table4419[Category],Table13614[[#Headers],[Income]]) -> 0 | U28: =SUMIFS(Table413[Amount],Table413[Date],S28,Table413[Category],"<>"&Table13614[[#Headers],[Income]])+SUMIFS(Table4419[Amount],Table4419[Date],S28,Table4419[Category],"<>"&Table13614[[#Headers],[Income]]) -> 0 | V28: =V27+T28-U28 -> 3298.88 | W28: =W27 -> 3298.88
C29: Total | D29: =SUBTOTAL(109,Table111[Budget]) -> 0 | E29: =SUBTOTAL(109,Table111[Actual]) -> 0 | F29: =SUBTOTAL(109,Table111[Variance]) -> 0 | S29: =S28+1 -> 41565 | T29: =SUMIFS(Table442021[Amount],Table442021[Date],S29,Table442021[Category],Table13614[[#Headers],[Income]])+SUMIFS(Table4419[Amount],Table4419[Date],S29,Table4419[Category],Table13614[[#Headers],[Income]]) -> 0 | U29: =SUMIFS(Table413[Amount],Table413[Date],S29,Table413[Category],"<>"&Table13614[[#Headers],[Income]])+SUMIFS(Table4419[Amount],Table4419[Date],S29,Table4419[Category],"<>"&Table13614[[#Headers],[Income]]) -> 0 | V29: =V28+T29-U29 -> 3298.88 | W29: =W28 -> 3298.88
S30: =S29+1 -> 41566 | T30: =SUMIFS(Table442021[Amount],Table442021[Date],S30,Table442021[Category],Table13614[[#Headers],[Income]])+SUMIFS(Table4419[Amount],Table4419[Date],S30,Table4419[Category],Table13614[[#Headers],[Income]]) -> 0 | U30: =SUMIFS(Table413[Amount],Table413[Date],S30,Table413[Category],"<>"&Table13614[[#Headers],[Income]])+SUMIFS(Table4419[Amount],Table4419[Date],S30,Table4419[Category],"<>"&Table13614[[#Headers],[Income]]) -> 0 | V30: =V29+T30-U30 -> 3298.88 | W30: =W29 -> 3298.88
C31: =CONCATENATE(Table1312[[#Headers],[Transportation]]," - Budget & Tracking") -> Transportation - Budget & Tracking | S31: =S30+1 -> 41567 | T31: =SUMIFS(Table442021[Amount],Table442021[Date],S31,Table442021[Category],Table13614[[#Headers],[Income]])+SUMIFS(Table4419[Amount],Table4419[Date],S31,Table4419[Category],Table13614[[#Headers],[Income]]) -> 0 | U31: =SUMIFS(Table413[Amount],Table413[Date],S31,Table413[Category],"<>"&Table13614[[#Headers],[Income]])+SUMIFS(Table4419[Amount],Table4419[Date],S31,Table4419[Category],"<>"&Table13614[[#Headers],[Income]]) -> 0 | V31: =V30+T31-U31 -> 3298.88 | W31: =W30 -> 3298.88
C32: Transportation | D32: Budget | E32: Actual | F32: Variance | S32: =S31+1 -> 41568 | T32: =SUMIFS(Table442021[Amount],Table442021[Date],S32,Table442021[Category],Table13614[[#Headers],[Income]])+SUMIFS(Table4419[Amount],Table4419[Date],S32,Table4419[Category],Table13614[[#Headers],[Income]]) -> 0 | U32: =SUMIFS(Table413[Amount],Table413[Date],S32,Table413[Category],"<>"&Table13614[[#Headers],[Income]])+SUMIFS(Table4419[Amount],Table4419[Date],S32,Table4419[Category],"<>"&Table13614[[#Headers],[Income]]) -> 0 | V32: =V31+T32-U32 -> 3298.88 | W32: =W31 -> 3298.88
E33: =SUMIFS(Table413[Amount],Table413[Category],Table1312[[#Headers],[Transportation]],Table413[Sub-Category],Table1312[[#This Row],[Transportation]])+SUMIFS(Table4419[Amount],Table4419[Category],Table1312[[#Headers],[Transportation]],Table4419[Sub-Category],Table1312[[#This Row],[Transportation]]) -> 0 | F33: =Table1312[[#This Row],[Budget]]-Table1312[[#This Row],[Actual]] -> 0 | J33: All Other Transactions | S33: =S32+1 -> 41569 | T33: =SUMIFS(Table442021[Amount],Table442021[Date],S33,Table442021[Category],Table13614[[#Headers],[Income]])+SUMIFS(Table4419[Amount],Table4419[Date],S33,Table4419[Category],Table13614[[#Headers],[Income]]) -> 0 | U33: =SUMIFS(Table413[Amount],Table413[Date],S33,Table413[Category],"<>"&Table13614[[#Headers],[Income]])+SUMIFS(Table4419[Amount],Table4419[Date],S33,Table4419[Category],"<>"&Table13614[[#Headers],[Income]]) -> 0 | V33: =V32+T33-U33 -> 3298.88 | W33: =W32 -> 3298.88
E34: =SUMIFS(Table413[Amount],Table413[Category],Table1312[[#Headers],[Transportation]],Table413[Sub-Category],Table1312[[#This Row],[Transportation]])+SUMIFS(Table4419[Amount],Table4419[Category],Table1312[[#Headers],[Transportation]],Table4419[Sub-Category],Table1312[[#This Row],[Transportation]]) -> 0 | F34: =Table1312[[#This Row],[Budget]]-Table1312[[#This Row],[Actual]] -> 0 | J34: Description | K34: Category | L34: Sub-Category | M34: Date | N34: Amount | O34: Status | S34: =S33+1 -> 41570 | T34: =SUMIFS(Table442021[Amount],Table442021[Date],S34,Table442021[Category],Table13614[[#Headers],[Income]])+SUMIFS(Table4419[Amount],Table4419[Date],S34,Table4419[Category],Table13614[[#Headers],[Income]]) -> 0 | U34: =SUMIFS(Table413[Amount],Table413[Date],S34,Table413[Category],"<>"&Table13614[[#Headers],[Income]])+SUMIFS(Table4419[Amount],Table4419[Date],S34,Table4419[Category],"<>"&Table13614[[#Headers],[Income]]) -> 0 | V34: =V33+T34-U34 -> 3298.88 | W34: =W33 -> 3298.88
E35: =SUMIFS(Table413[Amount],Table413[Category],Table1312[[#Headers],[Transportation]],Table413[Sub-Category],Table1312[[#This Row],[Transportation]])+SUMIFS(Table4419[Amount],Table4419[Category],Table1312[[#Headers],[Transportation]],Table4419[Sub-Category],Table1312[[#This Row],[Transportation]]) -> 0 | F35: =Table1312[[#This Row],[Budget]]-Table1312[[#This Row],[Actual]] -> 0 | S35: =S34+1 -> 41571 | T35: =SUMIFS(Table442021[Amount],Table442021[Date],S35,Table442021[Category],Table13614[[#Headers],[Income]])+SUMIFS(Table4419[Amount],Table4419[Date],S35,Table4419[Category],Table13614[[#Headers],[Income]]) -> 0 | U35: =SUMIFS(Table413[Amount],Table413[Date],S35,Table413[Category],"<>"&Table13614[[#Headers],[Income]])+SUMIFS(Table4419[Amount],Table4419[Date],S35,Table4419[Category],"<>"&Table13614[[#Headers],[Income]]) -> 0 | V35: =V34+T35-U35 -> 3298.88 | W35: =W34 -> 3298.88
E36: =SUMIFS(Table413[Amount],Table413[Category],Table1312[[#Headers],[Transportation]],Table413[Sub-Category],Table1312[[#This Row],[Transportation]])+SUMIFS(Table4419[Amount],Table4419[Category],Table1312[[#Headers],[Transportation]],Table4419[Sub-Category],Table1312[[#This Row],[Transportation]]) -> 0 | F36: =Table1312[[#This Row],[Budget]]-Table1312[[#This Row],[Actual]] -> 0 | S36: =S35+1 -> 41572 | T36: =SUMIFS(Table442021[Amount],Table442021[Date],S36,Table442021[Category],Table13614[[#Headers],[Income]])+SUMIFS(Table4419[Amount],Table4419[Date],S36,Table4419[Category],Table13614[[#Headers],[Income]]) -> 0 | U36: =SUMIFS(Table413[Amount],Table413[Date],S36,Table413[Category],"<>"&Table13614[[#Headers],[Income]])+SUMIFS(Table4419[Amount],Table4419[Date],S36,Table4419[Category],"<>"&Table13614[[#Headers],[Income]]) -> 0 | V36: =V35+T36-U36 -> 3298.88 | W36: =W35 -> 3298.88
C37: Total | D37: =SUBTOTAL(109,Table1312[Budget]) -> 0 | E37: =SUBTOTAL(109,Table1312[Actual]) -> 0 | F37: =SUBTOTAL(109,Table1312[Variance]) -> 0 | S37: =S36+1 -> 41573 | T37: =SUMIFS(Table442021[Amount],Table442021[Date],S37,Table442021[Category],Table13614[[#Headers],[Income]])+SUMIFS(Table4419[Amount],Table4419[Date],S37,Table4419[Category],Table13614[[#Headers],[Income]]) -> 0 | U37: =SUMIFS(Table413[Amount],Table413[Date],S37,Table413[Category],"<>"&Table13614[[#Headers],[Income]])+SUMIFS(Table4419[Amount],Table4419[Date],S37,Table4419[Category],"<>"&Table13614[[#Headers],[Income]]) -> 0 | V37: =V36+T37-U37 -> 3298.88 | W37: =W36 -> 3298.88
S38: =S37+1 -> 41574 | T38: =SUMIFS(Table442021[Amount],Table442021[Date],S38,Table442021[Category],Table13614[[#Headers],[Income]])+SUMIFS(Table4419[Amount],Table4419[Date],S38,Table4419[Category],Table13614[[#Headers],[Income]]) -> 0 | U38: =SUMIFS(Table413[Amount],Table413[Date],S38,Table413[Category],"<>"&Table13614[[#Headers],[Income]])+SUMIFS(Table4419[Amount],Table4419[Date],S38,Table4419[Category],"<>"&Table13614[[#Headers],[Income]]) -> 0 | V38: =V37+T38-U38 -> 3298.88 | W38: =W37 -> 3298.88
C39: =CONCATENATE(Table1391018[[#Headers],[Bills]]," - Budget & Tracking") -> Bills - Budget & Tracking | S39: =S38+1 -> 41575 | T39: =SUMIFS(Table442021[Amount],Table442021[Date],S39,Table442021[Category],Table13614[[#Headers],[Income]])+SUMIFS(Table4419[Amount],Table4419[Date],S39,Table4419[Category],Table13614[[#Headers],[Income]]) -> 0 | U39: =SUMIFS(Table413[Amount],Table413[Date],S39,Table413[Category],"<>"&Table13614[[#Headers],[Income]])+SUMIFS(Table4419[Amount],Table4419[Date],S39,Table4419[Category],"<>"&Table13614[[#Headers],[Income]]) -> 0 | V39: =V38+T39-U39 -> 3298.88 | W39: =W38 -> 3298.88
C40: Bills | D40: Budget | E40: Actual | F40: Variance | S40: =S39+1 -> 41576 | T40: =SUMIFS(Table442021[Amount],Table442021[Date],S40,Table442021[Category],Table13614[[#Headers],[Income]])+SUMIFS(Table4419[Amount],Table4419[Date],S40,Table4419[Category],Table13614[[#Headers],[Income]]) -> 0 | U40: =SUMIFS(Table413[Amount],Table413[Date],S40,Table413[Category],"<>"&Table13614[[#Headers],[Income]])+SUMIFS(Table4419[Amount],Table4419[Date],S40,Table4419[Category],"<>"&Table13614[[#Headers],[Income]]) -> 0 | V40: =V39+T40-U40 -> 3298.88 | W40: =W39 -> 3298.88
E41: =SUMIFS(Table413[Amount],Table413[Category],Table1391018[[#Headers],[Bills]],Table413[Sub-Category],Table1391018[[#This Row],[Bills]])+SUMIFS(Table4419[Amount],Table4419[Category],Table1391018[[#Headers],[Bills]],Table4419[Sub-Category],Table1391018[[#This Row],[Bills]]) -> 0 | F41: =Table1391018[[#This Row],[Budget]]-Table1391018[[#This Row],[Actual]] -> 0 | S41: =S40+1 -> 41577 | T41: =SUMIFS(Table442021[Amount],Table442021[Date],S41,Table442021[Category],Table13614[[#Headers],[Income]])+SUMIFS(Table4419[Amount],Table4419[Date],S41,Table4419[Category],Table13614[[#Headers],[Income]]) -> 0 | U41: =SUMIFS(Table413[Amount],Table413[Date],S41,Table413[Category],"<>"&Table13614[[#Headers],[Income]])+SUMIFS(Table4419[Amount],Table4419[Date],S41,Table4419[Category],"<>"&Table13614[[#Headers],[Income]]) -> 0 | V41: =V40+T41-U41 -> 3298.88 | W41: =W40 -> 3298.88
E42: =SUMIFS(Table413[Amount],Table413[Category],Table1391018[[#Headers],[Bills]],Table413[Sub-Category],Table1391018[[#This Row],[Bills]])+SUMIFS(Table4419[Amount],Table4419[Category],Table1391018[[#Headers],[Bills]],Table4419[Sub-Category],Table1391018[[#This Row],[Bills]]) -> 0 | F42: =Table1391018[[#This Row],[Budget]]-Table1391018[[#This Row],[Actual]] -> 0 | S42: =S41+1 -> 41578 | T42: =SUMIFS(Table442021[Amount],Table442021[Date],S42,Table442021[Category],Table13614[[#Headers],[Income]])+SUMIFS(Table4419[Amount],Table4419[Date],S42,Table4419[Category],Table13614[[#Headers],[Income]]) -> 0 | U42: =SUMIFS(Table413[Amount],Table413[Date],S42,Table413[Category],"<>"&Table13614[[#Headers],[Income]])+SUMIFS(Table4419[Amount],Table4419[Date],S42,Table4419[Category],"<>"&Table13614[[#Headers],[Income]]) -> 0 | V42: =V41+T42-U42 -> 3298.88 | W42: =W41 -> 3298.88
E43: =SUMIFS(Table413[Amount],Table413[Category],Table1391018[[#Headers],[Bills]],Table413[Sub-Category],Table1391018[[#This Row],[Bills]])+SUMIFS(Table4419[Amount],Table4419[Category],Table1391018[[#Headers],[Bills]],Table4419[Sub-Category],Table1391018[[#This Row],[Bills]]) -> 0 | F43: =Table1391018[[#This Row],[Budget]]-Table1391018[[#This Row],[Actual]] -> 0
E44: =SUMIFS(Table413[Amount],Table413[Category],Table1391018[[#Headers],[Bills]],Table413[Sub-Category],Table1391018[[#This Row],[Bills]])+SUMIFS(Table4419[Amount],Table4419[Category],Table1391018[[#Headers],[Bills]],Table4419[Sub-Category],Table1391018[[#This Row],[Bills]]) -> 0 | F44: =Table1391018[[#This Row],[Budget]]-Table1391018[[#This Row],[Actual]] -> 0
E45: =SUMIFS(Table413[Amount],Table413[Category],Table1391018[[#Headers],[Bills]],Table413[Sub-Category],Table1391018[[#This Row],[Bills]])+SUMIFS(Table4419[Amount],Table4419[Category],Table1391018[[#Headers],[Bills]],Table4419[Sub-Category],Table1391018[[#This Row],[Bills]]) -> 0 | F45: =Table1391018[[#This Row],[Budget]]-Table1391018[[#This Row],[Actual]] -> 0
C46: Total | D46: =SUBTOTAL(109,Table1391018[Budget]) -> 0 | E46: =SUBTOTAL(109,Table1391018[Actual]) -> 0 | F46: =SUBTOTAL(109,Table1391018[Variance]) -> 0
C48: =CONCATENATE(Table13715[[#Headers],[Living]]," - Budget & Tracking") -> Living - Budget & Tracking
C49: Living | D49: Budget | E49: Actual | F49: Variance
E50: =SUMIFS(Table413[Amount],Table413[Category],Table13715[[#Headers],[Living]],Table413[Sub-Category],Table13715[[#This Row],[Living]])+SUMIFS(Table4419[Amount],Table4419[Category],Table13715[[#Headers],[Living]],Table4419[Sub-Category],Table13715[[#This Row],[Living]]) -> 0 | F50: =Table13715[[#This Row],[Budget]]-Table13715[[#This Row],[Actual]] -> 0
E51: =SUMIFS(Table413[Amount],Table413[Category],Table13715[[#Headers],[Living]],Table413[Sub-Category],Table13715[[#This Row],[Living]])+SUMIFS(Table4419[Amount],Table4419[Category],Table13715[[#Headers],[Living]],Table4419[Sub-Category],Table13715[[#This Row],[Living]]) -> 0 | F51: =Table13715[[#This Row],[Budget]]-Table13715[[#This Row],[Actual]] -> 0
E52: =SUMIFS(Table413[Amount],Table413[Category],Table13715[[#Headers],[Living]],Table413[Sub-Category],Table13715[[#This Row],[Living]])+SUMIFS(Table4419[Amount],Table4419[Category],Table13715[[#Headers],[Living]],Table4419[Sub-Category],Table13715[[#This Row],[Living]]) -> 0 | F52: =Table13715[[#This Row],[Budget]]-Table13715[[#This Row],[Actual]] -> 0
E53: =SUMIFS(Table413[Amount],Table413[Category],Table13715[[#Headers],[Living]],Table413[Sub-Category],Table13715[[#This Row],[Living]])+SUMIFS(Table4419[Amount],Table4419[Category],Table13715[[#Headers],[Living]],Table4419[Sub-Category],Table13715[[#This Row],[Living]]) -> 0 | F53: =Table13715[[#This Row],[Budget]]-Table13715[[#This Row],[Actual]] -> 0
C54: Total | D54: =SUBTOTAL(109,Table13715[Budget]) -> 0 | E54: =SUBTOTAL(109,Table13715[Actual]) -> 0 | F54: =SUBTOTAL(109,Table13715[Variance]) -> 0
C56: =CONCATENATE(Table13816[[#Headers],[Entertainment]]," - Budget & Tracking") -> Entertainment - Budget & Tracking
C57: Entertainment | D57: Budget | E57: Actual | F57: Variance
E58: =SUMIFS(Table413[Amount],Table413[Category],Table13816[[#Headers],[Entertainment]],Table413[Sub-Category],Table13816[[#This Row],[Entertainment]])+SUMIFS(Table4419[Amount],Table4419[Category],Table13816[[#Headers],[Entertainment]],Table4419[Sub-Category],Table13816[[#This Row],[Entertainment]]) -> 0 | F58: =Table13816[[#This Row],[Budget]]-Table13816[[#This Row],[Actual]] -> 0
E59: =SUMIFS(Table413[Amount],Table413[Category],Table13816[[#Headers],[Entertainment]],Table413[Sub-Category],Table13816[[#This Row],[Entertainment]])+SUMIFS(Table4419[Amount],Table4419[Category],Table13816[[#Headers],[Entertainment]],Table4419[Sub-Category],Table13816[[#This Row],[Entertainment]]) -> 0 | F59: =Table13816[[#This Row],[Budget]]-Table13816[[#This Row],[Actual]] -> 0
C60: Total | D60: =SUBTOTAL(109,Table13816[Budget]) -> 0 | E60: =SUBTOTAL(109,Table13816[Actual]) -> 0 | F60: =SUBTOTAL(109,Table13816[Variance]) -> 0
C62: =CONCATENATE(Table13917[[#Headers],[Misc.]]," - Budget & Tracking") -> Misc. - Budget & Tracking
C63: Misc. | D63: Budget | E63: Actual | F63: Variance
E64: =SUMIFS(Table413[Amount],Table413[Category],Table13917[[#Headers],[Misc.]],Table413[Sub-Category],Table13917[[#This Row],[Misc.]])+SUMIFS(Table4419[Amount],Table4419[Category],Table13917[[#Headers],[Misc.]],Table4419[Sub-Category],Table13917[[#This Row],[Misc.]]) -> 0 | F64: =Table13917[[#This Row],[Budget]]-Table13917[[#This Row],[Actual]] -> 0
E65: =SUMIFS(Table413[Amount],Table413[Category],Table13917[[#Headers],[Misc.]],Table413[Sub-Category],Table13917[[#This Row],[Misc.]])+SUMIFS(Table4419[Amount],Table4419[Category],Table13917[[#Headers],[Misc.]],Table4419[Sub-Category],Table13917[[#This Row],[Misc.]]) -> 0 | F65: =Table13917[[#This Row],[Budget]]-Table13917[[#This Row],[Actual]] -> 0
C66: Total | D66: =SUBTOTAL(109,Table13917[Budget]) -> 0 | E66: =SUBTOTAL(109,Table13917[Actual]) -> 0 | F66: =SUBTOTAL(109,Table13917[Variance]) -> 0

Sheet Mo.3
C1: =DATE(YEAR(Mo.2!C1),MONTH(Mo.2!C1)+1,DAY(Mo.2!C1)) -> 41579 | R1: Category | S1: Budget | T1: Actual | U1: Status | V1: Min Bal
D2: Budget | E2: Actual | F2: Variance | R2: =Table13635[[#Headers],[Income]] -> Income | S2: =SUM(Table13635[Budget]) -> 0 | T2: =SUM(Table13635[Actual]) -> 0 | U2: Pending | V2: =AVERAGE(V12:V42) -> 3298.88
C3: BOM Balance | D3: =Mo.2!D6 -> 1971.74 | E3: =Mo.2!E6 -> 3298.88 | F3: =E3-D3 -> 1327.14 | R3: =Table132[[#Headers],[Housing]] -> Housing | S3: =SUM(Table132[Budget]) -> 0 | T3: =SUM(Table132[Actual]) -> 0 | U3: Scheduled
C4: Total Inflow | D4: =Table13635[[#Totals],[Budget]] -> 0 | E4: =Table13635[[#Totals],[Actual]] -> 0 | F4: =E4-D4 -> 0 | R4: =Table1333[[#Headers],[Transportation]] -> Transportation | S4: =SUM(Table1333[Budget]) -> 0 | T4: =SUM(Table1333[Actual]) -> 0 | U4: Cleared
C5: Total Outflow | D5: =Table132[[#Totals],[Budget]]+Table1333[[#Totals],[Budget]]+Table1391039[[#Totals],[Budget]]+Table13736[[#Totals],[Budget]]+Table13837[[#Totals],[Budget]]+Table13938[[#Totals],[Budget]] -> 0 | E5: =Table132[[#Totals],[Actual]]+Table1333[[#Totals],[Actual]]+Table1391039[[#Totals],[Actual]]+Table13736[[#Totals],[Actual]]+Table13837[[#Totals],[Actual]]+Table13938[[#Totals],[Actual]] -> 0 | F5: =E5-D5 -> 0 | R5: =Table1391039[[#Headers],[Bills]] -> Bills | S5: =SUM(Table1391039[Budget]) -> 0 | T5: =SUM(Table1391039[Actual]) -> 0
C6: Difference | D6: =D3+D4-D5 -> 1971.74 | E6: =E3+E4-E5 -> 3298.88 | F6: =F3+F4-F5 -> 1327.14 | R6: =Table13736[[#Headers],[Living]] -> Living | S6: =SUM(Table13736[Budget]) -> 0 | T6: =SUM(Table13736[Actual]) -> 0
R7: =Table13837[[#Headers],[Entertainment]] -> Entertainment | S7: =SUM(Table13837[Budget]) -> 0 | T7: =SUM(Table13837[Actual]) -> 0
R8: =Table13938[[#Headers],[Misc.]] -> Misc. | S8: =SUM(Table13938[Budget]) -> 0 | T8: =SUM(Table13938[Actual]) -> 0
C10: =CONCATENATE(Table13635[[#Headers],[Income]]," - Budget & Tracking") -> Income - Budget & Tracking | J10: Budgeted Credits | S10: Account Balance / Tracking & Forecast
C11: Income | D11: Budget | E11: Actual | F11: Variance | J11: Description | K11: Category | L11: Sub-Category | M11: Date | N11: Amount | O11: Status | S11: Date | T11: Credit | U11: Debit | V11: Balance
E12: =SUMIFS(Table442041[Amount],Table442041[Category],Table13635[[#Headers],[Income]],Table442041[Sub-Category],Table13635[[#This Row],[Income]])+SUMIFS(Table4440[Amount],Table4440[Category],Table13635[[#Headers],[Income]],Table4440[Sub-Category],Table13635[[#This Row],[Income]]) -> 0 | F12: =Table13635[[#This Row],[Actual]]-Table13635[[#This Row],[Budget]] -> 0 | S12: =C1 -> 41579 | T12: =SUMIFS(Table442041[Amount],Table442041[Date],S12,Table442041[Category],Table13635[[#Headers],[Income]])+SUMIFS(Table4440[Amount],Table4440[Date],S12,Table4440[Category],Table13635[[#Headers],[Income]]) -> 0 | U12: =SUMIFS(Table434[Amount],Table434[Date],S12,Table434[Category],"<>"&Table13635[[#Headers],[Income]])+SUMIFS(Table4440[Amount],Table4440[Date],S12,Table4440[Category],"<>"&Table13635[[#Headers],[Income]]) -> 0 | V12: =E3+T12-U12 -> 3298.88 | W12: =V2 -> 3298.88
E13: =SUMIFS(Table442041[Amount],Table442041[Category],Table13635[[#Headers],[Income]],Table442041[Sub-Category],Table13635[[#This Row],[Income]])+SUMIFS(Table4440[Amount],Table4440[Category],Table13635[[#Headers],[Income]],Table4440[Sub-Category],Table13635[[#This Row],[Income]]) -> 0 | F13: =Table13635[[#This Row],[Actual]]-Table13635[[#This Row],[Budget]] -> 0 | S13: =S12+1 -> 41580 | T13: =SUMIFS(Table442041[Amount],Table442041[Date],S13,Table442041[Category],Table13635[[#Headers],[Income]])+SUMIFS(Table4440[Amount],Table4440[Date],S13,Table4440[Category],Table13635[[#Headers],[Income]]) -> 0 | U13: =SUMIFS(Table434[Amount],Table434[Date],S13,Table434[Category],"<>"&Table13635[[#Headers],[Income]])+SUMIFS(Table4440[Amount],Table4440[Date],S13,Table4440[Category],"<>"&Table13635[[#Headers],[Income]]) -> 0 | V13: =V12+T13-U13 -> 3298.88 | W13: =W12 -> 3298.88
E14: =SUMIFS(Table442041[Amount],Table442041[Category],Table13635[[#Headers],[Income]],Table442041[Sub-Category],Table13635[[#This Row],[Income]])+SUMIFS(Table4440[Amount],Table4440[Category],Table13635[[#Headers],[Income]],Table4440[Sub-Category],Table13635[[#This Row],[Income]]) -> 0 | F14: =Table13635[[#This Row],[Actual]]-Table13635[[#This Row],[Budget]] -> 0 | S14: =S13+1 -> 41581 | T14: =SUMIFS(Table442041[Amount],Table442041[Date],S14,Table442041[Category],Table13635[[#Headers],[Income]])+SUMIFS(Table4440[Amount],Table4440[Date],S14,Table4440[Category],Table13635[[#Headers],[Income]]) -> 0 | U14: =SUMIFS(Table434[Amount],Table434[Date],S14,Table434[Category],"<>"&Table13635[[#Headers],[Income]])+SUMIFS(Table4440[Amount],Table4440[Date],S14,Table4440[Category],"<>"&Table13635[[#Headers],[Income]]) -> 0 | V14: =V13+T14-U14 -> 3298.88 | W14: =W13 -> 3298.88
E15: =SUMIFS(Table442041[Amount],Table442041[Category],Table13635[[#Headers],[Income]],Table442041[Sub-Category],Table13635[[#This Row],[Income]])+SUMIFS(Table4440[Amount],Table4440[Category],Table13635[[#Headers],[Income]],Table4440[Sub-Category],Table13635[[#This Row],[Income]]) -> 0 | F15: =Table13635[[#This Row],[Actual]]-Table13635[[#This Row],[Budget]] -> 0 | S15: =S14+1 -> 41582 | T15: =SUMIFS(Table442041[Amount],Table442041[Date],S15,Table442041[Category],Table13635[[#Headers],[Income]])+SUMIFS(Table4440[Amount],Table4440[Date],S15,Table4440[Category],Table13635[[#Headers],[Income]]) -> 0 | U15: =SUMIFS(Table434[Amount],Table434[Date],S15,Table434[Category],"<>"&Table13635[[#Headers],[Income]])+SUMIFS(Table4440[Amount],Table4440[Date],S15,Table4440[Category],"<>"&Table13635[[#Headers],[Income]]) -> 0 | V15: =V14+T15-U15 -> 3298.88 | W15: =W14 -> 3298.88
C16: Total | D16: =SUBTOTAL(109,Table13635[Budget]) -> 0 | E16: =SUBTOTAL(109,Table13635[Actual]) -> 0 | F16: =SUBTOTAL(109,Table13635[Variance]) -> 0 | S16: =S15+1 -> 41583 | T16: =SUMIFS(Table442041[Amount],Table442041[Date],S16,Table442041[Category],Table13635[[#Headers],[Income]])+SUMIFS(Table4440[Amount],Table4440[Date],S16,Table4440[Category],Table13635[[#Headers],[Income]]) -> 0 | U16: =SUMIFS(Table434[Amount],Table434[Date],S16,Table434[Category],"<>"&Table13635[[#Headers],[Income]])+SUMIFS(Table4440[Amount],Table4440[Date],S16,Table4440[Category],"<>"&Table13635[[#Headers],[Income]]) -> 0 | V16: =V15+T16-U16 -> 3298.88 | W16: =W15 -> 3298.88
J17: Budgeted Debits | S17: =S16+1 -> 41584 | T17: =SUMIFS(Table442041[Amount],Table442041[Date],S17,Table442041[Category],Table13635[[#Headers],[Income]])+SUMIFS(Table4440[Amount],Table4440[Date],S17,Table4440[Category],Table13635[[#Headers],[Income]]) -> 0 | U17: =SUMIFS(Table434[Amount],Table434[Date],S17,Table434[Category],"<>"&Table13635[[#Headers],[Income]])+SUMIFS(Table4440[Amount],Table4440[Date],S17,Table4440[Category],"<>"&Table13635[[#Headers],[Income]]) -> 0 | V17: =V16+T17-U17 -> 3298.88 | W17: =W16 -> 3298.88
C18: =CONCATENATE(Table132[[#Headers],[Housing]]," - Budget & Tracking") -> Housing - Budget & Tracking | J18: Description | K18: Category | L18: Sub-Category | M18: Date | N18: Amount | O18: Status | S18: =S17+1 -> 41585 | T18: =SUMIFS(Table442041[Amount],Table442041[Date],S18,Table442041[Category],Table13635[[#Headers],[Income]])+SUMIFS(Table4440[Amount],Table4440[Date],S18,Table4440[Category],Table13635[[#Headers],[Income]]) -> 0 | U18: =SUMIFS(Table434[Amount],Table434[Date],S18,Table434[Category],"<>"&Table13635[[#Headers],[Income]])+SUMIFS(Table4440[Amount],Table4440[Date],S18,Table4440[Category],"<>"&Table13635[[#Headers],[Income]]) -> 0 | V18: =V17+T18-U18 -> 3298.88 | W18: =W17 -> 3298.88
C19: Housing | D19: Budget | E19: Actual | F19: Variance | S19: =S18+1 -> 41586 | T19: =SUMIFS(Table442041[Amount],Table442041[Date],S19,Table442041[Category],Table13635[[#Headers],[Income]])+SUMIFS(Table4440[Amount],Table4440[Date],S19,Table4440[Category],Table13635[[#Headers],[Income]]) -> 0 | U19: =SUMIFS(Table434[Amount],Table434[Date],S19,Table434[Category],"<>"&Table13635[[#Headers],[Income]])+SUMIFS(Table4440[Amount],Table4440[Date],S19,Table4440[Category],"<>"&Table13635[[#Headers],[Income]]) -> 0 | V19: =V18+T19-U19 -> 3298.88 | W19: =W18 -> 3298.88
E20: =SUMIFS(Table434[Amount],Table434[Category],Table132[[#Headers],[Housing]],Table434[Sub-Category],Table132[[#This Row],[Housing]])+SUMIFS(Table4440[Amount],Table4440[Category],Table132[[#Headers],[Housing]],Table4440[Sub-Category],Table132[[#This Row],[Housing]]) -> 0 | F20: =Table132[[#This Row],[Budget]]-Table132[[#This Row],[Actual]] -> 0 | S20: =S19+1 -> 41587 | T20: =SUMIFS(Table442041[Amount],Table442041[Date],S20,Table442041[Category],Table13635[[#Headers],[Income]])+SUMIFS(Table4440[Amount],Table4440[Date],S20,Table4440[Category],Table13635[[#Headers],[Income]]) -> 0 | U20: =SUMIFS(Table434[Amount],Table434[Date],S20,Table434[Category],"<>"&Table13635[[#Headers],[Income]])+SUMIFS(Table4440[Amount],Table4440[Date],S20,Table4440[Category],"<>"&Table13635[[#Headers],[Income]]) -> 0 | V20: =V19+T20-U20 -> 3298.88 | W20: =W19 -> 3298.88
E21: =SUMIFS(Table434[Amount],Table434[Category],Table132[[#Headers],[Housing]],Table434[Sub-Category],Table132[[#This Row],[Housing]])+SUMIFS(Table4440[Amount],Table4440[Category],Table132[[#Headers],[Housing]],Table4440[Sub-Category],Table132[[#This Row],[Housing]]) -> 0 | F21: =Table132[[#This Row],[Budget]]-Table132[[#This Row],[Actual]] -> 0 | S21: =S20+1 -> 41588 | T21: =SUMIFS(Table442041[Amount],Table442041[Date],S21,Table442041[Category],Table13635[[#Headers],[Income]])+SUMIFS(Table4440[Amount],Table4440[Date],S21,Table4440[Category],Table13635[[#Headers],[Income]]) -> 0 | U21: =SUMIFS(Table434[Amount],Table434[Date],S21,Table434[Category],"<>"&Table13635[[#Headers],[Income]])+SUMIFS(Table4440[Amount],Table4440[Date],S21,Table4440[Category],"<>"&Table13635[[#Headers],[Income]]) -> 0 | V21: =V20+T21-U21 -> 3298.88 | W21: =W20 -> 3298.88
E22: =SUMIFS(Table434[Amount],Table434[Category],Table132[[#Headers],[Housing]],Table434[Sub-Category],Table132[[#This Row],[Housing]])+SUMIFS(Table4440[Amount],Table4440[Category],Table132[[#Headers],[Housing]],Table4440[Sub-Category],Table132[[#This Row],[Housing]]) -> 0 | F22: =Table132[[#This Row],[Budget]]-Table132[[#This Row],[Actual]] -> 0 | S22: =S21+1 -> 41589 | T22: =SUMIFS(Table442041[Amount],Table442041[Date],S22,Table442041[Category],Table13635[[#Headers],[Income]])+SUMIFS(Table4440[Amount],Table4440[Date],S22,Table4440[Category],Table13635[[#Headers],[Income]]) -> 0 | U22: =SUMIFS(Table434[Amount],Table434[Date],S22,Table434[Category],"<>"&Table13635[[#Headers],[Income]])+SUMIFS(Table4440[Amount],Table4440[Date],S22,Table4440[Category],"<>"&Table13635[[#Headers],[Income]]) -> 0 | V22: =V21+T22-U22 -> 3298.88 | W22: =W21 -> 3298.88
E23: =SUMIFS(Table434[Amount],Table434[Category],Table132[[#Headers],[Housing]],Table434[Sub-Category],Table132[[#This Row],[Housing]])+SUMIFS(Table4440[Amount],Table4440[Category],Table132[[#Headers],[Housing]],Table4440[Sub-Category],Table132[[#This Row],[Housing]]) -> 0 | F23: =Table132[[#This Row],[Budget]]-Table132[[#This Row],[Actual]] -> 0 | S23: =S22+1 -> 41590 | T23: =SUMIFS(Table442041[Amount],Table442041[Date],S23,Table442041[Category],Table13635[[#Headers],[Income]])+SUMIFS(Table4440[Amount],Table4440[Date],S23,Table4440[Category],Table13635[[#Headers],[Income]]) -> 0 | U23: =SUMIFS(Table434[Amount],Table434[Date],S23,Table434[Category],"<>"&Table13635[[#Headers],[Income]])+SUMIFS(Table4440[Amount],Table4440[Date],S23,Table4440[Category],"<>"&Table13635[[#Headers],[Income]]) -> 0 | V23: =V22+T23-U23 -> 3298.88 | W23: =W22 -> 3298.88
E24: =SUMIFS(Table434[Amount],Table434[Category],Table132[[#Headers],[Housing]],Table434[Sub-Category],Table132[[#This Row],[Housing]])+SUMIFS(Table4440[Amount],Table4440[Category],Table132[[#Headers],[Housing]],Table4440[Sub-Category],Table132[[#This Row],[Housing]]) -> 0 | F24: =Table132[[#This Row],[Budget]]-Table132[[#This Row],[Actual]] -> 0 | S24: =S23+1 -> 41591 | T24: =SUMIFS(Table442041[Amount],Table442041[Date],S24,Table442041[Category],Table13635[[#Headers],[Income]])+SUMIFS(Table4440[Amount],Table4440[Date],S24,Table4440[Category],Table13635[[#Headers],[Income]]) -> 0 | U24: =SUMIFS(Table434[Amount],Table434[Date],S24,Table434[Category],"<>"&Table13635[[#Headers],[Income]])+SUMIFS(Table4440[Amount],Table4440[Date],S24,Table4440[Category],"<>"&Table13635[[#Headers],[Income]]) -> 0 | V24: =V23+T24-U24 -> 3298.88 | W24: =W23 -> 3298.88
E25: =SUMIFS(Table434[Amount],Table434[Category],Table132[[#Headers],[Housing]],Table434[Sub-Category],Table132[[#This Row],[Housing]])+SUMIFS(Table4440[Amount],Table4440[Category],Table132[[#Headers],[Housing]],Table4440[Sub-Category],Table132[[#This Row],[Housing]]) -> 0 | F25: =Table132[[#This Row],[Budget]]-Table132[[#This Row],[Actual]] -> 0 | S25: =S24+1 -> 41592 | T25: =SUMIFS(Table442041[Amount],Table442041[Date],S25,Table442041[Category],Table13635[[#Headers],[Income]])+SUMIFS(Table4440[Amount],Table4440[Date],S25,Table4440[Category],Table13635[[#Headers],[Income]]) -> 0 | U25: =SUMIFS(Table434[Amount],Table434[Date],S25,Table434[Category],"<>"&Table13635[[#Headers],[Income]])+SUMIFS(Table4440[Amount],Table4440[Date],S25,Table4440[Category],"<>"&Table13635[[#Headers],[Income]]) -> 0 | V25: =V24+T25-U25 -> 3298.88 | W25: =W24 -> 3298.88
E26: =SUMIFS(Table434[Amount],Table434[Category],Table132[[#Headers],[Housing]],Table434[Sub-Category],Table132[[#This Row],[Housing]])+SUMIFS(Table4440[Amount],Table4440[Category],Table132[[#Headers],[Housing]],Table4440[Sub-Category],Table132[[#This Row],[Housing]]) -> 0 | F26: =Table132[[#This Row],[Budget]]-Table132[[#This Row],[Actual]] -> 0 | S26: =S25+1 -> 41593 | T26: =SUMIFS(Table442041[Amount],Table442041[Date],S26,Table442041[Category],Table13635[[#Headers],[Income]])+SUMIFS(Table4440[Amount],Table4440[Date],S26,Table4440[Category],Table13635[[#Headers],[Income]]) -> 0 | U26: =SUMIFS(Table434[Amount],Table434[Date],S26,Table434[Category],"<>"&Table13635[[#Headers],[Income]])+SUMIFS(Table4440[Amount],Table4440[Date],S26,Table4440[Category],"<>"&Table13635[[#Headers],[Income]]) -> 0 | V26: =V25+T26-U26 -> 3298.88 | W26: =W25 -> 3298.88
E27: =SUMIFS(Table434[Amount],Table434[Category],Table132[[#Headers],[Housing]],Table434[Sub-Category],Table132[[#This Row],[Housing]])+SUMIFS(Table4440[Amount],Table4440[Category],Table132[[#Headers],[Housing]],Table4440[Sub-Category],Table132[[#This Row],[Housing]]) -> 0 | F27: =Table132[[#This Row],[Budget]]-Table132[[#This Row],[Actual]] -> 0 | S27: =S26+1 -> 41594 | T27: =SUMIFS(Table442041[Amount],Table442041[Date],S27,Table442041[Category],Table13635[[#Headers],[Income]])+SUMIFS(Table4440[Amount],Table4440[Date],S27,Table4440[Category],Table13635[[#Headers],[Income]]) -> 0 | U27: =SUMIFS(Table434[Amount],Table434[Date],S27,Table434[Category],"<>"&Table13635[[#Headers],[Income]])+SUMIFS(Table4440[Amount],Table4440[Date],S27,Table4440[Category],"<>"&Table13635[[#Headers],[Income]]) -> 0 | V27: =V26+T27-U27 -> 3298.88 | W27: =W26 -> 3298.88
E28: =SUMIFS(Table434[Amount],Table434[Category],Table132[[#Headers],[Housing]],Table434[Sub-Category],Table132[[#This Row],[Housing]])+SUMIFS(Table4440[Amount],Table4440[Category],Table132[[#Headers],[Housing]],Table4440[Sub-Category],Table132[[#This Row],[Housing]]) -> 0 | F28: =Table132[[#This Row],[Budget]]-Table132[[#This Row],[Actual]] -> 0 | S28: =S27+1 -> 41595 | T28: =SUMIFS(Table442041[Amount],Table442041[Date],S28,Table442041[Category],Table13635[[#Headers],[Income]])+SUMIFS(Table4440[Amount],Table4440[Date],S28,Table4440[Category],Table13635[[#Headers],[Income]]) -> 0 | U28: =SUMIFS(Table434[Amount],Table434[Date],S28,Table434[Category],"<>"&Table13635[[#Headers],[Income]])+SUMIFS(Table4440[Amount],Table4440[Date],S28,Table4440[Category],"<>"&Table13635[[#Headers],[Income]]) -> 0 | V28: =V27+T28-U28 -> 3298.88 | W28: =W27 -> 3298.88
C29: Total | D29: =SUBTOTAL(109,Table132[Budget]) -> 0 | E29: =SUBTOTAL(109,Table132[Actual]) -> 0 | F29: =SUBTOTAL(109,Table132[Variance]) -> 0 | S29: =S28+1 -> 41596 | T29: =SUMIFS(Table442041[Amount],Table442041[Date],S29,Table442041[Category],Table13635[[#Headers],[Income]])+SUMIFS(Table4440[Amount],Table4440[Date],S29,Table4440[Category],Table13635[[#Headers],[Income]]) -> 0 | U29: =SUMIFS(Table434[Amount],Table434[Date],S29,Table434[Category],"<>"&Table13635[[#Headers],[Income]])+SUMIFS(Table4440[Amount],Table4440[Date],S29,Table4440[Category],"<>"&Table13635[[#Headers],[Income]]) -> 0 | V29: =V28+T29-U29 -> 3298.88 | W29: =W28 -> 3298.88
S30: =S29+1 -> 41597 | T30: =SUMIFS(Table442041[Amount],Table442041[Date],S30,Table442041[Category],Table13635[[#Headers],[Income]])+SUMIFS(Table4440[Amount],Table4440[Date],S30,Table4440[Category],Table13635[[#Headers],[Income]]) -> 0 | U30: =SUMIFS(Table434[Amount],Table434[Date],S30,Table434[Category],"<>"&Table13635[[#Headers],[Income]])+SUMIFS(Table4440[Amount],Table4440[Date],S30,Table4440[Category],"<>"&Table13635[[#Headers],[Income]]) -> 0 | V30: =V29+T30-U30 -> 3298.88 | W30: =W29 -> 3298.88
C31: =CONCATENATE(Table1333[[#Headers],[Transportation]]," - Budget & Tracking") -> Transportation - Budget & Tracking | S31: =S30+1 -> 41598 | T31: =SUMIFS(Table442041[Amount],Table442041[Date],S31,Table442041[Category],Table13635[[#Headers],[Income]])+SUMIFS(Table4440[Amount],Table4440[Date],S31,Table4440[Category],Table13635[[#Headers],[Income]]) -> 0 | U31: =SUMIFS(Table434[Amount],Table434[Date],S31,Table434[Category],"<>"&Table13635[[#Headers],[Income]])+SUMIFS(Table4440[Amount],Table4440[Date],S31,Table4440[Category],"<>"&Table13635[[#Headers],[Income]]) -> 0 | V31: =V30+T31-U31 -> 3298.88 | W31: =W30 -> 3298.88
C32: Transportation | D32: Budget | E32: Actual | F32: Variance | S32: =S31+1 -> 41599 | T32: =SUMIFS(Table442041[Amount],Table442041[Date],S32,Table442041[Category],Table13635[[#Headers],[Income]])+SUMIFS(Table4440[Amount],Table4440[Date],S32,Table4440[Category],Table13635[[#Headers],[Income]]) -> 0 | U32: =SUMIFS(Table434[Amount],Table434[Date],S32,Table434[Category],"<>"&Table13635[[#Headers],[Income]])+SUMIFS(Table4440[Amount],Table4440[Date],S32,Table4440[Category],"<>"&Table13635[[#Headers],[Income]]) -> 0 | V32: =V31+T32-U32 -> 3298.88 | W32: =W31 -> 3298.88
E33: =SUMIFS(Table434[Amount],Table434[Category],Table1333[[#Headers],[Transportation]],Table434[Sub-Category],Table1333[[#This Row],[Transportation]])+SUMIFS(Table4440[Amount],Table4440[Category],Table1333[[#Headers],[Transportation]],Table4440[Sub-Category],Table1333[[#This Row],[Transportation]]) -> 0 | F33: =Table1333[[#This Row],[Budget]]-Table1333[[#This Row],[Actual]] -> 0 | J33: All Other Transactions | S33: =S32+1 -> 41600 | T33: =SUMIFS(Table442041[Amount],Table442041[Date],S33,Table442041[Category],Table13635[[#Headers],[Income]])+SUMIFS(Table4440[Amount],Table4440[Date],S33,Table4440[Category],Table13635[[#Headers],[Income]]) -> 0 | U33: =SUMIFS(Table434[Amount],Table434[Date],S33,Table434[Category],"<>"&Table13635[[#Headers],[Income]])+SUMIFS(Table4440[Amount],Table4440[Date],S33,Table4440[Category],"<>"&Table13635[[#Headers],[Income]]) -> 0 | V33: =V32+T33-U33 -> 3298.88 | W33: =W32 -> 3298.88
E34: =SUMIFS(Table434[Amount],Table434[Category],Table1333[[#Headers],[Transportation]],Table434[Sub-Category],Table1333[[#This Row],[Transportation]])+SUMIFS(Table4440[Amount],Table4440[Category],Table1333[[#Headers],[Transportation]],Table4440[Sub-Category],Table1333[[#This Row],[Transportation]]) -> 0 | F34: =Table1333[[#This Row],[Budget]]-Table1333[[#This Row],[Actual]] -> 0 | J34: Description | K34: Category | L34: Sub-Category | M34: Date | N34: Amount | O34: Status | S34: =S33+1 -> 41601 | T34: =SUMIFS(Table442041[Amount],Table442041[Date],S34,Table442041[Category],Table13635[[#Headers],[Income]])+SUMIFS(Table4440[Amount],Table4440[Date],S34,Table4440[Category],Table13635[[#Headers],[Income]]) -> 0 | U34: =SUMIFS(Table434[Amount],Table434[Date],S34,Table434[Category],"<>"&Table13635[[#Headers],[Income]])+SUMIFS(Table4440[Amount],Table4440[Date],S34,Table4440[Category],"<>"&Table13635[[#Headers],[Income]]) -> 0 | V34: =V33+T34-U34 -> 3298.88 | W34: =W33 -> 3298.88
E35: =SUMIFS(Table434[Amount],Table434[Category],Table1333[[#Headers],[Transportation]],Table434[Sub-Category],Table1333[[#This Row],[Transportation]])+SUMIFS(Table4440[Amount],Table4440[Category],Table1333[[#Headers],[Transportation]],Table4440[Sub-Category],Table1333[[#This Row],[Transportation]]) -> 0 | F35: =Table1333[[#This Row],[Budget]]-Table1333[[#This Row],[Actual]] -> 0 | S35: =S34+1 -> 41602 | T35: =SUMIFS(Table442041[Amount],Table442041[Date],S35,Table442041[Category],Table13635[[#Headers],[Income]])+SUMIFS(Table4440[Amount],Table4440[Date],S35,Table4440[Category],Table13635[[#Headers],[Income]]) -> 0 | U35: =SUMIFS(Table434[Amount],Table434[Date],S35,Table434[Category],"<>"&Table13635[[#Headers],[Income]])+SUMIFS(Table4440[Amount],Table4440[Date],S35,Table4440[Category],"<>"&Table13635[[#Headers],[Income]]) -> 0 | V35: =V34+T35-U35 -> 3298.88 | W35: =W34 -> 3298.88
E36: =SUMIFS(Table434[Amount],Table434[Category],Table1333[[#Headers],[Transportation]],Table434[Sub-Category],Table1333[[#This Row],[Transportation]])+SUMIFS(Table4440[Amount],Table4440[Category],Table1333[[#Headers],[Transportation]],Table4440[Sub-Category],Table1333[[#This Row],[Transportation]]) -> 0 | F36: =Table1333[[#This Row],[Budget]]-Table1333[[#This Row],[Actual]] -> 0 | S36: =S35+1 -> 41603 | T36: =SUMIFS(Table442041[Amount],Table442041[Date],S36,Table442041[Category],Table13635[[#Headers],[Income]])+SUMIFS(Table4440[Amount],Table4440[Date],S36,Table4440[Category],Table13635[[#Headers],[Income]]) -> 0 | U36: =SUMIFS(Table434[Amount],Table434[Date],S36,Table434[Category],"<>"&Table13635[[#Headers],[Income]])+SUMIFS(Table4440[Amount],Table4440[Date],S36,Table4440[Category],"<>"&Table13635[[#Headers],[Income]]) -> 0 | V36: =V35+T36-U36 -> 3298.88 | W36: =W35 -> 3298.88
C37: Total | D37: =SUBTOTAL(109,Table1333[Budget]) -> 0 | E37: =SUBTOTAL(109,Table1333[Actual]) -> 0 | F37: =SUBTOTAL(109,Table1333[Variance]) -> 0 | S37: =S36+1 -> 41604 | T37: =SUMIFS(Table442041[Amount],Table442041[Date],S37,Table442041[Category],Table13635[[#Headers],[Income]])+SUMIFS(Table4440[Amount],Table4440[Date],S37,Table4440[Category],Table13635[[#Headers],[Income]]) -> 0 | U37: =SUMIFS(Table434[Amount],Table434[Date],S37,Table434[Category],"<>"&Table13635[[#Headers],[Income]])+SUMIFS(Table4440[Amount],Table4440[Date],S37,Table4440[Category],"<>"&Table13635[[#Headers],[Income]]) -> 0 | V37: =V36+T37-U37 -> 3298.88 | W37: =W36 -> 3298.88
S38: =S37+1 -> 41605 | T38: =SUMIFS(Table442041[Amount],Table442041[Date],S38,Table442041[Category],Table13635[[#Headers],[Income]])+SUMIFS(Table4440[Amount],Table4440[Date],S38,Table4440[Category],Table13635[[#Headers],[Income]]) -> 0 | U38: =SUMIFS(Table434[Amount],Table434[Date],S38,Table434[Category],"<>"&Table13635[[#Headers],[Income]])+SUMIFS(Table4440[Amount],Table4440[Date],S38,Table4440[Category],"<>"&Table13635[[#Headers],[Income]]) -> 0 | V38: =V37+T38-U38 -> 3298.88 | W38: =W37 -> 3298.88
C39: =CONCATENATE(Table1391039[[#Headers],[Bills]]," - Budget & Tracking") -> Bills - Budget & Tracking | S39: =S38+1 -> 41606 | T39: =SUMIFS(Table442041[Amount],Table442041[Date],S39,Table442041[Category],Table13635[[#Headers],[Income]])+SUMIFS(Table4440[Amount],Table4440[Date],S39,Table4440[Category],Table13635[[#Headers],[Income]]) -> 0 | U39: =SUMIFS(Table434[Amount],Table434[Date],S39,Table434[Category],"<>"&Table13635[[#Headers],[Income]])+SUMIFS(Table4440[Amount],Table4440[Date],S39,Table4440[Category],"<>"&Table13635[[#Headers],[Income]]) -> 0 | V39: =V38+T39-U39 -> 3298.88 | W39: =W38 -> 3298.88
C40: Bills | D40: Budget | E40: Actual | F40: Variance | S40: =S39+1 -> 41607 | T40: =SUMIFS(Table442041[Amount],Table442041[Date],S40,Table442041[Category],Table13635[[#Headers],[Income]])+SUMIFS(Table4440[Amount],Table4440[Date],S40,Table4440[Category],Table13635[[#Headers],[Income]]) -> 0 | U40: =SUMIFS(Table434[Amount],Table434[Date],S40,Table434[Category],"<>"&Table13635[[#Headers],[Income]])+SUMIFS(Table4440[Amount],Table4440[Date],S40,Table4440[Category],"<>"&Table13635[[#Headers],[Income]]) -> 0 | V40: =V39+T40-U40 -> 3298.88 | W40: =W39 -> 3298.88
E41: =SUMIFS(Table434[Amount],Table434[Category],Table1391039[[#Headers],[Bills]],Table434[Sub-Category],Table1391039[[#This Row],[Bills]])+SUMIFS(Table4440[Amount],Table4440[Category],Table1391039[[#Headers],[Bills]],Table4440[Sub-Category],Table1391039[[#This Row],[Bills]]) -> 0 | F41: =Table1391039[[#This Row],[Budget]]-Table1391039[[#This Row],[Actual]] -> 0 | S41: =S40+1 -> 41608 | T41: =SUMIFS(Table442041[Amount],Table442041[Date],S41,Table442041[Category],Table13635[[#Headers],[Income]])+SUMIFS(Table4440[Amount],Table4440[Date],S41,Table4440[Category],Table13635[[#Headers],[Income]]) -> 0 | U41: =SUMIFS(Table434[Amount],Table434[Date],S41,Table434[Category],"<>"&Table13635[[#Headers],[Income]])+SUMIFS(Table4440[Amount],Table4440[Date],S41,Table4440[Category],"<>"&Table13635[[#Headers],[Income]]) -> 0 | V41: =V40+T41-U41 -> 3298.88 | W41: =W40 -> 3298.88
E42: =SUMIFS(Table434[Amount],Table434[Category],Table1391039[[#Headers],[Bills]],Table434[Sub-Category],Table1391039[[#This Row],[Bills]])+SUMIFS(Table4440[Amount],Table4440[Category],Table1391039[[#Headers],[Bills]],Table4440[Sub-Category],Table1391039[[#This Row],[Bills]]) -> 0 | F42: =Table1391039[[#This Row],[Budget]]-Table1391039[[#This Row],[Actual]] -> 0 | S42: =S41+1 -> 41609 | T42: =SUMIFS(Table442041[Amount],Table442041[Date],S42,Table442041[Category],Table13635[[#Headers],[Income]])+SUMIFS(Table4440[Amount],Table4440[Date],S42,Table4440[Category],Table13635[[#Headers],[Income]]) -> 0 | U42: =SUMIFS(Table434[Amount],Table434[Date],S42,Table434[Category],"<>"&Table13635[[#Headers],[Income]])+SUMIFS(Table4440[Amount],Table4440[Date],S42,Table4440[Category],"<>"&Table13635[[#Headers],[Income]]) -> 0 | V42: =V41+T42-U42 -> 3298.88 | W42: =W41 -> 3298.88
E43: =SUMIFS(Table434[Amount],Table434[Category],Table1391039[[#Headers],[Bills]],Table434[Sub-Category],Table1391039[[#This Row],[Bills]])+SUMIFS(Table4440[Amount],Table4440[Category],Table1391039[[#Headers],[Bills]],Table4440[Sub-Category],Table1391039[[#This Row],[Bills]]) -> 0 | F43: =Table1391039[[#This Row],[Budget]]-Table1391039[[#This Row],[Actual]] -> 0
E44: =SUMIFS(Table434[Amount],Table434[Category],Table1391039[[#Headers],[Bills]],Table434[Sub-Category],Table1391039[[#This Row],[Bills]])+SUMIFS(Table4440[Amount],Table4440[Category],Table1391039[[#Headers],[Bills]],Table4440[Sub-Category],Table1391039[[#This Row],[Bills]]) -> 0 | F44: =Table1391039[[#This Row],[Budget]]-Table1391039[[#This Row],[Actual]] -> 0
E45: =SUMIFS(Table434[Amount],Table434[Category],Table1391039[[#Headers],[Bills]],Table434[Sub-Category],Table1391039[[#This Row],[Bills]])+SUMIFS(Table4440[Amount],Table4440[Category],Table1391039[[#Headers],[Bills]],Table4440[Sub-Category],Table1391039[[#This Row],[Bills]]) -> 0 | F45: =Table1391039[[#This Row],[Budget]]-Table1391039[[#This Row],[Actual]] -> 0
C46: Total | D46: =SUBTOTAL(109,Table1391039[Budget]) -> 0 | E46: =SUBTOTAL(109,Table1391039[Actual]) -> 0 | F46: =SUBTOTAL(109,Table1391039[Variance]) -> 0
C48: =CONCATENATE(Table13736[[#Headers],[Living]]," - Budget & Tracking") -> Living - Budget & Tracking
C49: Living | D49: Budget | E49: Actual | F49: Variance
E50: =SUMIFS(Table434[Amount],Table434[Category],Table13736[[#Headers],[Living]],Table434[Sub-Category],Table13736[[#This Row],[Living]])+SUMIFS(Table4440[Amount],Table4440[Category],Table13736[[#Headers],[Living]],Table4440[Sub-Category],Table13736[[#This Row],[Living]]) -> 0 | F50: =Table13736[[#This Row],[Budget]]-Table13736[[#This Row],[Actual]] -> 0
E51: =SUMIFS(Table434[Amount],Table434[Category],Table13736[[#Headers],[Living]],Table434[Sub-Category],Table13736[[#This Row],[Living]])+SUMIFS(Table4440[Amount],Table4440[Category],Table13736[[#Headers],[Living]],Table4440[Sub-Category],Table13736[[#This Row],[Living]]) -> 0 | F51: =Table13736[[#This Row],[Budget]]-Table13736[[#This Row],[Actual]] -> 0
E52: =SUMIFS(Table434[Amount],Table434[Category],Table13736[[#Headers],[Living]],Table434[Sub-Category],Table13736[[#This Row],[Living]])+SUMIFS(Table4440[Amount],Table4440[Category],Table13736[[#Headers],[Living]],Table4440[Sub-Category],Table13736[[#This Row],[Living]]) -> 0 | F52: =Table13736[[#This Row],[Budget]]-Table13736[[#This Row],[Actual]] -> 0
E53: =SUMIFS(Table434[Amount],Table434[Category],Table13736[[#Headers],[Living]],Table434[Sub-Category],Table13736[[#This Row],[Living]])+SUMIFS(Table4440[Amount],Table4440[Category],Table13736[[#Headers],[Living]],Table4440[Sub-Category],Table13736[[#This Row],[Living]]) -> 0 | F53: =Table13736[[#This Row],[Budget]]-Table13736[[#This Row],[Actual]] -> 0
C54: Total | D54: =SUBTOTAL(109,Table13736[Budget]) -> 0 | E54: =SUBTOTAL(109,Table13736[Actual]) -> 0 | F54: =SUBTOTAL(109,Table13736[Variance]) -> 0
C56: =CONCATENATE(Table13837[[#Headers],[Entertainment]]," - Budget & Tracking") -> Entertainment - Budget & Tracking
C57: Entertainment | D57: Budget | E57: Actual | F57: Variance
E58: =SUMIFS(Table434[Amount],Table434[Category],Table13837[[#Headers],[Entertainment]],Table434[Sub-Category],Table13837[[#This Row],[Entertainment]])+SUMIFS(Table4440[Amount],Table4440[Category],Table13837[[#Headers],[Entertainment]],Table4440[Sub-Category],Table13837[[#This Row],[Entertainment]]) -> 0 | F58: =Table13837[[#This Row],[Budget]]-Table13837[[#This Row],[Actual]] -> 0
E59: =SUMIFS(Table434[Amount],Table434[Category],Table13837[[#Headers],[Entertainment]],Table434[Sub-Category],Table13837[[#This Row],[Entertainment]])+SUMIFS(Table4440[Amount],Table4440[Category],Table13837[[#Headers],[Entertainment]],Table4440[Sub-Category],Table13837[[#This Row],[Entertainment]]) -> 0 | F59: =Table13837[[#This Row],[Budget]]-Table13837[[#This Row],[Actual]] -> 0
C60: Total | D60: =SUBTOTAL(109,Table13837[Budget]) -> 0 | E60: =SUBTOTAL(109,Table13837[Actual]) -> 0 | F60: =SUBTOTAL(109,Table13837[Variance]) -> 0
C62: =CONCATENATE(Table13938[[#Headers],[Misc.]]," - Budget & Tracking") -> Misc. - Budget & Tracking
C63: Misc. | D63: Budget | E63: Actual | F63: Variance
E64: =SUMIFS(Table434[Amount],Table434[Category],Table13938[[#Headers],[Misc.]],Table434[Sub-Category],Table13938[[#This Row],[Misc.]])+SUMIFS(Table4440[Amount],Table4440[Category],Table13938[[#Headers],[Misc.]],Table4440[Sub-Category],Table13938[[#This Row],[Misc.]]) -> 0 | F64: =Table13938[[#This Row],[Budget]]-Table13938[[#This Row],[Actual]] -> 0
E65: =SUMIFS(Table434[Amount],Table434[Category],Table13938[[#Headers],[Misc.]],Table434[Sub-Category],Table13938[[#This Row],[Misc.]])+SUMIFS(Table4440[Amount],Table4440[Category],Table13938[[#Headers],[Misc.]],Table4440[Sub-Category],Table13938[[#This Row],[Misc.]]) -> 0 | F65: =Table13938[[#This Row],[Budget]]-Table13938[[#This Row],[Actual]] -> 0
C66: Total | D66: =SUBTOTAL(109,Table13938[Budget]) -> 0 | E66: =SUBTOTAL(109,Table13938[Actual]) -> 0 | F66: =SUBTOTAL(109,Table13938[Variance]) -> 0

Sheet Mo.4
C1: =DATE(YEAR(Mo.3!C1),MONTH(Mo.3!C1)+1,DAY(Mo.3!C1)) -> 41609 | R1: Category | S1: Budget | T1: Actual | U1: Status | V1: Min Bal
D2: Budget | E2: Actual | F2: Variance | R2: =Table13645[[#Headers],[Income]] -> Income | S2: =SUM(Table13645[Budget]) -> 0 | T2: =SUM(Table13645[Actual]) -> 0 | U2: Pending | V2: =AVERAGE(V12:V42) -> 1156.74
C3: BOM Balance | D3: =E3 -> 1156.74 | E3: 1156.74 | F3: =E3-D3 -> 0 | R3: =Table142[[#Headers],[Housing]] -> Housing | S3: =SUM(Table142[Budget]) -> 0 | T3: =SUM(Table142[Actual]) -> 0 | U3: Scheduled
C4: Total Inflow | D4: =Table13645[[#Totals],[Budget]] -> 0 | E4: =Table13645[[#Totals],[Actual]] -> 0 | F4: =E4-D4 -> 0 | R4: =Table1343[[#Headers],[Transportation]] -> Transportation | S4: =SUM(Table1343[Budget]) -> 0 | T4: =SUM(Table1343[Actual]) -> 0 | U4: Cleared
C5: Total Outflow | D5: =Table142[[#Totals],[Budget]]+Table1343[[#Totals],[Budget]]+Table1391049[[#Totals],[Budget]]+Table13746[[#Totals],[Budget]]+Table13847[[#Totals],[Budget]]+Table13948[[#Totals],[Budget]] -> 0 | E5: =Table142[[#Totals],[Actual]]+Table1343[[#Totals],[Actual]]+Table1391049[[#Totals],[Actual]]+Table13746[[#Totals],[Actual]]+Table13847[[#Totals],[Actual]]+Table13948[[#Totals],[Actual]] -> 0 | F5: =E5-D5 -> 0 | R5: =Table1391049[[#Headers],[Bills]] -> Bills | S5: =SUM(Table1391049[Budget]) -> 0 | T5: =SUM(Table1391049[Actual]) -> 0
C6: Difference | D6: =D3+D4-D5 -> 1156.74 | E6: =E3+E4-E5 -> 1156.74 | F6: =F3+F4-F5 -> 0 | R6: =Table13746[[#Headers],[Living]] -> Living | S6: =SUM(Table13746[Budget]) -> 0 | T6: =SUM(Table13746[Actual]) -> 0
R7: =Table13847[[#Headers],[Entertainment]] -> Entertainment | S7: =SUM(Table13847[Budget]) -> 0 | T7: =SUM(Table13847[Actual]) -> 0
R8: =Table13948[[#Headers],[Misc.]] -> Misc. | S8: =SUM(Table13948[Budget]) -> 0 | T8: =SUM(Table13948[Actual]) -> 0
C10: =CONCATENATE(Table13645[[#Headers],[Income]]," - Budget & Tracking") -> Income - Budget & Tracking | J10: Budgeted Credits | S10: Account Balance / Tracking & Forecast
C11: Income | D11: Budget | E11: Actual | F11: Variance | J11: Description | K11: Category | L11: Sub-Category | M11: Date | N11: Amount | O11: Status | S11: Date | T11: Credit | U11: Debit | V11: Balance
E12: =SUMIFS(Table442051[Amount],Table442051[Category],Table13645[[#Headers],[Income]],Table442051[Sub-Category],Table13645[[#This Row],[Income]])+SUMIFS(Table4450[Amount],Table4450[Category],Table13645[[#Headers],[Income]],Table4450[Sub-Category],Table13645[[#This Row],[Income]]) -> 0 | F12: =Table13645[[#This Row],[Actual]]-Table13645[[#This Row],[Budget]] -> 0 | S12: =C1 -> 41609 | T12: =SUMIFS(Table442051[Amount],Table442051[Date],S12,Table442051[Category],Table13645[[#Headers],[Income]])+SUMIFS(Table4450[Amount],Table4450[Date],S12,Table4450[Category],Table13645[[#Headers],[Income]]) -> 0 | U12: =SUMIFS(Table444[Amount],Table444[Date],S12,Table444[Category],"<>"&Table13645[[#Headers],[Income]])+SUMIFS(Table4450[Amount],Table4450[Date],S12,Table4450[Category],"<>"&Table13645[[#Headers],[Income]]) -> 0 | V12: =E3+T12-U12 -> 1156.74 | W12: =V2 -> 1156.74
E13: =SUMIFS(Table442051[Amount],Table442051[Category],Table13645[[#Headers],[Income]],Table442051[Sub-Category],Table13645[[#This Row],[Income]])+SUMIFS(Table4450[Amount],Table4450[Category],Table13645[[#Headers],[Income]],Table4450[Sub-Category],Table13645[[#This Row],[Income]]) -> 0 | F13: =Table13645[[#This Row],[Actual]]-Table13645[[#This Row],[Budget]] -> 0 | S13: =S12+1 -> 41610 | T13: =SUMIFS(Table442051[Amount],Table442051[Date],S13,Table442051[Category],Table13645[[#Headers],[Income]])+SUMIFS(Table4450[Amount],Table4450[Date],S13,Table4450[Category],Table13645[[#Headers],[Income]]) -> 0 | U13: =SUMIFS(Table444[Amount],Table444[Date],S13,Table444[Category],"<>"&Table13645[[#Headers],[Income]])+SUMIFS(Table4450[Amount],Table4450[Date],S13,Table4450[Category],"<>"&Table13645[[#Headers],[Income]]) -> 0 | V13: =V12+T13-U13 -> 1156.74 | W13: =W12 -> 1156.74
E14: =SUMIFS(Table442051[Amount],Table442051[Category],Table13645[[#Headers],[Income]],Table442051[Sub-Category],Table13645[[#This Row],[Income]])+SUMIFS(Table4450[Amount],Table4450[Category],Table13645[[#Headers],[Income]],Table4450[Sub-Category],Table13645[[#This Row],[Income]]) -> 0 | F14: =Table13645[[#This Row],[Actual]]-Table13645[[#This Row],[Budget]] -> 0 | S14: =S13+1 -> 41611 | T14: =SUMIFS(Table442051[Amount],Table442051[Date],S14,Table442051[Category],Table13645[[#Headers],[Income]])+SUMIFS(Table4450[Amount],Table4450[Date],S14,Table4450[Category],Table13645[[#Headers],[Income]]) -> 0 | U14: =SUMIFS(Table444[Amount],Table444[Date],S14,Table444[Category],"<>"&Table13645[[#Headers],[Income]])+SUMIFS(Table4450[Amount],Table4450[Date],S14,Table4450[Category],"<>"&Table13645[[#Headers],[Income]]) -> 0 | V14: =V13+T14-U14 -> 1156.74 | W14: =W13 -> 1156.74
E15: =SUMIFS(Table442051[Amount],Table442051[Category],Table13645[[#Headers],[Income]],Table442051[Sub-Category],Table13645[[#This Row],[Income]])+SUMIFS(Table4450[Amount],Table4450[Category],Table13645[[#Headers],[Income]],Table4450[Sub-Category],Table13645[[#This Row],[Income]]) -> 0 | F15: =Table13645[[#This Row],[Actual]]-Table13645[[#This Row],[Budget]] -> 0 | S15: =S14+1 -> 41612 | T15: =SUMIFS(Table442051[Amount],Table442051[Date],S15,Table442051[Category],Table13645[[#Headers],[Income]])+SUMIFS(Table4450[Amount],Table4450[Date],S15,Table4450[Category],Table13645[[#Headers],[Income]]) -> 0 | U15: =SUMIFS(Table444[Amount],Table444[Date],S15,Table444[Category],"<>"&Table13645[[#Headers],[Income]])+SUMIFS(Table4450[Amount],Table4450[Date],S15,Table4450[Category],"<>"&Table13645[[#Headers],[Income]]) -> 0 | V15: =V14+T15-U15 -> 1156.74 | W15: =W14 -> 1156.74
C16: Total | D16: =SUBTOTAL(109,Table13645[Budget]) -> 0 | E16: =SUBTOTAL(109,Table13645[Actual]) -> 0 | F16: =SUBTOTAL(109,Table13645[Variance]) -> 0 | S16: =S15+1 -> 41613 | T16: =SUMIFS(Table442051[Amount],Table442051[Date],S16,Table442051[Category],Table13645[[#Headers],[Income]])+SUMIFS(Table4450[Amount],Table4450[Date],S16,Table4450[Category],Table13645[[#Headers],[Income]]) -> 0 | U16: =SUMIFS(Table444[Amount],Table444[Date],S16,Table444[Category],"<>"&Table13645[[#Headers],[Income]])+SUMIFS(Table4450[Amount],Table4450[Date],S16,Table4450[Category],"<>"&Table13645[[#Headers],[Income]]) -> 0 | V16: =V15+T16-U16 -> 1156.74 | W16: =W15 -> 1156.74
J17: Budgeted Debits | S17: =S16+1 -> 41614 | T17: =SUMIFS(Table442051[Amount],Table442051[Date],S17,Table442051[Category],Table13645[[#Headers],[Income]])+SUMIFS(Table4450[Amount],Table4450[Date],S17,Table4450[Category],Table13645[[#Headers],[Income]]) -> 0 | U17: =SUMIFS(Table444[Amount],Table444[Date],S17,Table444[Category],"<>"&Table13645[[#Headers],[Income]])+SUMIFS(Table4450[Amount],Table4450[Date],S17,Table4450[Category],"<>"&Table13645[[#Headers],[Income]]) -> 0 | V17: =V16+T17-U17 -> 1156.74 | W17: =W16 -> 1156.74
C18: =CONCATENATE(Table142[[#Headers],[Housing]]," - Budget & Tracking") -> Housing - Budget & Tracking | J18: Description | K18: Category | L18: Sub-Category | M18: Date | N18: Amount | O18: Status | S18: =S17+1 -> 41615 | T18: =SUMIFS(Table442051[Amount],Table442051[Date],S18,Table442051[Category],Table13645[[#Headers],[Income]])+SUMIFS(Table4450[Amount],Table4450[Date],S18,Table4450[Category],Table13645[[#Headers],[Income]]) -> 0 | U18: =SUMIFS(Table444[Amount],Table444[Date],S18,Table444[Category],"<>"&Table13645[[#Headers],[Income]])+SUMIFS(Table4450[Amount],Table4450[Date],S18,Table4450[Category],"<>"&Table13645[[#Headers],[Income]]) -> 0 | V18: =V17+T18-U18 -> 1156.74 | W18: =W17 -> 1156.74
C19: Housing | D19: Budget | E19: Actual | F19: Variance | S19: =S18+1 -> 41616 | T19: =SUMIFS(Table442051[Amount],Table442051[Date],S19,Table442051[Category],Table13645[[#Headers],[Income]])+SUMIFS(Table4450[Amount],Table4450[Date],S19,Table4450[Category],Table13645[[#Headers],[Income]]) -> 0 | U19: =SUMIFS(Table444[Amount],Table444[Date],S19,Table444[Category],"<>"&Table13645[[#Headers],[Income]])+SUMIFS(Table4450[Amount],Table4450[Date],S19,Table4450[Category],"<>"&Table13645[[#Headers],[Income]]) -> 0 | V19: =V18+T19-U19 -> 1156.74 | W19: =W18 -> 1156.74
E20: =SUMIFS(Table444[Amount],Table444[Category],Table142[[#Headers],[Housing]],Table444[Sub-Category],Table142[[#This Row],[Housing]])+SUMIFS(Table4450[Amount],Table4450[Category],Table142[[#Headers],[Housing]],Table4450[Sub-Category],Table142[[#This Row],[Housing]]) -> 0 | F20: =Table142[[#This Row],[Budget]]-Table142[[#This Row],[Actual]] -> 0 | S20: =S19+1 -> 41617 | T20: =SUMIFS(Table442051[Amount],Table442051[Date],S20,Table442051[Category],Table13645[[#Headers],[Income]])+SUMIFS(Table4450[Amount],Table4450[Date],S20,Table4450[Category],Table13645[[#Headers],[Income]]) -> 0 | U20: =SUMIFS(Table444[Amount],Table444[Date],S20,Table444[Category],"<>"&Table13645[[#Headers],[Income]])+SUMIFS(Table4450[Amount],Table4450[Date],S20,Table4450[Category],"<>"&Table13645[[#Headers],[Income]]) -> 0 | V20: =V19+T20-U20 -> 1156.74 | W20: =W19 -> 1156.74
E21: =SUMIFS(Table444[Amount],Table444[Category],Table142[[#Headers],[Housing]],Table444[Sub-Category],Table142[[#This Row],[Housing]])+SUMIFS(Table4450[Amount],Table4450[Category],Table142[[#Headers],[Housing]],Table4450[Sub-Category],Table142[[#This Row],[Housing]]) -> 0 | F21: =Table142[[#This Row],[Budget]]-Table142[[#This Row],[Actual]] -> 0 | S21: =S20+1 -> 41618 | T21: =SUMIFS(Table442051[Amount],Table442051[Date],S21,Table442051[Category],Table13645[[#Headers],[Income]])+SUMIFS(Table4450[Amount],Table4450[Date],S21,Table4450[Category],Table13645[[#Headers],[Income]]) -> 0 | U21: =SUMIFS(Table444[Amount],Table444[Date],S21,Table444[Category],"<>"&Table13645[[#Headers],[Income]])+SUMIFS(Table4450[Amount],Table4450[Date],S21,Table4450[Category],"<>"&Table13645[[#Headers],[Income]]) -> 0 | V21: =V20+T21-U21 -> 1156.74 | W21: =W20 -> 1156.74
E22: =SUMIFS(Table444[Amount],Table444[Category],Table142[[#Headers],[Housing]],Table444[Sub-Category],Table142[[#This Row],[Housing]])+SUMIFS(Table4450[Amount],Table4450[Category],Table142[[#Headers],[Housing]],Table4450[Sub-Category],Table142[[#This Row],[Housing]]) -> 0 | F22: =Table142[[#This Row],[Budget]]-Table142[[#This Row],[Actual]] -> 0 | S22: =S21+1 -> 41619 | T22: =SUMIFS(Table442051[Amount],Table442051[Date],S22,Table442051[Category],Table13645[[#Headers],[Income]])+SUMIFS(Table4450[Amount],Table4450[Date],S22,Table4450[Category],Table13645[[#Headers],[Income]]) -> 0 | U22: =SUMIFS(Table444[Amount],Table444[Date],S22,Table444[Category],"<>"&Table13645[[#Headers],[Income]])+SUMIFS(Table4450[Amount],Table4450[Date],S22,Table4450[Category],"<>"&Table13645[[#Headers],[Income]]) -> 0 | V22: =V21+T22-U22 -> 1156.74 | W22: =W21 -> 1156.74
E23: =SUMIFS(Table444[Amount],Table444[Category],Table142[[#Headers],[Housing]],Table444[Sub-Category],Table142[[#This Row],[Housing]])+SUMIFS(Table4450[Amount],Table4450[Category],Table142[[#Headers],[Housing]],Table4450[Sub-Category],Table142[[#This Row],[Housing]]) -> 0 | F23: =Table142[[#This Row],[Budget]]-Table142[[#This Row],[Actual]] -> 0 | S23: =S22+1 -> 41620 | T23: =SUMIFS(Table442051[Amount],Table442051[Date],S23,Table442051[Category],Table13645[[#Headers],[Income]])+SUMIFS(Table4450[Amount],Table4450[Date],S23,Table4450[Category],Table13645[[#Headers],[Income]]) -> 0 | U23: =SUMIFS(Table444[Amount],Table444[Date],S23,Table444[Category],"<>"&Table13645[[#Headers],[Income]])+SUMIFS(Table4450[Amount],Table4450[Date],S23,Table4450[Category],"<>"&Table13645[[#Headers],[Income]]) -> 0 | V23: =V22+T23-U23 -> 1156.74 | W23: =W22 -> 1156.74
E24: =SUMIFS(Table444[Amount],Table444[Category],Table142[[#Headers],[Housing]],Table444[Sub-Category],Table142[[#This Row],[Housing]])+SUMIFS(Table4450[Amount],Table4450[Category],Table142[[#Headers],[Housing]],Table4450[Sub-Category],Table142[[#This Row],[Housing]]) -> 0 | F24: =Table142[[#This Row],[Budget]]-Table142[[#This Row],[Actual]] -> 0 | S24: =S23+1 -> 41621 | T24: =SUMIFS(Table442051[Amount],Table442051[Date],S24,Table442051[Category],Table13645[[#Headers],[Income]])+SUMIFS(Table4450[Amount],Table4450[Date],S24,Table4450[Category],Table13645[[#Headers],[Income]]) -> 0 | U24: =SUMIFS(Table444[Amount],Table444[Date],S24,Table444[Category],"<>"&Table13645[[#Headers],[Income]])+SUMIFS(Table4450[Amount],Table4450[Date],S24,Table4450[Category],"<>"&Table13645[[#Headers],[Income]]) -> 0 | V24: =V23+T24-U24 -> 1156.74 | W24: =W23 -> 1156.74
E25: =SUMIFS(Table444[Amount],Table444[Category],Table142[[#Headers],[Housing]],Table444[Sub-Category],Table142[[#This Row],[Housing]])+SUMIFS(Table4450[Amount],Table4450[Category],Table142[[#Headers],[Housing]],Table4450[Sub-Category],Table142[[#This Row],[Housing]]) -> 0 | F25: =Table142[[#This Row],[Budget]]-Table142[[#This Row],[Actual]] -> 0 | S25: =S24+1 -> 41622 | T25: =SUMIFS(Table442051[Amount],Table442051[Date],S25,Table442051[Category],Table13645[[#Headers],[Income]])+SUMIFS(Table4450[Amount],Table4450[Date],S25,Table4450[Category],Table13645[[#Headers],[Income]]) -> 0 | U25: =SUMIFS(Table444[Amount],Table444[Date],S25,Table444[Category],"<>"&Table13645[[#Headers],[Income]])+SUMIFS(Table4450[Amount],Table4450[Date],S25,Table4450[Category],"<>"&Table13645[[#Headers],[Income]]) -> 0 | V25: =V24+T25-U25 -> 1156.74 | W25: =W24 -> 1156.74
E26: =SUMIFS(Table444[Amount],Table444[Category],Table142[[#Headers],[Housing]],Table444[Sub-Category],Table142[[#This Row],[Housing]])+SUMIFS(Table4450[Amount],Table4450[Category],Table142[[#Headers],[Housing]],Table4450[Sub-Category],Table142[[#This Row],[Housing]]) -> 0 | F26: =Table142[[#This Row],[Budget]]-Table142[[#This Row],[Actual]] -> 0 | S26: =S25+1 -> 41623 | T26: =SUMIFS(Table442051[Amount],Table442051[Date],S26,Table442051[Category],Table13645[[#Headers],[Income]])+SUMIFS(Table4450[Amount],Table4450[Date],S26,Table4450[Category],Table13645[[#Headers],[Income]]) -> 0 | U26: =SUMIFS(Table444[Amount],Table444[Date],S26,Table444[Category],"<>"&Table13645[[#Headers],[Income]])+SUMIFS(Table4450[Amount],Table4450[Date],S26,Table4450[Category],"<>"&Table13645[[#Headers],[Income]]) -> 0 | V26: =V25+T26-U26 -> 1156.74 | W26: =W25 -> 1156.74
E27: =SUMIFS(Table444[Amount],Table444[Category],Table142[[#Headers],[Housing]],Table444[Sub-Category],Table142[[#This Row],[Housing]])+SUMIFS(Table4450[Amount],Table4450[Category],Table142[[#Headers],[Housing]],Table4450[Sub-Category],Table142[[#This Row],[Housing]]) -> 0 | F27: =Table142[[#This Row],[Budget]]-Table142[[#This Row],[Actual]] -> 0 | S27: =S26+1 -> 41624 | T27: =SUMIFS(Table442051[Amount],Table442051[Date],S27,Table442051[Category],Table13645[[#Headers],[Income]])+SUMIFS(Table4450[Amount],Table4450[Date],S27,Table4450[Category],Table13645[[#Headers],[Income]]) -> 0 | U27: =SUMIFS(Table444[Amount],Table444[Date],S27,Table444[Category],"<>"&Table13645[[#Headers],[Income]])+SUMIFS(Table4450[Amount],Table4450[Date],S27,Table4450[Category],"<>"&Table13645[[#Headers],[Income]]) -> 0 | V27: =V26+T27-U27 -> 1156.74 | W27: =W26 -> 1156.74
E28: =SUMIFS(Table444[Amount],Table444[Category],Table142[[#Headers],[Housing]],Table444[Sub-Category],Table142[[#This Row],[Housing]])+SUMIFS(Table4450[Amount],Table4450[Category],Table142[[#Headers],[Housing]],Table4450[Sub-Category],Table142[[#This Row],[Housing]]) -> 0 | F28: =Table142[[#This Row],[Budget]]-Table142[[#This Row],[Actual]] -> 0 | S28: =S27+1 -> 41625 | T28: =SUMIFS(Table442051[Amount],Table442051[Date],S28,Table442051[Category],Table13645[[#Headers],[Income]])+SUMIFS(Table4450[Amount],Table4450[Date],S28,Table4450[Category],Table13645[[#Headers],[Income]]) -> 0 | U28: =SUMIFS(Table444[Amount],Table444[Date],S28,Table444[Category],"<>"&Table13645[[#Headers],[Income]])+SUMIFS(Table4450[Amount],Table4450[Date],S28,Table4450[Category],"<>"&Table13645[[#Headers],[Income]]) -> 0 | V28: =V27+T28-U28 -> 1156.74 | W28: =W27 -> 1156.74
C29: Total | D29: =SUBTOTAL(109,Table142[Budget]) -> 0 | E29: =SUBTOTAL(109,Table142[Actual]) -> 0 | F29: =SUBTOTAL(109,Table142[Variance]) -> 0 | S29: =S28+1 -> 41626 | T29: =SUMIFS(Table442051[Amount],Table442051[Date],S29,Table442051[Category],Table13645[[#Headers],[Income]])+SUMIFS(Table4450[Amount],Table4450[Date],S29,Table4450[Category],Table13645[[#Headers],[Income]]) -> 0 | U29: =SUMIFS(Table444[Amount],Table444[Date],S29,Table444[Category],"<>"&Table13645[[#Headers],[Income]])+SUMIFS(Table4450[Amount],Table4450[Date],S29,Table4450[Category],"<>"&Table13645[[#Headers],[Income]]) -> 0 | V29: =V28+T29-U29 -> 1156.74 | W29: =W28 -> 1156.74
S30: =S29+1 -> 41627 | T30: =SUMIFS(Table442051[Amount],Table442051[Date],S30,Table442051[Category],Table13645[[#Headers],[Income]])+SUMIFS(Table4450[Amount],Table4450[Date],S30,Table4450[Category],Table13645[[#Headers],[Income]]) -> 0 | U30: =SUMIFS(Table444[Amount],Table444[Date],S30,Table444[Category],"<>"&Table13645[[#Headers],[Income]])+SUMIFS(Table4450[Amount],Table4450[Date],S30,Table4450[Category],"<>"&Table13645[[#Headers],[Income]]) -> 0 | V30: =V29+T30-U30 -> 1156.74 | W30: =W29 -> 1156.74
C31: =CONCATENATE(Table1343[[#Headers],[Transportation]]," - Budget & Tracking") -> Transportation - Budget & Tracking | S31: =S30+1 -> 41628 | T31: =SUMIFS(Table442051[Amount],Table442051[Date],S31,Table442051[Category],Table13645[[#Headers],[Income]])+SUMIFS(Table4450[Amount],Table4450[Date],S31,Table4450[Category],Table13645[[#Headers],[Income]]) -> 0 | U31: =SUMIFS(Table444[Amount],Table444[Date],S31,Table444[Category],"<>"&Table13645[[#Headers],[Income]])+SUMIFS(Table4450[Amount],Table4450[Date],S31,Table4450[Category],"<>"&Table13645[[#Headers],[Income]]) -> 0 | V31: =V30+T31-U31 -> 1156.74 | W31: =W30 -> 1156.74
C32: Transportation | D32: Budget | E32: Actual | F32: Variance | S32: =S31+1 -> 41629 | T32: =SUMIFS(Table442051[Amount],Table442051[Date],S32,Table442051[Category],Table13645[[#Headers],[Income]])+SUMIFS(Table4450[Amount],Table4450[Date],S32,Table4450[Category],Table13645[[#Headers],[Income]]) -> 0 | U32: =SUMIFS(Table444[Amount],Table444[Date],S32,Table444[Category],"<>"&Table13645[[#Headers],[Income]])+SUMIFS(Table4450[Amount],Table4450[Date],S32,Table4450[Category],"<>"&Table13645[[#Headers],[Income]]) -> 0 | V32: =V31+T32-U32 -> 1156.74 | W32: =W31 -> 1156.74
E33: =SUMIFS(Table444[Amount],Table444[Category],Table1343[[#Headers],[Transportation]],Table444[Sub-Category],Table1343[[#This Row],[Transportation]])+SUMIFS(Table4450[Amount],Table4450[Category],Table1343[[#Headers],[Transportation]],Table4450[Sub-Category],Table1343[[#This Row],[Transportation]]) -> 0 | F33: =Table1343[[#This Row],[Budget]]-Table1343[[#This Row],[Actual]] -> 0 | J33: All Other Transactions | S33: =S32+1 -> 41630 | T33: =SUMIFS(Table442051[Amount],Table442051[Date],S33,Table442051[Category],Table13645[[#Headers],[Income]])+SUMIFS(Table4450[Amount],Table4450[Date],S33,Table4450[Category],Table13645[[#Headers],[Income]]) -> 0 | U33: =SUMIFS(Table444[Amount],Table444[Date],S33,Table444[Category],"<>"&Table13645[[#Headers],[Income]])+SUMIFS(Table4450[Amount],Table4450[Date],S33,Table4450[Category],"<>"&Table13645[[#Headers],[Income]]) -> 0 | V33: =V32+T33-U33 -> 1156.74 | W33: =W32 -> 1156.74
E34: =SUMIFS(Table444[Amount],Table444[Category],Table1343[[#Headers],[Transportation]],Table444[Sub-Category],Table1343[[#This Row],[Transportation]])+SUMIFS(Table4450[Amount],Table4450[Category],Table1343[[#Headers],[Transportation]],Table4450[Sub-Category],Table1343[[#This Row],[Transportation]]) -> 0 | F34: =Table1343[[#This Row],[Budget]]-Table1343[[#This Row],[Actual]] -> 0 | J34: Description | K34: Category | L34: Sub-Category | M34: Date | N34: Amount | O34: Status | S34: =S33+1 -> 41631 | T34: =SUMIFS(Table442051[Amount],Table442051[Date],S34,Table442051[Category],Table13645[[#Headers],[Income]])+SUMIFS(Table4450[Amount],Table4450[Date],S34,Table4450[Category],Table13645[[#Headers],[Income]]) -> 0 | U34: =SUMIFS(Table444[Amount],Table444[Date],S34,Table444[Category],"<>"&Table13645[[#Headers],[Income]])+SUMIFS(Table4450[Amount],Table4450[Date],S34,Table4450[Category],"<>"&Table13645[[#Headers],[Income]]) -> 0 | V34: =V33+T34-U34 -> 1156.74 | W34: =W33 -> 1156.74
E35: =SUMIFS(Table444[Amount],Table444[Category],Table1343[[#Headers],[Transportation]],Table444[Sub-Category],Table1343[[#This Row],[Transportation]])+SUMIFS(Table4450[Amount],Table4450[Category],Table1343[[#Headers],[Transportation]],Table4450[Sub-Category],Table1343[[#This Row],[Transportation]]) -> 0 | F35: =Table1343[[#This Row],[Budget]]-Table1343[[#This Row],[Actual]] -> 0 | S35: =S34+1 -> 41632 | T35: =SUMIFS(Table442051[Amount],Table442051[Date],S35,Table442051[Category],Table13645[[#Headers],[Income]])+SUMIFS(Table4450[Amount],Table4450[Date],S35,Table4450[Category],Table13645[[#Headers],[Income]]) -> 0 | U35: =SUMIFS(Table444[Amount],Table444[Date],S35,Table444[Category],"<>"&Table13645[[#Headers],[Income]])+SUMIFS(Table4450[Amount],Table4450[Date],S35,Table4450[Category],"<>"&Table13645[[#Headers],[Income]]) -> 0 | V35: =V34+T35-U35 -> 1156.74 | W35: =W34 -> 1156.74
E36: =SUMIFS(Table444[Amount],Table444[Category],Table1343[[#Headers],[Transportation]],Table444[Sub-Category],Table1343[[#This Row],[Transportation]])+SUMIFS(Table4450[Amount],Table4450[Category],Table1343[[#Headers],[Transportation]],Table4450[Sub-Category],Table1343[[#This Row],[Transportation]]) -> 0 | F36: =Table1343[[#This Row],[Budget]]-Table1343[[#This Row],[Actual]] -> 0 | S36: =S35+1 -> 41633 | T36: =SUMIFS(Table442051[Amount],Table442051[Date],S36,Table442051[Category],Table13645[[#Headers],[Income]])+SUMIFS(Table4450[Amount],Table4450[Date],S36,Table4450[Category],Table13645[[#Headers],[Income]]) -> 0 | U36: =SUMIFS(Table444[Amount],Table444[Date],S36,Table444[Category],"<>"&Table13645[[#Headers],[Income]])+SUMIFS(Table4450[Amount],Table4450[Date],S36,Table4450[Category],"<>"&Table13645[[#Headers],[Income]]) -> 0 | V36: =V35+T36-U36 -> 1156.74 | W36: =W35 -> 1156.74
C37: Total | D37: =SUBTOTAL(109,Table1343[Budget]) -> 0 | E37: =SUBTOTAL(109,Table1343[Actual]) -> 0 | F37: =SUBTOTAL(109,Table1343[Variance]) -> 0 | S37: =S36+1 -> 41634 | T37: =SUMIFS(Table442051[Amount],Table442051[Date],S37,Table442051[Category],Table13645[[#Headers],[Income]])+SUMIFS(Table4450[Amount],Table4450[Date],S37,Table4450[Category],Table13645[[#Headers],[Income]]) -> 0 | U37: =SUMIFS(Table444[Amount],Table444[Date],S37,Table444[Category],"<>"&Table13645[[#Headers],[Income]])+SUMIFS(Table4450[Amount],Table4450[Date],S37,Table4450[Category],"<>"&Table13645[[#Headers],[Income]]) -> 0 | V37: =V36+T37-U37 -> 1156.74 | W37: =W36 -> 1156.74
S38: =S37+1 -> 41635 | T38: =SUMIFS(Table442051[Amount],Table442051[Date],S38,Table442051[Category],Table13645[[#Headers],[Income]])+SUMIFS(Table4450[Amount],Table4450[Date],S38,Table4450[Category],Table13645[[#Headers],[Income]]) -> 0 | U38: =SUMIFS(Table444[Amount],Table444[Date],S38,Table444[Category],"<>"&Table13645[[#Headers],[Income]])+SUMIFS(Table4450[Amount],Table4450[Date],S38,Table4450[Category],"<>"&Table13645[[#Headers],[Income]]) -> 0 | V38: =V37+T38-U38 -> 1156.74 | W38: =W37 -> 1156.74
C39: =CONCATENATE(Table1391049[[#Headers],[Bills]]," - Budget & Tracking") -> Bills - Budget & Tracking | S39: =S38+1 -> 41636 | T39: =SUMIFS(Table442051[Amount],Table442051[Date],S39,Table442051[Category],Table13645[[#Headers],[Income]])+SUMIFS(Table4450[Amount],Table4450[Date],S39,Table4450[Category],Table13645[[#Headers],[Income]]) -> 0 | U39: =SUMIFS(Table444[Amount],Table444[Date],S39,Table444[Category],"<>"&Table13645[[#Headers],[Income]])+SUMIFS(Table4450[Amount],Table4450[Date],S39,Table4450[Category],"<>"&Table13645[[#Headers],[Income]]) -> 0 | V39: =V38+T39-U39 -> 1156.74 | W39: =W38 -> 1156.74
C40: Bills | D40: Budget | E40: Actual | F40: Variance | S40: =S39+1 -> 41637 | T40: =SUMIFS(Table442051[Amount],Table442051[Date],S40,Table442051[Category],Table13645[[#Headers],[Income]])+SUMIFS(Table4450[Amount],Table4450[Date],S40,Table4450[Category],Table13645[[#Headers],[Income]]) -> 0 | U40: =SUMIFS(Table444[Amount],Table444[Date],S40,Table444[Category],"<>"&Table13645[[#Headers],[Income]])+SUMIFS(Table4450[Amount],Table4450[Date],S40,Table4450[Category],"<>"&Table13645[[#Headers],[Income]]) -> 0 | V40: =V39+T40-U40 -> 1156.74 | W40: =W39 -> 1156.74
E41: =SUMIFS(Table444[Amount],Table444[Category],Table1391049[[#Headers],[Bills]],Table444[Sub-Category],Table1391049[[#This Row],[Bills]])+SUMIFS(Table4450[Amount],Table4450[Category],Table1391049[[#Headers],[Bills]],Table4450[Sub-Category],Table1391049[[#This Row],[Bills]]) -> 0 | F41: =Table1391049[[#This Row],[Budget]]-Table1391049[[#This Row],[Actual]] -> 0 | S41: =S40+1 -> 41638 | T41: =SUMIFS(Table442051[Amount],Table442051[Date],S41,Table442051[Category],Table13645[[#Headers],[Income]])+SUMIFS(Table4450[Amount],Table4450[Date],S41,Table4450[Category],Table13645[[#Headers],[Income]]) -> 0 | U41: =SUMIFS(Table444[Amount],Table444[Date],S41,Table444[Category],"<>"&Table13645[[#Headers],[Income]])+SUMIFS(Table4450[Amount],Table4450[Date],S41,Table4450[Category],"<>"&Table13645[[#Headers],[Income]]) -> 0 | V41: =V40+T41-U41 -> 1156.74 | W41: =W40 -> 1156.74
E42: =SUMIFS(Table444[Amount],Table444[Category],Table1391049[[#Headers],[Bills]],Table444[Sub-Category],Table1391049[[#This Row],[Bills]])+SUMIFS(Table4450[Amount],Table4450[Category],Table1391049[[#Headers],[Bills]],Table4450[Sub-Category],Table1391049[[#This Row],[Bills]]) -> 0 | F42: =Table1391049[[#This Row],[Budget]]-Table1391049[[#This Row],[Actual]] -> 0 | S42: =S41+1 -> 41639 | T42: =SUMIFS(Table442051[Amount],Table442051[Date],S42,Table442051[Category],Table13645[[#Headers],[Income]])+SUMIFS(Table4450[Amount],Table4450[Date],S42,Table4450[Category],Table13645[[#Headers],[Income]]) -> 0 | U42: =SUMIFS(Table444[Amount],Table444[Date],S42,Table444[Category],"<>"&Table13645[[#Headers],[Income]])+SUMIFS(Table4450[Amount],Table4450[Date],S42,Table4450[Category],"<>"&Table13645[[#Headers],[Income]]) -> 0 | V42: =V41+T42-U42 -> 1156.74 | W42: =W41 -> 1156.74
E43: =SUMIFS(Table444[Amount],Table444[Category],Table1391049[[#Headers],[Bills]],Table444[Sub-Category],Table1391049[[#This Row],[Bills]])+SUMIFS(Table4450[Amount],Table4450[Category],Table1391049[[#Headers],[Bills]],Table4450[Sub-Category],Table1391049[[#This Row],[Bills]]) -> 0 | F43: =Table1391049[[#This Row],[Budget]]-Table1391049[[#This Row],[Actual]] -> 0
E44: =SUMIFS(Table444[Amount],Table444[Category],Table1391049[[#Headers],[Bills]],Table444[Sub-Category],Table1391049[[#This Row],[Bills]])+SUMIFS(Table4450[Amount],Table4450[Category],Table1391049[[#Headers],[Bills]],Table4450[Sub-Category],Table1391049[[#This Row],[Bills]]) -> 0 | F44: =Table1391049[[#This Row],[Budget]]-Table1391049[[#This Row],[Actual]] -> 0
E45: =SUMIFS(Table444[Amount],Table444[Category],Table1391049[[#Headers],[Bills]],Table444[Sub-Category],Table1391049[[#This Row],[Bills]])+SUMIFS(Table4450[Amount],Table4450[Category],Table1391049[[#Headers],[Bills]],Table4450[Sub-Category],Table1391049[[#This Row],[Bills]]) -> 0 | F45: =Table1391049[[#This Row],[Budget]]-Table1391049[[#This Row],[Actual]] -> 0
C46: Total | D46: =SUBTOTAL(109,Table1391049[Budget]) -> 0 | E46: =SUBTOTAL(109,Table1391049[Actual]) -> 0 | F46: =SUBTOTAL(109,Table1391049[Variance]) -> 0
C48: =CONCATENATE(Table13746[[#Headers],[Living]]," - Budget & Tracking") -> Living - Budget & Tracking
C49: Living | D49: Budget | E49: Actual | F49: Variance
E50: =SUMIFS(Table444[Amount],Table444[Category],Table13746[[#Headers],[Living]],Table444[Sub-Category],Table13746[[#This Row],[Living]])+SUMIFS(Table4450[Amount],Table4450[Category],Table13746[[#Headers],[Living]],Table4450[Sub-Category],Table13746[[#This Row],[Living]]) -> 0 | F50: =Table13746[[#This Row],[Budget]]-Table13746[[#This Row],[Actual]] -> 0
E51: =SUMIFS(Table444[Amount],Table444[Category],Table13746[[#Headers],[Living]],Table444[Sub-Category],Table13746[[#This Row],[Living]])+SUMIFS(Table4450[Amount],Table4450[Category],Table13746[[#Headers],[Living]],Table4450[Sub-Category],Table13746[[#This Row],[Living]]) -> 0 | F51: =Table13746[[#This Row],[Budget]]-Table13746[[#This Row],[Actual]] -> 0
E52: =SUMIFS(Table444[Amount],Table444[Category],Table13746[[#Headers],[Living]],Table444[Sub-Category],Table13746[[#This Row],[Living]])+SUMIFS(Table4450[Amount],Table4450[Category],Table13746[[#Headers],[Living]],Table4450[Sub-Category],Table13746[[#This Row],[Living]]) -> 0 | F52: =Table13746[[#This Row],[Budget]]-Table13746[[#This Row],[Actual]] -> 0
E53: =SUMIFS(Table444[Amount],Table444[Category],Table13746[[#Headers],[Living]],Table444[Sub-Category],Table13746[[#This Row],[Living]])+SUMIFS(Table4450[Amount],Table4450[Category],Table13746[[#Headers],[Living]],Table4450[Sub-Category],Table13746[[#This Row],[Living]]) -> 0 | F53: =Table13746[[#This Row],[Budget]]-Table13746[[#This Row],[Actual]] -> 0
C54: Total | D54: =SUBTOTAL(109,Table13746[Budget]) -> 0 | E54: =SUBTOTAL(109,Table13746[Actual]) -> 0 | F54: =SUBTOTAL(109,Table13746[Variance]) -> 0
C56: =CONCATENATE(Table13847[[#Headers],[Entertainment]]," - Budget & Tracking") -> Entertainment - Budget & Tracking
C57: Entertainment | D57: Budget | E57: Actual | F57: Variance
E58: =SUMIFS(Table444[Amount],Table444[Category],Table13847[[#Headers],[Entertainment]],Table444[Sub-Category],Table13847[[#This Row],[Entertainment]])+SUMIFS(Table4450[Amount],Table4450[Category],Table13847[[#Headers],[Entertainment]],Table4450[Sub-Category],Table13847[[#This Row],[Entertainment]]) -> 0 | F58: =Table13847[[#This Row],[Budget]]-Table13847[[#This Row],[Actual]] -> 0
E59: =SUMIFS(Table444[Amount],Table444[Category],Table13847[[#Headers],[Entertainment]],Table444[Sub-Category],Table13847[[#This Row],[Entertainment]])+SUMIFS(Table4450[Amount],Table4450[Category],Table13847[[#Headers],[Entertainment]],Table4450[Sub-Category],Table13847[[#This Row],[Entertainment]]) -> 0 | F59: =Table13847[[#This Row],[Budget]]-Table13847[[#This Row],[Actual]] -> 0
C60: Total | D60: =SUBTOTAL(109,Table13847[Budget]) -> 0 | E60: =SUBTOTAL(109,Table13847[Actual]) -> 0 | F60: =SUBTOTAL(109,Table13847[Variance]) -> 0
C62: =CONCATENATE(Table13948[[#Headers],[Misc.]]," - Budget & Tracking") -> Misc. - Budget & Tracking
C63: Misc. | D63: Budget | E63: Actual | F63: Variance
E64: =SUMIFS(Table444[Amount],Table444[Category],Table13948[[#Headers],[Misc.]],Table444[Sub-Category],Table13948[[#This Row],[Misc.]])+SUMIFS(Table4450[Amount],Table4450[Category],Table13948[[#Headers],[Misc.]],Table4450[Sub-Category],Table13948[[#This Row],[Misc.]]) -> 0 | F64: =Table13948[[#This Row],[Budget]]-Table13948[[#This Row],[Actual]] -> 0
E65: =SUMIFS(Table444[Amount],Table444[Category],Table13948[[#Headers],[Misc.]],Table444[Sub-Category],Table13948[[#This Row],[Misc.]])+SUMIFS(Table4450[Amount],Table4450[Category],Table13948[[#Headers],[Misc.]],Table4450[Sub-Category],Table13948[[#This Row],[Misc.]]) -> 0 | F65: =Table13948[[#This Row],[Budget]]-Table13948[[#This Row],[Actual]] -> 0
C66: Total | D66: =SUBTOTAL(109,Table13948[Budget]) -> 0 | E66: =SUBTOTAL(109,Table13948[Actual]) -> 0 | F66: =SUBTOTAL(109,Table13948[Variance]) -> 0

Sheet Mo.5
C1: =DATE(YEAR(Mo.4!C1),MONTH(Mo.4!C1)+1,DAY(Mo.4!C1)) -> 41640 | R1: Category | S1: Budget | T1: Actual | U1: Status | V1: Min Bal
D2: Budget | E2: Actual | F2: Variance | R2: =Table13655[[#Headers],[Income]] -> Income | S2: =SUM(Table13655[Budget]) -> 0 | T2: =SUM(Table13655[Actual]) -> 0 | U2: Pending | V2: =AVERAGE(V12:V42) -> 1156.74
C3: BOM Balance | D3: =Mo.4!D6 -> 1156.74 | E3: =Mo.4!E6 -> 1156.74 | F3: =E3-D3 -> 0 | R3: =Table152[[#Headers],[Housing]] -> Housing | S3: =SUM(Table152[Budget]) -> 0 | T3: =SUM(Table152[Actual]) -> 0 | U3: Scheduled
C4: Total Inflow | D4: =Table13655[[#Totals],[Budget]] -> 0 | E4: =Table13655[[#Totals],[Actual]] -> 0 | F4: =E4-D4 -> 0 | R4: =Table1353[[#Headers],[Transportation]] -> Transportation | S4: =SUM(Table1353[Budget]) -> 0 | T4: =SUM(Table1353[Actual]) -> 0 | U4: Cleared
C5: Total Outflow | D5: =Table152[[#Totals],[Budget]]+Table1353[[#Totals],[Budget]]+Table1391059[[#Totals],[Budget]]+Table13756[[#Totals],[Budget]]+Table13857[[#Totals],[Budget]]+Table13958[[#Totals],[Budget]] -> 0 | E5: =Table152[[#Totals],[Actual]]+Table1353[[#Totals],[Actual]]+Table1391059[[#Totals],[Actual]]+Table13756[[#Totals],[Actual]]+Table13857[[#Totals],[Actual]]+Table13958[[#Totals],[Actual]] -> 0 | F5: =E5-D5 -> 0 | R5: =Table1391059[[#Headers],[Bills]] -> Bills | S5: =SUM(Table1391059[Budget]) -> 0 | T5: =SUM(Table1391059[Actual]) -> 0
C6: Difference | D6: =D3+D4-D5 -> 1156.74 | E6: =E3+E4-E5 -> 1156.74 | F6: =F3+F4-F5 -> 0 | R6: =Table13756[[#Headers],[Living]] -> Living | S6: =SUM(Table13756[Budget]) -> 0 | T6: =SUM(Table13756[Actual]) -> 0
R7: =Table13857[[#Headers],[Entertainment]] -> Entertainment | S7: =SUM(Table13857[Budget]) -> 0 | T7: =SUM(Table13857[Actual]) -> 0
R8: =Table13958[[#Headers],[Misc.]] -> Misc. | S8: =SUM(Table13958[Budget]) -> 0 | T8: =SUM(Table13958[Actual]) -> 0
C10: =CONCATENATE(Table13655[[#Headers],[Income]]," - Budget & Tracking") -> Income - Budget & Tracking | J10: Budgeted Credits | S10: Account Balance / Tracking & Forecast
C11: Income | D11: Budget | E11: Actual | F11: Variance | J11: Description | K11: Category | L11: Sub-Category | M11: Date | N11: Amount | O11: Status | S11: Date | T11: Credit | U11: Debit | V11: Balance
E12: =SUMIFS(Table442061[Amount],Table442061[Category],Table13655[[#Headers],[Income]],Table442061[Sub-Category],Table13655[[#This Row],[Income]])+SUMIFS(Table4460[Amount],Table4460[Category],Table13655[[#Headers],[Income]],Table4460[Sub-Category],Table13655[[#This Row],[Income]]) -> 0 | F12: =Table13655[[#This Row],[Actual]]-Table13655[[#This Row],[Budget]] -> 0 | S12: =C1 -> 41640 | T12: =SUMIFS(Table442061[Amount],Table442061[Date],S12,Table442061[Category],Table13655[[#Headers],[Income]])+SUMIFS(Table4460[Amount],Table4460[Date],S12,Table4460[Category],Table13655[[#Headers],[Income]]) -> 0 | U12: =SUMIFS(Table454[Amount],Table454[Date],S12,Table454[Category],"<>"&Table13655[[#Headers],[Income]])+SUMIFS(Table4460[Amount],Table4460[Date],S12,Table4460[Category],"<>"&Table13655[[#Headers],[Income]]) -> 0 | V12: =E3+T12-U12 -> 1156.74 | W12: =V2 -> 1156.74
E13: =SUMIFS(Table442061[Amount],Table442061[Category],Table13655[[#Headers],[Income]],Table442061[Sub-Category],Table13655[[#This Row],[Income]])+SUMIFS(Table4460[Amount],Table4460[Category],Table13655[[#Headers],[Income]],Table4460[Sub-Category],Table13655[[#This Row],[Income]]) -> 0 | F13: =Table13655[[#This Row],[Actual]]-Table13655[[#This Row],[Budget]] -> 0 | S13: =S12+1 -> 41641 | T13: =SUMIFS(Table442061[Amount],Table442061[Date],S13,Table442061[Category],Table13655[[#Headers],[Income]])+SUMIFS(Table4460[Amount],Table4460[Date],S13,Table4460[Category],Table13655[[#Headers],[Income]]) -> 0 | U13: =SUMIFS(Table454[Amount],Table454[Date],S13,Table454[Category],"<>"&Table13655[[#Headers],[Income]])+SUMIFS(Table4460[Amount],Table4460[Date],S13,Table4460[Category],"<>"&Table13655[[#Headers],[Income]]) -> 0 | V13: =V12+T13-U13 -> 1156.74 | W13: =W12 -> 1156.74
E14: =SUMIFS(Table442061[Amount],Table442061[Category],Table13655[[#Headers],[Income]],Table442061[Sub-Category],Table13655[[#This Row],[Income]])+SUMIFS(Table4460[Amount],Table4460[Category],Table13655[[#Headers],[Income]],Table4460[Sub-Category],Table13655[[#This Row],[Income]]) -> 0 | F14: =Table13655[[#This Row],[Actual]]-Table13655[[#This Row],[Budget]] -> 0 | S14: =S13+1 -> 41642 | T14: =SUMIFS(Table442061[Amount],Table442061[Date],S14,Table442061[Category],Table13655[[#Headers],[Income]])+SUMIFS(Table4460[Amount],Table4460[Date],S14,Table4460[Category],Table13655[[#Headers],[Income]]) -> 0 | U14: =SUMIFS(Table454[Amount],Table454[Date],S14,Table454[Category],"<>"&Table13655[[#Headers],[Income]])+SUMIFS(Table4460[Amount],Table4460[Date],S14,Table4460[Category],"<>"&Table13655[[#Headers],[Income]]) -> 0 | V14: =V13+T14-U14 -> 1156.74 | W14: =W13 -> 1156.74
E15: =SUMIFS(Table442061[Amount],Table442061[Category],Table13655[[#Headers],[Income]],Table442061[Sub-Category],Table13655[[#This Row],[Income]])+SUMIFS(Table4460[Amount],Table4460[Category],Table13655[[#Headers],[Income]],Table4460[Sub-Category],Table13655[[#This Row],[Income]]) -> 0 | F15: =Table13655[[#This Row],[Actual]]-Table13655[[#This Row],[Budget]] -> 0 | S15: =S14+1 -> 41643 | T15: =SUMIFS(Table442061[Amount],Table442061[Date],S15,Table442061[Category],Table13655[[#Headers],[Income]])+SUMIFS(Table4460[Amount],Table4460[Date],S15,Table4460[Category],Table13655[[#Headers],[Income]]) -> 0 | U15: =SUMIFS(Table454[Amount],Table454[Date],S15,Table454[Category],"<>"&Table13655[[#Headers],[Income]])+SUMIFS(Table4460[Amount],Table4460[Date],S15,Table4460[Category],"<>"&Table13655[[#Headers],[Income]]) -> 0 | V15: =V14+T15-U15 -> 1156.74 | W15: =W14 -> 1156.74
C16: Total | D16: =SUBTOTAL(109,Table13655[Budget]) -> 0 | E16: =SUBTOTAL(109,Table13655[Actual]) -> 0 | F16: =SUBTOTAL(109,Table13655[Variance]) -> 0 | S16: =S15+1 -> 41644 | T16: =SUMIFS(Table442061[Amount],Table442061[Date],S16,Table442061[Category],Table13655[[#Headers],[Income]])+SUMIFS(Table4460[Amount],Table4460[Date],S16,Table4460[Category],Table13655[[#Headers],[Income]]) -> 0 | U16: =SUMIFS(Table454[Amount],Table454[Date],S16,Table454[Category],"<>"&Table13655[[#Headers],[Income]])+SUMIFS(Table4460[Amount],Table4460[Date],S16,Table4460[Category],"<>"&Table13655[[#Headers],[Income]]) -> 0 | V16: =V15+T16-U16 -> 1156.74 | W16: =W15 -> 1156.74
J17: Budgeted Debits | S17: =S16+1 -> 41645 | T17: =SUMIFS(Table442061[Amount],Table442061[Date],S17,Table442061[Category],Table13655[[#Headers],[Income]])+SUMIFS(Table4460[Amount],Table4460[Date],S17,Table4460[Category],Table13655[[#Headers],[Income]]) -> 0 | U17: =SUMIFS(Table454[Amount],Table454[Date],S17,Table454[Category],"<>"&Table13655[[#Headers],[Income]])+SUMIFS(Table4460[Amount],Table4460[Date],S17,Table4460[Category],"<>"&Table13655[[#Headers],[Income]]) -> 0 | V17: =V16+T17-U17 -> 1156.74 | W17: =W16 -> 1156.74
C18: =CONCATENATE(Table152[[#Headers],[Housing]]," - Budget & Tracking") -> Housing - Budget & Tracking | J18: Description | K18: Category | L18: Sub-Category | M18: Date | N18: Amount | O18: Status | S18: =S17+1 -> 41646 | T18: =SUMIFS(Table442061[Amount],Table442061[Date],S18,Table442061[Category],Table13655[[#Headers],[Income]])+SUMIFS(Table4460[Amount],Table4460[Date],S18,Table4460[Category],Table13655[[#Headers],[Income]]) -> 0 | U18: =SUMIFS(Table454[Amount],Table454[Date],S18,Table454[Category],"<>"&Table13655[[#Headers],[Income]])+SUMIFS(Table4460[Amount],Table4460[Date],S18,Table4460[Category],"<>"&Table13655[[#Headers],[Income]]) -> 0 | V18: =V17+T18-U18 -> 1156.74 | W18: =W17 -> 1156.74
C19: Housing | D19: Budget | E19: Actual | F19: Variance | S19: =S18+1 -> 41647 | T19: =SUMIFS(Table442061[Amount],Table442061[Date],S19,Table442061[Category],Table13655[[#Headers],[Income]])+SUMIFS(Table4460[Amount],Table4460[Date],S19,Table4460[Category],Table13655[[#Headers],[Income]]) -> 0 | U19: =SUMIFS(Table454[Amount],Table454[Date],S19,Table454[Category],"<>"&Table13655[[#Headers],[Income]])+SUMIFS(Table4460[Amount],Table4460[Date],S19,Table4460[Category],"<>"&Table13655[[#Headers],[Income]]) -> 0 | V19: =V18+T19-U19 -> 1156.74 | W19: =W18 -> 1156.74
E20: =SUMIFS(Table454[Amount],Table454[Category],Table152[[#Headers],[Housing]],Table454[Sub-Category],Table152[[#This Row],[Housing]])+SUMIFS(Table4460[Amount],Table4460[Category],Table152[[#Headers],[Housing]],Table4460[Sub-Category],Table152[[#This Row],[Housing]]) -> 0 | F20: =Table152[[#This Row],[Budget]]-Table152[[#This Row],[Actual]] -> 0 | S20: =S19+1 -> 41648 | T20: =SUMIFS(Table442061[Amount],Table442061[Date],S20,Table442061[Category],Table13655[[#Headers],[Income]])+SUMIFS(Table4460[Amount],Table4460[Date],S20,Table4460[Category],Table13655[[#Headers],[Income]]) -> 0 | U20: =SUMIFS(Table454[Amount],Table454[Date],S20,Table454[Category],"<>"&Table13655[[#Headers],[Income]])+SUMIFS(Table4460[Amount],Table4460[Date],S20,Table4460[Category],"<>"&Table13655[[#Headers],[Income]]) -> 0 | V20: =V19+T20-U20 -> 1156.74 | W20: =W19 -> 1156.74
E21: =SUMIFS(Table454[Amount],Table454[Category],Table152[[#Headers],[Housing]],Table454[Sub-Category],Table152[[#This Row],[Housing]])+SUMIFS(Table4460[Amount],Table4460[Category],Table152[[#Headers],[Housing]],Table4460[Sub-Category],Table152[[#This Row],[Housing]]) -> 0 | F21: =Table152[[#This Row],[Budget]]-Table152[[#This Row],[Actual]] -> 0 | S21: =S20+1 -> 41649 | T21: =SUMIFS(Table442061[Amount],Table442061[Date],S21,Table442061[Category],Table13655[[#Headers],[Income]])+SUMIFS(Table4460[Amount],Table4460[Date],S21,Table4460[Category],Table13655[[#Headers],[Income]]) -> 0 | U21: =SUMIFS(Table454[Amount],Table454[Date],S21,Table454[Category],"<>"&Table13655[[#Headers],[Income]])+SUMIFS(Table4460[Amount],Table4460[Date],S21,Table4460[Category],"<>"&Table13655[[#Headers],[Income]]) -> 0 | V21: =V20+T21-U21 -> 1156.74 | W21: =W20 -> 1156.74
E22: =SUMIFS(Table454[Amount],Table454[Category],Table152[[#Headers],[Housing]],Table454[Sub-Category],Table152[[#This Row],[Housing]])+SUMIFS(Table4460[Amount],Table4460[Category],Table152[[#Headers],[Housing]],Table4460[Sub-Category],Table152[[#This Row],[Housing]]) -> 0 | F22: =Table152[[#This Row],[Budget]]-Table152[[#This Row],[Actual]] -> 0 | S22: =S21+1 -> 41650 | T22: =SUMIFS(Table442061[Amount],Table442061[Date],S22,Table442061[Category],Table13655[[#Headers],[Income]])+SUMIFS(Table4460[Amount],Table4460[Date],S22,Table4460[Category],Table13655[[#Headers],[Income]]) -> 0 | U22: =SUMIFS(Table454[Amount],Table454[Date],S22,Table454[Category],"<>"&Table13655[[#Headers],[Income]])+SUMIFS(Table4460[Amount],Table4460[Date],S22,Table4460[Category],"<>"&Table13655[[#Headers],[Income]]) -> 0 | V22: =V21+T22-U22 -> 1156.74 | W22: =W21 -> 1156.74
E23: =SUMIFS(Table454[Amount],Table454[Category],Table152[[#Headers],[Housing]],Table454[Sub-Category],Table152[[#This Row],[Housing]])+SUMIFS(Table4460[Amount],Table4460[Category],Table152[[#Headers],[Housing]],Table4460[Sub-Category],Table152[[#This Row],[Housing]]) -> 0 | F23: =Table152[[#This Row],[Budget]]-Table152[[#This Row],[Actual]] -> 0 | S23: =S22+1 -> 41651 | T23: =SUMIFS(Table442061[Amount],Table442061[Date],S23,Table442061[Category],Table13655[[#Headers],[Income]])+SUMIFS(Table4460[Amount],Table4460[Date],S23,Table4460[Category],Table13655[[#Headers],[Income]]) -> 0 | U23: =SUMIFS(Table454[Amount],Table454[Date],S23,Table454[Category],"<>"&Table13655[[#Headers],[Income]])+SUMIFS(Table4460[Amount],Table4460[Date],S23,Table4460[Category],"<>"&Table13655[[#Headers],[Income]]) -> 0 | V23: =V22+T23-U23 -> 1156.74 | W23: =W22 -> 1156.74
E24: =SUMIFS(Table454[Amount],Table454[Category],Table152[[#Headers],[Housing]],Table454[Sub-Category],Table152[[#This Row],[Housing]])+SUMIFS(Table4460[Amount],Table4460[Category],Table152[[#Headers],[Housing]],Table4460[Sub-Category],Table152[[#This Row],[Housing]]) -> 0 | F24: =Table152[[#This Row],[Budget]]-Table152[[#This Row],[Actual]] -> 0 | S24: =S23+1 -> 41652 | T24: =SUMIFS(Table442061[Amount],Table442061[Date],S24,Table442061[Category],Table13655[[#Headers],[Income]])+SUMIFS(Table4460[Amount],Table4460[Date],S24,Table4460[Category],Table13655[[#Headers],[Income]]) -> 0 | U24: =SUMIFS(Table454[Amount],Table454[Date],S24,Table454[Category],"<>"&Table13655[[#Headers],[Income]])+SUMIFS(Table4460[Amount],Table4460[Date],S24,Table4460[Category],"<>"&Table13655[[#Headers],[Income]]) -> 0 | V24: =V23+T24-U24 -> 1156.74 | W24: =W23 -> 1156.74
E25: =SUMIFS(Table454[Amount],Table454[Category],Table152[[#Headers],[Housing]],Table454[Sub-Category],Table152[[#This Row],[Housing]])+SUMIFS(Table4460[Amount],Table4460[Category],Table152[[#Headers],[Housing]],Table4460[Sub-Category],Table152[[#This Row],[Housing]]) -> 0 | F25: =Table152[[#This Row],[Budget]]-Table152[[#This Row],[Actual]] -> 0 | S25: =S24+1 -> 41653 | T25: =SUMIFS(Table442061[Amount],Table442061[Date],S25,Table442061[Category],Table13655[[#Headers],[Income]])+SUMIFS(Table4460[Amount],Table4460[Date],S25,Table4460[Category],Table13655[[#Headers],[Income]]) -> 0 | U25: =SUMIFS(Table454[Amount],Table454[Date],S25,Table454[Category],"<>"&Table13655[[#Headers],[Income]])+SUMIFS(Table4460[Amount],Table4460[Date],S25,Table4460[Category],"<>"&Table13655[[#Headers],[Income]]) -> 0 | V25: =V24+T25-U25 -> 1156.74 | W25: =W24 -> 1156.74
E26: =SUMIFS(Table454[Amount],Table454[Category],Table152[[#Headers],[Housing]],Table454[Sub-Category],Table152[[#This Row],[Housing]])+SUMIFS(Table4460[Amount],Table4460[Category],Table152[[#Headers],[Housing]],Table4460[Sub-Category],Table152[[#This Row],[Housing]]) -> 0 | F26: =Table152[[#This Row],[Budget]]-Table152[[#This Row],[Actual]] -> 0 | S26: =S25+1 -> 41654 | T26: =SUMIFS(Table442061[Amount],Table442061[Date],S26,Table442061[Category],Table13655[[#Headers],[Income]])+SUMIFS(Table4460[Amount],Table4460[Date],S26,Table4460[Category],Table13655[[#Headers],[Income]]) -> 0 | U26: =SUMIFS(Table454[Amount],Table454[Date],S26,Table454[Category],"<>"&Table13655[[#Headers],[Income]])+SUMIFS(Table4460[Amount],Table4460[Date],S26,Table4460[Category],"<>"&Table13655[[#Headers],[Income]]) -> 0 | V26: =V25+T26-U26 -> 1156.74 | W26: =W25 -> 1156.74
E27: =SUMIFS(Table454[Amount],Table454[Category],Table152[[#Headers],[Housing]],Table454[Sub-Category],Table152[[#This Row],[Housing]])+SUMIFS(Table4460[Amount],Table4460[Category],Table152[[#Headers],[Housing]],Table4460[Sub-Category],Table152[[#This Row],[Housing]]) -> 0 | F27: =Table152[[#This Row],[Budget]]-Table152[[#This Row],[Actual]] -> 0 | S27: =S26+1 -> 41655 | T27: =SUMIFS(Table442061[Amount],Table442061[Date],S27,Table442061[Category],Table13655[[#Headers],[Income]])+SUMIFS(Table4460[Amount],Table4460[Date],S27,Table4460[Category],Table13655[[#Headers],[Income]]) -> 0 | U27: =SUMIFS(Table454[Amount],Table454[Date],S27,Table454[Category],"<>"&Table13655[[#Headers],[Income]])+SUMIFS(Table4460[Amount],Table4460[Date],S27,Table4460[Category],"<>"&Table13655[[#Headers],[Income]]) -> 0 | V27: =V26+T27-U27 -> 1156.74 | W27: =W26 -> 1156.74
E28: =SUMIFS(Table454[Amount],Table454[Category],Table152[[#Headers],[Housing]],Table454[Sub-Category],Table152[[#This Row],[Housing]])+SUMIFS(Table4460[Amount],Table4460[Category],Table152[[#Headers],[Housing]],Table4460[Sub-Category],Table152[[#This Row],[Housing]]) -> 0 | F28: =Table152[[#This Row],[Budget]]-Table152[[#This Row],[Actual]] -> 0 | S28: =S27+1 -> 41656 | T28: =SUMIFS(Table442061[Amount],Table442061[Date],S28,Table442061[Category],Table13655[[#Headers],[Income]])+SUMIFS(Table4460[Amount],Table4460[Date],S28,Table4460[Category],Table13655[[#Headers],[Income]]) -> 0 | U28: =SUMIFS(Table454[Amount],Table454[Date],S28,Table454[Category],"<>"&Table13655[[#Headers],[Income]])+SUMIFS(Table4460[Amount],Table4460[Date],S28,Table4460[Category],"<>"&Table13655[[#Headers],[Income]]) -> 0 | V28: =V27+T28-U28 -> 1156.74 | W28: =W27 -> 1156.74
C29: Total | D29: =SUBTOTAL(109,Table152[Budget]) -> 0 | E29: =SUBTOTAL(109,Table152[Actual]) -> 0 | F29: =SUBTOTAL(109,Table152[Variance]) -> 0 | S29: =S28+1 -> 41657 | T29: =SUMIFS(Table442061[Amount],Table442061[Date],S29,Table442061[Category],Table13655[[#Headers],[Income]])+SUMIFS(Table4460[Amount],Table4460[Date],S29,Table4460[Category],Table13655[[#Headers],[Income]]) -> 0 | U29: =SUMIFS(Table454[Amount],Table454[Date],S29,Table454[Category],"<>"&Table13655[[#Headers],[Income]])+SUMIFS(Table4460[Amount],Table4460[Date],S29,Table4460[Category],"<>"&Table13655[[#Headers],[Income]]) -> 0 | V29: =V28+T29-U29 -> 1156.74 | W29: =W28 -> 1156.74
S30: =S29+1 -> 41658 | T30: =SUMIFS(Table442061[Amount],Table442061[Date],S30,Table442061[Category],Table13655[[#Headers],[Income]])+SUMIFS(Table4460[Amount],Table4460[Date],S30,Table4460[Category],Table13655[[#Headers],[Income]]) -> 0 | U30: =SUMIFS(Table454[Amount],Table454[Date],S30,Table454[Category],"<>"&Table13655[[#Headers],[Income]])+SUMIFS(Table4460[Amount],Table4460[Date],S30,Table4460[Category],"<>"&Table13655[[#Headers],[Income]]) -> 0 | V30: =V29+T30-U30 -> 1156.74 | W30: =W29 -> 1156.74
C31: =CONCATENATE(Table1353[[#Headers],[Transportation]]," - Budget & Tracking") -> Transportation - Budget & Tracking | S31: =S30+1 -> 41659 | T31: =SUMIFS(Table442061[Amount],Table442061[Date],S31,Table442061[Category],Table13655[[#Headers],[Income]])+SUMIFS(Table4460[Amount],Table4460[Date],S31,Table4460[Category],Table13655[[#Headers],[Income]]) -> 0 | U31: =SUMIFS(Table454[Amount],Table454[Date],S31,Table454[Category],"<>"&Table13655[[#Headers],[Income]])+SUMIFS(Table4460[Amount],Table4460[Date],S31,Table4460[Category],"<>"&Table13655[[#Headers],[Income]]) -> 0 | V31: =V30+T31-U31 -> 1156.74 | W31: =W30 -> 1156.74
C32: Transportation | D32: Budget | E32: Actual | F32: Variance | S32: =S31+1 -> 41660 | T32: =SUMIFS(Table442061[Amount],Table442061[Date],S32,Table442061[Category],Table13655[[#Headers],[Income]])+SUMIFS(Table4460[Amount],Table4460[Date],S32,Table4460[Category],Table13655[[#Headers],[Income]]) -> 0 | U32: =SUMIFS(Table454[Amount],Table454[Date],S32,Table454[Category],"<>"&Table13655[[#Headers],[Income]])+SUMIFS(Table4460[Amount],Table4460[Date],S32,Table4460[Category],"<>"&Table13655[[#Headers],[Income]]) -> 0 | V32: =V31+T32-U32 -> 1156.74 | W32: =W31 -> 1156.74
E33: =SUMIFS(Table454[Amount],Table454[Category],Table1353[[#Headers],[Transportation]],Table454[Sub-Category],Table1353[[#This Row],[Transportation]])+SUMIFS(Table4460[Amount],Table4460[Category],Table1353[[#Headers],[Transportation]],Table4460[Sub-Category],Table1353[[#This Row],[Transportation]]) -> 0 | F33: =Table1353[[#This Row],[Budget]]-Table1353[[#This Row],[Actual]] -> 0 | J33: All Other Transactions | S33: =S32+1 -> 41661 | T33: =SUMIFS(Table442061[Amount],Table442061[Date],S33,Table442061[Category],Table13655[[#Headers],[Income]])+SUMIFS(Table4460[Amount],Table4460[Date],S33,Table4460[Category],Table13655[[#Headers],[Income]]) -> 0 | U33: =SUMIFS(Table454[Amount],Table454[Date],S33,Table454[Category],"<>"&Table13655[[#Headers],[Income]])+SUMIFS(Table4460[Amount],Table4460[Date],S33,Table4460[Category],"<>"&Table13655[[#Headers],[Income]]) -> 0 | V33: =V32+T33-U33 -> 1156.74 | W33: =W32 -> 1156.74
E34: =SUMIFS(Table454[Amount],Table454[Category],Table1353[[#Headers],[Transportation]],Table454[Sub-Category],Table1353[[#This Row],[Transportation]])+SUMIFS(Table4460[Amount],Table4460[Category],Table1353[[#Headers],[Transportation]],Table4460[Sub-Category],Table1353[[#This Row],[Transportation]]) -> 0 | F34: =Table1353[[#This Row],[Budget]]-Table1353[[#This Row],[Actual]] -> 0 | J34: Description | K34: Category | L34: Sub-Category | M34: Date | N34: Amount | O34: Status | S34: =S33+1 -> 41662 | T34: =SUMIFS(Table442061[Amount],Table442061[Date],S34,Table442061[Category],Table13655[[#Headers],[Income]])+SUMIFS(Table4460[Amount],Table4460[Date],S34,Table4460[Category],Table13655[[#Headers],[Income]]) -> 0 | U34: =SUMIFS(Table454[Amount],Table454[Date],S34,Table454[Category],"<>"&Table13655[[#Headers],[Income]])+SUMIFS(Table4460[Amount],Table4460[Date],S34,Table4460[Category],"<>"&Table13655[[#Headers],[Income]]) -> 0 | V34: =V33+T34-U34 -> 1156.74 | W34: =W33 -> 1156.74
E35: =SUMIFS(Table454[Amount],Table454[Category],Table1353[[#Headers],[Transportation]],Table454[Sub-Category],Table1353[[#This Row],[Transportation]])+SUMIFS(Table4460[Amount],Table4460[Category],Table1353[[#Headers],[Transportation]],Table4460[Sub-Category],Table1353[[#This Row],[Transportation]]) -> 0 | F35: =Table1353[[#This Row],[Budget]]-Table1353[[#This Row],[Actual]] -> 0 | S35: =S34+1 -> 41663 | T35: =SUMIFS(Table442061[Amount],Table442061[Date],S35,Table442061[Category],Table13655[[#Headers],[Income]])+SUMIFS(Table4460[Amount],Table4460[Date],S35,Table4460[Category],Table13655[[#Headers],[Income]]) -> 0 | U35: =SUMIFS(Table454[Amount],Table454[Date],S35,Table454[Category],"<>"&Table13655[[#Headers],[Income]])+SUMIFS(Table4460[Amount],Table4460[Date],S35,Table4460[Category],"<>"&Table13655[[#Headers],[Income]]) -> 0 | V35: =V34+T35-U35 -> 1156.74 | W35: =W34 -> 1156.74
E36: =SUMIFS(Table454[Amount],Table454[Category],Table1353[[#Headers],[Transportation]],Table454[Sub-Category],Table1353[[#This Row],[Transportation]])+SUMIFS(Table4460[Amount],Table4460[Category],Table1353[[#Headers],[Transportation]],Table4460[Sub-Category],Table1353[[#This Row],[Transportation]]) -> 0 | F36: =Table1353[[#This Row],[Budget]]-Table1353[[#This Row],[Actual]] -> 0 | S36: =S35+1 -> 41664 | T36: =SUMIFS(Table442061[Amount],Table442061[Date],S36,Table442061[Category],Table13655[[#Headers],[Income]])+SUMIFS(Table4460[Amount],Table4460[Date],S36,Table4460[Category],Table13655[[#Headers],[Income]]) -> 0 | U36: =SUMIFS(Table454[Amount],Table454[Date],S36,Table454[Category],"<>"&Table13655[[#Headers],[Income]])+SUMIFS(Table4460[Amount],Table4460[Date],S36,Table4460[Category],"<>"&Table13655[[#Headers],[Income]]) -> 0 | V36: =V35+T36-U36 -> 1156.74 | W36: =W35 -> 1156.74
C37: Total | D37: =SUBTOTAL(109,Table1353[Budget]) -> 0 | E37: =SUBTOTAL(109,Table1353[Actual]) -> 0 | F37: =SUBTOTAL(109,Table1353[Variance]) -> 0 | S37: =S36+1 -> 41665 | T37: =SUMIFS(Table442061[Amount],Table442061[Date],S37,Table442061[Category],Table13655[[#Headers],[Income]])+SUMIFS(Table4460[Amount],Table4460[Date],S37,Table4460[Category],Table13655[[#Headers],[Income]]) -> 0 | U37: =SUMIFS(Table454[Amount],Table454[Date],S37,Table454[Category],"<>"&Table13655[[#Headers],[Income]])+SUMIFS(Table4460[Amount],Table4460[Date],S37,Table4460[Category],"<>"&Table13655[[#Headers],[Income]]) -> 0 | V37: =V36+T37-U37 -> 1156.74 | W37: =W36 -> 1156.74
S38: =S37+1 -> 41666 | T38: =SUMIFS(Table442061[Amount],Table442061[Date],S38,Table442061[Category],Table13655[[#Headers],[Income]])+SUMIFS(Table4460[Amount],Table4460[Date],S38,Table4460[Category],Table13655[[#Headers],[Income]]) -> 0 | U38: =SUMIFS(Table454[Amount],Table454[Date],S38,Table454[Category],"<>"&Table13655[[#Headers],[Income]])+SUMIFS(Table4460[Amount],Table4460[Date],S38,Table4460[Category],"<>"&Table13655[[#Headers],[Income]]) -> 0 | V38: =V37+T38-U38 -> 1156.74 | W38: =W37 -> 1156.74
C39: =CONCATENATE(Table1391059[[#Headers],[Bills]]," - Budget & Tracking") -> Bills - Budget & Tracking | S39: =S38+1 -> 41667 | T39: =SUMIFS(Table442061[Amount],Table442061[Date],S39,Table442061[Category],Table13655[[#Headers],[Income]])+SUMIFS(Table4460[Amount],Table4460[Date],S39,Table4460[Category],Table13655[[#Headers],[Income]]) -> 0 | U39: =SUMIFS(Table454[Amount],Table454[Date],S39,Table454[Category],"<>"&Table13655[[#Headers],[Income]])+SUMIFS(Table4460[Amount],Table4460[Date],S39,Table4460[Category],"<>"&Table13655[[#Headers],[Income]]) -> 0 | V39: =V38+T39-U39 -> 1156.74 | W39: =W38 -> 1156.74
C40: Bills | D40: Budget | E40: Actual | F40: Variance | S40: =S39+1 -> 41668 | T40: =SUMIFS(Table442061[Amount],Table442061[Date],S40,Table442061[Category],Table13655[[#Headers],[Income]])+SUMIFS(Table4460[Amount],Table4460[Date],S40,Table4460[Category],Table13655[[#Headers],[Income]]) -> 0 | U40: =SUMIFS(Table454[Amount],Table454[Date],S40,Table454[Category],"<>"&Table13655[[#Headers],[Income]])+SUMIFS(Table4460[Amount],Table4460[Date],S40,Table4460[Category],"<>"&Table13655[[#Headers],[Income]]) -> 0 | V40: =V39+T40-U40 -> 1156.74 | W40: =W39 -> 1156.74
E41: =SUMIFS(Table454[Amount],Table454[Category],Table1391059[[#Headers],[Bills]],Table454[Sub-Category],Table1391059[[#This Row],[Bills]])+SUMIFS(Table4460[Amount],Table4460[Category],Table1391059[[#Headers],[Bills]],Table4460[Sub-Category],Table1391059[[#This Row],[Bills]]) -> 0 | F41: =Table1391059[[#This Row],[Budget]]-Table1391059[[#This Row],[Actual]] -> 0 | S41: =S40+1 -> 41669 | T41: =SUMIFS(Table442061[Amount],Table442061[Date],S41,Table442061[Category],Table13655[[#Headers],[Income]])+SUMIFS(Table4460[Amount],Table4460[Date],S41,Table4460[Category],Table13655[[#Headers],[Income]]) -> 0 | U41: =SUMIFS(Table454[Amount],Table454[Date],S41,Table454[Category],"<>"&Table13655[[#Headers],[Income]])+SUMIFS(Table4460[Amount],Table4460[Date],S41,Table4460[Category],"<>"&Table13655[[#Headers],[Income]]) -> 0 | V41: =V40+T41-U41 -> 1156.74 | W41: =W40 -> 1156.74
E42: =SUMIFS(Table454[Amount],Table454[Category],Table1391059[[#Headers],[Bills]],Table454[Sub-Category],Table1391059[[#This Row],[Bills]])+SUMIFS(Table4460[Amount],Table4460[Category],Table1391059[[#Headers],[Bills]],Table4460[Sub-Category],Table1391059[[#This Row],[Bills]]) -> 0 | F42: =Table1391059[[#This Row],[Budget]]-Table1391059[[#This Row],[Actual]] -> 0 | S42: =S41+1 -> 41670 | T42: =SUMIFS(Table442061[Amount],Table442061[Date],S42,Table442061[Category],Table13655[[#Headers],[Income]])+SUMIFS(Table4460[Amount],Table4460[Date],S42,Table4460[Category],Table13655[[#Headers],[Income]]) -> 0 | U42: =SUMIFS(Table454[Amount],Table454[Date],S42,Table454[Category],"<>"&Table13655[[#Headers],[Income]])+SUMIFS(Table4460[Amount],Table4460[Date],S42,Table4460[Category],"<>"&Table13655[[#Headers],[Income]]) -> 0 | V42: =V41+T42-U42 -> 1156.74 | W42: =W41 -> 1156.74
E43: =SUMIFS(Table454[Amount],Table454[Category],Table1391059[[#Headers],[Bills]],Table454[Sub-Category],Table1391059[[#This Row],[Bills]])+SUMIFS(Table4460[Amount],Table4460[Category],Table1391059[[#Headers],[Bills]],Table4460[Sub-Category],Table1391059[[#This Row],[Bills]]) -> 0 | F43: =Table1391059[[#This Row],[Budget]]-Table1391059[[#This Row],[Actual]] -> 0
E44: =SUMIFS(Table454[Amount],Table454[Category],Table1391059[[#Headers],[Bills]],Table454[Sub-Category],Table1391059[[#This Row],[Bills]])+SUMIFS(Table4460[Amount],Table4460[Category],Table1391059[[#Headers],[Bills]],Table4460[Sub-Category],Table1391059[[#This Row],[Bills]]) -> 0 | F44: =Table1391059[[#This Row],[Budget]]-Table1391059[[#This Row],[Actual]] -> 0
E45: =SUMIFS(Table454[Amount],Table454[Category],Table1391059[[#Headers],[Bills]],Table454[Sub-Category],Table1391059[[#This Row],[Bills]])+SUMIFS(Table4460[Amount],Table4460[Category],Table1391059[[#Headers],[Bills]],Table4460[Sub-Category],Table1391059[[#This Row],[Bills]]) -> 0 | F45: =Table1391059[[#This Row],[Budget]]-Table1391059[[#This Row],[Actual]] -> 0
C46: Total | D46: =SUBTOTAL(109,Table1391059[Budget]) -> 0 | E46: =SUBTOTAL(109,Table1391059[Actual]) -> 0 | F46: =SUBTOTAL(109,Table1391059[Variance]) -> 0
C48: =CONCATENATE(Table13756[[#Headers],[Living]]," - Budget & Tracking") -> Living - Budget & Tracking
C49: Living | D49: Budget | E49: Actual | F49: Variance
E50: =SUMIFS(Table454[Amount],Table454[Category],Table13756[[#Headers],[Living]],Table454[Sub-Category],Table13756[[#This Row],[Living]])+SUMIFS(Table4460[Amount],Table4460[Category],Table13756[[#Headers],[Living]],Table4460[Sub-Category],Table13756[[#This Row],[Living]]) -> 0 | F50: =Table13756[[#This Row],[Budget]]-Table13756[[#This Row],[Actual]] -> 0
E51: =SUMIFS(Table454[Amount],Table454[Category],Table13756[[#Headers],[Living]],Table454[Sub-Category],Table13756[[#This Row],[Living]])+SUMIFS(Table4460[Amount],Table4460[Category],Table13756[[#Headers],[Living]],Table4460[Sub-Category],Table13756[[#This Row],[Living]]) -> 0 | F51: =Table13756[[#This Row],[Budget]]-Table13756[[#This Row],[Actual]] -> 0
E52: =SUMIFS(Table454[Amount],Table454[Category],Table13756[[#Headers],[Living]],Table454[Sub-Category],Table13756[[#This Row],[Living]])+SUMIFS(Table4460[Amount],Table4460[Category],Table13756[[#Headers],[Living]],Table4460[Sub-Category],Table13756[[#This Row],[Living]]) -> 0 | F52: =Table13756[[#This Row],[Budget]]-Table13756[[#This Row],[Actual]] -> 0
E53: =SUMIFS(Table454[Amount],Table454[Category],Table13756[[#Headers],[Living]],Table454[Sub-Category],Table13756[[#This Row],[Living]])+SUMIFS(Table4460[Amount],Table4460[Category],Table13756[[#Headers],[Living]],Table4460[Sub-Category],Table13756[[#This Row],[Living]]) -> 0 | F53: =Table13756[[#This Row],[Budget]]-Table13756[[#This Row],[Actual]] -> 0
C54: Total | D54: =SUBTOTAL(109,Table13756[Budget]) -> 0 | E54: =SUBTOTAL(109,Table13756[Actual]) -> 0 | F54: =SUBTOTAL(109,Table13756[Variance]) -> 0
C56: =CONCATENATE(Table13857[[#Headers],[Entertainment]]," - Budget & Tracking") -> Entertainment - Budget & Tracking
C57: Entertainment | D57: Budget | E57: Actual | F57: Variance
E58: =SUMIFS(Table454[Amount],Table454[Category],Table13857[[#Headers],[Entertainment]],Table454[Sub-Category],Table13857[[#This Row],[Entertainment]])+SUMIFS(Table4460[Amount],Table4460[Category],Table13857[[#Headers],[Entertainment]],Table4460[Sub-Category],Table13857[[#This Row],[Entertainment]]) -> 0 | F58: =Table13857[[#This Row],[Budget]]-Table13857[[#This Row],[Actual]] -> 0
E59: =SUMIFS(Table454[Amount],Table454[Category],Table13857[[#Headers],[Entertainment]],Table454[Sub-Category],Table13857[[#This Row],[Entertainment]])+SUMIFS(Table4460[Amount],Table4460[Category],Table13857[[#Headers],[Entertainment]],Table4460[Sub-Category],Table13857[[#This Row],[Entertainment]]) -> 0 | F59: =Table13857[[#This Row],[Budget]]-Table13857[[#This Row],[Actual]] -> 0
C60: Total | D60: =SUBTOTAL(109,Table13857[Budget]) -> 0 | E60: =SUBTOTAL(109,Table13857[Actual]) -> 0 | F60: =SUBTOTAL(109,Table13857[Variance]) -> 0
C62: =CONCATENATE(Table13958[[#Headers],[Misc.]]," - Budget & Tracking") -> Misc. - Budget & Tracking
C63: Misc. | D63: Budget | E63: Actual | F63: Variance
E64: =SUMIFS(Table454[Amount],Table454[Category],Table13958[[#Headers],[Misc.]],Table454[Sub-Category],Table13958[[#This Row],[Misc.]])+SUMIFS(Table4460[Amount],Table4460[Category],Table13958[[#Headers],[Misc.]],Table4460[Sub-Category],Table13958[[#This Row],[Misc.]]) -> 0 | F64: =Table13958[[#This Row],[Budget]]-Table13958[[#This Row],[Actual]] -> 0
E65: =SUMIFS(Table454[Amount],Table454[Category],Table13958[[#Headers],[Misc.]],Table454[Sub-Category],Table13958[[#This Row],[Misc.]])+SUMIFS(Table4460[Amount],Table4460[Category],Table13958[[#Headers],[Misc.]],Table4460[Sub-Category],Table13958[[#This Row],[Misc.]]) -> 0 | F65: =Table13958[[#This Row],[Budget]]-Table13958[[#This Row],[Actual]] -> 0
C66: Total | D66: =SUBTOTAL(109,Table13958[Budget]) -> 0 | E66: =SUBTOTAL(109,Table13958[Actual]) -> 0 | F66: =SUBTOTAL(109,Table13958[Variance]) -> 0

Sheet Mo.6
C1: =DATE(YEAR(Mo.5!C1),MONTH(Mo.5!C1)+1,DAY(Mo.5!C1)) -> 41671 | R1: Category | S1: Budget | T1: Actual | U1: Status | V1: Min Bal
D2: Budget | E2: Actual | F2: Variance | R2: =Table13665[[#Headers],[Income]] -> Income | S2: =SUM(Table13665[Budget]) -> 0 | T2: =SUM(Table13665[Actual]) -> 0 | U2: Pending | V2: =AVERAGE(V12:V42) -> 1156.74
C3: BOM Balance | D3: =Mo.5!D6 -> 1156.74 | E3: =Mo.5!E6 -> 1156.74 | F3: =E3-D3 -> 0 | R3: =Table162[[#Headers],[Housing]] -> Housing | S3: =SUM(Table162[Budget]) -> 0 | T3: =SUM(Table162[Actual]) -> 0 | U3: Scheduled
C4: Total Inflow | D4: =Table13665[[#Totals],[Budget]] -> 0 | E4: =Table13665[[#Totals],[Actual]] -> 0 | F4: =E4-D4 -> 0 | R4: =Table1363[[#Headers],[Transportation]] -> Transportation | S4: =SUM(Table1363[Budget]) -> 0 | T4: =SUM(Table1363[Actual]) -> 0 | U4: Cleared
C5: Total Outflow | D5: =Table162[[#Totals],[Budget]]+Table1363[[#Totals],[Budget]]+Table1391069[[#Totals],[Budget]]+Table13766[[#Totals],[Budget]]+Table13867[[#Totals],[Budget]]+Table13968[[#Totals],[Budget]] -> 0 | E5: =Table162[[#Totals],[Actual]]+Table1363[[#Totals],[Actual]]+Table1391069[[#Totals],[Actual]]+Table13766[[#Totals],[Actual]]+Table13867[[#Totals],[Actual]]+Table13968[[#Totals],[Actual]] -> 0 | F5: =E5-D5 -> 0 | R5: =Table1391069[[#Headers],[Bills]] -> Bills | S5: =SUM(Table1391069[Budget]) -> 0 | T5: =SUM(Table1391069[Actual]) -> 0
C6: Difference | D6: =D3+D4-D5 -> 1156.74 | E6: =E3+E4-E5 -> 1156.74 | F6: =F3+F4-F5 -> 0 | R6: =Table13766[[#Headers],[Living]] -> Living | S6: =SUM(Table13766[Budget]) -> 0 | T6: =SUM(Table13766[Actual]) -> 0
R7: =Table13867[[#Headers],[Entertainment]] -> Entertainment | S7: =SUM(Table13867[Budget]) -> 0 | T7: =SUM(Table13867[Actual]) -> 0
R8: =Table13968[[#Headers],[Misc.]] -> Misc. | S8: =SUM(Table13968[Budget]) -> 0 | T8: =SUM(Table13968[Actual]) -> 0
C10: =CONCATENATE(Table13665[[#Headers],[Income]]," - Budget & Tracking") -> Income - Budget & Tracking | J10: Budgeted Credits | S10: Account Balance / Tracking & Forecast
C11: Income | D11: Budget | E11: Actual | F11: Variance | J11: Description | K11: Category | L11: Sub-Category | M11: Date | N11: Amount | O11: Status | S11: Date | T11: Credit | U11: Debit | V11: Balance
E12: =SUMIFS(Table442071[Amount],Table442071[Category],Table13665[[#Headers],[Income]],Table442071[Sub-Category],Table13665[[#This Row],[Income]])+SUMIFS(Table4470[Amount],Table4470[Category],Table13665[[#Headers],[Income]],Table4470[Sub-Category],Table13665[[#This Row],[Income]]) -> 0 | F12: =Table13665[[#This Row],[Actual]]-Table13665[[#This Row],[Budget]] -> 0 | S12: =C1 -> 41671 | T12: =SUMIFS(Table442071[Amount],Table442071[Date],S12,Table442071[Category],Table13665[[#Headers],[Income]])+SUMIFS(Table4470[Amount],Table4470[Date],S12,Table4470[Category],Table13665[[#Headers],[Income]]) -> 0 | U12: =SUMIFS(Table464[Amount],Table464[Date],S12,Table464[Category],"<>"&Table13665[[#Headers],[Income]])+SUMIFS(Table4470[Amount],Table4470[Date],S12,Table4470[Category],"<>"&Table13665[[#Headers],[Income]]) -> 0 | V12: =E3+T12-U12 -> 1156.74 | W12: =V2 -> 1156.74
E13: =SUMIFS(Table442071[Amount],Table442071[Category],Table13665[[#Headers],[Income]],Table442071[Sub-Category],Table13665[[#This Row],[Income]])+SUMIFS(Table4470[Amount],Table4470[Category],Table13665[[#Headers],[Income]],Table4470[Sub-Category],Table13665[[#This Row],[Income]]) -> 0 | F13: =Table13665[[#This Row],[Actual]]-Table13665[[#This Row],[Budget]] -> 0 | S13: =S12+1 -> 41672 | T13: =SUMIFS(Table442071[Amount],Table442071[Date],S13,Table442071[Category],Table13665[[#Headers],[Income]])+SUMIFS(Table4470[Amount],Table4470[Date],S13,Table4470[Category],Table13665[[#Headers],[Income]]) -> 0 | U13: =SUMIFS(Table464[Amount],Table464[Date],S13,Table464[Category],"<>"&Table13665[[#Headers],[Income]])+SUMIFS(Table4470[Amount],Table4470[Date],S13,Table4470[Category],"<>"&Table13665[[#Headers],[Income]]) -> 0 | V13: =V12+T13-U13 -> 1156.74 | W13: =W12 -> 1156.74
E14: =SUMIFS(Table442071[Amount],Table442071[Category],Table13665[[#Headers],[Income]],Table442071[Sub-Category],Table13665[[#This Row],[Income]])+SUMIFS(Table4470[Amount],Table4470[Category],Table13665[[#Headers],[Income]],Table4470[Sub-Category],Table13665[[#This Row],[Income]]) -> 0 | F14: =Table13665[[#This Row],[Actual]]-Table13665[[#This Row],[Budget]] -> 0 | S14: =S13+1 -> 41673 | T14: =SUMIFS(Table442071[Amount],Table442071[Date],S14,Table442071[Category],Table13665[[#Headers],[Income]])+SUMIFS(Table4470[Amount],Table4470[Date],S14,Table4470[Category],Table13665[[#Headers],[Income]]) -> 0 | U14: =SUMIFS(Table464[Amount],Table464[Date],S14,Table464[Category],"<>"&Table13665[[#Headers],[Income]])+SUMIFS(Table4470[Amount],Table4470[Date],S14,Table4470[Category],"<>"&Table13665[[#Headers],[Income]]) -> 0 | V14: =V13+T14-U14 -> 1156.74 | W14: =W13 -> 1156.74
E15: =SUMIFS(Table442071[Amount],Table442071[Category],Table13665[[#Headers],[Income]],Table442071[Sub-Category],Table13665[[#This Row],[Income]])+SUMIFS(Table4470[Amount],Table4470[Category],Table13665[[#Headers],[Income]],Table4470[Sub-Category],Table13665[[#This Row],[Income]]) -> 0 | F15: =Table13665[[#This Row],[Actual]]-Table13665[[#This Row],[Budget]] -> 0 | S15: =S14+1 -> 41674 | T15: =SUMIFS(Table442071[Amount],Table442071[Date],S15,Table442071[Category],Table13665[[#Headers],[Income]])+SUMIFS(Table4470[Amount],Table4470[Date],S15,Table4470[Category],Table13665[[#Headers],[Income]]) -> 0 | U15: =SUMIFS(Table464[Amount],Table464[Date],S15,Table464[Category],"<>"&Table13665[[#Headers],[Income]])+SUMIFS(Table4470[Amount],Table4470[Date],S15,Table4470[Category],"<>"&Table13665[[#Headers],[Income]]) -> 0 | V15: =V14+T15-U15 -> 1156.74 | W15: =W14 -> 1156.74
C16: Total | D16: =SUBTOTAL(109,Table13665[Budget]) -> 0 | E16: =SUBTOTAL(109,Table13665[Actual]) -> 0 | F16: =SUBTOTAL(109,Table13665[Variance]) -> 0 | S16: =S15+1 -> 41675 | T16: =SUMIFS(Table442071[Amount],Table442071[Date],S16,Table442071[Category],Table13665[[#Headers],[Income]])+SUMIFS(Table4470[Amount],Table4470[Date],S16,Table4470[Category],Table13665[[#Headers],[Income]]) -> 0 | U16: =SUMIFS(Table464[Amount],Table464[Date],S16,Table464[Category],"<>"&Table13665[[#Headers],[Income]])+SUMIFS(Table4470[Amount],Table4470[Date],S16,Table4470[Category],"<>"&Table13665[[#Headers],[Income]]) -> 0 | V16: =V15+T16-U16 -> 1156.74 | W16: =W15 -> 1156.74
J17: Budgeted Debits | S17: =S16+1 -> 41676 | T17: =SUMIFS(Table442071[Amount],Table442071[Date],S17,Table442071[Category],Table13665[[#Headers],[Income]])+SUMIFS(Table4470[Amount],Table4470[Date],S17,Table4470[Category],Table13665[[#Headers],[Income]]) -> 0 | U17: =SUMIFS(Table464[Amount],Table464[Date],S17,Table464[Category],"<>"&Table13665[[#Headers],[Income]])+SUMIFS(Table4470[Amount],Table4470[Date],S17,Table4470[Category],"<>"&Table13665[[#Headers],[Income]]) -> 0 | V17: =V16+T17-U17 -> 1156.74 | W17: =W16 -> 1156.74
C18: =CONCATENATE(Table162[[#Headers],[Housing]]," - Budget & Tracking") -> Housing - Budget & Tracking | J18: Description | K18: Category | L18: Sub-Category | M18: Date | N18: Amount | O18: Status | S18: =S17+1 -> 41677 | T18: =SUMIFS(Table442071[Amount],Table442071[Date],S18,Table442071[Category],Table13665[[#Headers],[Income]])+SUMIFS(Table4470[Amount],Table4470[Date],S18,Table4470[Category],Table13665[[#Headers],[Income]]) -> 0 | U18: =SUMIFS(Table464[Amount],Table464[Date],S18,Table464[Category],"<>"&Table13665[[#Headers],[Income]])+SUMIFS(Table4470[Amount],Table4470[Date],S18,Table4470[Category],"<>"&Table13665[[#Headers],[Income]]) -> 0 | V18: =V17+T18-U18 -> 1156.74 | W18: =W17 -> 1156.74
C19: Housing | D19: Budget | E19: Actual | F19: Variance | S19: =S18+1 -> 41678 | T19: =SUMIFS(Table442071[Amount],Table442071[Date],S19,Table442071[Category],Table13665[[#Headers],[Income]])+SUMIFS(Table4470[Amount],Table4470[Date],S19,Table4470[Category],Table13665[[#Headers],[Income]]) -> 0 | U19: =SUMIFS(Table464[Amount],Table464[Date],S19,Table464[Category],"<>"&Table13665[[#Headers],[Income]])+SUMIFS(Table4470[Amount],Table4470[Date],S19,Table4470[Category],"<>"&Table13665[[#Headers],[Income]]) -> 0 | V19: =V18+T19-U19 -> 1156.74 | W19: =W18 -> 1156.74
E20: =SUMIFS(Table464[Amount],Table464[Category],Table162[[#Headers],[Housing]],Table464[Sub-Category],Table162[[#This Row],[Housing]])+SUMIFS(Table4470[Amount],Table4470[Category],Table162[[#Headers],[Housing]],Table4470[Sub-Category],Table162[[#This Row],[Housing]]) -> 0 | F20: =Table162[[#This Row],[Budget]]-Table162[[#This Row],[Actual]] -> 0 | S20: =S19+1 -> 41679 | T20: =SUMIFS(Table442071[Amount],Table442071[Date],S20,Table442071[Category],Table13665[[#Headers],[Income]])+SUMIFS(Table4470[Amount],Table4470[Date],S20,Table4470[Category],Table13665[[#Headers],[Income]]) -> 0 | U20: =SUMIFS(Table464[Amount],Table464[Date],S20,Table464[Category],"<>"&Table13665[[#Headers],[Income]])+SUMIFS(Table4470[Amount],Table4470[Date],S20,Table4470[Category],"<>"&Table13665[[#Headers],[Income]]) -> 0 | V20: =V19+T20-U20 -> 1156.74 | W20: =W19 -> 1156.74
E21: =SUMIFS(Table464[Amount],Table464[Category],Table162[[#Headers],[Housing]],Table464[Sub-Category],Table162[[#This Row],[Housing]])+SUMIFS(Table4470[Amount],Table4470[Category],Table162[[#Headers],[Housing]],Table4470[Sub-Category],Table162[[#This Row],[Housing]]) -> 0 | F21: =Table162[[#This Row],[Budget]]-Table162[[#This Row],[Actual]] -> 0 | S21: =S20+1 -> 41680 | T21: =SUMIFS(Table442071[Amount],Table442071[Date],S21,Table442071[Category],Table13665[[#Headers],[Income]])+SUMIFS(Table4470[Amount],Table4470[Date],S21,Table4470[Category],Table13665[[#Headers],[Income]]) -> 0 | U21: =SUMIFS(Table464[Amount],Table464[Date],S21,Table464[Category],"<>"&Table13665[[#Headers],[Income]])+SUMIFS(Table4470[Amount],Table4470[Date],S21,Table4470[Category],"<>"&Table13665[[#Headers],[Income]]) -> 0 | V21: =V20+T21-U21 -> 1156.74 | W21: =W20 -> 1156.74
E22: =SUMIFS(Table464[Amount],Table464[Category],Table162[[#Headers],[Housing]],Table464[Sub-Category],Table162[[#This Row],[Housing]])+SUMIFS(Table4470[Amount],Table4470[Category],Table162[[#Headers],[Housing]],Table4470[Sub-Category],Table162[[#This Row],[Housing]]) -> 0 | F22: =Table162[[#This Row],[Budget]]-Table162[[#This Row],[Actual]] -> 0 | S22: =S21+1 -> 41681 | T22: =SUMIFS(Table442071[Amount],Table442071[Date],S22,Table442071[Category],Table13665[[#Headers],[Income]])+SUMIFS(Table4470[Amount],Table4470[Date],S22,Table4470[Category],Table13665[[#Headers],[Income]]) -> 0 | U22: =SUMIFS(Table464[Amount],Table464[Date],S22,Table464[Category],"<>"&Table13665[[#Headers],[Income]])+SUMIFS(Table4470[Amount],Table4470[Date],S22,Table4470[Category],"<>"&Table13665[[#Headers],[Income]]) -> 0 | V22: =V21+T22-U22 -> 1156.74 | W22: =W21 -> 1156.74
E23: =SUMIFS(Table464[Amount],Table464[Category],Table162[[#Headers],[Housing]],Table464[Sub-Category],Table162[[#This Row],[Housing]])+SUMIFS(Table4470[Amount],Table4470[Category],Table162[[#Headers],[Housing]],Table4470[Sub-Category],Table162[[#This Row],[Housing]]) -> 0 | F23: =Table162[[#This Row],[Budget]]-Table162[[#This Row],[Actual]] -> 0 | S23: =S22+1 -> 41682 | T23: =SUMIFS(Table442071[Amount],Table442071[Date],S23,Table442071[Category],Table13665[[#Headers],[Income]])+SUMIFS(Table4470[Amount],Table4470[Date],S23,Table4470[Category],Table13665[[#Headers],[Income]]) -> 0 | U23: =SUMIFS(Table464[Amount],Table464[Date],S23,Table464[Category],"<>"&Table13665[[#Headers],[Income]])+SUMIFS(Table4470[Amount],Table4470[Date],S23,Table4470[Category],"<>"&Table13665[[#Headers],[Income]]) -> 0 | V23: =V22+T23-U23 -> 1156.74 | W23: =W22 -> 1156.74
E24: =SUMIFS(Table464[Amount],Table464[Category],Table162[[#Headers],[Housing]],Table464[Sub-Category],Table162[[#This Row],[Housing]])+SUMIFS(Table4470[Amount],Table4470[Category],Table162[[#Headers],[Housing]],Table4470[Sub-Category],Table162[[#This Row],[Housing]]) -> 0 | F24: =Table162[[#This Row],[Budget]]-Table162[[#This Row],[Actual]] -> 0 | S24: =S23+1 -> 41683 | T24: =SUMIFS(Table442071[Amount],Table442071[Date],S24,Table442071[Category],Table13665[[#Headers],[Income]])+SUMIFS(Table4470[Amount],Table4470[Date],S24,Table4470[Category],Table13665[[#Headers],[Income]]) -> 0 | U24: =SUMIFS(Table464[Amount],Table464[Date],S24,Table464[Category],"<>"&Table13665[[#Headers],[Income]])+SUMIFS(Table4470[Amount],Table4470[Date],S24,Table4470[Category],"<>"&Table13665[[#Headers],[Income]]) -> 0 | V24: =V23+T24-U24 -> 1156.74 | W24: =W23 -> 1156.74
E25: =SUMIFS(Table464[Amount],Table464[Category],Table162[[#Headers],[Housing]],Table464[Sub-Category],Table162[[#This Row],[Housing]])+SUMIFS(Table4470[Amount],Table4470[Category],Table162[[#Headers],[Housing]],Table4470[Sub-Category],Table162[[#This Row],[Housing]]) -> 0 | F25: =Table162[[#This Row],[Budget]]-Table162[[#This Row],[Actual]] -> 0 | S25: =S24+1 -> 41684 | T25: =SUMIFS(Table442071[Amount],Table442071[Date],S25,Table442071[Category],Table13665[[#Headers],[Income]])+SUMIFS(Table4470[Amount],Table4470[Date],S25,Table4470[Category],Table13665[[#Headers],[Income]]) -> 0 | U25: =SUMIFS(Table464[Amount],Table464[Date],S25,Table464[Category],"<>"&Table13665[[#Headers],[Income]])+SUMIFS(Table4470[Amount],Table4470[Date],S25,Table4470[Category],"<>"&Table13665[[#Headers],[Income]]) -> 0 | V25: =V24+T25-U25 -> 1156.74 | W25: =W24 -> 1156.74
E26: =SUMIFS(Table464[Amount],Table464[Category],Table162[[#Headers],[Housing]],Table464[Sub-Category],Table162[[#This Row],[Housing]])+SUMIFS(Table4470[Amount],Table4470[Category],Table162[[#Headers],[Housing]],Table4470[Sub-Category],Table162[[#This Row],[Housing]]) -> 0 | F26: =Table162[[#This Row],[Budget]]-Table162[[#This Row],[Actual]] -> 0 | S26: =S25+1 -> 41685 | T26: =SUMIFS(Table442071[Amount],Table442071[Date],S26,Table442071[Category],Table13665[[#Headers],[Income]])+SUMIFS(Table4470[Amount],Table4470[Date],S26,Table4470[Category],Table13665[[#Headers],[Income]]) -> 0 | U26: =SUMIFS(Table464[Amount],Table464[Date],S26,Table464[Category],"<>"&Table13665[[#Headers],[Income]])+SUMIFS(Table4470[Amount],Table4470[Date],S26,Table4470[Category],"<>"&Table13665[[#Headers],[Income]]) -> 0 | V26: =V25+T26-U26 -> 1156.74 | W26: =W25 -> 1156.74
E27: =SUMIFS(Table464[Amount],Table464[Category],Table162[[#Headers],[Housing]],Table464[Sub-Category],Table162[[#This Row],[Housing]])+SUMIFS(Table4470[Amount],Table4470[Category],Table162[[#Headers],[Housing]],Table4470[Sub-Category],Table162[[#This Row],[Housing]]) -> 0 | F27: =Table162[[#This Row],[Budget]]-Table162[[#This Row],[Actual]] -> 0 | S27: =S26+1 -> 41686 | T27: =SUMIFS(Table442071[Amount],Table442071[Date],S27,Table442071[Category],Table13665[[#Headers],[Income]])+SUMIFS(Table4470[Amount],Table4470[Date],S27,Table4470[Category],Table13665[[#Headers],[Income]]) -> 0 | U27: =SUMIFS(Table464[Amount],Table464[Date],S27,Table464[Category],"<>"&Table13665[[#Headers],[Income]])+SUMIFS(Table4470[Amount],Table4470[Date],S27,Table4470[Category],"<>"&Table13665[[#Headers],[Income]]) -> 0 | V27: =V26+T27-U27 -> 1156.74 | W27: =W26 -> 1156.74
E28: =SUMIFS(Table464[Amount],Table464[Category],Table162[[#Headers],[Housing]],Table464[Sub-Category],Table162[[#This Row],[Housing]])+SUMIFS(Table4470[Amount],Table4470[Category],Table162[[#Headers],[Housing]],Table4470[Sub-Category],Table162[[#This Row],[Housing]]) -> 0 | F28: =Table162[[#This Row],[Budget]]-Table162[[#This Row],[Actual]] -> 0 | S28: =S27+1 -> 41687 | T28: =SUMIFS(Table442071[Amount],Table442071[Date],S28,Table442071[Category],Table13665[[#Headers],[Income]])+SUMIFS(Table4470[Amount],Table4470[Date],S28,Table4470[Category],Table13665[[#Headers],[Income]]) -> 0 | U28: =SUMIFS(Table464[Amount],Table464[Date],S28,Table464[Category],"<>"&Table13665[[#Headers],[Income]])+SUMIFS(Table4470[Amount],Table4470[Date],S28,Table4470[Category],"<>"&Table13665[[#Headers],[Income]]) -> 0 | V28: =V27+T28-U28 -> 1156.74 | W28: =W27 -> 1156.74
C29: Total | D29: =SUBTOTAL(109,Table162[Budget]) -> 0 | E29: =SUBTOTAL(109,Table162[Actual]) -> 0 | F29: =SUBTOTAL(109,Table162[Variance]) -> 0 | S29: =S28+1 -> 41688 | T29: =SUMIFS(Table442071[Amount],Table442071[Date],S29,Table442071[Category],Table13665[[#Headers],[Income]])+SUMIFS(Table4470[Amount],Table4470[Date],S29,Table4470[Category],Table13665[[#Headers],[Income]]) -> 0 | U29: =SUMIFS(Table464[Amount],Table464[Date],S29,Table464[Category],"<>"&Table13665[[#Headers],[Income]])+SUMIFS(Table4470[Amount],Table4470[Date],S29,Table4470[Category],"<>"&Table13665[[#Headers],[Income]]) -> 0 | V29: =V28+T29-U29 -> 1156.74 | W29: =W28 -> 1156.74
S30: =S29+1 -> 41689 | T30: =SUMIFS(Table442071[Amount],Table442071[Date],S30,Table442071[Category],Table13665[[#Headers],[Income]])+SUMIFS(Table4470[Amount],Table4470[Date],S30,Table4470[Category],Table13665[[#Headers],[Income]]) -> 0 | U30: =SUMIFS(Table464[Amount],Table464[Date],S30,Table464[Category],"<>"&Table13665[[#Headers],[Income]])+SUMIFS(Table4470[Amount],Table4470[Date],S30,Table4470[Category],"<>"&Table13665[[#Headers],[Income]]) -> 0 | V30: =V29+T30-U30 -> 1156.74 | W30: =W29 -> 1156.74
C31: =CONCATENATE(Table1363[[#Headers],[Transportation]]," - Budget & Tracking") -> Transportation - Budget & Tracking | S31: =S30+1 -> 41690 | T31: =SUMIFS(Table442071[Amount],Table442071[Date],S31,Table442071[Category],Table13665[[#Headers],[Income]])+SUMIFS(Table4470[Amount],Table4470[Date],S31,Table4470[Category],Table13665[[#Headers],[Income]]) -> 0 | U31: =SUMIFS(Table464[Amount],Table464[Date],S31,Table464[Category],"<>"&Table13665[[#Headers],[Income]])+SUMIFS(Table4470[Amount],Table4470[Date],S31,Table4470[Category],"<>"&Table13665[[#Headers],[Income]]) -> 0 | V31: =V30+T31-U31 -> 1156.74 | W31: =W30 -> 1156.74
C32: Transportation | D32: Budget | E32: Actual | F32: Variance | S32: =S31+1 -> 41691 | T32: =SUMIFS(Table442071[Amount],Table442071[Date],S32,Table442071[Category],Table13665[[#Headers],[Income]])+SUMIFS(Table4470[Amount],Table4470[Date],S32,Table4470[Category],Table13665[[#Headers],[Income]]) -> 0 | U32: =SUMIFS(Table464[Amount],Table464[Date],S32,Table464[Category],"<>"&Table13665[[#Headers],[Income]])+SUMIFS(Table4470[Amount],Table4470[Date],S32,Table4470[Category],"<>"&Table13665[[#Headers],[Income]]) -> 0 | V32: =V31+T32-U32 -> 1156.74 | W32: =W31 -> 1156.74
E33: =SUMIFS(Table464[Amount],Table464[Category],Table1363[[#Headers],[Transportation]],Table464[Sub-Category],Table1363[[#This Row],[Transportation]])+SUMIFS(Table4470[Amount],Table4470[Category],Table1363[[#Headers],[Transportation]],Table4470[Sub-Category],Table1363[[#This Row],[Transportation]]) -> 0 | F33: =Table1363[[#This Row],[Budget]]-Table1363[[#This Row],[Actual]] -> 0 | J33: All Other Transactions | S33: =S32+1 -> 41692 | T33: =SUMIFS(Table442071[Amount],Table442071[Date],S33,Table442071[Category],Table13665[[#Headers],[Income]])+SUMIFS(Table4470[Amount],Table4470[Date],S33,Table4470[Category],Table13665[[#Headers],[Income]]) -> 0 | U33: =SUMIFS(Table464[Amount],Table464[Date],S33,Table464[Category],"<>"&Table13665[[#Headers],[Income]])+SUMIFS(Table4470[Amount],Table4470[Date],S33,Table4470[Category],"<>"&Table13665[[#Headers],[Income]]) -> 0 | V33: =V32+T33-U33 -> 1156.74 | W33: =W32 -> 1156.74
E34: =SUMIFS(Table464[Amount],Table464[Category],Table1363[[#Headers],[Transportation]],Table464[Sub-Category],Table1363[[#This Row],[Transportation]])+SUMIFS(Table4470[Amount],Table4470[Category],Table1363[[#Headers],[Transportation]],Table4470[Sub-Category],Table1363[[#This Row],[Transportation]]) -> 0 | F34: =Table1363[[#This Row],[Budget]]-Table1363[[#This Row],[Actual]] -> 0 | J34: Description | K34: Category | L34: Sub-Category | M34: Date | N34: Amount | O34: Status | S34: =S33+1 -> 41693 | T34: =SUMIFS(Table442071[Amount],Table442071[Date],S34,Table442071[Category],Table13665[[#Headers],[Income]])+SUMIFS(Table4470[Amount],Table4470[Date],S34,Table4470[Category],Table13665[[#Headers],[Income]]) -> 0 | U34: =SUMIFS(Table464[Amount],Table464[Date],S34,Table464[Category],"<>"&Table13665[[#Headers],[Income]])+SUMIFS(Table4470[Amount],Table4470[Date],S34,Table4470[Category],"<>"&Table13665[[#Headers],[Income]]) -> 0 | V34: =V33+T34-U34 -> 1156.74 | W34: =W33 -> 1156.74
E35: =SUMIFS(Table464[Amount],Table464[Category],Table1363[[#Headers],[Transportation]],Table464[Sub-Category],Table1363[[#This Row],[Transportation]])+SUMIFS(Table4470[Amount],Table4470[Category],Table1363[[#Headers],[Transportation]],Table4470[Sub-Category],Table1363[[#This Row],[Transportation]]) -> 0 | F35: =Table1363[[#This Row],[Budget]]-Table1363[[#This Row],[Actual]] -> 0 | S35: =S34+1 -> 41694 | T35: =SUMIFS(Table442071[Amount],Table442071[Date],S35,Table442071[Category],Table13665[[#Headers],[Income]])+SUMIFS(Table4470[Amount],Table4470[Date],S35,Table4470[Category],Table13665[[#Headers],[Income]]) -> 0 | U35: =SUMIFS(Table464[Amount],Table464[Date],S35,Table464[Category],"<>"&Table13665[[#Headers],[Income]])+SUMIFS(Table4470[Amount],Table4470[Date],S35,Table4470[Category],"<>"&Table13665[[#Headers],[Income]]) -> 0 | V35: =V34+T35-U35 -> 1156.74 | W35: =W34 -> 1156.74
E36: =SUMIFS(Table464[Amount],Table464[Category],Table1363[[#Headers],[Transportation]],Table464[Sub-Category],Table1363[[#This Row],[Transportation]])+SUMIFS(Table4470[Amount],Table4470[Category],Table1363[[#Headers],[Transportation]],Table4470[Sub-Category],Table1363[[#This Row],[Transportation]]) -> 0 | F36: =Table1363[[#This Row],[Budget]]-Table1363[[#This Row],[Actual]] -> 0 | S36: =S35+1 -> 41695 | T36: =SUMIFS(Table442071[Amount],Table442071[Date],S36,Table442071[Category],Table13665[[#Headers],[Income]])+SUMIFS(Table4470[Amount],Table4470[Date],S36,Table4470[Category],Table13665[[#Headers],[Income]]) -> 0 | U36: =SUMIFS(Table464[Amount],Table464[Date],S36,Table464[Category],"<>"&Table13665[[#Headers],[Income]])+SUMIFS(Table4470[Amount],Table4470[Date],S36,Table4470[Category],"<>"&Table13665[[#Headers],[Income]]) -> 0 | V36: =V35+T36-U36 -> 1156.74 | W36: =W35 -> 1156.74
C37: Total | D37: =SUBTOTAL(109,Table1363[Budget]) -> 0 | E37: =SUBTOTAL(109,Table1363[Actual]) -> 0 | F37: =SUBTOTAL(109,Table1363[Variance]) -> 0 | S37: =S36+1 -> 41696 | T37: =SUMIFS(Table442071[Amount],Table442071[Date],S37,Table442071[Category],Table13665[[#Headers],[Income]])+SUMIFS(Table4470[Amount],Table4470[Date],S37,Table4470[Category],Table13665[[#Headers],[Income]]) -> 0 | U37: =SUMIFS(Table464[Amount],Table464[Date],S37,Table464[Category],"<>"&Table13665[[#Headers],[Income]])+SUMIFS(Table4470[Amount],Table4470[Date],S37,Table4470[Category],"<>"&Table13665[[#Headers],[Income]]) -> 0 | V37: =V36+T37-U37 -> 1156.74 | W37: =W36 -> 1156.74
S38: =S37+1 -> 41697 | T38: =SUMIFS(Table442071[Amount],Table442071[Date],S38,Table442071[Category],Table13665[[#Headers],[Income]])+SUMIFS(Table4470[Amount],Table4470[Date],S38,Table4470[Category],Table13665[[#Headers],[Income]]) -> 0 | U38: =SUMIFS(Table464[Amount],Table464[Date],S38,Table464[Category],"<>"&Table13665[[#Headers],[Income]])+SUMIFS(Table4470[Amount],Table4470[Date],S38,Table4470[Category],"<>"&Table13665[[#Headers],[Income]]) -> 0 | V38: =V37+T38-U38 -> 1156.74 | W38: =W37 -> 1156.74
C39: =CONCATENATE(Table1391069[[#Headers],[Bills]]," - Budget & Tracking") -> Bills - Budget & Tracking | S39: =S38+1 -> 41698 | T39: =SUMIFS(Table442071[Amount],Table442071[Date],S39,Table442071[Category],Table13665[[#Headers],[Income]])+SUMIFS(Table4470[Amount],Table4470[Date],S39,Table4470[Category],Table13665[[#Headers],[Income]]) -> 0 | U39: =SUMIFS(Table464[Amount],Table464[Date],S39,Table464[Category],"<>"&Table13665[[#Headers],[Income]])+SUMIFS(Table4470[Amount],Table4470[Date],S39,Table4470[Category],"<>"&Table13665[[#Headers],[Income]]) -> 0 | V39: =V38+T39-U39 -> 1156.74 | W39: =W38 -> 1156.74
C40: Bills | D40: Budget | E40: Actual | F40: Variance | S40: =S39+1 -> 41699 | T40: =SUMIFS(Table442071[Amount],Table442071[Date],S40,Table442071[Category],Table13665[[#Headers],[Income]])+SUMIFS(Table4470[Amount],Table4470[Date],S40,Table4470[Category],Table13665[[#Headers],[Income]]) -> 0 | U40: =SUMIFS(Table464[Amount],Table464[Date],S40,Table464[Category],"<>"&Table13665[[#Headers],[Income]])+SUMIFS(Table4470[Amount],Table4470[Date],S40,Table4470[Category],"<>"&Table13665[[#Headers],[Income]]) -> 0 | V40: =V39+T40-U40 -> 1156.74 | W40: =W39 -> 1156.74
E41: =SUMIFS(Table464[Amount],Table464[Category],Table1391069[[#Headers],[Bills]],Table464[Sub-Category],Table1391069[[#This Row],[Bills]])+SUMIFS(Table4470[Amount],Table4470[Category],Table1391069[[#Headers],[Bills]],Table4470[Sub-Category],Table1391069[[#This Row],[Bills]]) -> 0 | F41: =Table1391069[[#This Row],[Budget]]-Table1391069[[#This Row],[Actual]] -> 0 | S41: =S40+1 -> 41700 | T41: =SUMIFS(Table442071[Amount],Table442071[Date],S41,Table442071[Category],Table13665[[#Headers],[Income]])+SUMIFS(Table4470[Amount],Table4470[Date],S41,Table4470[Category],Table13665[[#Headers],[Income]]) -> 0 | U41: =SUMIFS(Table464[Amount],Table464[Date],S41,Table464[Category],"<>"&Table13665[[#Headers],[Income]])+SUMIFS(Table4470[Amount],Table4470[Date],S41,Table4470[Category],"<>"&Table13665[[#Headers],[Income]]) -> 0 | V41: =V40+T41-U41 -> 1156.74 | W41: =W40 -> 1156.74
E42: =SUMIFS(Table464[Amount],Table464[Category],Table1391069[[#Headers],[Bills]],Table464[Sub-Category],Table1391069[[#This Row],[Bills]])+SUMIFS(Table4470[Amount],Table4470[Category],Table1391069[[#Headers],[Bills]],Table4470[Sub-Category],Table1391069[[#This Row],[Bills]]) -> 0 | F42: =Table1391069[[#This Row],[Budget]]-Table1391069[[#This Row],[Actual]] -> 0 | S42: =S41+1 -> 41701 | T42: =SUMIFS(Table442071[Amount],Table442071[Date],S42,Table442071[Category],Table13665[[#Headers],[Income]])+SUMIFS(Table4470[Amount],Table4470[Date],S42,Table4470[Category],Table13665[[#Headers],[Income]]) -> 0 | U42: =SUMIFS(Table464[Amount],Table464[Date],S42,Table464[Category],"<>"&Table13665[[#Headers],[Income]])+SUMIFS(Table4470[Amount],Table4470[Date],S42,Table4470[Category],"<>"&Table13665[[#Headers],[Income]]) -> 0 | V42: =V41+T42-U42 -> 1156.74 | W42: =W41 -> 1156.74
E43: =SUMIFS(Table464[Amount],Table464[Category],Table1391069[[#Headers],[Bills]],Table464[Sub-Category],Table1391069[[#This Row],[Bills]])+SUMIFS(Table4470[Amount],Table4470[Category],Table1391069[[#Headers],[Bills]],Table4470[Sub-Category],Table1391069[[#This Row],[Bills]]) -> 0 | F43: =Table1391069[[#This Row],[Budget]]-Table1391069[[#This Row],[Actual]] -> 0
E44: =SUMIFS(Table464[Amount],Table464[Category],Table1391069[[#Headers],[Bills]],Table464[Sub-Category],Table1391069[[#This Row],[Bills]])+SUMIFS(Table4470[Amount],Table4470[Category],Table1391069[[#Headers],[Bills]],Table4470[Sub-Category],Table1391069[[#This Row],[Bills]]) -> 0 | F44: =Table1391069[[#This Row],[Budget]]-Table1391069[[#This Row],[Actual]] -> 0
E45: =SUMIFS(Table464[Amount],Table464[Category],Table1391069[[#Headers],[Bills]],Table464[Sub-Category],Table1391069[[#This Row],[Bills]])+SUMIFS(Table4470[Amount],Table4470[Category],Table1391069[[#Headers],[Bills]],Table4470[Sub-Category],Table1391069[[#This Row],[Bills]]) -> 0 | F45: =Table1391069[[#This Row],[Budget]]-Table1391069[[#This Row],[Actual]] -> 0
C46: Total | D46: =SUBTOTAL(109,Table1391069[Budget]) -> 0 | E46: =SUBTOTAL(109,Table1391069[Actual]) -> 0 | F46: =SUBTOTAL(109,Table1391069[Variance]) -> 0
C48: =CONCATENATE(Table13766[[#Headers],[Living]]," - Budget & Tracking") -> Living - Budget & Tracking
C49: Living | D49: Budget | E49: Actual | F49: Variance
E50: =SUMIFS(Table464[Amount],Table464[Category],Table13766[[#Headers],[Living]],Table464[Sub-Category],Table13766[[#This Row],[Living]])+SUMIFS(Table4470[Amount],Table4470[Category],Table13766[[#Headers],[Living]],Table4470[Sub-Category],Table13766[[#This Row],[Living]]) -> 0 | F50: =Table13766[[#This Row],[Budget]]-Table13766[[#This Row],[Actual]] -> 0
E51: =SUMIFS(Table464[Amount],Table464[Category],Table13766[[#Headers],[Living]],Table464[Sub-Category],Table13766[[#This Row],[Living]])+SUMIFS(Table4470[Amount],Table4470[Category],Table13766[[#Headers],[Living]],Table4470[Sub-Category],Table13766[[#This Row],[Living]]) -> 0 | F51: =Table13766[[#This Row],[Budget]]-Table13766[[#This Row],[Actual]] -> 0
E52: =SUMIFS(Table464[Amount],Table464[Category],Table13766[[#Headers],[Living]],Table464[Sub-Category],Table13766[[#This Row],[Living]])+SUMIFS(Table4470[Amount],Table4470[Category],Table13766[[#Headers],[Living]],Table4470[Sub-Category],Table13766[[#This Row],[Living]]) -> 0 | F52: =Table13766[[#This Row],[Budget]]-Table13766[[#This Row],[Actual]] -> 0
E53: =SUMIFS(Table464[Amount],Table464[Category],Table13766[[#Headers],[Living]],Table464[Sub-Category],Table13766[[#This Row],[Living]])+SUMIFS(Table4470[Amount],Table4470[Category],Table13766[[#Headers],[Living]],Table4470[Sub-Category],Table13766[[#This Row],[Living]]) -> 0 | F53: =Table13766[[#This Row],[Budget]]-Table13766[[#This Row],[Actual]] -> 0
C54: Total | D54: =SUBTOTAL(109,Table13766[Budget]) -> 0 | E54: =SUBTOTAL(109,Table13766[Actual]) -> 0 | F54: =SUBTOTAL(109,Table13766[Variance]) -> 0
C56: =CONCATENATE(Table13867[[#Headers],[Entertainment]]," - Budget & Tracking") -> Entertainment - Budget & Tracking
C57: Entertainment | D57: Budget | E57: Actual | F57: Variance
E58: =SUMIFS(Table464[Amount],Table464[Category],Table13867[[#Headers],[Entertainment]],Table464[Sub-Category],Table13867[[#This Row],[Entertainment]])+SUMIFS(Table4470[Amount],Table4470[Category],Table13867[[#Headers],[Entertainment]],Table4470[Sub-Category],Table13867[[#This Row],[Entertainment]]) -> 0 | F58: =Table13867[[#This Row],[Budget]]-Table13867[[#This Row],[Actual]] -> 0
E59: =SUMIFS(Table464[Amount],Table464[Category],Table13867[[#Headers],[Entertainment]],Table464[Sub-Category],Table13867[[#This Row],[Entertainment]])+SUMIFS(Table4470[Amount],Table4470[Category],Table13867[[#Headers],[Entertainment]],Table4470[Sub-Category],Table13867[[#This Row],[Entertainment]]) -> 0 | F59: =Table13867[[#This Row],[Budget]]-Table13867[[#This Row],[Actual]] -> 0
C60: Total | D60: =SUBTOTAL(109,Table13867[Budget]) -> 0 | E60: =SUBTOTAL(109,Table13867[Actual]) -> 0 | F60: =SUBTOTAL(109,Table13867[Variance]) -> 0
C62: =CONCATENATE(Table13968[[#Headers],[Misc.]]," - Budget & Tracking") -> Misc. - Budget & Tracking
C63: Misc. | D63: Budget | E63: Actual | F63: Variance
E64: =SUMIFS(Table464[Amount],Table464[Category],Table13968[[#Headers],[Misc.]],Table464[Sub-Category],Table13968[[#This Row],[Misc.]])+SUMIFS(Table4470[Amount],Table4470[Category],Table13968[[#Headers],[Misc.]],Table4470[Sub-Category],Table13968[[#This Row],[Misc.]]) -> 0 | F64: =Table13968[[#This Row],[Budget]]-Table13968[[#This Row],[Actual]] -> 0
E65: =SUMIFS(Table464[Amount],Table464[Category],Table13968[[#Headers],[Misc.]],Table464[Sub-Category],Table13968[[#This Row],[Misc.]])+SUMIFS(Table4470[Amount],Table4470[Category],Table13968[[#Headers],[Misc.]],Table4470[Sub-Category],Table13968[[#This Row],[Misc.]]) -> 0 | F65: =Table13968[[#This Row],[Budget]]-Table13968[[#This Row],[Actual]] -> 0
C66: Total | D66: =SUBTOTAL(109,Table13968[Budget]) -> 0 | E66: =SUBTOTAL(109,Table13968[Actual]) -> 0 | F66: =SUBTOTAL(109,Table13968[Variance]) -> 0

Sheet Mo.7
C1: =DATE(YEAR(Mo.6!C1),MONTH(Mo.6!C1)+1,DAY(Mo.6!C1)) -> 41699 | R1: Category | S1: Budget | T1: Actual | U1: Status | V1: Min Bal
D2: Budget | E2: Actual | F2: Variance | R2: =Table13675[[#Headers],[Income]] -> Income | S2: =SUM(Table13675[Budget]) -> 0 | T2: =SUM(Table13675[Actual]) -> 0 | U2: Pending | V2: =AVERAGE(V12:V42) -> 1156.74
C3: BOM Balance | D3: =Mo.6!D6 -> 1156.74 | E3: =Mo.6!E6 -> 1156.74 | F3: =E3-D3 -> 0 | R3: =Table172[[#Headers],[Housing]] -> Housing | S3: =SUM(Table172[Budget]) -> 0 | T3: =SUM(Table172[Actual]) -> 0 | U3: Scheduled
C4: Total Inflow | D4: =Table13675[[#Totals],[Budget]] -> 0 | E4: =Table13675[[#Totals],[Actual]] -> 0 | F4: =E4-D4 -> 0 | R4: =Table1373[[#Headers],[Transportation]] -> Transportation | S4: =SUM(Table1373[Budget]) -> 0 | T4: =SUM(Table1373[Actual]) -> 0 | U4: Cleared
C5: Total Outflow | D5: =Table172[[#Totals],[Budget]]+Table1373[[#Totals],[Budget]]+Table1391079[[#Totals],[Budget]]+Table13776[[#Totals],[Budget]]+Table13877[[#Totals],[Budget]]+Table13978[[#Totals],[Budget]] -> 0 | E5: =Table172[[#Totals],[Actual]]+Table1373[[#Totals],[Actual]]+Table1391079[[#Totals],[Actual]]+Table13776[[#Totals],[Actual]]+Table13877[[#Totals],[Actual]]+Table13978[[#Totals],[Actual]] -> 0 | F5: =E5-D5 -> 0 | R5: =Table1391079[[#Headers],[Bills]] -> Bills | S5: =SUM(Table1391079[Budget]) -> 0 | T5: =SUM(Table1391079[Actual]) -> 0
C6: Difference | D6: =D3+D4-D5 -> 1156.74 | E6: =E3+E4-E5 -> 1156.74 | F6: =F3+F4-F5 -> 0 | R6: =Table13776[[#Headers],[Living]] -> Living | S6: =SUM(Table13776[Budget]) -> 0 | T6: =SUM(Table13776[Actual]) -> 0
R7: =Table13877[[#Headers],[Entertainment]] -> Entertainment | S7: =SUM(Table13877[Budget]) -> 0 | T7: =SUM(Table13877[Actual]) -> 0
R8: =Table13978[[#Headers],[Misc.]] -> Misc. | S8: =SUM(Table13978[Budget]) -> 0 | T8: =SUM(Table13978[Actual]) -> 0
C10: =CONCATENATE(Table13675[[#Headers],[Income]]," - Budget & Tracking") -> Income - Budget & Tracking | J10: Budgeted Credits | S10: Account Balance / Tracking & Forecast
C11: Income | D11: Budget | E11: Actual | F11: Variance | J11: Description | K11: Category | L11: Sub-Category | M11: Date | N11: Amount | O11: Status | S11: Date | T11: Credit | U11: Debit | V11: Balance
E12: =SUMIFS(Table442081[Amount],Table442081[Category],Table13675[[#Headers],[Income]],Table442081[Sub-Category],Table13675[[#This Row],[Income]])+SUMIFS(Table4480[Amount],Table4480[Category],Table13675[[#Headers],[Income]],Table4480[Sub-Category],Table13675[[#This Row],[Income]]) -> 0 | F12: =Table13675[[#This Row],[Actual]]-Table13675[[#This Row],[Budget]] -> 0 | S12: =C1 -> 41699 | T12: =SUMIFS(Table442081[Amount],Table442081[Date],S12,Table442081[Category],Table13675[[#Headers],[Income]])+SUMIFS(Table4480[Amount],Table4480[Date],S12,Table4480[Category],Table13675[[#Headers],[Income]]) -> 0 | U12: =SUMIFS(Table474[Amount],Table474[Date],S12,Table474[Category],"<>"&Table13675[[#Headers],[Income]])+SUMIFS(Table4480[Amount],Table4480[Date],S12,Table4480[Category],"<>"&Table13675[[#Headers],[Income]]) -> 0 | V12: =E3+T12-U12 -> 1156.74 | W12: =V2 -> 1156.74
E13: =SUMIFS(Table442081[Amount],Table442081[Category],Table13675[[#Headers],[Income]],Table442081[Sub-Category],Table13675[[#This Row],[Income]])+SUMIFS(Table4480[Amount],Table4480[Category],Table13675[[#Headers],[Income]],Table4480[Sub-Category],Table13675[[#This Row],[Income]]) -> 0 | F13: =Table13675[[#This Row],[Actual]]-Table13675[[#This Row],[Budget]] -> 0 | S13: =S12+1 -> 41700 | T13: =SUMIFS(Table442081[Amount],Table442081[Date],S13,Table442081[Category],Table13675[[#Headers],[Income]])+SUMIFS(Table4480[Amount],Table4480[Date],S13,Table4480[Category],Table13675[[#Headers],[Income]]) -> 0 | U13: =SUMIFS(Table474[Amount],Table474[Date],S13,Table474[Category],"<>"&Table13675[[#Headers],[Income]])+SUMIFS(Table4480[Amount],Table4480[Date],S13,Table4480[Category],"<>"&Table13675[[#Headers],[Income]]) -> 0 | V13: =V12+T13-U13 -> 1156.74 | W13: =W12 -> 1156.74
E14: =SUMIFS(Table442081[Amount],Table442081[Category],Table13675[[#Headers],[Income]],Table442081[Sub-Category],Table13675[[#This Row],[Income]])+SUMIFS(Table4480[Amount],Table4480[Category],Table13675[[#Headers],[Income]],Table4480[Sub-Category],Table13675[[#This Row],[Income]]) -> 0 | F14: =Table13675[[#This Row],[Actual]]-Table13675[[#This Row],[Budget]] -> 0 | S14: =S13+1 -> 41701 | T14: =SUMIFS(Table442081[Amount],Table442081[Date],S14,Table442081[Category],Table13675[[#Headers],[Income]])+SUMIFS(Table4480[Amount],Table4480[Date],S14,Table4480[Category],Table13675[[#Headers],[Income]]) -> 0 | U14: =SUMIFS(Table474[Amount],Table474[Date],S14,Table474[Category],"<>"&Table13675[[#Headers],[Income]])+SUMIFS(Table4480[Amount],Table4480[Date],S14,Table4480[Category],"<>"&Table13675[[#Headers],[Income]]) -> 0 | V14: =V13+T14-U14 -> 1156.74 | W14: =W13 -> 1156.74
E15: =SUMIFS(Table442081[Amount],Table442081[Category],Table13675[[#Headers],[Income]],Table442081[Sub-Category],Table13675[[#This Row],[Income]])+SUMIFS(Table4480[Amount],Table4480[Category],Table13675[[#Headers],[Income]],Table4480[Sub-Category],Table13675[[#This Row],[Income]]) -> 0 | F15: =Table13675[[#This Row],[Actual]]-Table13675[[#This Row],[Budget]] -> 0 | S15: =S14+1 -> 41702 | T15: =SUMIFS(Table442081[Amount],Table442081[Date],S15,Table442081[Category],Table13675[[#Headers],[Income]])+SUMIFS(Table4480[Amount],Table4480[Date],S15,Table4480[Category],Table13675[[#Headers],[Income]]) -> 0 | U15: =SUMIFS(Table474[Amount],Table474[Date],S15,Table474[Category],"<>"&Table13675[[#Headers],[Income]])+SUMIFS(Table4480[Amount],Table4480[Date],S15,Table4480[Category],"<>"&Table13675[[#Headers],[Income]]) -> 0 | V15: =V14+T15-U15 -> 1156.74 | W15: =W14 -> 1156.74
C16: Total | D16: =SUBTOTAL(109,Table13675[Budget]) -> 0 | E16: =SUBTOTAL(109,Table13675[Actual]) -> 0 | F16: =SUBTOTAL(109,Table13675[Variance]) -> 0 | S16: =S15+1 -> 41703 | T16: =SUMIFS(Table442081[Amount],Table442081[Date],S16,Table442081[Category],Table13675[[#Headers],[Income]])+SUMIFS(Table4480[Amount],Table4480[Date],S16,Table4480[Category],Table13675[[#Headers],[Income]]) -> 0 | U16: =SUMIFS(Table474[Amount],Table474[Date],S16,Table474[Category],"<>"&Table13675[[#Headers],[Income]])+SUMIFS(Table4480[Amount],Table4480[Date],S16,Table4480[Category],"<>"&Table13675[[#Headers],[Income]]) -> 0 | V16: =V15+T16-U16 -> 1156.74 | W16: =W15 -> 1156.74
J17: Budgeted Debits | S17: =S16+1 -> 41704 | T17: =SUMIFS(Table442081[Amount],Table442081[Date],S17,Table442081[Category],Table13675[[#Headers],[Income]])+SUMIFS(Table4480[Amount],Table4480[Date],S17,Table4480[Category],Table13675[[#Headers],[Income]]) -> 0 | U17: =SUMIFS(Table474[Amount],Table474[Date],S17,Table474[Category],"<>"&Table13675[[#Headers],[Income]])+SUMIFS(Table4480[Amount],Table4480[Date],S17,Table4480[Category],"<>"&Table13675[[#Headers],[Income]]) -> 0 | V17: =V16+T17-U17 -> 1156.74 | W17: =W16 -> 1156.74
C18: =CONCATENATE(Table172[[#Headers],[Housing]]," - Budget & Tracking") -> Housing - Budget & Tracking | J18: Description | K18: Category | L18: Sub-Category | M18: Date | N18: Amount | O18: Status | S18: =S17+1 -> 41705 | T18: =SUMIFS(Table442081[Amount],Table442081[Date],S18,Table442081[Category],Table13675[[#Headers],[Income]])+SUMIFS(Table4480[Amount],Table4480[Date],S18,Table4480[Category],Table13675[[#Headers],[Income]]) -> 0 | U18: =SUMIFS(Table474[Amount],Table474[Date],S18,Table474[Category],"<>"&Table13675[[#Headers],[Income]])+SUMIFS(Table4480[Amount],Table4480[Date],S18,Table4480[Category],"<>"&Table13675[[#Headers],[Income]]) -> 0 | V18: =V17+T18-U18 -> 1156.74 | W18: =W17 -> 1156.74
C19: Housing | D19: Budget | E19: Actual | F19: Variance | S19: =S18+1 -> 41706 | T19: =SUMIFS(Table442081[Amount],Table442081[Date],S19,Table442081[Category],Table13675[[#Headers],[Income]])+SUMIFS(Table4480[Amount],Table4480[Date],S19,Table4480[Category],Table13675[[#Headers],[Income]]) -> 0 | U19: =SUMIFS(Table474[Amount],Table474[Date],S19,Table474[Category],"<>"&Table13675[[#Headers],[Income]])+SUMIFS(Table4480[Amount],Table4480[Date],S19,Table4480[Category],"<>"&Table13675[[#Headers],[Income]]) -> 0 | V19: =V18+T19-U19 -> 1156.74 | W19: =W18 -> 1156.74
E20: =SUMIFS(Table474[Amount],Table474[Category],Table172[[#Headers],[Housing]],Table474[Sub-Category],Table172[[#This Row],[Housing]])+SUMIFS(Table4480[Amount],Table4480[Category],Table172[[#Headers],[Housing]],Table4480[Sub-Category],Table172[[#This Row],[Housing]]) -> 0 | F20: =Table172[[#This Row],[Budget]]-Table172[[#This Row],[Actual]] -> 0 | S20: =S19+1 -> 41707 | T20: =SUMIFS(Table442081[Amount],Table442081[Date],S20,Table442081[Category],Table13675[[#Headers],[Income]])+SUMIFS(Table4480[Amount],Table4480[Date],S20,Table4480[Category],Table13675[[#Headers],[Income]]) -> 0 | U20: =SUMIFS(Table474[Amount],Table474[Date],S20,Table474[Category],"<>"&Table13675[[#Headers],[Income]])+SUMIFS(Table4480[Amount],Table4480[Date],S20,Table4480[Category],"<>"&Table13675[[#Headers],[Income]]) -> 0 | V20: =V19+T20-U20 -> 1156.74 | W20: =W19 -> 1156.74
